Workbook

Sheet Times
B3: Tribo | C3: Squad
B4: Aprendizagem Digital | C4: Aprendizagem
B5: Aprendizagem Digital | C5: Avaliação
B6: Aprendizagem Digital | C6: Comunicação
B7: Aprendizagem Digital | C7: Interação
B8: Aprendizagem Digital | C8: Plataforma
B9: Aprendizagem Digital | C9: Secretaria e Financeiro
B10: Atendimento & Serviço | C10: Athenas Atendimento
B11: Atendimento & Serviço | C11: kbots
B12: Atendimento & Serviço | C12: Papa-léguas
B13: Atendimento & Serviço | C13: Route66
B14: Financeiro | C14: Eagles
... B49: Total Geral | C49: Total Geral

Sheet Apoio
A1: Sprint 2026 | B1: Dias Úteis | C1: Inicio | D1: Fim | F1: PIs 2026 | H1: Sprint 2025 | I1: Dias Úteis | J1: Inicio | K1: Fim | M1: PIs 2025 | O1: Sprint 2024 | P1: Dias Úteis | Q1: Inicio | R1: Fim | T1: PIs 2024 | V1: Pis 2023
A2: SP 26.1.1 | B2: 7 | C2: 46041 | D2: =C2+11 -> 46052 | F2: PI 1/26 | H2: SP 25.1.1 | I2: 7 | J2: 45677 | K2: =J2+11 -> 45688 | M2: PI 1/25 | O2: SP 24.1.1 | P2: 8 | Q2: 45313 | R2: 45324 | T2: PI 1/24 | V2: PI 1/23
A3: SP 26.1.2 | B3: 8 | C3: =D2+3 -> 46055 | D3: =C3+11 -> 46066 | F3: PI 2/26 | H3: SP 25.1.2 | I3: 8 | J3: =K2+3 -> 45691 | K3: =J3+11 -> 45702 | M3: PI 2/25 | O3: SP 24.1.2 | P3: 6 | Q3: 45327 | R3: 45338 | T3: PI 2/24 | V3: PI 2/23
A4: SP 26.1.3 | B4: 6 | C4: =D3+3 -> 46069 | D4: =C4+11 -> 46080 | F4: PI 3/26 | H4: SP 25.1.3 | I4: 8 | J4: =K3+3 -> 45705 | K4: =J4+11 -> 45716 | M4: PI 3/25 | O4: SP 24.1.3 | P4: 8 | Q4: 45341 | R4: 45352 | T4: PI 3/24 | V4: PI 3/23
A5: SP 26.1.4 | B5: 8 | C5: =D4+3 -> 46083 | D5: =C5+11 -> 46094 | F5: PI 4/26 | H5: SP 25.1.4 | I5: 6 | J5: =K4+3 -> 45719 | K5: =J5+11 -> 45730 | M5: PI 4/25 | O5: SP 24.1.4 | P5: 8 | Q5: 45355 | R5: 45366 | T5: PI 4/24 | V5: PI 4/23
A6: SP 26.1.5 | B6: 8 | C6: =D5+3 -> 46097 | D6: =C6+11 -> 46108 | H6: SP 25.1.5 | I6: 8 | J6: =K5+3 -> 45733 | K6: =J6+11 -> 45744 | O6: SP 24.1.5 | P6: 7 | Q6: 45369 | R6: 45380
A7: SP 26.1.6 | B7: 2 | C7: =D6+3 -> 46111 | D7: =C7+11 -> 46122 | H7: SP 25.1.6 | I7: 3 | J7: =K6+3 -> 45747 | K7: =J7+11 -> 45758 | O7: SP 24.1.6 | P7: 3 | Q7: 45383 | R7: 45394
A8: SP 26.2.1 | B8: 5 | C8: =D7+3 -> 46125 | D8: =C8+11 -> 46136 | H8: SP 25.2.1 | I8: 6 | J8: =K7+3 -> 45761 | K8: =J8+11 -> 45772 | O8: SP 24.2.1 | P8: 8 | Q8: 45397 | R8: 45408
A9: SP 26.2.2 | B9: 7 | C9: =D8+3 -> 46139 | D9: =C9+11 -> 46150 | H9: SP 25.2.2 | I9: 7 | J9: =K8+3 -> 45775 | K9: =J9+11 -> 45786 | O9: SP 24.2.2 | P9: 7 | Q9: 45411 | R9: 45422
A10: SP 26.2.3 | B10: 8 | C10: =D9+3 -> 46153 | D10: =C10+11 -> 46164 | H10: SP 25.2.3 | I10: 8 | J10: =K9+3 -> 45789 | K10: =J10+11 -> 45800 | O10: SP 24.2.3 | P10: 8 | Q10: 45425 | R10: 45436
A11: SP 26.2.4 | B11: 7 | C11: =D10+3 -> 46167 | D11: =C11+11 -> 46178 | H11: SP 25.2.4 | I11: 8 | J11: =K10+3 -> 45803 | K11: =J11+11 -> 45814 | O11: SP 24.2.4 | P11: 7 | Q11: 45439 | R11: 45450
A12: SP 26.2.5 | B12: 8 | C12: =D11+3 -> 46181 | D12: =C12+11 -> 46192 | H12: SP 25.2.5 | I12: 7 | J12: =K11+3 -> 45817 | K12: =J12+11 -> 45828 | O12: SP 24.2.5 | P12: 4 | Q12: 45453 | R12: 45464
A13: SP 26.2.6 | B13: 3 | C13: =D12+3 -> 46195 | D13: =C13+11 -> 46206 | H13: SP 25.2.6 | I13: 3 | J13: =K12+3 -> 45831 | K13: =J13+11 -> 45842 | O13: SP 24.3.1 | P13: 12 | Q13: 45467 | R13: 45485
A14: SP 26.3.1 | B14: 7 | C14: =D13+3 -> 46209 | D14: =C14+11 -> 46220 | H14: SP 25.3.1 | I14: 7 | J14: =K13+3 -> 45845 | K14: =J14+11 -> 45856 | O14: SP 24.3.2 | P14: 8 | Q14: 45488 | R14: 45499
A15: SP 26.3.2 | B15: 8 | C15: =D14+3 -> 46223 | D15: =C15+11 -> 46234 | H15: SP 25.3.2 | I15: 8 | J15: =K14+3 -> 45859 | K15: =J15+11 -> 45870 | O15: SP 24.3.3 | P15: 8 | Q15: 45502 | R15: 45513
A16: SP 26.3.3 | B16: 8 | C16: =D15+3 -> 46237 | D16: =C16+11 -> 46248 | H16: SP 25.3.3 | I16: 8 | J16: =K15+3 -> 45873 | K16: =J16+11 -> 45884 | O16: SP 24.3.4 | P16: 8 | Q16: 45516 | R16: 45527
A17: SP 26.3.4 | B17: 8 | C17: =D16+3 -> 46251 | D17: =C17+11 -> 46262 | H17: SP 25.3.4 | I17: 13 | J17: =K16+3 -> 45887 | K17: =J17+18 -> 45905 | O17: SP 24.3.5 | P17: 8 | Q17: 45530 | R17: 45541
A18: SP 26.3.5 | B18: 7 | C18: =D17+3 -> 46265 | D18: =C18+11 -> 46276 | H18: SP 25.3.5 | I18: 3 | J18: =K17+3 -> 45908 | K18: =J18+11 -> 45919 | O18: SP 24.3.6 | P18: 3 | Q18: 45544 | R18: 45555
A19: SP 26.3.6 | B19: 3 | C19: =D18+3 -> 46279 | D19: =C19+11 -> 46290 | H19: SP 25.4.1 | I19: 13 | J19: =K18+3 -> 45922 | K19: =J19+18 -> 45940 | O19: SP 24.4.1 | P19: 13 | Q19: 45558 | R19: 45576
A20: SP 26.4.1 | B20: 8 | C20: =D19+3 -> 46293 | D20: =C20+11 -> 46304 | H20: SP 25.4.2 | I20: 8 | J20: =K19+3 -> 45943 | K20: =J20+11 -> 45954 | O20: SP 24.4.2 | P20: 8 | Q20: 45579 | R20: 45590
A21: SP 26.4.2 | B21: 7 | C21: =D20+3 -> 46307 | D21: =C21+11 -> 46318 | H21: SP 25.4.3 | I21: 8 | J21: =K20+3 -> 45957 | K21: =J21+11 -> 45968 | O21: SP 24.4.3 | P21: 8 | Q21: 45593 | R21: 45604
A22: SP 26.4.3 | B22: 7 | C22: =D21+3 -> 46321 | D22: =C22+11 -> 46332 | H22: SP 25.4.4 | I22: 7 | J22: =K21+3 -> 45971 | K22: =J22+11 -> 45982 | O22: SP 24.4.4 | P22: 6 | Q22: 45607 | R22: 45618
A23: SP 26.4.4 | B23: 7 | C23: =D22+3 -> 46335 | D23: =C23+11 -> 46346 | H23: SP 25.4.5 | I23: 8 | J23: =K22+3 -> 45985 | K23: =J23+11 -> 45996 | O23: SP 24.4.5 | P23: 8 | Q23: 45621 | R23: 45632
A24: SP 26.4.5 | B24: 8 | C24: =D23+3 -> 46349 | D24: =C24+11 -> 46360 | H24: SP 25.4.6 | I24: 8 | J24: =K23+3 -> 45999 | K24: =J24+11 -> 46010 | O24: SP 24.4.6 | P24: 8 | Q24: 45635 | R24: 45646
A25: SP 26.4.6 | B25: 8 | C25: =D24+3 -> 46363 | D25: =C25+11 -> 46374
O46: S

Sheet 2023
A1: Jornada | B1: Time | C1: PI | D1: Sprint | E1: Velocity
A2: Financeira | B2: House of Money | C2: PI 1/23 | D2: SP 23.1.1 | E2: 35
A3: Financeira | B3: House of Money | C3: PI 1/23 | D3: SP 23.1.2 | E3: 35
A4: Financeira | B4: House of Money | C4: PI 1/23 | D4: SP 23.1.3 | E4: 25
A5: Financeira | B5: House of Money | C5: PI 1/23 | D5: SP 23.1.4 | E5: 35
A6: Financeira | B6: House of Money | C6: PI 1/23 | D6: SP 23.1.5 | E6: 18
A7: Financeira | B7: House of Money | C7: PI 2/23 | D7: SP 23.2.1 | E7: 27
A8: Financeira | B8: House of Money | C8: PI 2/23 | D8: SP 23.2.2 | E8: 33
A9: Financeira | B9: House of Money | C9: PI 2/23 | D9: SP 23.2.3 | E9: 25
A10: Financeira | B10: House of Money | C10: PI 2/23 | D10: SP 23.2.4 | E10: 30
A11: Financeira | B11: House of Money | C11: PI 2/23 | D11: SP 23.2.5 | E11: 29
A12: Financeira | B12: House of Money | C12: PI 2/23 | D12: SP 23.2.6 | E12: 37
A13: Financeira | B13: House of Money | C13: PI 2/23 | D13: SP 23.2.7 | E13: 0
... A434: Academico | B434: Aprendizagem | C434: PI 2/23 | D434: SP 23.2.4 | E434: 42
A435: Academico | B435: Aprendizagem | C435: PI 2/23 | D435: SP 23.2.5 | E435: 9 | G435: 36
A436: Academico | B436: Aprendizagem | C436: PI 2/23 | D436: SP 23.2.6 | E436: 63
A437: Academico | B437: Aprendizagem | C437: PI 2/23 | D437: SP 23.2.7 | E437: 40
A438: Academico | B438: Aprendizagem | C438: PI 3/23 | D438: SP 23.3.1 | E438: 41
A439: Academico | B439: Aprendizagem | C439: PI 3/23 | D439: SP 23.3.2 | E439: 32
A440: Academico | B440: Aprendizagem | C440: PI 3/23 | D440: SP 23.3.3 | E440: 31
A441: Academico | B441: Aprendizagem | C441: PI 3/23 | D441: SP 23.3.4 | E441: 36
A442: Academico | B442: Aprendizagem | C442: PI 3/23 | D442: SP 23.3.5 | E442: 16
A443: Academico | B443: Aprendizagem | C443: PI 4/23 | D443: SP 23.4.1 | E443: 35
A444: Academico | B444: Aprendizagem | C444: PI 4/23 | D444: SP 23.4.2 | E444: 31
A445: Academico | B445: Aprendizagem | C445: PI 4/23 | D445: SP 23.4.3 | E445: 31
A446: Academico | B446: Aprendizagem | C446: PI 4/23 | D446: SP 23.4.4 | E446: 31
A447: Academico | B447: Aprendizagem | C447: PI 4/23 | D447: SP 23.4.5 | E447: 31
... A464: Academico | B464: Avaliação | C464: PI 3/23 | D464: SP 23.3.4 | E464: 32
A465: Academico | B465: Avaliação | C465: PI 3/23 | D465: SP 23.3.5 | E465: 13 | G465: 27
A466: Academico | B466: Avaliação | C466: PI 4/23 | D466: SP 23.4.1 | E466: 24
A467: Academico | B467: Avaliação | C467: PI 4/23 | D467: SP 23.4.2 | E467: 24
A468: Academico | B468: Avaliação | C468: PI 4/23 | D468: SP 23.4.3 | E468: 24
A469: Academico | B469: Avaliação | C469: PI 4/23 | D469: SP 23.4.4 | E469: 24
A470: Academico | B470: Avaliação | C470: PI 4/23 | D470: SP 23.4.5 | E470: 24
A471: Academico | B471: Avaliação | C471: PI 4/23 | D471: SP 23.4.6 | E471: 5
A472: Academico | B472: Docencia | C472: PI 1/23 | D472: SP 23.1.1 | E472: 0
A473: Academico | B473: Docencia | C473: PI 1/23 | D473: SP 23.1.2 | E473: 0
A474: Academico | B474: Docencia | C474: PI 1/23 | D474: SP 23.1.3 | E474: 0
A475: Academico | B475: Docencia | C475: PI 1/23 | D475: SP 23.1.4 | E475: 0
A476: Academico | B476: Docencia | C476: PI 1/23 | D476: SP 23.1.5 | E476: 0
A477: Academico | B477: Docencia | C477: PI 2/23 | D477: SP 23.2.1 | E477: 0
... A483: Academico | B483: Docencia | C483: PI 2/23 | D483: SP 23.2.7 | E483: 25
A484: Academico | B484: Docencia | C484: PI 3/23 | D484: SP 23.3.1 | E484: 30 | G484: 25
A485: Academico | B485: Docencia | C485: PI 3/23 | D485: SP 23.3.2 | E485: 19
A486: Academico | B486: Docencia | C486: PI 3/23 | D486: SP 23.3.3 | E486: 22
A487: Academico | B487: Docencia | C487: PI 3/23 | D487: SP 23.3.4 | E487: 9
A488: Academico | B488: Docencia | C488: PI 3/23 | D488: SP 23.3.5 | E488: 22
A489: Academico | B489: Docencia | C489: PI 4/23 | D489: SP 23.4.1 | E489: 22
A490: Academico | B490: Docencia | C490: PI 4/23 | D490: SP 23.4.2 | E490: 22
A491: Academico | B491: Docencia | C491: PI 4/23 | D491: SP 23.4.3 | E491: 22
A492: Academico | B492: Docencia | C492: PI 4/23 | D492: SP 23.4.4 | E492: 22
A493: Academico | B493: Docencia | C493: PI 4/23 | D493: SP 23.4.5 | E493: 22
A494: Academico | B494: Docencia | C494: PI 4/23 | D494: SP 23.4.6 | E494: 5
A495: Academico | B495: Moodle | C495: PI 1/23 | D495: SP 23.1.1 | E495: 15
A496: Academico | B496: Moodle | C496: PI 1/23 | D496: SP 23.1.2 | E496: 12
... A504: Academico | B504: Moodle | C504: PI 2/23 | D504: SP 23.2.5 | E504: 14
A505: Academico | B505: Moodle | C505: PI 2/23 | D505: SP 23.2.6 | E505: 20 | G505: 21
A506: Academico | B506: Moodle | C506: PI 2/23 | D506: SP 23.2.7 | E506: 10
A507: Academico | B507: Moodle | C507: PI 3/23 | D507: SP 23.3.1 | E507: 29
A508: Academico | B508: Moodle | C508: PI 3/23 | D508: SP 23.3.2 | E508: 24
A509: Academico | B509: Moodle | C509: PI 3/23 | D509: SP 23.3.3 | E509: 13
A510: Academico | B510: Moodle | C510: PI 3/23 | D510: SP 23.3.4 | E510: 27
A511: Academico | B511: Moodle | C511: PI 3/23 | D511: SP 23.3.5 | E511: 10
A512: Academico | B512: Moodle | C512: PI 4/23 | D512: SP 23.4.1 | E512: 19
A513: Academico | B513: Moodle | C513: PI 4/23 | D513: SP 23.4.2 | E513: 19
A514: Academico | B514: Moodle | C514: PI 4/23 | D514: SP 23.4.3 | E514: 19
A515: Academico | B515: Moodle | C515: PI 4/23 | D515: SP 23.4.4 | E515: 19
A516: Academico | B516: Moodle | C516: PI 4/23 | D516: SP 23.4.5 | E516: 19
A517: Academico | B517: Moodle | C517: PI 4/23 | D517: SP 23.4.6 | E517: 4
... A527: Academico | B527: Colaborar | C527: PI 2/23 | D527: SP 23.2.5 | E527: 28
A528: Academico | B528: Colaborar | C528: PI 2/23 | D528: SP 23.2.6 | E528: 19 | G528: 21
A529: Academico | B529: Colaborar | C529: PI 2/23 | D529: SP 23.2.7 | E529: 25
A530: Academico | B530: Colaborar | C530: PI 3/23 | D530: SP 23.3.1 | E530: 36
A531: Academico | B531: Colaborar | C531: PI 3/23 | D531: SP 23.3.2 | E531: 11
A532: Academico | B532: Colaborar | C532: PI 3/23 | D532: SP 23.3.3 | E532: 21
A533: Academico | B533: Colaborar | C533: PI 3/23 | D533: SP 23.3.4 | E533: 13
A534: Academico | B534: Colaborar | C534: PI 3/23 | D534: SP 23.3.5 | E534: 10
A535: Academico | B535: Colaborar | C535: PI 4/23 | D535: SP 23.4.1 | E535: 19
A536: Academico | B536: Colaborar | C536: PI 4/23 | D536: SP 23.4.2 | E536: 19
A537: Academico | B537: Colaborar | C537: PI 4/23 | D537: SP 23.4.3 | E537: 19
A538: Academico | B538: Colaborar | C538: PI 4/23 | D538: SP 23.4.4 | E538: 19
A539: Academico | B539: Colaborar | C539: PI 4/23 | D539: SP 23.4.5 | E539: 19
A540: Academico | B540: Colaborar | C540: PI 4/23 | D540: SP 23.4.6 | E540: 4
... A552: Academico | B552: Plataforma | C552: PI 2/23 | D552: SP 23.2.7 | E552: 30
A553: Academico | B553: Plataforma | C553: PI 3/23 | D553: SP 23.3.1 | E553: 28 | G553: 41
A554: Academico | B554: Plataforma | C554: PI 3/23 | D554: SP 23.3.2 | E554: 24
A555: Academico | B555: Plataforma | C555: PI 3/23 | D555: SP 23.3.3 | E555: 55
A556: Academico | B556: Plataforma | C556: PI 3/23 | D556: SP 23.3.4 | E556: 68
A557: Academico | B557: Plataforma | C557: PI 3/23 | D557: SP 23.3.5 | E557: 20
A558: Academico | B558: Plataforma | C558: PI 4/23 | D558: SP 23.4.1 | E558: 37
A559: Academico | B559: Plataforma | C559: PI 4/23 | D559: SP 23.4.2 | E559: 37
A560: Academico | B560: Plataforma | C560: PI 4/23 | D560: SP 23.4.3 | E560: 37
A561: Academico | B561: Plataforma | C561: PI 4/23 | D561: SP 23.4.4 | E561: 37
A562: Academico | B562: Plataforma | C562: PI 4/23 | D562: SP 23.4.5 | E562: 37
A563: Academico | B563: Plataforma | C563: PI 4/23 | D563: SP 23.4.6 | E563: 8
A564: Academico | B564: Financeiro | C564: PI 1/23 | D564: SP 23.1.1 | E564: 7
A565: Academico | B565: Financeiro | C565: PI 1/23 | D565: SP 23.1.2 | E565: 11
... A573: Academico | B573: Financeiro | C573: PI 2/23 | D573: SP 23.2.5 | E573: 39
A574: Academico | B574: Financeiro | C574: PI 2/23 | D574: SP 23.2.6 | E574: 48 | G574: 38
A575: Academico | B575: Financeiro | C575: PI 2/23 | D575: SP 23.2.7 | E575: 26
...

Sheet 2024
A1: Jornada | B1: Time | C1: Qtde de Devs | D1: Produtividade (H/P) | E1: Horas Produtivas por dia e por Dev | F1: PI | G1: Sprint | H1: Dias Úteis da Sprint | I1: Velocity
A2: Administrativo | B2: kbots | C2: 5 | D2: 7.5 | E2: 7.5 | F2: PI 1/24 | G2: SP 24.1.1 | H2: =IF(G2>0,VLOOKUP(G2,Apoio!$O$2:$P$24,2,0),"") -> 8 | I2: =IF(D2>0,(((H2*E2)*C2)/D2),"") -> 40
A3: Administrativo | B3: kbots | C3: 5 | D3: 7.5 | E3: 7.5 | F3: PI 1/24 | G3: SP 24.1.2 | H3: =IF(G3>0,VLOOKUP(G3,Apoio!$O$2:$P$24,2,0),"") -> 6 | I3: =IF(D3>0,(((H3*E3)*C3)/D3),"") -> 30
A4: Administrativo | B4: kbots | C4: 5 | D4: 7.5 | E4: 7.5 | F4: PI 1/24 | G4: SP 24.1.3 | H4: =IF(G4>0,VLOOKUP(G4,Apoio!$O$2:$P$24,2,0),"") -> 8 | I4: =IF(D4>0,(((H4*E4)*C4)/D4),"") -> 40
A5: Administrativo | B5: kbots | C5: 5 | D5: 7.5 | E5: 7.5 | F5: PI 1/24 | G5: SP 24.1.4 | H5: =IF(G5>0,VLOOKUP(G5,Apoio!$O$2:$P$24,2,0),"") -> 8 | I5: =IF(D5>0,(((H5*E5)*C5)/D5),"") -> 40
A6: Administrativo | B6: kbots | C6: 5 | D6: 7.5 | E6: 7.5 | F6: PI 1/24 | G6: SP 24.1.5 | H6: =IF(G6>0,VLOOKUP(G6,Apoio!$O$2:$P$24,2,0),"") -> 7 | I6: =IF(D6>0,(((H6*E6)*C6)/D6),"") -> 35
A7: Administrativo | B7: kbots | C7: 5 | D7: 7.5 | E7: 7.5 | F7: PI 1/24 | G7: SP 24.1.6 | H7: =IF(G7>0,VLOOKUP(G7,Apoio!$O$2:$P$24,2,0),"") -> 3 | I7: =IF(D7>0,(((H7*E7)*C7)/D7),"") -> 15
A8: Administrativo | B8: kbots | C8: 4 | D8: 6.4 | E8: 7.5 | F8: PI 2/24 | G8: SP 24.2.1 | H8: =IF(G8>0,VLOOKUP(G8,Apoio!$O$2:$P$24,2,0),"") -> 8 | I8: =IF(D8>0,(((H8*E8)*C8)/D8),"") -> 37.5
A9: Administrativo | B9: kbots | C9: 4 | D9: 6.4 | E9: 7.5 | F9: PI 2/24 | G9: SP 24.2.2 | H9: =IF(G9>0,VLOOKUP(G9,Apoio!$O$2:$P$24,2,0),"") -> 7 | I9: =IF(D9>0,(((H9*E9)*C9)/D9),"") -> 32.8125
A10: Administrativo | B10: kbots | C10: 4 | D10: 6.4 | E10: 7.5 | F10: PI 2/24 | G10: SP 24.2.3 | H10: =IF(G10>0,VLOOKUP(G10,Apoio!$O$2:$P$24,2,0),"") -> 8 | I10: =IF(D10>0,(((H10*E10)*C10)/D10),"") -> 37.5
A11: Administrativo | B11: kbots | C11: 4 | D11: 6.4 | E11: 7.5 | F11: PI 2/24 | G11: SP 24.2.4 | H11: =IF(G11>0,VLOOKUP(G11,Apoio!$O$2:$P$24,2,0),"") -> 7 | I11: =IF(D11>0,(((H11*E11)*C11)/D11),"") -> 32.8125
A12: Administrativo | B12: kbots | C12: 4 | D12: 6.4 | E12: 7.5 | F12: PI 2/24 | G12: SP 24.2.5 | H12: =IF(G12>0,VLOOKUP(G12,Apoio!$O$2:$P$24,2,0),"") -> 4 | I12: =IF(D12>0,(((H12*E12)*C12)/D12),"") -> 18.75
A13: Administrativo | B13: kbots | C13: 3 | D13: 5.8 | E13: 7.5 | F13: PI 3/24 | G13: SP 24.3.1 | H13: =IF(G13>0,VLOOKUP(G13,Apoio!$O$2:$P$24,2,0),"") -> 12 | I13: =IF(D13>0,(((H13*E13)*C13)/D13),"") -> 46.551724
... A151: Administrativo | B151: ThreadPool | C151: 5 | D151: 6.7 | E151: 7.5 | F151: PI 4/24 | G151: SP 24.4.6 | H151: =IF(G151>0,VLOOKUP(G151,Apoio!$O$2:$P$24,2,0),"") -> 8 | I151: =IF(D151>0,(((H151*E151)*C151)/D151),"") -> 44.776119
A152: Aprendizagem Digital | B152: Aprendizagem | C152: 7 | D152: 11 | E152: 7.5 | F152: PI 1/24 | G152: SP 24.1.1 | H152: 7 | I152: =IF(D152>0,(((H152*E152)*C152)/D152),"") -> 33.409091
A153: Aprendizagem Digital | B153: Aprendizagem | C153: 7.5 | D153: 11 | E153: 7.5 | F153: PI 1/24 | G153: SP 24.1.2 | H153: 6 | I153: =IF(D153>0,(((H153*E153)*C153)/D153),"") -> 30.681818
A154: Aprendizagem Digital | B154: Aprendizagem | C154: 8 | D154: 11 | E154: 7.5 | F154: PI 1/24 | G154: SP 24.1.3 | H154: 8 | I154: =IF(D154>0,(((H154*E154)*C154)/D154),"") -> 43.636364
A155: Aprendizagem Digital | B155: Aprendizagem | C155: 7 | D155: 11 | E155: 7.5 | F155: PI 1/24 | G155: SP 24.1.4 | H155: 8 | I155: =IF(D155>0,(((H155*E155)*C155)/D155),"") -> 38.181818
A156: Aprendizagem Digital | B156: Aprendizagem | C156: 7 | D156: 11 | E156: 7.5 | F156: PI 1/24 | G156: SP 24.1.5 | H156: 7 | I156: =IF(D156>0,(((H156*E156)*C156)/D156),"") -> 33.409091
A157: Aprendizagem Digital | B157: Aprendizagem | C157: 7 | D157: 11 | E157: 7.5 | F157: PI 1/24 | G157: SP 24.1.6 | H157: 3 | I157: =IF(D157>0,(((H157*E157)*C157)/D157),"") -> 14.318182
A158: Aprendizagem Digital | B158: Aprendizagem | C158: 6 | D158: 7 | E158: 7.5 | F158: PI 2/24 | G158: SP 24.2.1 | H158: 8 | I158: =IF(D158>0,(((H158*E158)*C158)/D158),"") -> 51.428571
A159: Aprendizagem Digital | B159: Aprendizagem | C159: 6 | D159: 7 | E159: 7.5 | F159: PI 2/24 | G159: SP 24.2.1 | H159: 8 | I159: =IF(D159>0,(((H159*E159)*C159)/D159),"") -> 51.428571
A160: Aprendizagem Digital | B160: Aprendizagem | C160: 6 | D160: 7 | E160: 7.5 | F160: PI 2/24 | G160: SP 24.2.2 | H160: 7 | I160: =IF(D160>0,(((H160*E160)*C160)/D160),"") -> 45
A161: Aprendizagem Digital | B161: Aprendizagem | C161: 6 | D161: 7 | E161: 7.5 | F161: PI 2/24 | G161: SP 24.2.2 | H161: 7 | I161: =IF(D161>0,(((H161*E161)*C161)/D161),"") -> 45
A162: Aprendizagem Digital | B162: Aprendizagem | C162: 6 | D162: 7 | E162: 7.5 | F162: PI 2/24 | G162: SP 24.2.3 | H162: 8 | I162: =IF(D162>0,(((H162*E162)*C162)/D162),"") -> 51.428571
A163: Aprendizagem Digital | B163: Aprendizagem | C163: 6 | D163: 7 | E163: 7.5 | F163: PI 2/24 | G163: SP 24.2.3 | H163: 8 | I163: =IF(D163>0,(((H163*E163)*C163)/D163),"") -> 51.428571
... A167: Aprendizagem Digital | B167: Aprendizagem | C167: 6 | D167: 7 | E167: 7.5 | F167: PI 2/24 | G167: SP 24.2.5 | H167: 4 | I167: =IF(D167>0,(((H167*E167)*C167)/D167),"") -> 25.714286
A168: Aprendizagem Digital | B168: Aprendizagem | C168: 4.7 | D168: 5.6 | E168: 7.5 | F168: PI 3/24 | G168: SP 24.3.1 | H168: =IF(G168>0,VLOOKUP(G168,Apoio!$O$2:$P$24,2,0),"") -> 12 | I168: =IF(D168>0,(((H168*E168)*C168)/D168),"") -> 75.535714
A169: Aprendizagem Digital | B169: Aprendizagem | C169: 4 | D169: 5.6 | E169: 7.5 | F169: PI 3/24 | G169: SP 24.3.2 | H169: =IF(G169>0,VLOOKUP(G169,Apoio!$O$2:$P$24,2,0),"") -> 8 | I169: =IF(D169>0,(((H169*E169)*C169)/D169),"") -> 42.857143
A170: Aprendizagem Digital | B170: Aprendizagem | C170: 5 | D170: 5.6 | E170: 7.5 | F170: PI 3/24 | G170: SP 24.3.3 | H170: =IF(G170>0,VLOOKUP(G170,Apoio!$O$2:$P$24,2,0),"") -> 8 | I170: =IF(D170>0,(((H170*E170)*C170)/D170),"") -> 53.571429
A171: Aprendizagem Digital | B171: Aprendizagem | C171: 4 | D171: 5.6 | E171: 7.5 | F171: PI 3/24 | G171: SP 24.3.4 | H171: =IF(G171>0,VLOOKUP(G171,Apoio!$O$2:$P$24,2,0),"") -> 8 | I171: =IF(D171>0,(((H171*E171)*C171)/D171),"") -> 42.857143
A172: Aprendizagem Digital | B172: Aprendizagem | C172: 5 | D172: 5.6 | E172: 7.5 | F172: PI 3/24 | G172: SP 24.3.5 | H172: =IF(G172>0,VLOOKUP(G172,Apoio!$O$2:$P$24,2,0),"") -> 8 | I172: =IF(D172>0,(((H172*E172)*C172)/D172),"") -> 53.571429
A173: Aprendizagem Digital | B173: Aprendizagem | C173: 4 | D173: 5.6 | E173: 7.5 | F173: PI 3/24 | G173: SP 24.3.6 | H173: =IF(G173>0,VLOOKUP(G173,Apoio!$O$2:$P$24,2,0),"") -> 3 | I173: =IF(D173>0,(((H173*E173)*C173)/D173),"") -> 16.071429
A174: Aprendizagem Digital | B174: Aprendizagem | C174: 4.2 | D174: 5.5 | E174: 7.5 | F174: PI 4/24 | G174: SP 24.4.1 | H174: 12 | I174: =IF(D174>0,(((H174*E174)*C174)/D174),"") -> 68.727273
A175: Aprendizagem Digital | B175: Aprendizagem | C175: 4.5 | D175: 5.5 | E175: 7.5 | F175: PI 4/24 | G175: SP 24.4.2 | H175: 8 | I175: =IF(D175>0,(((H175*E175)*C175)/D175),"") -> 49.090909
A176: Aprendizagem Digital | B176: Aprendizagem | C176: 4 | D176: 5.5 | E176: 7.5 | F176: PI 4/24 | G176: SP 24.4.3 | H176: 8 | I176: =IF(D176>0,(((H176*E176)*C176)/D176),"") -> 43.636364
A177: Aprendizagem Digital | B177: Aprendizagem | C177: 5 | D177: 5.5 | E177: 7.5 | F177: PI 4/24 | G177: SP 24.4.4 | H177: 6 | I177: =IF(D177>0,(((H177*E177)*C177)/D177),"") -> 40.909091
A178: Aprendizagem Digital | B178: Aprendizagem | C178: 5 | D178: 5.5 | E178: 7.5 | F178: PI 4/24 | G178: SP 24.4.5 | H178: 8 | I178: =IF(D178>0,(((H178*E178)*C178)/D178),"") -> 54.545455
A179: Aprendizagem Digital | B179: Aprendizagem | C179: 5 | D179: 5.5 | E179: 7.5 | F179: PI 4/24 | G179: SP 24.4.6 | H179: 8 | I179: =IF(D179>0,(((H179*E179)*C179)/D179),"") -> 54.545455
A180: Aprendizagem Digital | B180: Avaliação | C180: 7 | D180: 14 | E180: 7.5 | F180: PI 1/24 | G180: SP 24.1.1 | H180: 7 | I180: =IF(D180>0,(((H180*E180)*C180)/D180),"") -> 26.25
A181: Aprendizagem Digital | B181: Avaliação | C181: 5 | D181: 14 | E181: 7.5 | F181: PI 1/24 | G181: SP 24.1.1 | H181: 7 | I181: =IF(D181>0,(((H181*E181)*C181)/D181),"") -> 18.75
A182: Aprendizagem Digital | B182: Avaliação | C182: 7 | D182: 14 | E182: 7.5 | F182: PI 1/24 | G182: SP 24.1.2 | H182: 6 | I182: =IF(D182>0,(((H182*E182)*C182)/D182),"") -> 22.5
A183: Aprendizagem Digital | B183: Avaliação | C183: 6 | D183: 14 | E183: 7.5 | F183: PI 1/24 | G183: SP 24.1.2 | H183: 6 | I183: =IF(D183>0,(((H183*E183)*C183)/D183),"") -> 19.285714
A184: Aprendizagem Digital | B184: Avaliação | C184: 8 | D184: 14 | E184: 7.5 | F184: PI 1/24 | G184: SP 24.1.3 | H184: 8 | I184: =IF(D184>0,(((H184*E184)*C184)/D184),"") -> 34.285714
A185: Aprendizagem Digital | B185: Avaliação | C185: 6 | D185: 14 | E185: 7.5 | F185: PI 1/24 | G185: SP 24.1.3 | H185: 8 | I185: =IF(D185>0,(((H185*E185)*C185)/D185),"") -> 25.714286
... A201: Aprendizagem Digital | B201: Avaliação | C201: 6 | D201: 7 | E201: 7.5 | F201: PI 2/24 | G201: SP 24.2.5 | H201: 4 | I201: =IF(D201>0,(((H201*E201)*C201)/D201),"") -> 25.714286
A202: Aprendizagem Digital | B202: Avaliação | C202: 5 | D202: 6 | E202: 7.5 | F202: PI 3/24 | G202: SP 24.3.1 | H202: =IF(G202>0,VLOOKUP(G202,Apoio!$O$2:$P$24,2,0),"") -> 12 | I202: =IF(D202>0,(((H202*E202)*C202)/D202),"") -> 75
A203: Aprendizagem Digital | B203: Avaliação | C203: 5 | D203: 6 | E203: 7.5 | F203: PI 3/24 | G203: SP 24.3.2 | H203: =IF(G203>0,VLOOKUP(G203,Apoio!$O$2:$P$24,2,0),"") -> 8 | I203: =IF(D203>0,(((H203*E203)*C203)/D203),"") -> 50
A204: Aprendizagem Digital | B204: Avaliação | C204: 5 | D204: 6 | E204: 7.5 | F204: PI 3/24 | G204: SP 24.3.3 | H204: =IF(G204>0,VLOOKUP(G204,Apoio!$O$2:$P$24,2,0),"") -> 8 | I204: =IF(D204>0,(((H204*E204)*C204)/D204),"") -> 50
A205: Aprendizagem Digital | B205: Avaliação | C205: 5 | D205: 6 | E205: 7.5 | F205: PI 3/24 | G205: SP 24.3.4 | H205: =IF(G205>0,VLOOKUP(G205,Apoio!$O$2:$P$24,2,0),"") -> 8 | I205: =IF(D205>0,(((H205*E205)*C205)/D205),"") -> 50
A206: Aprendizagem Digital | B206: Avaliação | C206: 4 | D206: 6 | E206: 7.5 | F206: PI 3/24 | G206: SP 24.3.5 | H206: =IF(G206>0,VLOOKUP(G206,Apoio!$O$2:$P$24,2,0),"") -> 8 | I206: =IF(D206>0,(((H206*E206)*C206)/D206),"") -> 40
A207: Aprendizagem Digital | B207: Avaliação | C207: 5 | D207: 6 | E207: 7.5 | F207: PI 3/24 | G207: SP 24.3.6 | H207: =IF(G207>0,VLOOKUP(G207,Apoio!$O$2:$P$24,2,0),"") -> 3 | I207: =IF(D207>0,(((H207*E207)*C207)/D207),"") -> 18.75
A208: Aprendizagem Digital | B208: Avaliação | C208: 5 | D208: 5.5 | E208: 7.5 | F208: PI 4/24 | G208: SP 24.4.1 | H208: 12 | I208: =IF(D208>0,(((H208*E208)*C208)/D208),"") -> 81.818182
A209: Aprendizagem Digital | B209: Avaliação | C209: 5 | D209: 5.5 | E209: 7.5 | F209: PI 4/24 | G209: SP 24.4.2 | H209: 8 | I209: =IF(D209>0,(((H209*E209)*C209)/D209),"") -> 54.545455
A210: Aprendizagem Digital | B210: Avaliação | C210: 6.5 | D210: 5.5 | E210: 7.5 | F210: PI 4/24 | G210: SP 24.4.3 | H210: 8 | I210: =IF(D210>0,(((H210*E210)*C210)/D210),"") -> 70.909091
A211: Aprendizagem Digital | B211: Avaliação | C211: 6 | D211: 5.5 | E211: 7.5 | F211: PI 4/24 | G211: SP 24.4.4 | H211: 6 | I211: =IF(D211>0,(((H211*E211)*C211)/D211),"") -> 49.090909
A212: Aprendizagem Digital | B212: Avaliação | C212: 7 | D212: 5.5 | E212: 7.5 | F212: PI 4/24 | G212: SP 24.4.5 | H212: 8 | I212: =IF(D212>0,(((H212*E212)*C212)/D212),"") -> 76.363636
A213: Aprendizagem Digital | B213: Avaliação | C213: 5 | D213: 5.5 | E213: 7.5 | F213: PI 4/24 | G213: SP 24.4.6 | H213: 8 | I213: =IF(D213>0,(((H213*E213)*C213)/D213),"") -> 54.545455
A214: Aprendizagem Digital | B214: Comunicação | C214: 6 | D214: 15 | E214: 7.5 | F214: PI 1/24 | G214: SP 24.1.1 | H214: 7 | I214: =IF(D214>0,(((H214*E214)*C214)/D214),"") -> 21
A215: Aprendizagem Digital | B215: Comunicação | C215: 6 | D215: 15 | E215: 7.5 | F215: PI 1/24 | G215: SP 24.1.1 | H215: 7 | I215: =IF(D215>0,(((H215*E215)*C215)/D215),"") -> 21
A216: Aprendizagem Digital | B216: Comunicação | C216: 6 | D216: 15 | E216: 7.5 | F216: PI 1/24 | G216: SP 24.1.2 | H216: 6 | I216: =IF(D216>0,(((H216*E216)*C216)/D216),"") -> 18
A217: Aprendizagem Digital | B217: Comunicação | C217: 6 | D217: 15 | E217: 7.5 | F217: PI 1/24 | G217: SP 24.1.2 | H217: 6 | I217: =IF(D217>0,(((H217*E217)*C217)/D217),"") -> 18
A218: Aprendizagem Digital | B218: Comunicação | C218: 6 | D218: 15 | E218: 7.5 | F218: PI 1/24 | G218: SP 24.1.3 | H218: 8 | I218: =IF(D218>0,(((H218*E218)*C218)/D218),"") -> 24
A219: Aprendizagem Digital | B219: Comunicação | C219: 6 | D219: 15 | E219: 7.5 | F219: PI 1/24 | G219: SP 24.1.3 | H219: 8 | I219: =IF(D219>0,(((H219*E219)*C219)/D219),"") -> 24
... A269: Aprendizagem Digital | B269: Docencia | C269: 6 | D269: 7 | E269: 7.5 | F269: PI 2/24 | G269: SP 24.2.5 | H269: 4 | I269: =IF(D269>0,(((H269*E269)*C269)/D269),"") -> 25.714286
A270: Aprendizagem Digital | B270: Docencia | C270: 5 | D270: 6 | E270: 7.5 | F270: PI 3/24 | G270: SP 24.3.1 | H270: =IF(G270>0,VLOOKUP(G270,Apoio!$O$2:$P$24,2,0),"") -> 12 | I270: =IF(D270>0,(((H270*E270)*C270)/D270),"") -> 75
A271: Aprendizagem Digital | B271: Docencia | C271: 5 | D271: 6 | E271: 7.5 | F271: PI 3/24 | G271: SP 24.3.2 | H271: =IF(G271>0,VLOOKUP(G271,Apoio!$O$2:$P$24,2,0),"") -> 8 | I271: =IF(D271>0,(((H271*E271)*C271)/D271),"") -> 50
A272: Aprendizagem Digital | B272: Docencia | C272: 6 | D272: 6 | E272: 7.5 | F272: PI 3/24 | G272: SP 24.3.3 | H272: =IF(G272>0,VLOOKUP(G272,Apoio!$O$2:$P$24,2,0),"") -> 8 | I272: =IF(D272>0,(((H272*E272)*C272)/D272),"") -> 60
A273: Aprendizagem Digital | B273: Docencia | C273: 6 | D273: 6 | E273: 7.5 | F273: PI 3/24 | G273: SP 24.3.4 | H273: =IF(G273>0,VLOOKUP(G273,Apoio!$O$2:$P$24,2,0),"") -> 8 | I273: =IF(D273>0,(((H273*E273)*C273)/D273),"") -> 60
A274: Aprendizagem Digital | B274: Docencia | C274: 7 | D274: 6 | E274: 7.5 | F274: PI 3/24 | G274: SP 24.3.5 | H274: =IF(G274>0,VLOOKUP(G274,Apoio!$O$2:$P$24,2,0),"") -> 8 | I274: =IF(D274>0,(((H274*E274)*C274)/D274),"") -> 70
A275: Aprendizagem Digital | B275: Docencia | C275: 7 | D275: 6 | E275: 7.5 | F275: PI 3/24 | G275: SP 24.3.6 | H275: =IF(G275>0,VLOOKUP(G275,Apoio!$O$2:$P$24,2,0),"") -> 3 | I275: =IF(D275>0,(((H275*E275)*C275)/D275),"") -> 26.25
A276: Aprendizagem Digital | B276: Docencia | C276: 7 | D276: 5.5 | E276: 7.5 | F276: PI 4/24 | G276: SP 24.4.1 | H276: 12 | I276: =IF(D276>0,(((H276*E276)*C276)/D276),"") -> 114.54545
A277: Aprendizagem Digital | B277: Docencia | C277: 7 | D277: 5.5 | E277: 7.5 | F277: PI 4/24 | G277: SP 24.4.2 | H277: 8 | I277: =IF(D277>0,(((H277*E277)*C277)/D277),"") -> 76.363636
A278: Aprendizagem Digital | B278: Docencia | C278: 7 | D278: 5.5 | E278: 7.5 | F278: PI 4/24 | G278: SP 24.4.3 | H278: 8 | I278: =IF(D278>0,(((H278*E278)*C278)/D278),"") -> 76.363636
A279: Aprendizagem Digital | B279: Docencia | C279: 7 | D279: 5.5 | E279: 7.5 | F279: PI 4/24 | G279: SP 24.4.4 | H279: 6 | I279: =IF(D279>0,(((H279*E279)*C279)/D279),"") -> 57.272727
A280: Aprendizagem Digital | B280: Docencia | C280: 7 | D280: 5.5 | E280: 7.5 | F280: PI 4/24 | G280: SP 24.4.5 | H280: 8 | I280: =IF(D280>0,(((H280*E280)*C280)/D280),"") -> 76.363636
A281: Aprendizagem Digital | B281: Docencia | C281: 7 | D281: 5.5 | E281: 7.5 | F281: PI 4/24 | G281: SP 24.4.6 | H281: 8 | I281: =IF(D281>0,(((H281*E281)*C281)/D281),"") -> 76.363636
A282: Aprendizagem Digital | B282: Financeiro | C282: 5 | D282: 7.6 | E282: 7.5 | F282: PI 1/24 | G282: SP 24.1.1 | H282: 7 | I282: =IF(D282>0,(((H282*E282)*C282)/D282),"") -> 34.539474
A283: Aprendizagem Digital | B283: Financeiro | C283: 5 | D283: 7.6 | E283: 7.5 | F283: PI 1/24 | G283: SP 24.1.1 | H283: 7 | I283: =IF(D283>0,(((H283*E283)*C283)/D283),"") -> 34.539474
A284: Aprendizagem Digital | B284: Financeiro | C284: 5 | D284: 7.6 | E284: 7.5 | F284: PI 1/24 | G284: SP 24.1.2 | H284: 6 | I284: =IF(D284>0,(((H284*E284)*C284)/D284),"") -> 29.605263
A285: Aprendizagem Digital | B285: Financeiro | C285: 5 | D285: 7.6 | E285: 7.5 | F285: PI 1/24 | G285: SP 24.1.2 | H285: 6 | I285: =IF(D285>0,(((H285*E285)*C285)/D285),"") -> 29.605263
A286: Aprendizagem Digital | B286: Financeiro | C286: 5 | D286: 7.6 | E286: 7.5 | F286: PI 1/24 | G286: SP 24.1.3 | H286: 8 | I286: =IF(D286>0,(((H286*E286)*C286)/D286),"") -> 39.473684
A287: Aprendizagem Digital | B287: Financeiro | C287: 5 | D287: 7.6 | E287: 7.5 | F287: PI 1/24 | G287: SP 24.1.3 | H287: 8 | I287: =IF(D287>0,(((H287*E287)*C287)/D287),"") -> 39.473684
... A303: Aprendizagem Digital | B303: Financeiro | C303: 6 | D303: 8 | E303: 7.5 | F303: PI 2/24 | G303: SP 24.2.5 | H303: 4 | I303: =IF(D303>0,(((H303*E303)*C303)/D303),"") -> 22.5
A304: Aprendizagem Digital | B304: Financeiro | C304: 4.2 | D304: 4.3 | E304: 7.5 | F304: PI 3/24 | G304: SP 24.3.1 | H304: =IF(G304>0,VLOOKUP(G304,Apoio!$O$2:$P$24,2,0),"") -> 12 | I304: =IF(D304>0,(((H304*E304)*C304)/D304),"") -> 87.906977
A305: Aprendizagem Digital | B305: Financeiro | C305: 4 | D305: 4.3 | E305: 7.5 | F305: PI 3/24 | G305: SP 24.3.2 | H305: =IF(G305>0,VLOOKUP(G305,Apoio!$O$2:$P$24,2,0),"") -> 8 | I305: =IF(D305>0,(((H305*E305)*C305)/D305),"") -> 55.813953
A306: Aprendizagem Digital | B306: Financeiro | C306: 3 | D306: 4.3 | E306: 7.5 | F306: PI 3/24 | G306: SP 24.3.3 | H306: =IF(G306>0,VLOOKUP(G306,Apoio!$O$2:$P$24,2,0),"") -> 8 | I306: =IF(D306>0,(((H306*E306)*C306)/D306),"") -> 41.860465
A307: Aprendizagem Digital | B307: Financeiro | C307: 5 | D307: 4.3 | E307: 7.5 | F307: PI 3/24 | G307: SP 24.3.4 | H307: 8 | I307: =IF(D307>0,(((H307*E307)*C307)/D307),"") -> 69.767442
A308: Aprendizagem Digital | B308: Financeiro | C308: 6 | D308: 4.3 | E308: 7.5 | F308: PI 3/24 | G308: SP 24.3.5 | H308: 8 | I308: =IF(D308>0,(((H308*E308)*C308)/D308),"") -> 83.72093
A309: Aprendizagem Digital | B309: Financeiro | C309: 5 | D309: 4.3 | E309: 7.5 | F309: PI 3/24 | G309: SP 24.3.6 | H309: 3 | I309: =IF(D309>0,(((H309*E309)*C309)/D309),"") -> 26.162791
A310: Aprendizagem Digital | B310: Financeiro | C310: 4.5 | D310: 5.6 | E310: 7.5 | F310: PI 4/24 | G310: SP 24.4.1 | H310: 12 | I310: =IF(D310>0,(((H310*E310)*C310)/D310),"") -> 72.321429
A311: Aprendizagem Digital | B311: Financeiro | C311: 3.5 | D311: 5.6 | E311: 7.5 | F311: PI 4/24 | G311: SP 24.4.2 | H311: 8 | I311: =IF(D311>0,(((H311*E311)*C311)/D311),"") -> 37.5
A312: Aprendizagem Digital | B312: Financeiro | C312: 5 | D312: 5.6 | E312: 7.5 | F312: PI 4/24 | G312: SP 24.4.3 | H312: 8 | I312: =IF(D312>0,(((H312*E312)*C312)/D312),"") -> 53.571429
A313: Aprendizagem Digital | B313: Financeiro | C313: 5 | D313: 5.6 | E313: 7.5 | F313: PI 4/24 | G313: SP 24.4.4 | H313: 6 | I313: =IF(D313>0,(((H313*E313)*C313)/D313),"") -> 40.178571
A314: Aprendizagem Digital | B314: Financeiro | C314: 5 | D314: 5.6 | E314: 7.5 | F314: PI 4/24 | G314: SP 24.4.5 | H314: 8 | I314: =IF(D314>0,(((H314*E314)*C314)/D314),"") -> 53.571429
A315: Aprendizagem Digital | B315: Financeiro | C315: 5 | D315: 5.6 | E315: 7.5 | F315: PI 4/24 | G315: SP 24.4.6 | H315: 8 | I315: =IF(D315>0,(((H315*E315)*C315)/D315),"") -> 53.571429
A316: Aprendizagem Digital | B316: Interação | C316: 5.2 | D316: 4.8 | E316: 7.5 | F316: PI 3/24 | G316: SP 24.3.1 | H316: =IF(G316>0,VLOOKUP(G316,Apoio!$O$2:$P$24,2,0),"") -> 12 | I316: =IF(D316>0,(((H316*E316)*C316)/D316),"") -> 97.5
A317: Aprendizagem Digital | B317: Interação | C317: 7.2 | D317: 4.8 | E317: 7.5 | F317: PI 3/24 | G317: SP 24.3.2 | H317: =IF(G317>0,VLOOKUP(G317,Apoio!$O$2:$P$24,2,0),"") -> 8 | I317: =IF(D317>0,(((H317*E317)*C317)/D317),"") -> 90
A318: Aprendizagem Digital | B318: Interação | C318: 7 | D318: 4.8 | E318: 7.5 | F318: PI 3/24 | G318: SP 24.3.3 | H318: =IF(G318>0,VLOOKUP(G318,Apoio!$O$2:$P$24,2,0),"") -> 8 | I318: =IF(D318>0,(((H318*E318)*C318)/D318),"") -> 87.5
A319: Aprendizagem Digital | B319: Interação | C319: 6 | D319: 4.8 | E319: 7.5 | F319: PI 3/24 | G319: SP 24.3.4 | H319: =IF(G319>0,VLOOKUP(G319,Apoio!$O$2:$P$24,2,0),"") -> 8 | I319: =IF(D319>0,(((H319*E319)*C319)/D319),"") -> 75
...

Sheet 2025
A1: Jornada | B1: Time | C1: Qtde de Devs | D1: Produtividade (H/P) | E1: Horas Produtivas por dia e por Dev | F1: PI | G1: Sprint | H1: Dias Úteis da Sprint | I1: Velocity | J1: Sustentação | K1: Status Time
A2: Administrativo | B2: kbots | C2: 4 | D2: 5.3 | E2: 7 | F2: PI 1/25 | G2: SP 25.1.1 | H2: =IF(G2>0,VLOOKUP(G2,Apoio!$H$2:$I$24,2,0),"") -> 7 | I2: =IF(D2>0,(((H2*E2)*C2)/D2),"") -> 36.981132
A3: Administrativo | B3: kbots | C3: 4 | D3: 5.3 | E3: 7 | F3: PI 1/25 | G3: SP 25.1.2 | H3: =IF(G3>0,VLOOKUP(G3,Apoio!$H$2:$I$24,2,0),"") -> 8 | I3: =IF(D3>0,(((H3*E3)*C3)/D3),"") -> 42.264151
A4: Administrativo | B4: kbots | C4: 4 | D4: 5.3 | E4: 7 | F4: PI 1/25 | G4: SP 25.1.3 | H4: =IF(G4>0,VLOOKUP(G4,Apoio!$H$2:$I$24,2,0),"") -> 8 | I4: =IF(D4>0,(((H4*E4)*C4)/D4),"") -> 42.264151
A5: Administrativo | B5: kbots | C5: 4 | D5: 5.3 | E5: 7 | F5: PI 1/25 | G5: SP 25.1.4 | H5: =IF(G5>0,VLOOKUP(G5,Apoio!$H$2:$I$24,2,0),"") -> 6 | I5: =IF(D5>0,(((H5*E5)*C5)/D5),"") -> 31.698113
A6: Administrativo | B6: kbots | C6: 4 | D6: 5.3 | E6: 7 | F6: PI 1/25 | G6: SP 25.1.5 | H6: =IF(G6>0,VLOOKUP(G6,Apoio!$H$2:$I$24,2,0),"") -> 8 | I6: =IF(D6>0,(((H6*E6)*C6)/D6),"") -> 42.264151
A7: Administrativo | B7: kbots | C7: 4 | D7: 5.3 | E7: 7 | F7: PI 1/25 | G7: SP 25.1.6 | H7: =IF(G7>0,VLOOKUP(G7,Apoio!$H$2:$I$24,2,0),"") -> 3 | I7: =IF(D7>0,(((H7*E7)*C7)/D7),"") -> 15.849057
A8: Administrativo | B8: kbots | C8: 4 | D8: 8 | E8: 7 | F8: PI 2/25 | G8: SP 25.2.1 | H8: =IF(G8>0,VLOOKUP(G8,Apoio!$H$2:$I$24,2,0),"") -> 6 | I8: =IF(D8>0,(((H8*E8)*C8)/D8),"") -> 21
A9: Administrativo | B9: kbots | C9: 4 | D9: 8 | E9: 7 | F9: PI 2/25 | G9: SP 25.2.2 | H9: =IF(G9>0,VLOOKUP(G9,Apoio!$H$2:$I$24,2,0),"") -> 7 | I9: =IF(D9>0,(((H9*E9)*C9)/D9),"") -> 24.5
A10: Administrativo | B10: kbots | C10: 4 | D10: 8 | E10: 7 | F10: PI 2/25 | G10: SP 25.2.3 | H10: =IF(G10>0,VLOOKUP(G10,Apoio!$H$2:$I$24,2,0),"") -> 8 | I10: =IF(D10>0,(((H10*E10)*C10)/D10),"") -> 28
A11: Administrativo | B11: kbots | C11: 4 | D11: 8 | E11: 7 | F11: PI 2/25 | G11: SP 25.2.4 | H11: =IF(G11>0,VLOOKUP(G11,Apoio!$H$2:$I$24,2,0),"") -> 8 | I11: =IF(D11>0,(((H11*E11)*C11)/D11),"") -> 28
A12: Administrativo | B12: kbots | C12: 4 | D12: 8 | E12: 7 | F12: PI 2/25 | G12: SP 25.2.5 | H12: =IF(G12>0,VLOOKUP(G12,Apoio!$H$2:$I$24,2,0),"") -> 7 | I12: =IF(D12>0,(((H12*E12)*C12)/D12),"") -> 24.5
A13: Administrativo | B13: kbots | C13: 4 | D13: 8 | E13: 7 | F13: PI 2/25 | G13: SP 25.2.6 | H13: =IF(G13>0,VLOOKUP(G13,Apoio!$H$2:$I$24,2,0),"") -> 3 | I13: =IF(D13>0,(((H13*E13)*C13)/D13),"") -> 10.5
... A89: Atendimento & Serviço | B89: Athenas Atendimento | C89: 6 | D89: 5 | E89: 7 | F89: PI 3/25 | G89: SP 25.3.1 | H89: =IF(G89>0,VLOOKUP(G89,Apoio!$H$2:$I$24,2,0),"") -> 7 | I89: =IF(D89>0,(((H89*E89)*C89)/D89),"") -> 58.8
A90: Atendimento & Serviço | B90: Athenas Atendimento | C90: 6 | D90: 5 | E90: 7 | F90: PI 3/25 | G90: SP 25.3.2 | H90: =IF(G90>0,VLOOKUP(G90,Apoio!$H$2:$I$24,2,0),"") -> 8 | I90: =IF(D90>0,(((H90*E90)*C90)/D90),"") -> 67.2 | O90: =625-116 -> 509
A91: Atendimento & Serviço | B91: Athenas Atendimento | C91: 6 | D91: 5 | E91: 7 | F91: PI 3/25 | G91: SP 25.3.3 | H91: =IF(G91>0,VLOOKUP(G91,Apoio!$H$2:$I$24,2,0),"") -> 8 | I91: =IF(D91>0,(((H91*E91)*C91)/D91),"") -> 67.2
A92: Atendimento & Serviço | B92: Athenas Atendimento | C92: 6 | D92: 5 | E92: 7 | F92: PI 3/25 | G92: SP 25.3.4 | H92: =IF(G92>0,VLOOKUP(G92,Apoio!$H$2:$I$24,2,0),"") -> 13 | I92: =IF(D92>0,(((H92*E92)*C92)/D92),"") -> 109.2
A93: Atendimento & Serviço | B93: Athenas Atendimento | C93: 6 | D93: 5 | E93: 7 | F93: PI 3/25 | G93: SP 25.3.5 | H93: =IF(G93>0,VLOOKUP(G93,Apoio!$H$2:$I$24,2,0),"") -> 3 | I93: =IF(D93>0,(((H93*E93)*C93)/D93),"") -> 25.2
A94: Atendimento & Serviço | B94: Athenas Atendimento | C94: 6 | D94: 6 | E94: 6 | F94: PI 4/25 | G94: SP 25.4.1 | H94: =IF(G94>0,VLOOKUP(G94,Apoio!$H$2:$I$24,2,0),"") -> 13 | I94: =IF(D94>0,(((H94*E94)*C94)/D94),"") -> 78
A95: Atendimento & Serviço | B95: Athenas Atendimento | C95: 6 | D95: 6 | E95: 6 | F95: PI 4/25 | G95: SP 25.4.2 | H95: =IF(G95>0,VLOOKUP(G95,Apoio!$H$2:$I$24,2,0),"") -> 8 | I95: =IF(D95>0,(((H95*E95)*C95)/D95),"") -> 48
A96: Atendimento & Serviço | B96: Athenas Atendimento | C96: 6 | D96: 6 | E96: 6 | F96: PI 4/25 | G96: SP 25.4.3 | H96: =IF(G96>0,VLOOKUP(G96,Apoio!$H$2:$I$24,2,0),"") -> 8 | I96: =IF(D96>0,(((H96*E96)*C96)/D96),"") -> 48
A97: Atendimento & Serviço | B97: Athenas Atendimento | C97: 6 | D97: 6 | E97: 6 | F97: PI 4/25 | G97: SP 25.4.4 | H97: =IF(G97>0,VLOOKUP(G97,Apoio!$H$2:$I$24,2,0),"") -> 7 | I97: =IF(D97>0,(((H97*E97)*C97)/D97),"") -> 42
A98: Atendimento & Serviço | B98: Athenas Atendimento | C98: 6 | D98: 6 | E98: 6 | F98: PI 4/25 | G98: SP 25.4.5 | H98: =IF(G98>0,VLOOKUP(G98,Apoio!$H$2:$I$24,2,0),"") -> 8 | I98: =IF(D98>0,(((H98*E98)*C98)/D98),"") -> 48
A99: Atendimento & Serviço | B99: Athenas Atendimento | C99: 6 | D99: 6 | E99: 6 | F99: PI 4/25 | G99: SP 25.4.6 | H99: =IF(G99>0,VLOOKUP(G99,Apoio!$H$2:$I$24,2,0),"") -> 8 | I99: =IF(D99>0,(((H99*E99)*C99)/D99),"") -> 48
A100: Atendimento & Serviço | B100: Athenas Atendimento | C100: 6 | D100: 6 | E100: 6 | F100: PI 4/25 | G100: SP 25.4.6 | H100: =IF(G100>0,VLOOKUP(G100,Apoio!$H$2:$I$24,2,0),"") -> 8 | I100: =IF(D100>0,(((H100*E100)*C100)/D100),"") -> 48
A101: Administrativo | B101: Athenas Sec. Enturmação | C101: 6 | D101: 7 | E101: 7 | F101: PI 1/25 | G101: SP 25.1.1 | H101: =IF(G101>0,VLOOKUP(G101,Apoio!$H$2:$I$24,2,0),"") -> 7 | I101: =IF(D101>0,(((H101*E101)*C101)/D101),"") -> 42
A102: Administrativo | B102: Athenas Sec. Enturmação | C102: 6 | D102: 7 | E102: 7 | F102: PI 1/25 | G102: SP 25.1.2 | H102: =IF(G102>0,VLOOKUP(G102,Apoio!$H$2:$I$24,2,0),"") -> 8 | I102: =IF(D102>0,(((H102*E102)*C102)/D102),"") -> 48
... A114: Secretaria & Gestor de Unidades | B114: Athenas Sec. Enturmação | C114: 6 | D114: 4.4 | E114: 7 | F114: PI 3/25 | G114: SP 25.3.2 | H114: =IF(G114>0,VLOOKUP(G114,Apoio!$H$2:$I$24,2,0),"") -> 8 | I114: =IF(D114>0,(((H114*E114)*C114)/D114),"") -> 76.363636
A115: Secretaria & Gestor de Unidades | B115: Athenas Sec. Enturmação | C115: 6 | D115: 4.4 | E115: 7 | F115: PI 3/25 | G115: SP 25.3.3 | H115: =IF(G115>0,VLOOKUP(G115,Apoio!$H$2:$I$24,2,0),"") -> 8 | I115: =IF(D115>0,(((H115*E115)*C115)/D115),"") -> 76.363636 | L115: -1 dev | M115: -2 dev (a partir da 4)
A116: Secretaria & Gestor de Unidades | B116: Athenas Sec. Enturmação | C116: 6 | D116: 4.4 | E116: 7 | F116: PI 3/25 | G116: SP 25.3.4 | H116: =IF(G116>0,VLOOKUP(G116,Apoio!$H$2:$I$24,2,0),"") -> 13 | I116: =IF(D116>0,(((H116*E116)*C116)/D116),"") -> 124.09091
A117: Secretaria & Gestor de Unidades | B117: Athenas Sec. Enturmação | C117: 6 | D117: 4.4 | E117: 7 | F117: PI 3/25 | G117: SP 25.3.5 | H117: =IF(G117>0,VLOOKUP(G117,Apoio!$H$2:$I$24,2,0),"") -> 3 | I117: =IF(D117>0,(((H117*E117)*C117)/D117),"") -> 28.636364
A118: Secretaria & Gestor de Unidades | B118: Athenas Sec. Enturmação | C118: 4 | D118: 4.4 | E118: 6 | F118: PI 4/25 | G118: SP 25.4.1 | H118: =IF(G118>0,VLOOKUP(G118,Apoio!$H$2:$I$24,2,0),"") -> 13 | I118: =IF(D118>0,(((H118*E118)*C118)/D118),"") -> 70.909091
A119: Secretaria & Gestor de Unidades | B119: Athenas Sec. Enturmação | C119: 4 | D119: 4.4 | E119: 6 | F119: PI 4/25 | G119: SP 25.4.2 | H119: =IF(G119>0,VLOOKUP(G119,Apoio!$H$2:$I$24,2,0),"") -> 8 | I119: =IF(D119>0,(((H119*E119)*C119)/D119),"") -> 43.636364
A120: Secretaria & Gestor de Unidades | B120: Athenas Sec. Enturmação | C120: 4 | D120: 4.4 | E120: 6 | F120: PI 4/25 | G120: SP 25.4.3 | H120: =IF(G120>0,VLOOKUP(G120,Apoio!$H$2:$I$24,2,0),"") -> 8 | I120: =IF(D120>0,(((H120*E120)*C120)/D120),"") -> 43.636364
A121: Secretaria & Gestor de Unidades | B121: Athenas Sec. Enturmação | C121: 4 | D121: 4.4 | E121: 6 | F121: PI 4/25 | G121: SP 25.4.4 | H121: =IF(G121>0,VLOOKUP(G121,Apoio!$H$2:$I$24,2,0),"") -> 7 | I121: =IF(D121>0,(((H121*E121)*C121)/D121),"") -> 38.181818
A122: Secretaria & Gestor de Unidades | B122: Athenas Sec. Enturmação | C122: 4 | D122: 4.4 | E122: 6 | F122: PI 4/25 | G122: SP 25.4.5 | H122: =IF(G122>0,VLOOKUP(G122,Apoio!$H$2:$I$24,2,0),"") -> 8 | I122: =IF(D122>0,(((H122*E122)*C122)/D122),"") -> 43.636364
A123: Secretaria & Gestor de Unidades | B123: Athenas Sec. Enturmação | C123: 4 | D123: 4.4 | E123: 6 | F123: PI 4/25 | G123: SP 25.4.6 | H123: =IF(G123>0,VLOOKUP(G123,Apoio!$H$2:$I$24,2,0),"") -> 8 | I123: =IF(D123>0,(((H123*E123)*C123)/D123),"") -> 43.636364
A124: Administrativo | B124: Athenas Sec. Gestão Acad. | C124: 6 | D124: 7 | E124: 7 | F124: PI 1/25 | G124: SP 25.1.1 | H124: =IF(G124>0,VLOOKUP(G124,Apoio!$H$2:$I$24,2,0),"") -> 7 | I124: =IF(D124>0,(((H124*E124)*C124)/D124),"") -> 42
A125: Administrativo | B125: Athenas Sec. Gestão Acad. | C125: 6 | D125: 7 | E125: 7 | F125: PI 1/25 | G125: SP 25.1.2 | H125: =IF(G125>0,VLOOKUP(G125,Apoio!$H$2:$I$24,2,0),"") -> 8 | I125: =IF(D125>0,(((H125*E125)*C125)/D125),"") -> 48
A126: Administrativo | B126: Athenas Sec. Gestão Acad. | C126: 6 | D126: 7 | E126: 7 | F126: PI 1/25 | G126: SP 25.1.3 | H126: =IF(G126>0,VLOOKUP(G126,Apoio!$H$2:$I$24,2,0),"") -> 8 | I126: =IF(D126>0,(((H126*E126)*C126)/D126),"") -> 48
A127: Administrativo | B127: Athenas Sec. Gestão Acad. | C127: 6 | D127: 7 | E127: 7 | F127: PI 1/25 | G127: SP 25.1.4 | H127: =IF(G127>0,VLOOKUP(G127,Apoio!$H$2:$I$24,2,0),"") -> 6 | I127: =IF(D127>0,(((H127*E127)*C127)/D127),"") -> 36
... A181: Administrativo | B181: Thanos | C181: 6 | D181: 5.6 | E181: 7 | F181: PI 2/25 | G181: SP 25.2.6 | H181: =IF(G181>0,VLOOKUP(G181,Apoio!$H$2:$I$24,2,0),"") -> 3 | I181: =IF(D181>0,(((H181*E181)*C181)/D181),"") -> 22.5
A182: Secretaria & Gestor de Unidades | B182: Thanos | C182: 6 | D182: 6 | E182: 7 | F182: PI 3/25 | G182: SP 25.3.1 | H182: =IF(G182>0,VLOOKUP(G182,Apoio!$H$2:$I$24,2,0),"") -> 7 | I182: =IF(D182>0,(((H182*E182)*C182)/D182),"") -> 49 | M182: -1 dev (a partir da 4)
A183: Secretaria & Gestor de Unidades | B183: Thanos | C183: 6 | D183: 6 | E183: 7 | F183: PI 3/25 | G183: SP 25.3.2 | H183: =IF(G183>0,VLOOKUP(G183,Apoio!$H$2:$I$24,2,0),"") -> 8 | I183: =IF(D183>0,(((H183*E183)*C183)/D183),"") -> 56
A184: Secretaria & Gestor de Unidades | B184: Thanos | C184: 6 | D184: 6 | E184: 7 | F184: PI 3/25 | G184: SP 25.3.3 | H184: =IF(G184>0,VLOOKUP(G184,Apoio!$H$2:$I$24,2,0),"") -> 8 | I184: =IF(D184>0,(((H184*E184)*C184)/D184),"") -> 56
A185: Secretaria & Gestor de Unidades | B185: Thanos | C185: 6 | D185: 6 | E185: 7 | F185: PI 3/25 | G185: SP 25.3.4 | H185: =IF(G185>0,VLOOKUP(G185,Apoio!$H$2:$I$24,2,0),"") -> 13 | I185: =IF(D185>0,(((H185*E185)*C185)/D185),"") -> 91
A186: Secretaria & Gestor de Unidades | B186: Thanos | C186: 6 | D186: 6 | E186: 7 | F186: PI 3/25 | G186: SP 25.3.5 | H186: =IF(G186>0,VLOOKUP(G186,Apoio!$H$2:$I$24,2,0),"") -> 3 | I186: =IF(D186>0,(((H186*E186)*C186)/D186),"") -> 21
A187: Secretaria & Gestor de Unidades | B187: Thanos | C187: 5 | D187: 4.8 | E187: 7 | F187: PI 4/25 | G187: SP 25.4.1 | H187: =IF(G187>0,VLOOKUP(G187,Apoio!$H$2:$I$24,2,0),"") -> 13 | I187: =IF(D187>0,(((H187*E187)*C187)/D187),"") -> 94.791667
A188: Secretaria & Gestor de Unidades | B188: Thanos | C188: 5 | D188: 4.8 | E188: 7 | F188: PI 4/25 | G188: SP 25.4.2 | H188: =IF(G188>0,VLOOKUP(G188,Apoio!$H$2:$I$24,2,0),"") -> 8 | I188: =IF(D188>0,(((H188*E188)*C188)/D188),"") -> 58.333333
A189: Secretaria & Gestor de Unidades | B189: Thanos | C189: 5 | D189: 4.8 | E189: 7 | F189: PI 4/25 | G189: SP 25.4.3 | H189: =IF(G189>0,VLOOKUP(G189,Apoio!$H$2:$I$24,2,0),"") -> 8 | I189: =IF(D189>0,(((H189*E189)*C189)/D189),"") -> 58.333333
A190: Secretaria & Gestor de Unidades | B190: Thanos | C190: 5 | D190: 4.8 | E190: 7 | F190: PI 4/25 | G190: SP 25.4.4 | H190: =IF(G190>0,VLOOKUP(G190,Apoio!$H$2:$I$24,2,0),"") -> 7 | I190: =IF(D190>0,(((H190*E190)*C190)/D190),"") -> 51.041667
A191: Secretaria & Gestor de Unidades | B191: Thanos | C191: 5 | D191: 4.8 | E191: 7 | F191: PI 4/25 | G191: SP 25.4.5 | H191: =IF(G191>0,VLOOKUP(G191,Apoio!$H$2:$I$24,2,0),"") -> 8 | I191: =IF(D191>0,(((H191*E191)*C191)/D191),"") -> 58.333333
A192: Secretaria & Gestor de Unidades | B192: Thanos | C192: 5 | D192: 4.8 | E192: 7 | F192: PI 4/25 | G192: SP 25.4.6 | H192: =IF(G192>0,VLOOKUP(G192,Apoio!$H$2:$I$24,2,0),"") -> 8 | I192: =IF(D192>0,(((H192*E192)*C192)/D192),"") -> 58.333333
A193: Administrativo | B193: ThreadPool | C193: 4 | D193: 6.7 | E193: 7 | F193: PI 1/25 | G193: SP 25.1.1 | H193: =IF(G193>0,VLOOKUP(G193,Apoio!$H$2:$I$24,2,0),"") -> 7 | I193: =IF(D193>0,(((H193*E193)*C193)/D193),"") -> 29.253731
A194: Administrativo | B194: ThreadPool | C194: 4 | D194: 6.7 | E194: 7 | F194: PI 1/25 | G194: SP 25.1.2 | H194: =IF(G194>0,VLOOKUP(G194,Apoio!$H$2:$I$24,2,0),"") -> 8 | I194: =IF(D194>0,(((H194*E194)*C194)/D194),"") -> 33.432836
... A215: Secretaria & Gestor de Unidades | B215: ThreadPool | C215: 4.5 | D215: 6.9 | E215: 7 | F215: PI 4/25 | G215: SP 25.4.6 | H215: =IF(G215>0,VLOOKUP(G215,Apoio!$H$2:$I$24,2,0),"") -> 8 | I215: =IF(D215>0,(((H215*E215)*C215)/D215),"") -> 36.521739
A216: Aprendizagem Digital | B216: Aprendizagem | C216: 7 | D216: 4.9 | E216: 7 | F216: PI 1/25 | G216: SP 25.1.1 | H216: =IF(G216>0,VLOOKUP(G216,Apoio!$H$2:$I$24,2,0),"") -> 7 | I216: =IF(D216>0,(((H216*E216)*C216)/D216),"") -> 70 | J216: =I216*30% -> 21
A217: Aprendizagem Digital | B217: Aprendizagem | C217: 7 | D217: 4.9 | E217: 7 | F217: PI 1/25 | G217: SP 25.1.2 | H217: =IF(G217>0,VLOOKUP(G217,Apoio!$H$2:$I$24,2,0),"") -> 8 | I217: =IF(D217>0,(((H217*E217)*C217)/D217),"") -> 80 | J217: =I217*30% -> 24
A218: Aprendizagem Digital | B218: Aprendizagem | C218: 7 | D218: 4.9 | E218: 7 | F218: PI 1/25 | G218: SP 25.1.3 | H218: =IF(G218>0,VLOOKUP(G218,Apoio!$H$2:$I$24,2,0),"") -> 8 | I218: =IF(D218>0,(((H218*E218)*C218)/D218),"") -> 80 | J218: =I218*30% -> 24
A219: Aprendizagem Digital | B219: Aprendizagem | C219: 7 | D219: 4.9 | E219: 7 | F219: PI 1/25 | G219: SP 25.1.4 | H219: =IF(G219>0,VLOOKUP(G219,Apoio!$H$2:$I$24,2,0),"") -> 6 | I219: =IF(D219>0,(((H219*E219)*C219)/D219),"") -> 60 | J219: =I219*30% -> 18
A220: Aprendizagem Digital | B220: Aprendizagem | C220: 7 | D220: 4.9 | E220: 7 | F220: PI 1/25 | G220: SP 25.1.5 | H220: =IF(G220>0,VLOOKUP(G220,Apoio!$H$2:$I$24,2,0),"") -> 8 | I220: =IF(D220>0,(((H220*E220)*C220)/D220),"") -> 80 | J220: =I220*30% -> 24
A221: Aprendizagem Digital | B221: Aprendizagem | C221: 7 | D221: 4.9 | E221: 7 | F221: PI 1/25 | G221: SP 25.1.6 | H221: =IF(G221>0,VLOOKUP(G221,Apoio!$H$2:$I$24,2,0),"") -> 3 | I221: =IF(D221>0,(((H221*E221)*C221)/D221),"") -> 30 | J221: =I221*30% -> 9
A222: Aprendizagem Digital | B222: Aprendizagem | C222: 4.6 | D222: 5.3 | E222: 7 | F222: PI 2/25 | G222: SP 25.2.1 | H222: =IF(G222>0,VLOOKUP(G222,Apoio!$H$2:$I$24,2,0),"") -> 6 | I222: =IF(D222>0,(((H222*E222)*C222)/D222),"") -> 36.45283 | J222: =I222*15% -> 5.4679245
A223: Aprendizagem Digital | B223: Aprendizagem | C223: 5 | D223: 5.3 | E223: 7 | F223: PI 2/25 | G223: SP 25.2.2 | H223: =IF(G223>0,VLOOKUP(G223,Apoio!$H$2:$I$24,2,0),"") -> 7 | I223: =IF(D223>0,(((H223*E223)*C223)/D223),"") -> 46.226415 | J223: =I223*15% -> 6.9339623
A224: Aprendizagem Digital | B224: Aprendizagem | C224: 6 | D224: 5.3 | E224: 7 | F224: PI 2/25 | G224: SP 25.2.3 | H224: =IF(G224>0,VLOOKUP(G224,Apoio!$H$2:$I$24,2,0),"") -> 8 | I224: =IF(D224>0,(((H224*E224)*C224)/D224),"") -> 63.396226 | J224: =I224*15% -> 9.509434
A225: Aprendizagem Digital | B225: Aprendizagem | C225: 4 | D225: 5.3 | E225: 7 | F225: PI 2/25 | G225: SP 25.2.4 | H225: =IF(G225>0,VLOOKUP(G225,Apoio!$H$2:$I$24,2,0),"") -> 8 | I225: =IF(D225>0,(((H225*E225)*C225)/D225),"") -> 42.264151 | J225: =I225*15% -> 6.3396226
A226: Aprendizagem Digital | B226: Aprendizagem | C226: 5 | D226: 5.3 | E226: 7 | F226: PI 2/25 | G226: SP 25.2.5 | H226: =IF(G226>0,VLOOKUP(G226,Apoio!$H$2:$I$24,2,0),"") -> 7 | I226: =IF(D226>0,(((H226*E226)*C226)/D226),"") -> 46.226415 | J226: =I226*15% -> 6.9339623
A227: Aprendizagem Digital | B227: Aprendizagem | C227: 4 | D227: 5.3 | E227: 7 | F227: PI 2/25 | G227: SP 25.2.6 | H227: =IF(G227>0,VLOOKUP(G227,Apoio!$H$2:$I$24,2,0),"") -> 3 | I227: =IF(D227>0,(((H227*E227)*C227)/D227),"") -> 15.849057 | J227: =I227*15% -> 2.3773585
A228: Aprendizagem Digital | B228: Aprendizagem | C228: 4.2 | D228: 6.1 | E228: 7 | F228: PI 3/25 | G228: SP 25.3.1 | H228: =IF(G228>0,VLOOKUP(G228,Apoio!$H$2:$I$24,2,0),"") -> 7 | I228: =IF(D228>0,(((H228*E228)*C228)/D228),"") -> 33.737705 | J228: 7 | K228: atualizado
A229: Aprendizagem Digital | B229: Aprendizagem | C229: 3.5 | D229: 6.1 | E229: 7 | F229: PI 3/25 | G229: SP 25.3.2 | H229: =IF(G229>0,VLOOKUP(G229,Apoio!$H$2:$I$24,2,0),"") -> 8 | I229: =IF(D229>0,(((H229*E229)*C229)/D229),"") -> 32.131148 | J229: 6 | K229: atualizado
A230: Aprendizagem Digital | B230: Aprendizagem | C230: 4.8 | D230: 6.1 | E230: 7 | F230: PI 3/25 | G230: SP 25.3.3 | H230: =IF(G230>0,VLOOKUP(G230,Apoio!$H$2:$I$24,2,0),"") -> 8 | I230: =IF(D230>0,(((H230*E230)*C230)/D230),"") -> 44.065574 | J230: 10 | K230: atualizado
A231: Aprendizagem Digital | B231: Aprendizagem | C231: 4.3 | D231: 6.1 | E231: 7 | F231: PI 3/25 | G231: SP 25.3.4 | H231: =IF(G231>0,VLOOKUP(G231,Apoio!$H$2:$I$24,2,0),"") -> 13 | I231: =IF(D231>0,(((H231*E231)*C231)/D231),"") -> 64.147541 | J231: 13 | K231: atualizado
A232: Aprendizagem Digital | B232: Aprendizagem | C232: 5 | D232: 6.1 | E232: 7 | F232: PI 3/25 | G232: SP 25.3.5 | H232: =IF(G232>0,VLOOKUP(G232,Apoio!$H$2:$I$24,2,0),"") -> 3 | I232: =IF(D232>0,(((H232*E232)*C232)/D232),"") -> 17.213115 | J232: 5 | K232: atualizado
A233: Aprendizagem Digital | B233: Aprendizagem | C233: 5 | D233: 8.3 | E233: 7 | F233: PI 4/25 | G233: SP 25.4.1 | H233: =IF(G233>0,VLOOKUP(G233,Apoio!$H$2:$I$24,2,0),"") -> 13 | I233: =IF(D233>0,(((H233*E233)*C233)/D233),"") -> 54.819277 | J233: =I233*30% -> 16.445783
A234: Aprendizagem Digital | B234: Aprendizagem | C234: 5 | D234: 8.3 | E234: 7 | F234: PI 4/25 | G234: SP 25.4.2 | H234: =IF(G234>0,VLOOKUP(G234,Apoio!$H$2:$I$24,2,0),"") -> 8 | I234: =IF(D234>0,(((H234*E234)*C234)/D234),"") -> 33.73494 | J234: =I234*30% -> 10.120482
A235: Aprendizagem Digital | B235: Aprendizagem | C235: 5 | D235: 8.3 | E235: 7 | F235: PI 4/25 | G235: SP 25.4.3 | H235: =IF(G235>0,VLOOKUP(G235,Apoio!$H$2:$I$24,2,0),"") -> 8 | I235: =IF(D235>0,(((H235*E235)*C235)/D235),"") -> 33.73494 | J235: =I235*30% -> 10.120482
A236: Aprendizagem Digital | B236: Aprendizagem | C236: 5 | D236: 8.3 | E236: 7 | F236: PI 4/25 | G236: SP 25.4.4 | H236: =IF(G236>0,VLOOKUP(G236,Apoio!$H$2:$I$24,2,0),"") -> 7 | I236: =IF(D236>0,(((H236*E236)*C236)/D236),"") -> 29.518072 | J236: =I236*30% -> 8.8554217
A237: Aprendizagem Digital | B237: Aprendizagem | C237: 5 | D237: 8.3 | E237: 7 | F237: PI 4/25 | G237: SP 25.4.5 | H237: =IF(G237>0,VLOOKUP(G237,Apoio!$H$2:$I$24,2,0),"") -> 8 | I237: =IF(D237>0,(((H237*E237)*C237)/D237),"") -> 33.73494 | J237: =I237*30% -> 10.120482
A238: Aprendizagem Digital | B238: Aprendizagem | C238: 5 | D238: 8.3 | E238: 7 | F238: PI 4/25 | G238: SP 25.4.6 | H238: =IF(G238>0,VLOOKUP(G238,Apoio!$H$2:$I$24,2,0),"") -> 8 | I238: =IF(D238>0,(((H238*E238)*C238)/D238),"") -> 33.73494 | J238: =I238*30% -> 10.120482
A239: Aprendizagem Digital | B239: Avaliação | C239: 6 | D239: 4.4 | E239: 7 | F239: PI 1/25 | G239: SP 25.1.1 | H239: =IF(G239>0,VLOOKUP(G239,Apoio!$H$2:$I$24,2,0),"") -> 7 | I239: =IF(D239>0,(((H239*E239)*C239)/D239),"") -> 66.818182 | J239: =I239*30% -> 20.045455
A240: Aprendizagem Digital | B240: Avaliação | C240: 10 | D240: 4.4 | E240: 7 | F240: PI 1/25 | G240: SP 25.1.2 | H240: =IF(G240>0,VLOOKUP(G240,Apoio!$H$2:$I$24,2,0),"") -> 8 | I240: =IF(D240>0,(((H240*E240)*C240)/D240),"") -> 127.27273 | J240: =I240*30% -> 38.181818
A241: Aprendizagem Digital | B241: Avaliação | C241: 7.5 | D241: 4.4 | E241: 7 | F241: PI 1/25 | G241: SP 25.1.3 | H241: =IF(G241>0,VLOOKUP(G241,Apoio!$H$2:$I$24,2,0),"") -> 8 | I241: =IF(D241>0,(((H241*E241)*C241)/D241),"") -> 95.454545 | J241: =I241*30% -> 28.636364
A242: Aprendizagem Digital | B242: Avaliação | C242: 7 | D242: 4.4 | E242: 7 | F242: PI 1/25 | G242: SP 25.1.4 | H242: =IF(G242>0,VLOOKUP(G242,Apoio!$H$2:$I$24,2,0),"") -> 6 | I242: =IF(D242>0,(((H242*E242)*C242)/D242),"") -> 66.818182 | J242: =I242*30% -> 20.045455
A243: Aprendizagem Digital | B243: Avaliação | C243: 7 | D243: 4.4 | E243: 7 | F243: PI 1/25 | G243: SP 25.1.5 | H243: =IF(G243>0,VLOOKUP(G243,Apoio!$H$2:$I$24,2,0),"") -> 8 | I243: =IF(D243>0,(((H243*E243)*C243)/D243),"") -> 89.090909 | J243: =I243*30% -> 26.727273
A244: Aprendizagem Digital | B244: Avaliação | C244: 7 | D244: 4.4 | E244: 7 | F244: PI 1/25 | G244: SP 25.1.6 | H244: =IF(G244>0,VLOOKUP(G244,Apoio!$H$2:$I$24,2,0),"") -> 3 | I244: =IF(D244>0,(((H244*E244)*C244)/D244),"") -> 33.409091 | J244: =I244*30% -> 10.022727
A245: Aprendizagem Digital | B245: Avaliação | C245: 4 | D245: 4 | E245: 7 | F245: PI 2/25 | G245: SP 25.2.1 | H245: =IF(G245>0,VLOOKUP(G245,Apoio!$H$2:$I$24,2,0),"") -> 6 | I245: =IF(D245>0,(((H245*E245)*C245)/D245),"") -> 42 | J245: =I245*15% -> 6.3
A246: Aprendizagem Digital | B246: Avaliação | C246: 7 | D246: 4 | E246: 7 | F246: PI 2/25 | G246: SP 25.2.2 | H246: =IF(G246>0,VLOOKUP(G246,Apoio!$H$2:$I$24,2,0),"") -> 7 | I246: =IF(D246>0,(((H246*E246)*C246)/D246),"") -> 85.75 | J246: =I246*15% -> 12.8625
A247: Aprendizagem Digital | B247: Avaliação | C247: 8 | D247: 4 | E247: 7 | F247: PI 2/25 | G247: SP 25.2.3 | H247: =IF(G247>0,VLOOKUP(G247,Apoio!$H$2:$I$24,2,0),"") -> 8 | I247: =IF(D247>0,(((H247*E247)*C247)/D247),"") -> 112 | J247: =I247*15% -> 16.8
A248: Aprendizagem Digital | B248: Avaliação | C248: 8 | D248: 4 | E248: 7 | F248: PI 2/25 | G248: SP 25.2.4 | H248: =IF(G248>0,VLOOKUP(G248,Apoio!$H$2:$I$24,2,0),"") -> 8 | I248: =IF(D248>0,(((H248*E248)*C248)/D248),"") -> 112 | J248: =I248*15% -> 16.8
A249: Aprendizagem Digital | B249: Avaliação | C249: 8 | D249: 4 | E249: 7 | F249: PI 2/25 | G249: SP 25.2.5 | H249: =IF(G249>0,VLOOKUP(G249,Apoio!$H$2:$I$24,2,0),"") -> 7 | I249: =IF(D249>0,(((H249*E249)*C249)/D249),"") -> 98 | J249: =I249*15% -> 14.7
A250: Aprendizagem Digital | B250: Avaliação | C250: 8 | D250: 4 | E250: 7 | F250: PI 2/25 | G250: SP 25.2.6 | H250: =IF(G250>0,VLOOKUP(G250,Apoio!$H$2:$I$24,2,0),"") -> 3 | I250: =IF(D250>0,(((H250*E250)*C250)/D250),"") -> 42 | J250: =I250*15% -> 6.3
A251: Aprendizagem Digital | B251: Avaliação | C251: 4.5 | D251: 4.4 | E251: 7 | F251: PI 3/25 | G251: SP 25.3.1 | H251: =IF(G251>0,VLOOKUP(G251,Apoio!$H$2:$I$24,2,0),"") -> 7 | I251: =IF(D251>0,(((H251*E251)*C251)/D251),"") -> 50.113636 | J251: 16 | K251: atualizado
A252: Aprendizagem Digital | B252: Avaliação | C252: 3.5 | D252: 4.4 | E252: 7 | F252: PI 3/25 | G252: SP 25.3.2 | H252: =IF(G252>0,VLOOKUP(G252,Apoio!$H$2:$I$24,2,0),"") -> 8 | I252: =IF(D252>0,(((H252*E252)*C252)/D252),"") -> 44.545455 | J252: 21 | K252: atualizado
A253: Aprendizagem Digital | B253: Avaliação | C253: 5.5 | D253: 4.4 | E253: 7 | F253: PI 3/25 | G253: SP 25.3.3 | H253: =IF(G253>0,VLOOKUP(G253,Apoio!$H$2:$I$24,2,0),"") -> 8 | I253: =IF(D253>0,(((H253*E253)*C253)/D253),"") -> 70 | J253: 25 | K253: atualizado
A254: Aprendizagem Digital | B254: Avaliação | C254: 5 | D254: 4.4 | E254: 7 | F254: PI 3/25 | G254: SP 25.3.4 | H254: =IF(G254>0,VLOOKUP(G254,Apoio!$H$2:$I$24,2,0),"") -> 13 | I254: =IF(D254>0,(((H254*E254)*C254)/D254),"") -> 103.40909 | J254: 30 | K254: atualizado
A255: Aprendizagem Digital | B255: Avaliação | C255: 4 | D255: 4.4 | E255: 7 | F255: PI 3/25 | G255: SP 25.3.5 | H255: =IF(G255>0,VLOOKUP(G255,Apoio!$H$2:$I$24,2,0),"") -> 3 | I255: =IF(D255>0,(((H255*E255)*C255)/D255),"") -> 19.090909 | J255: 10 | K255: atualizado
A256: Aprendizagem Digital | B256: Avaliação | C256: 6 | D256: 3.9 | E256: 7 | F256: PI 4/25 | G256: SP 25.4.1 | H256: =IF(G256>0,VLOOKUP(G256,Apoio!$H$2:$I$24,2,0),"") -> 13 | I256: =IF(D256>0,(((H256*E256)*C256)/D256),"") -> 140 | J256: =I256*30% -> 42
A257: Aprendizagem Digital | B257: Avaliação | C257: 6 | D257: 3.9 | E257: 7 | F257: PI 4/25 | G257: SP 25.4.2 | H257: =IF(G257>0,VLOOKUP(G257,Apoio!$H$2:$I$24,2,0),"") -> 8 | I257: =IF(D257>0,(((H257*E257)*C257)/D257),"") -> 86.153846 | J257: =I257*30% -> 25.846154
A258: Aprendizagem Digital | B258: Avaliação | C258: 6 | D258: 3.9 | E258: 7 | F258: PI 4/25 | G258: SP 25.4.3 | H258: =IF(G258>0,VLOOKUP(G258,Apoio!$H$2:$I$24,2,0),"") -> 8 | I258: =IF(D258>0,(((H258*E258)*C258)/D258),"") -> 86.153846 | J258: =I258*30% -> 25.846154
A259: Aprendizagem Digital | B259: Avaliação | C259: 6 | D259: 3.9 | E259: 7 | F259: PI 4/25 | G259: SP 25.4.4 | H259: =IF(G259>0,VLOOKUP(G259,Apoio!$H$2:$I$24,2,0),"") -> 7 | I259: =IF(D259>0,(((H259*E259)*C259)/D259),"") -> 75.384615 | J259: =I259*30% -> 22.615385
...

Sheet Dinamica 2025
A1: PI | B1: PI 4/25
A2: Status Time | B2: (Vários itens)
A4: Rótulos de Linha | B4: Soma de Velocity | C4: Soma de Sustentação
A5: Aprendizagem Digital | B5: 2765.9716 | C5: 677.94601
A6: Financeiro | B6: 855.24389 | C6: 264.22934
A7: Ingresso | B7: 1787.8505
A8: Jornada Acadêmica | B8: 1047.5238 | C8: 276.58132
A9: Pos Graduação | B9: 636.55172
A10: Saber | B10: 1255.55 | C10: 168.0525
A11: Inteligencia Artificial | B11: 744.375
A12: Voomp | B12: 1205.868
A13: Atendimento & Serviço | B13: 1337.0047
A14: Secretaria & Gestor de Unidades | B14: 1683.0649
A15: Total Geral | B15: 13319.004 | C15: 1386.8092

Sheet Dinamica 2026
A1: PI | B1: (Tudo)
A2: Sprint | B2: SP 26.1.1
A4: Rótulos de Linha | B4: Média de Produtividade (H/P)
A5: Aprendizagem Digital | B5: 5.2833333
A6: Atendimento & Serviço | B6: 5.75
A7: Ingresso | B7: 6.5666667
A8: Inteligencia Artificial | B8: 6.9666667
A9: Jornada Acadêmica | B9: 5.375
A10: Pos Graduação | B10: 6.9
A11: Saber | B11: 5.2666667
A12: Secretaria & Gestor de Unidades | B12: 6.28
A13: Voomp | B13: 6.6285714
A14: Total Geral | B14: 6.0975

Sheet 2026_Produtividade
A1: Jornada | B1: Time | C1: Qtde de Devs | D1: Produtividade (H/P) | E1: Horas Produtivas por dia e por Dev | F1: PI | G1: Sprint | H1: Dias Úteis da Sprint | I1: Velocity | J1: Média dos Pts de Sustentação da PI passada | K1: Capacity | L1: Custo da Sprint: Pontos x Valor (R$ 2647,87) | M1: Status Time | N1: Observações: redução da capacidade por ausência
A2: Atendimento e Serviço | B2: kbots | C2: 4 | D2: 5 | E2: 7 | F2: PI 1/26 | G2: SP 26.1.1 | H2: =IF(G2>0,VLOOKUP(G2,Apoio!$A$2:$B$25,2,0),"") -> 7 | I2: =IF(D2>0,(((H2*E2)*C2)/D2),"") -> 39.2 | M2: Gestão Jéssica Molero
A3: Atendimento e Serviço | B3: kbots | C3: 4 | D3: 5 | E3: 7 | F3: PI 1/26 | G3: SP 26.1.2 | H3: =IF(G3>0,VLOOKUP(G3,Apoio!$A$2:$B$25,2,0),"") -> 8 | I3: =IF(D3>0,(((H3*E3)*C3)/D3),"") -> 44.8 | M3: Gestão Jéssica Molero
A4: Atendimento e Serviço | B4: kbots | C4: 4 | D4: 5 | E4: 7 | F4: PI 1/26 | G4: SP 26.1.3 | H4: =IF(G4>0,VLOOKUP(G4,Apoio!$A$2:$B$25,2,0),"") -> 6 | I4: =IF(D4>0,(((H4*E4)*C4)/D4),"") -> 33.6 | M4: Gestão Jéssica Molero
A5: Atendimento e Serviço | B5: kbots | C5: 4 | D5: 5 | E5: 7 | F5: PI 1/26 | G5: SP 26.1.4 | H5: =IF(G5>0,VLOOKUP(G5,Apoio!$A$2:$B$25,2,0),"") -> 8 | I5: =IF(D5>0,(((H5*E5)*C5)/D5),"") -> 44.8 | M5: Gestão Jéssica Molero
A6: Atendimento e Serviço | B6: kbots | C6: 4 | D6: 5 | E6: 7 | F6: PI 1/26 | G6: SP 26.1.5 | H6: =IF(G6>0,VLOOKUP(G6,Apoio!$A$2:$B$25,2,0),"") -> 8 | I6: =IF(D6>0,(((H6*E6)*C6)/D6),"") -> 44.8 | M6: Gestão Jéssica Molero
A7: Atendimento e Serviço | B7: kbots | C7: 4 | D7: 5 | E7: 7 | F7: PI 1/26 | G7: SP 26.1.6 | H7: =IF(G7>0,VLOOKUP(G7,Apoio!$A$2:$B$25,2,0),"") -> 2 | I7: =IF(D7>0,(((H7*E7)*C7)/D7),"") -> 11.2 | M7: Gestão Jéssica Molero
A8: Atendimento e Serviço | B8: kbots | C8: 4 | D8: 5 | E8: 7 | F8: PI 2/26 | G8: SP 26.2.1 | H8: =IF(G8>0,VLOOKUP(G8,Apoio!$A$2:$B$25,2,0),"") -> 5 | I8: =IF(D8>0,(((H8*E8)*C8)/D8),"") -> 28 | M8: Gestão Jéssica Molero
A9: Atendimento e Serviço | B9: kbots | C9: 4 | D9: 5 | E9: 7 | F9: PI 2/26 | G9: SP 26.2.2 | H9: =IF(G9>0,VLOOKUP(G9,Apoio!$A$2:$B$25,2,0),"") -> 7 | I9: =IF(D9>0,(((H9*E9)*C9)/D9),"") -> 39.2 | M9: Gestão Jéssica Molero
A10: Atendimento e Serviço | B10: kbots | C10: 4 | D10: 5 | E10: 7 | F10: PI 2/26 | G10: SP 26.2.3 | H10: =IF(G10>0,VLOOKUP(G10,Apoio!$A$2:$B$25,2,0),"") -> 8 | I10: =IF(D10>0,(((H10*E10)*C10)/D10),"") -> 44.8 | M10: Gestão Jéssica Molero
A11: Atendimento e Serviço | B11: kbots | C11: 4 | D11: 5 | E11: 7 | F11: PI 2/26 | G11: SP 26.2.4 | H11: =IF(G11>0,VLOOKUP(G11,Apoio!$A$2:$B$25,2,0),"") -> 7 | I11: =IF(D11>0,(((H11*E11)*C11)/D11),"") -> 39.2 | M11: Gestão Jéssica Molero
A12: Atendimento e Serviço | B12: kbots | C12: 4 | D12: 5 | E12: 7 | F12: PI 2/26 | G12: SP 26.2.5 | H12: =IF(G12>0,VLOOKUP(G12,Apoio!$A$2:$B$25,2,0),"") -> 8 | I12: =IF(D12>0,(((H12*E12)*C12)/D12),"") -> 44.8 | M12: Gestão Jéssica Molero
A13: Atendimento e Serviço | B13: kbots | C13: 4 | D13: 5 | E13: 7 | F13: PI 2/26 | G13: SP 26.2.6 | H13: =IF(G13>0,VLOOKUP(G13,Apoio!$A$2:$B$25,2,0),"") -> 3 | I13: =IF(D13>0,(((H13*E13)*C13)/D13),"") -> 16.8 | M13: Gestão Jéssica Molero
... A19: Atendimento e Serviço | B19: kbots | C19: 4 | D19: 5 | E19: 7 | F19: PI 3/26 | G19: SP 26.3.6 | H19: =IF(G19>0,VLOOKUP(G19,Apoio!$A$2:$B$25,2,0),"") -> 3 | I19: =IF(D19>0,(((H19*E19)*C19)/D19),"") -> 16.8 | M19: Gestão Jéssica Molero
A20: Atendimento e Serviço | B20: kbots | C20: 4 | D20: 5 | E20: 7 | F20: PI 4/26 | G20: SP 26.4.1 | H20: =IF(G20>0,VLOOKUP(G20,Apoio!$A$2:$B$25,2,0),"") -> 8 | I20: =IF(D20>0,(((H20*E20)*C20)/D20),"") -> 44.8 | J20: 8 | K20: =I20-J20 -> 36.8 | M20: Gestão Jéssica Molero
A21: Atendimento e Serviço | B21: kbots | C21: 4 | D21: 5 | E21: 7 | F21: PI 4/26 | G21: SP 26.4.2 | H21: =IF(G21>0,VLOOKUP(G21,Apoio!$A$2:$B$25,2,0),"") -> 7 | I21: =IF(D21>0,(((H21*E21)*C21)/D21),"") -> 39.2 | J21: 8 | K21: =I21-J21 -> 31.2 | M21: Gestão Jéssica Molero
A22: Atendimento e Serviço | B22: kbots | C22: 4 | D22: 5 | E22: 7 | F22: PI 4/26 | G22: SP 26.4.3 | H22: =IF(G22>0,VLOOKUP(G22,Apoio!$A$2:$B$25,2,0),"") -> 7 | I22: =IF(D22>0,(((H22*E22)*C22)/D22),"") -> 39.2 | J22: 8 | K22: =I22-J22 -> 31.2 | M22: Gestão Jéssica Molero
A23: Atendimento e Serviço | B23: kbots | C23: 4 | D23: 5 | E23: 7 | F23: PI 4/26 | G23: SP 26.4.4 | H23: =IF(G23>0,VLOOKUP(G23,Apoio!$A$2:$B$25,2,0),"") -> 7 | I23: =IF(D23>0,(((H23*E23)*C23)/D23),"") -> 39.2 | J23: 8 | K23: =I23-J23 -> 31.2 | M23: Gestão Jéssica Molero
A24: Atendimento e Serviço | B24: kbots | C24: 4 | D24: 5 | E24: 7 | F24: PI 4/26 | G24: SP 26.4.5 | H24: =IF(G24>0,VLOOKUP(G24,Apoio!$A$2:$B$25,2,0),"") -> 8 | I24: =IF(D24>0,(((H24*E24)*C24)/D24),"") -> 44.8 | J24: 8 | K24: =I24-J24 -> 36.8 | M24: Gestão Jéssica Molero
A25: Atendimento e Serviço | B25: kbots | C25: 4 | D25: 5 | E25: 7 | F25: PI 4/26 | G25: SP 26.4.6 | H25: =IF(G25>0,VLOOKUP(G25,Apoio!$A$2:$B$25,2,0),"") -> 8 | I25: =IF(D25>0,(((H25*E25)*C25)/D25),"") -> 44.8 | J25: 8 | K25: =I25-J25 -> 36.8 | M25: Gestão Jéssica Molero
A26: Atendimento e Serviço | B26: Papa-léguas | C26: 5 | D26: 6 | E26: 7 | F26: PI 1/26 | G26: SP 26.1.1 | H26: =IF(G26>0,VLOOKUP(G26,Apoio!$A$2:$B$25,2,0),"") -> 7 | I26: =IF(D26>0,(((H26*E26)*C26)/D26),"") -> 40.833333 | M26: Gestão Jéssica Molero
A27: Atendimento e Serviço | B27: Papa-léguas | C27: 5 | D27: 6 | E27: 7 | F27: PI 1/26 | G27: SP 26.1.2 | H27: =IF(G27>0,VLOOKUP(G27,Apoio!$A$2:$B$25,2,0),"") -> 8 | I27: =IF(D27>0,(((H27*E27)*C27)/D27),"") -> 46.666667 | M27: Gestão Jéssica Molero
A28: Atendimento e Serviço | B28: Papa-léguas | C28: 5 | D28: 6 | E28: 7 | F28: PI 1/26 | G28: SP 26.1.3 | H28: =IF(G28>0,VLOOKUP(G28,Apoio!$A$2:$B$25,2,0),"") -> 6 | I28: =IF(D28>0,(((H28*E28)*C28)/D28),"") -> 35 | M28: Gestão Jéssica Molero
A29: Atendimento e Serviço | B29: Papa-léguas | C29: 5 | D29: 6 | E29: 7 | F29: PI 1/26 | G29: SP 26.1.4 | H29: =IF(G29>0,VLOOKUP(G29,Apoio!$A$2:$B$25,2,0),"") -> 8 | I29: =IF(D29>0,(((H29*E29)*C29)/D29),"") -> 46.666667 | M29: Gestão Jéssica Molero
A30: Atendimento e Serviço | B30: Papa-léguas | C30: 5 | D30: 6 | E30: 7 | F30: PI 1/26 | G30: SP 26.1.5 | H30: =IF(G30>0,VLOOKUP(G30,Apoio!$A$2:$B$25,2,0),"") -> 8 | I30: =IF(D30>0,(((H30*E30)*C30)/D30),"") -> 46.666667 | M30: Gestão Jéssica Molero
A31: Atendimento e Serviço | B31: Papa-léguas | C31: 5 | D31: 6 | E31: 7 | F31: PI 1/26 | G31: SP 26.1.6 | H31: =IF(G31>0,VLOOKUP(G31,Apoio!$A$2:$B$25,2,0),"") -> 2 | I31: =IF(D31>0,(((H31*E31)*C31)/D31),"") -> 11.666667 | M31: Gestão Jéssica Molero
A32: Atendimento e Serviço | B32: Papa-léguas | C32: 5 | D32: 6 | E32: 7 | F32: PI 2/26 | G32: SP 26.2.1 | H32: =IF(G32>0,VLOOKUP(G32,Apoio!$A$2:$B$25,2,0),"") -> 5 | I32: =IF(D32>0,(((H32*E32)*C32)/D32),"") -> 29.166667 | M32: Gestão Jéssica Molero
A33: Atendimento e Serviço | B33: Papa-léguas | C33: 5 | D33: 6 | E33: 7 | F33: PI 2/26 | G33: SP 26.2.2 | H33: =IF(G33>0,VLOOKUP(G33,Apoio!$A$2:$B$25,2,0),"") -> 7 | I33: =IF(D33>0,(((H33*E33)*C33)/D33),"") -> 40.833333 | M33: Gestão Jéssica Molero
A34: Atendimento e Serviço | B34: Papa-léguas | C34: 5 | D34: 6 | E34: 7 | F34: PI 2/26 | G34: SP 26.2.3 | H34: =IF(G34>0,VLOOKUP(G34,Apoio!$A$2:$B$25,2,0),"") -> 8 | I34: =IF(D34>0,(((H34*E34)*C34)/D34),"") -> 46.666667 | M34: Gestão Jéssica Molero
A35: Atendimento e Serviço | B35: Papa-léguas | C35: 5 | D35: 6 | E35: 7 | F35: PI 2/26 | G35: SP 26.2.4 | H35: =IF(G35>0,VLOOKUP(G35,Apoio!$A$2:$B$25,2,0),"") -> 7 | I35: =IF(D35>0,(((H35*E35)*C35)/D35),"") -> 40.833333 | M35: Gestão Jéssica Molero
A36: Atendimento e Serviço | B36: Papa-léguas | C36: 5 | D36: 6 | E36: 7 | F36: PI 2/26 | G36: SP 26.2.5 | H36: =IF(G36>0,VLOOKUP(G36,Apoio!$A$2:$B$25,2,0),"") -> 8 | I36: =IF(D36>0,(((H36*E36)*C36)/D36),"") -> 46.666667 | M36: Gestão Jéssica Molero
A37: Atendimento e Serviço | B37: Papa-léguas | C37: 5 | D37: 6 | E37: 7 | F37: PI 2/26 | G37: SP 26.2.6 | H37: =IF(G37>0,VLOOKUP(G37,Apoio!$A$2:$B$25,2,0),"") -> 3 | I37: =IF(D37>0,(((H37*E37)*C37)/D37),"") -> 17.5 | M37: Gestão Jéssica Molero
... A43: Atendimento e Serviço | B43: Papa-léguas | C43: 5 | D43: 6 | E43: 7 | F43: PI 3/26 | G43: SP 26.3.6 | H43: =IF(G43>0,VLOOKUP(G43,Apoio!$A$2:$B$25,2,0),"") -> 3 | I43: =IF(D43>0,(((H43*E43)*C43)/D43),"") -> 17.5 | M43: Gestão Jéssica Molero
A44: Atendimento e Serviço | B44: Papa-léguas | C44: 5 | D44: 6 | E44: 7 | F44: PI 4/26 | G44: SP 26.4.1 | H44: =IF(G44>0,VLOOKUP(G44,Apoio!$A$2:$B$25,2,0),"") -> 8 | I44: =IF(D44>0,(((H44*E44)*C44)/D44),"") -> 46.666667 | J44: 8 | K44: =I44-J44 -> 38.666667 | M44: Gestão Jéssica Molero
A45: Atendimento e Serviço | B45: Papa-léguas | C45: 5 | D45: 6 | E45: 7 | F45: PI 4/26 | G45: SP 26.4.2 | H45: =IF(G45>0,VLOOKUP(G45,Apoio!$A$2:$B$25,2,0),"") -> 7 | I45: =IF(D45>0,(((H45*E45)*C45)/D45),"") -> 40.833333 | J45: 8 | K45: =I45-J45 -> 32.833333 | M45: Gestão Jéssica Molero
A46: Atendimento e Serviço | B46: Papa-léguas | C46: 5 | D46: 6 | E46: 7 | F46: PI 4/26 | G46: SP 26.4.3 | H46: =IF(G46>0,VLOOKUP(G46,Apoio!$A$2:$B$25,2,0),"") -> 7 | I46: =IF(D46>0,(((H46*E46)*C46)/D46),"") -> 40.833333 | J46: 8 | K46: =I46-J46 -> 32.833333 | M46: Gestão Jéssica Molero
A47: Atendimento e Serviço | B47: Papa-léguas | C47: 5 | D47: 6 | E47: 7 | F47: PI 4/26 | G47: SP 26.4.4 | H47: =IF(G47>0,VLOOKUP(G47,Apoio!$A$2:$B$25,2,0),"") -> 7 | I47: =IF(D47>0,(((H47*E47)*C47)/D47),"") -> 40.833333 | J47: 8 | K47: =I47-J47 -> 32.833333 | M47: Gestão Jéssica Molero
A48: Atendimento e Serviço | B48: Papa-léguas | C48: 5 | D48: 6 | E48: 7 | F48: PI 4/26 | G48: SP 26.4.5 | H48: =IF(G48>0,VLOOKUP(G48,Apoio!$A$2:$B$25,2,0),"") -> 8 | I48: =IF(D48>0,(((H48*E48)*C48)/D48),"") -> 46.666667 | J48: 8 | K48: =I48-J48 -> 38.666667 | M48: Gestão Jéssica Molero
A49: Atendimento e Serviço | B49: Papa-léguas | C49: 5 | D49: 6 | E49: 7 | F49: PI 4/26 | G49: SP 26.4.6 | H49: =IF(G49>0,VLOOKUP(G49,Apoio!$A$2:$B$25,2,0),"") -> 8 | I49: =IF(D49>0,(((H49*E49)*C49)/D49),"") -> 46.666667 | J49: 8 | K49: =I49-J49 -> 38.666667 | M49: Gestão Jéssica Molero
A50: Atendimento e Serviço | B50: Route66 | C50: 6 | D50: 6 | E50: 7 | F50: PI 1/26 | G50: SP 26.1.1 | H50: =IF(G50>0,VLOOKUP(G50,Apoio!$A$2:$B$25,2,0),"") -> 7 | I50: =IF(D50>0,(((H50*E50)*C50)/D50),"") -> 49 | M50: Gestão Jéssica Molero
A51: Atendimento e Serviço | B51: Route66 | C51: 6 | D51: 6 | E51: 7 | F51: PI 1/26 | G51: SP 26.1.2 | H51: =IF(G51>0,VLOOKUP(G51,Apoio!$A$2:$B$25,2,0),"") -> 8 | I51: =IF(D51>0,(((H51*E51)*C51)/D51),"") -> 56 | M51: Gestão Jéssica Molero
A52: Atendimento e Serviço | B52: Route66 | C52: 6 | D52: 6 | E52: 7 | F52: PI 1/26 | G52: SP 26.1.3 | H52: =IF(G52>0,VLOOKUP(G52,Apoio!$A$2:$B$25,2,0),"") -> 6 | I52: =IF(D52>0,(((H52*E52)*C52)/D52),"") -> 42 | M52: Gestão Jéssica Molero
A53: Atendimento e Serviço | B53: Route66 | C53: 6 | D53: 6 | E53: 7 | F53: PI 1/26 | G53: SP 26.1.4 | H53: =IF(G53>0,VLOOKUP(G53,Apoio!$A$2:$B$25,2,0),"") -> 8 | I53: =IF(D53>0,(((H53*E53)*C53)/D53),"") -> 56 | M53: Gestão Jéssica Molero
A54: Atendimento e Serviço | B54: Route66 | C54: 6 | D54: 6 | E54: 7 | F54: PI 1/26 | G54: SP 26.1.5 | H54: =IF(G54>0,VLOOKUP(G54,Apoio!$A$2:$B$25,2,0),"") -> 8 | I54: =IF(D54>0,(((H54*E54)*C54)/D54),"") -> 56 | M54: Gestão Jéssica Molero
A55: Atendimento e Serviço | B55: Route66 | C55: 6 | D55: 6 | E55: 7 | F55: PI 1/26 | G55: SP 26.1.6 | H55: =IF(G55>0,VLOOKUP(G55,Apoio!$A$2:$B$25,2,0),"") -> 2 | I55: =IF(D55>0,(((H55*E55)*C55)/D55),"") -> 14 | M55: Gestão Jéssica Molero
A56: Atendimento e Serviço | B56: Route66 | C56: 6 | D56: 6 | E56: 7 | F56: PI 2/26 | G56: SP 26.2.1 | H56: =IF(G56>0,VLOOKUP(G56,Apoio!$A$2:$B$25,2,0),"") -> 5 | I56: =IF(D56>0,(((H56*E56)*C56)/D56),"") -> 35 | M56: Gestão Jéssica Molero
A57: Atendimento e Serviço | B57: Route66 | C57: 6 | D57: 6 | E57: 7 | F57: PI 2/26 | G57: SP 26.2.2 | H57: =IF(G57>0,VLOOKUP(G57,Apoio!$A$2:$B$25,2,0),"") -> 7 | I57: =IF(D57>0,(((H57*E57)*C57)/D57),"") -> 49 | M57: Gestão Jéssica Molero
A58: Atendimento e Serviço | B58: Route66 | C58: 6 | D58: 6 | E58: 7 | F58: PI 2/26 | G58: SP 26.2.3 | H58: =IF(G58>0,VLOOKUP(G58,Apoio!$A$2:$B$25,2,0),"") -> 8 | I58: =IF(D58>0,(((H58*E58)*C58)/D58),"") -> 56 | M58: Gestão Jéssica Molero
A59: Atendimento e Serviço | B59: Route66 | C59: 6 | D59: 6 | E59: 7 | F59: PI 2/26 | G59: SP 26.2.4 | H59: =IF(G59>0,VLOOKUP(G59,Apoio!$A$2:$B$25,2,0),"") -> 7 | I59: =IF(D59>0,(((H59*E59)*C59)/D59),"") -> 49 | M59: Gestão Jéssica Molero
A60: Atendimento e Serviço | B60: Route66 | C60: 6 | D60: 6 | E60: 7 | F60: PI 2/26 | G60: SP 26.2.5 | H60: =IF(G60>0,VLOOKUP(G60,Apoio!$A$2:$B$25,2,0),"") -> 8 | I60: =IF(D60>0,(((H60*E60)*C60)/D60),"") -> 56 | M60: Gestão Jéssica Molero
A61: Atendimento e Serviço | B61: Route66 | C61: 6 | D61: 6 | E61: 7 | F61: PI 2/26 | G61: SP 26.2.6 | H61: =IF(G61>0,VLOOKUP(G61,Apoio!$A$2:$B$25,2,0),"") -> 3 | I61: =IF(D61>0,(((H61*E61)*C61)/D61),"") -> 21 | M61: Gestão Jéssica Molero
... A67: Atendimento e Serviço | B67: Route66 | C67: 6 | D67: 6 | E67: 7 | F67: PI 3/26 | G67: SP 26.3.6 | H67: =IF(G67>0,VLOOKUP(G67,Apoio!$A$2:$B$25,2,0),"") -> 3 | I67: =IF(D67>0,(((H67*E67)*C67)/D67),"") -> 21 | M67: Gestão Jéssica Molero
A68: Atendimento e Serviço | B68: Route66 | C68: 6 | D68: 6 | E68: 7 | F68: PI 4/26 | G68: SP 26.4.1 | H68: =IF(G68>0,VLOOKUP(G68,Apoio!$A$2:$B$25,2,0),"") -> 8 | I68: =IF(D68>0,(((H68*E68)*C68)/D68),"") -> 56 | J68: 8 | K68: =I68-J68 -> 48 | M68: Gestão Jéssica Molero
A69: Atendimento e Serviço | B69: Route66 | C69: 6 | D69: 6 | E69: 7 | F69: PI 4/26 | G69: SP 26.4.2 | H69: =IF(G69>0,VLOOKUP(G69,Apoio!$A$2:$B$25,2,0),"") -> 7 | I69: =IF(D69>0,(((H69*E69)*C69)/D69),"") -> 49 | J69: 8 | K69: =I69-J69 -> 41 | M69: Gestão Jéssica Molero
A70: Atendimento e Serviço | B70: Route66 | C70: 6 | D70: 6 | E70: 7 | F70: PI 4/26 | G70: SP 26.4.3 | H70: =IF(G70>0,VLOOKUP(G70,Apoio!$A$2:$B$25,2,0),"") -> 7 | I70: =IF(D70>0,(((H70*E70)*C70)/D70),"") -> 49 | J70: 8 | K70: =I70-J70 -> 41 | M70: Gestão Jéssica Molero
A71: Atendimento e Serviço | B71: Route66 | C71: 6 | D71: 6 | E71: 7 | F71: PI 4/26 | G71: SP 26.4.4 | H71: =IF(G71>0,VLOOKUP(G71,Apoio!$A$2:$B$25,2,0),"") -> 7 | I71: =IF(D71>0,(((H71*E71)*C71)/D71),"") -> 49 | J71: 8 | K71: =I71-J71 -> 41 | M71: Gestão Jéssica Molero
A72: Atendimento e Serviço | B72: Route66 | C72: 6 | D72: 6 | E72: 7 | F72: PI 4/26 | G72: SP 26.4.5 | H72: =IF(G72>0,VLOOKUP(G72,Apoio!$A$2:$B$25,2,0),"") -> 8 | I72: =IF(D72>0,(((H72*E72)*C72)/D72),"") -> 56 | J72: 8 | K72: =I72-J72 -> 48 | M72: Gestão Jéssica Molero
A73: Atendimento e Serviço | B73: Route66 | C73: 6 | D73: 6 | E73: 7 | F73: PI 4/26 | G73: SP 26.4.6 | H73: =IF(G73>0,VLOOKUP(G73,Apoio!$A$2:$B$25,2,0),"") -> 8 | I73: =IF(D73>0,(((H73*E73)*C73)/D73),"") -> 56 | J73: 8 | K73: =I73-J73 -> 48 | M73: Gestão Jéssica Molero
A74: Atendimento e Serviço | B74: Athenas Atendimento | C74: 5 | D74: 6 | E74: 6 | F74: PI 1/26 | G74: SP 26.1.1 | H74: =IF(G74>0,VLOOKUP(G74,Apoio!$A$2:$B$25,2,0),"") -> 7 | I74: =IF(D74>0,(((H74*E74)*C74)/D74),"") -> 35 | M74: Gestão Jéssica Molero
A75: Atendimento e Serviço | B75: Athenas Atendimento | C75: 5 | D75: 6 | E75: 6 | F75: PI 1/26 | G75: SP 26.1.2 | H75: =IF(G75>0,VLOOKUP(G75,Apoio!$A$2:$B$25,2,0),"") -> 8 | I75: =IF(D75>0,(((H75*E75)*C75)/D75),"") -> 40 | M75: Gestão Jéssica Molero
A76: Atendimento e Serviço | B76: Athenas Atendimento | C76: 5 | D76: 6 | E76: 6 | F76: PI 1/26 | G76: SP 26.1.3 | H76: =IF(G76>0,VLOOKUP(G76,Apoio!$A$2:$B$25,2,0),"") -> 6 | I76: =IF(D76>0,(((H76*E76)*C76)/D76),"") -> 30 | M76: Gestão Jéssica Molero
A77: Atendimento e Serviço | B77: Athenas Atendimento | C77: 5 | D77: 6 | E77: 6 | F77: PI 1/26 | G77: SP 26.1.4 | H77: =IF(G77>0,VLOOKUP(G77,Apoio!$A$2:$B$25,2,0),"") -> 8 | I77: =IF(D77>0,(((H77*E77)*C77)/D77),"") -> 40 | M77: Gestão Jéssica Molero
A78: Atendimento e Serviço | B78: Athenas Atendimento | C78: 5 | D78: 6 | E78: 6 | F78: PI 1/26 | G78: SP 26.1.5 | H78: =IF(G78>0,VLOOKUP(G78,Apoio!$A$2:$B$25,2,0),"") -> 8 | I78: =IF(D78>0,(((H78*E78)*C78)/D78),"") -> 40 | M78: Gestão Jéssica Molero
A79: Atendimento e Serviço | B79: Athenas Atendimento | C79: 5 | D79: 6 | E79: 6 | F79: PI 1/26 | G79: SP 26.1.6 | H79: =IF(G79>0,VLOOKUP(G79,Apoio!$A$2:$B$25,2,0),"") -> 2 | I79: =IF(D79>0,(((H79*E79)*C79)/D79),"") -> 10 | M79: Gestão Jéssica Molero
A80: Atendimento e Serviço | B80: Athenas Atendimento | C80: 5 | D80: 6 | E80: 6 | F80: PI 2/26 | G80: SP 26.2.1 | H80: =IF(G80>0,VLOOKUP(G80,Apoio!$A$2:$B$25,2,0),"") -> 5 | I80: =IF(D80>0,(((H80*E80)*C80)/D80),"") -> 25 | M80: Gestão Jéssica Molero
A81: Atendimento e Serviço | B81: Athenas Atendimento | C81: 5 | D81: 6 | E81: 6 | F81: PI 2/26 | G81: SP 26.2.2 | H81: =IF(G81>0,VLOOKUP(G81,Apoio!$A$2:$B$25,2,0),"") -> 7 | I81: =IF(D81>0,(((H81*E81)*C81)/D81),"") -> 35 | M81: Gestão Jéssica Molero
A82: Atendimento e Serviço | B82: Athenas Atendimento | C82: 5 | D82: 6 | E82: 6 | F82: PI 2/26 | G82: SP 26.2.3 | H82: =IF(G82>0,VLOOKUP(G82,Apoio!$A$2:$B$25,2,0),"") -> 8 | I82: =IF(D82>0,(((H82*E82)*C82)/D82),"") -> 40 | M82: Gestão Jéssica Molero
A83: Atendimento e Serviço | B83: Athenas Atendimento | C83: 5 | D83: 6 | E83: 6 | F83: PI 2/26 | G83: SP 26.2.4 | H83: =IF(G83>0,VLOOKUP(G83,Apoio!$A$2:$B$25,2,0),"") -> 7 | I83: =IF(D83>0,(((H83*E83)*C83)/D83),"") -> 35 | M83: Gestão Jéssica Molero
A84: Atendimento e Serviço | B84: Athenas Atendimento | C84: 5 | D84: 6 | E84: 6 | F84: PI 2/26 | G84: SP 26.2.5 | H84: =IF(G84>0,VLOOKUP(G84,Apoio!$A$2:$B$25,2,0),"") -> 8 | I84: =IF(D84>0,(((H84*E84)*C84)/D84),"") -> 40 | M84: Gestão Jéssica Molero
A85: Atendimento e Serviço | B85: Athenas Atendimento | C85: 5 | D85: 6 | E85: 6 | F85: PI 2/26 | G85: SP 26.2.6 | H85: =IF(G85>0,VLOOKUP(G85,Apoio!$A$2:$B$25,2,0),"") -> 3 | I85: =IF(D85>0,(((H85*E85)*C85)/D85),"") -> 15 | M85: Gestão Jéssica Molero
... A91: Atendimento e Serviço | B91: Athenas Atendimento | C91: 5 | D91: 6 | E91: 6 | F91: PI 3/26 | G91: SP 26.3.6 | H91: =IF(G91>0,VLOOKUP(G91,Apoio!$A$2:$B$25,2,0),"") -> 3 | I91: =IF(D91>0,(((H91*E91)*C91)/D91),"") -> 15 | M91: Gestão Jéssica Molero
A92: Atendimento e Serviço | B92: Athenas Atendimento | C92: 5 | D92: 6 | E92: 6 | F92: PI 4/26 | G92: SP 26.4.1 | H92: =IF(G92>0,VLOOKUP(G92,Apoio!$A$2:$B$25,2,0),"") -> 8 | I92: =IF(D92>0,(((H92*E92)*C92)/D92),"") -> 40 | J92: 8 | K92: =I92-J92 -> 32 | M92: Gestão Jéssica Molero
A93: Atendimento e Serviço | B93: Athenas Atendimento | C93: 5 | D93: 6 | E93: 6 | F93: PI 4/26 | G93: SP 26.4.2 | H93: =IF(G93>0,VLOOKUP(G93,Apoio!$A$2:$B$25,2,0),"") -> 7 | I93: =IF(D93>0,(((H93*E93)*C93)/D93),"") -> 35 | J93: 8 | K93: =I93-J93 -> 27 | M93: Gestão Jéssica Molero
A94: Atendimento e Serviço | B94: Athenas Atendimento | C94: 5 | D94: 6 | E94: 6 | F94: PI 4/26 | G94: SP 26.4.3 | H94: =IF(G94>0,VLOOKUP(G94,Apoio!$A$2:$B$25,2,0),"") -> 7 | I94: =IF(D94>0,(((H94*E94)*C94)/D94),"") -> 35 | J94: 8 | K94: =I94-J94 -> 27 | M94: Gestão Jéssica Molero
A95: Atendimento e Serviço | B95: Athenas Atendimento | C95: 5 | D95: 6 | E95: 6 | F95: PI 4/26 | G95: SP 26.4.4 | H95: =IF(G95>0,VLOOKUP(G95,Apoio!$A$2:$B$25,2,0),"") -> 7 | I95: =IF(D95>0,(((H95*E95)*C95)/D95),"") -> 35 | J95: 8 | K95: =I95-J95 -> 27 | M95: Gestão Jéssica Molero
A96: Atendimento e Serviço | B96: Athenas Atendimento | C96: 5 | D96: 6 | E96: 6 | F96: PI 4/26 | G96: SP 26.4.5 | H96: =IF(G96>0,VLOOKUP(G96,Apoio!$A$2:$B$25,2,0),"") -> 8 | I96: =IF(D96>0,(((H96*E96)*C96)/D96),"") -> 40 | J96: 8 | K96: =I96-J96 -> 32 | M96: Gestão Jéssica Molero
A97: Atendimento e Serviço | B97: Athenas Atendimento | C97: 5 | D97: 6 | E97: 6 | F97: PI 4/26 | G97: SP 26.4.6 | H97: =IF(G97>0,VLOOKUP(G97,Apoio!$A$2:$B$25,2,0),"") -> 8 | I97: =IF(D97>0,(((H97*E97)*C97)/D97),"") -> 40 | J97: 8 | K97: =I97-J97 -> 32 | M97: Gestão Jéssica Molero
A98: Secretaria e Gestor de Unidades | B98: Athenas Sec. Enturmação | C98: 5 | D98: 6 | E98: 6 | F98: PI 1/26 | G98: SP 26.1.1 | H98: 7 | I98: =IF(D98>0,(((H98*E98)*C98)/D98),"") -> 35 | J98: 8 | K98: =I98-J98 -> 27 | L98: =2647.87*I98 -> 92675.45 | M98: Atualizado | N98: Férias Rosana -7 pontos, descontado no campo qtde devs
A99: Secretaria e Gestor de Unidades | B99: Athenas Sec. Enturmação | C99: 4 | D99: 6 | E99: 6 | F99: PI 1/26 | G99: SP 26.1.2 | H99: =IF(G99>0,VLOOKUP(G99,Apoio!$A$2:$B$25,2,0),"") -> 8 | I99: =IF(D99>0,(((H99*E99)*C99)/D99),"") -> 32 | J99: 8 | K99: =I99-J99 -> 24 | L99: =2647.87*I99 -> 84731.84 | M99: Atualizado | N99: Rosana afastada
A100: Secretaria e Gestor de Unidades | B100: Athenas Sec. Enturmação | C100: 4 | D100: 6 | E100: 6 | F100: PI 1/26 | G100: SP 26.1.3 | H100: =IF(G100>0,VLOOKUP(G100,Apoio!$A$2:$B$25,2,0),"") -> 6 | I100: =IF(D100>0,(((H100*E100)*C100)/D100),"") -> 24 | J100: 8 | K100: =I100-J100 -> 16 | L100: =2647.87*I100 -> 63548.88 | M100: Atualizado
A101: Secretaria e Gestor de Unidades | B101: Athenas Sec. Enturmação | C101: 3 | D101: 6 | E101: 6 | F101: PI 1/26 | G101: SP 26.1.4 | H101: =IF(G101>0,VLOOKUP(G101,Apoio!$A$2:$B$25,2,0),"") -> 8 | I101: =IF(D101>0,(((H101*E101)*C101)/D101),"") -> 24 | J101: 5 | K101: =I101-J101 -> 19 | L101: =2647.87*I101 -> 63548.88 | M101: Atualizado | N101: Time N2 -1(Lary)
A102: Secretaria e Gestor de Unidades | B102: Athenas Sec. Enturmação | C102: 3.5 | D102: 6 | E102: 6 | F102: PI 1/26 | G102: SP 26.1.5 | H102: =IF(G102>0,VLOOKUP(G102,Apoio!$A$2:$B$25,2,0),"") -> 8 | I102: =IF(D102>0,(((H102*E102)*C102)/D102),"") -> 28 | J102: 5 | K102: =I102-J102 -> 23 | L102: =2647.87*I102 -> 74140.36 | M102: Atualizado | N102: Time N2 -1(Lary)
A103: Secretaria e Gestor de Unidades | B103: Athenas Sec. Enturmação | C103: 4 | D103: 6 | E103: 6 | F103: PI 1/26 | G103: SP 26.1.6 | H103: =IF(G103>0,VLOOKUP(G103,Apoio!$A$2:$B$25,2,0),"") -> 2 | I103: =IF(D103>0,(((H103*E103)*C103)/D103),"") -> 8 | J103: 3 | K103: =I103-J103 -> 5 | L103: =2647.87*I103 -> 21182.96 | M103: Atualizado | N103: Time N2 -1(Lary)
A104: Secretaria e Gestor de Unidades | B104: Athenas Sec. Enturmação | C104: 4.5 | D104: 6 | E104: 6 | F104: PI 2/26 | G104: SP 26.2.1 | H104: =IF(G104>0,VLOOKUP(G104,Apoio!$A$2:$B$25,2,0),"") -> 5 | I104: =IF(D104>0,(((H104*E104)*C104)/D104),"") -> 22.5 | J104: 5 | K104: =I104-J104+9-1 -> 25.5 | L104: =2647.87*I104 -> 59577.075 | M104: Atualizar | N104: Lary+1, Luna+2, Marcos+2, Ruanderson+1, Alexandre+2, Kauan+1
A105: Secretaria e Gestor de Unidades | B105: Athenas Sec. Enturmação | C105: 5 | D105: 6 | E105: 6 | F105: PI 2/26 | G105: SP 26.2.2 | H105: =IF(G105>0,VLOOKUP(G105,Apoio!$A$2:$B$25,2,0),"") -> 7 | I105: =IF(D105>0,(((H105*E105)*C105)/D105),"") -> 35 | J105: 8 | K105: =I105-J105+10 -> 37 | L105: =2647.87*I105 -> 92675.45 | M105: Atualizar | N105: Lary+2, Luna+2, Marcos+2, Ruanderson+1, Alexandre+2, Kauan+1
A106: Secretaria e Gestor de Unidades | B106: Athenas Sec. Enturmação | C106: 5.3 | D106: 6 | E106: 6 | F106: PI 2/26 | G106: SP 26.2.3 | H106: =IF(G106>0,VLOOKUP(G106,Apoio!$A$2:$B$25,2,0),"") -> 8 | I106: =IF(D106>0,(((H106*E106)*C106)/D106),"") -> 42.4 | J106: 8 | K106: =I106-J106+10+3 -> 47.4 | L106: =2647.87*I106 -> 112269.69 | M106: Atualizar | N106: Lary+2, Luna+2, Marcos+2, Ruanderson+1, Alexandre+2, Kauan+1
A107: Secretaria e Gestor de Unidades | B107: Athenas Sec. Enturmação | C107: 6 | D107: 6 | E107: 6 | F107: PI 2/26 | G107: SP 26.2.4 | H107: =IF(G107>0,VLOOKUP(G107,Apoio!$A$2:$B$25,2,0),"") -> 7 | I107: =IF(D107>0,(((H107*E107)*C107)/D107),"") -> 42 | J107: 8 | K107: =I107-J107+10+5 -> 49 | L107: =2647.87*I107 -> 111210.54 | M107: Atualizar | N107: Lary+2, Luna+2, Marcos+2, Ruanderson+1, Alexandre+2, Kauan+1
A108: Secretaria e Gestor de Unidades | B108: Athenas Sec. Enturmação | C108: 6.5 | D108: 6 | E108: 6 | F108: PI 2/26 | G108: SP 26.2.5 | H108: =IF(G108>0,VLOOKUP(G108,Apoio!$A$2:$B$25,2,0),"") -> 8 | I108: =IF(D108>0,(((H108*E108)*C108)/D108),"") -> 52 | J108: 8 | K108: =I108-J108+10+8 -> 62 | L108: =2647.87*I108 -> 137689.24 | M108: Atualizar | N108: Lary+2, Luna+2, Marcos+2, Ruanderson+1, Alexandre+2, Kauan+1
A109: Secretaria e Gestor de Unidades | B109: Athenas Sec. Enturmação | C109: 6.5 | D109: 6 | E109: 6 | F109: PI 2/26 | G109: SP 26.2.6 | H109: =IF(G109>0,VLOOKUP(G109,Apoio!$A$2:$B$25,2,0),"") -> 3 | I109: =IF(D109>0,(((H109*E109)*C109)/D109),"") -> 19.5 | J109: 5 | K109: =I109-J109 -> 14.5 | L109: =2647.87*I109 -> 51633.465 | M109: Atualizar
A110: Secretaria e Gestor de Unidades | B110: Athenas Sec. Enturmação | C110: 6.5 | D110: 7 | E110: 6 | F110: PI 3/26 | G110: SP 26.3.1 | H110: =IF(G110>0,VLOOKUP(G110,Apoio!$A$2:$B$25,2,0),"") -> 7 | I110: =IF(D110>0,(((H110*E110)*C110)/D110),"") -> 39 | J110: 7 | K110: =I110-J110-2 -> 30 | M110: Atualizado | N110: Day off Luna -2 pontos
A111: Secretaria e Gestor de Unidades | B111: Athenas Sec. Enturmação | C111: 6.5 | D111: 7 | E111: 6 | F111: PI 3/26 | G111: SP 26.3.2 | H111: =IF(G111>0,VLOOKUP(G111,Apoio!$A$2:$B$25,2,0),"") -> 8 | I111: =IF(D111>0,(((H111*E111)*C111)/D111),"") -> 44.571429 | J111: 7 | K111: =I111-J111-2 -> 35.571429 | M111: Atualizado | N111: Day Off Lary -2 pontos
A112: Secretaria e Gestor de Unidades | B112: Athenas Sec. Enturmação | C112: 6.5 | D112: 7 | E112: 6 | F112: PI 3/26 | G112: SP 26.3.3 | H112: =IF(G112>0,VLOOKUP(G112,Apoio!$A$2:$B$25,2,0),"") -> 8 | I112: =IF(D112>0,(((H112*E112)*C112)/D112),"") -> 44.571429 | J112: 10 | K112: =I112-J112 -> 34.571429 | M112: Atualizado
A113: Secretaria e Gestor de Unidades | B113: Athenas Sec. Enturmação | C113: 5.5 | D113: 7 | E113: 6 | F113: PI 3/26 | G113: SP 26.3.4 | H113: =IF(G113>0,VLOOKUP(G113,Apoio!$A$2:$B$25,2,0),"") -> 8 | I113: =IF(D113>0,(((H113*E113)*C113)/D113),"") -> 37.714286 | J113: 10 | K113: =I113-J113 -> 27.714286 | M113: Atualizado
A114: Secretaria e Gestor de Unidades | B114: Athenas Sec. Enturmação | C114: 6.5 | D114: 7 | E114: 6 | F114: PI 3/26 | G114: SP 26.3.5 | H114: =IF(G114>0,VLOOKUP(G114,Apoio!$A$2:$B$25,2,0),"") -> 7 | I114: =IF(D114>0,(((H114*E114)*C114)/D114),"")-1 -> 38 | J114: 7 | K114: =I114-J114 -> 31 | M114: Atualizado - 1 pt Yasmin Day Off
A115: Secretaria e Gestor de Unidades | B115: Athenas Sec. Enturmação | C115: 6.5 | D115: 7 | E115: 6 | F115: PI 3/26 | G115: SP 26.3.6 | H115: =IF(G115>0,VLOOKUP(G115,Apoio!$A$2:$B$25,2,0),"") -> 3 | I115: =IF(D115>0,(((H115*E115)*C115)/D115),"") -> 16.714286 | J115: 5 | K115: =I115-J115 -> 11.714286 | M115: Atualizado
A116: Secretaria e Gestor de Unidades | B116: Athenas Sec. Enturmação | C116: 7 | D116: 7 | E116: 6 | F116: PI 4/26 | G116: SP 26.4.1 | H116: =IF(G116>0,VLOOKUP(G116,Apoio!$A$2:$B$25,2,0),"") -> 8 | I116: =IF(D116>0,(((H116*E116)*C116)/D116),"") -> 48 | J116: 8 | K116: =I116-J116-4 -> 36 | M116: Atualizar
A117: Secretaria e Gestor de Unidades | B117: Athenas Sec. Enturmação | C117: 7 | D117: 7 | E117: 6 | F117: PI 4/26 | G117: SP 26.4.2 | H117: =IF(G117>0,VLOOKUP(G117,Apoio!$A$2:$B$25,2,0),"") -> 7 | I117: =IF(D117>0,(((H117*E117)*C117)/D117),"") -> 42 | J117: 8 | K117: =I117-J117-4 -> 30 | M117: Atualizar
A118: Secretaria e Gestor de Unidades | B118: Athenas Sec. Enturmação | C118: 7 | D118: 7 | E118: 6 | F118: PI 4/26 | G118: SP 26.4.3 | H118: =IF(G118>0,VLOOKUP(G118,Apoio!$A$2:$B$25,2,0),"") -> 7 | I118: =IF(D118>0,(((H118*E118)*C118)/D118),"") -> 42 | J118: 8 | K118: =I118-J118-4 -> 30 | M118: Atualizar
A119: Secretaria e Gestor de Unidades | B119: Athenas Sec. Enturmação | C119: 7 | D119: 7 | E119: 6 | F119: PI 4/26 | G119: SP 26.4.4 | H119: =IF(G119>0,VLOOKUP(G119,Apoio!$A$2:$B$25,2,0),"") -> 7 | I119: =IF(D119>0,(((H119*E119)*C119)/D119),"") -> 42 | J119: 8 | K119: =I119-J119-4 -> 30 | M119: Atualizar
A120: Secretaria e Gestor de Unidades | B120: Athenas Sec. Enturmação | C120: 7 | D120: 7 | E120: 6 | F120: PI 4/26 | G120: SP 26.4.5 | H120: =IF(G120>0,VLOOKUP(G120,Apoio!$A$2:$B$25,2,0),"") -> 8 | I120: =IF(D120>0,(((H120*E120)*C120)/D120),"") -> 48 | J120: 8 | K120: =I120-J120-4 -> 36 | M120: Atualizar
...
