Workbook
Name Tab_Baseline: OFFSET(Baseline!#REF!,0,0,COUNTA(Baseline!$A:$A),COUNTA(Baseline!#REF!))
Name Tab_Debitos_Tecnicos_Backlog: OFFSET('Debitos Tecnicos_Backlog'!$A$1,0,0,COUNTA('Debitos Tecnicos_Backlog'!$A:$A),COUNTA('Debitos Tecnicos_Backlog'!$1:$1))
Name Tab_Debitos_Tecnicos_PI: OFFSET('Debitos Tecnicos_PI'!$A$1,0,0,COUNTA('Debitos Tecnicos_PI'!$A:$A),COUNTA('Debitos Tecnicos_PI'!$1:$1))
Name Tab_Épicos_Jornada: OFFSET('Extração Jira - Épicos Jornada'!$A$1,0,0,COUNTA('Extração Jira - Épicos Jornada'!$A:$A),COUNTA('Extração Jira - Épicos Jornada'!$1:$1))
Name Tab_Extração_Jira_Épicos: OFFSET('Extração Jira - Itens (Épicos)'!$A$1,0,0,COUNTA('Extração Jira - Itens (Épicos)'!$A:$A),COUNTA('Extração Jira - Itens (Épicos)'!$1:$1))
Name Tab_Impedimentos: OFFSET(Impedimento!$K$2,0,0,COUNTA(Impedimento!$K$2:$K$135),COUNTA(Impedimento!$K$16:$BR$16))
Name Tab_Itens_Jira: OFFSET('Extração Jira - Itens'!$A$1,0,0,COUNTA('Extração Jira - Itens'!$A:$A),COUNTA('Extração Jira - Itens'!$1:$1))

Sheet Review
B2: REVIEW
B5: Data | C5: Versão | D5: Alteração
B6: 45961 | C6: 13 | D6: - Inclusão do tempo de bloqueio na extração do Jira e na fórmula do ciclo de desenvolvimento - Inclusão do total de story points faltantes para conclusão dos épicos na aba "Situação dos Épicos"

Sheet Informações
B2: INFORMAÇÕES PARA GERAR OS INDICADORES | F2: Leia com atenção
B4: PREMISSAS
B5: * Não deverá considerar as informações da última sprint para gerar os indicadores; * Épicos compartilhados só deverão ser contabilizados na Jornada que é responsavel pelo épico; * Atenção: Colunas pintadas da AZUL contém fórmulas
B7: 1º PASSO: EXTRAÇÃO DAS INFORMAÇÕES
B8: Nome | C8: Descrição | D8: JQL | E8: Colunas | F8: Onde colar as informações
B9: Baseline | C9: Extração de todos os itens planejado pelos times da Jornada na PI Planning OBS: Essa extração é uma foto, deve ter sido feita logo após a PI Planning | D9: project in (APAP, APAV, APSF, APCO, APPL, APIN, ADPL, ADR6, ADKB, ADTH, ADTP, ADGP, ADSE, ASEC, ATEN, JIEC, JICA, JIBK, JIMF, JIAE, JICE, JICS, JACO, JAMO, JAAM, JFHM, JFSP, JFTR, JFEA, APDO, PGCM, PGEX, PGIA, PGAL, PGIA, PGAL, SAJO, SATT, SADV, "[Voomp] Meios de Pagamento", "[Voomp] Admin", "[Voomp] App", "[Voomp] Play", "[Voomp] Pos") AND issuetype in standardIssueTypes() AND Sprint in ("25.2.1","25.2.2", "25.2.3", "25.2.4", "25.2.5", "25.2.6") ORDER BY project | E9: Tipo de item Resumo Chave Status Resolução Criado Start date Resolvido Versões corrigidas Tipo item pai parent Tempo gasto Σ de Tempo Gasto Story point estimate Story Points Sprint Ponto de compromisso Tipo Categoria do status Alteração de escopo (após a última PIP)? Inicio do fluxo Fim do fluxo Início Homologação Fim Homologação Início Implantação Fim Implantação Ciclo de Ideação Ciclo de Desenvolvimento Ciclo Homologação Ciclo de Implantação Lead Time Costumer Lead Time Tipo Sustentação Projeto | F9: Planilha Baseline
B10: Extração Jira - Itens | C10: Extração atual de todos os itens trabalhado pelos times independente do status até a penultima sprint, ou seja, não trazer as informações da última sprint. | D10: project in (ADKB,ADMD,ADPL,ADR6,ADTH,ADTP) AND issuetype in ("Débito Técnico", Enabler, Story, Spike, Teste, Incidente,"Solicitação de Serviço", bug, Sustentação, Suporte) AND SPRINT in ("24.3.1","24.3.2","24.3.3","24.3.4","24.3.5") ORDER BY cf[10315] DESC Link do filtro: https://cogna.atlassian.net/issues/?filter=16979&atlOrigin=eyJpIjoiMmU4ZjExYTU0YjE4NGU3YThkNTNlNTFhMTQ5OTY2ZDkiLCJwIjoiaiJ9 | E10: 1- Tipo de item 2- Resumo 3- Projeto 4- Chave 5- Status 6- Versões corrigidas 7- Sprint 8- Story Points 9- Story point estimate 10- Σ de Tempo Gasto 11- Tipo 12- Categoria do status 13- Pai 14- Alteração de escopo (após a última PIP)? 15- Resolução 16- Criado 17- Ponto de compromisso 18- Inicio do fluxo 19- Fim do fluxo 20- Início Homologação 21- Fim Homologação 22- Início Implantação 23- Fim Implantação 24- Ciclo de Ideação 25- Ciclo de Desenvolvimento 26- Ciclo Homologação 27- Ciclo de Implantação 28- Lead Time 29- Costumer Lead Time 30 - Tipo Sustentação 31 - Este item sofreu antecipação? 32 - Ambiente 33 - Tempo Total Bloqueado | F10: Planilha Extração Jira - Itens
B12: Débitos Tecnicos_Backlog | C12: Extração dos itens cadastrados com Débito técnico que os times ainda não entregaram e não estão planejados para a PI corrente | D12: project = ADPL and issuetype = "Débito Técnico" and status in (backlog) and (sprint not in("25.2") or Sprint = EMPTY) | E12: Recuperando dados. Aguarde alguns segundos e tente cortar ou copiar novamente. | F12: Planilha Débito Técnico *Abaixo da linha amarela
B13: Débitos Tecnicos_PI | C13: Backlog planejado (PI vigente) - todos os status Encerrados (PI vigente) - aceito, pendente produção, em produção Pendente (PI vigente) - tudo diferente de encerrado e cancelado Cancelados (PI vigente) | D13: project = ADPL and issuetype = "Débito Técnico" and sprint in ("25.2") | E13: 1 - Projeto 2 - Tipo de item 3 - Chave 4 - Status 5 - Versão Corrigida 6 - Sprint 7 - Story Points
B14: Extração Jira - Épicos Jornada | C14: Extração da lista de épicos que a tribo é a dona | D14: category IN (ARTPT, "Tribo - Jornada Acadêmica", "Squad - Jornada Acadêmica") And "Jornada dona do Epico[Group Picker (single group)]" = "[ART] Jornada Acadêmica" And issuetype = Epic And fixVersion ~ "*2/25*" | E14: 1- Tipo de item 2- Resumo 3- Projeto 4- Chave 5- Status 6- Versões corrigidas
B15: Extração Jira - Itens (Épicos) | C15: Extração da lista de itens (da tribo ou não) de todos os épicos que a tribo é dona | D15: issuetype in (standardIssueTypes()) and issuetype not in (Design, "Esforço Preliminar") and parent in (ARTPT-385,ARTPT-393, APDO-577, APDO-2061) ORDER BY parent | E15: 1- Tipo de item 2- Resumo 3- Projeto 4- Chave 5- Status 6- Versões corrigidas 7- Sprint 8- Story Points 9- Story point estimate 10- Σ de Tempo Gasto 11- Tipo 12- Categoria do status 13- Pai 14- Alteração de escopo (após a última PIP)? 15- Resolução 16- Criado 17- Ponto de compromisso 18- Inicio do fluxo 19- Fim do fluxo 20- Início Homologação 21- Fim Homologação 22- Início Implantação 23- Fim Implantação 24- Ciclo de Ideação 25- Ciclo de Desenvolvimento 26- Ciclo Homologação 27- Ciclo de Implantação 28- Lead Time 29- Costumer Lead Time 30 - Tipo Sustentação 31 - Este item sofreu antecipação?
B16: - Após colar os dados extraídos é importante converter para número ondem for necessário e verificar se as formulas estão indo até a última linha
B19: 2º PASSO: GERAR CADA INDICADOR
B20: (1) Clicar sobre a tabela dinâmica com o botão direito e clicar na opção "Atualizar"
B21: (2) Preencher as tabelinhas com os valores apresentados nas tabelas dinâmicas (conforme orientações apresentadas em cada indicador)
B22: (3) Conferir se os valores gerados estão conforme esperado
B23: (4) Copiar gráfico para os slides

Sheet Baseline
A1: Tipo de item | B1: Resumo | C1: Chave | D1: Status | E1: Criado | F1: Start date | G1: Versões corrigidas | H1: parent | I1: Tempo gasto | J1: Σ de Tempo Gasto | K1: Story point estimate | L1: Story Points | M1: Sprint | N1: Checklist Progress | O1: Ponto de compromisso | P1: Tipo | Q1: Categoria do status | R1: Alteração de escopo (após a última PIP)? | S1: Inicio do fluxo | T1: Fim do fluxo | U1: Início Homologação | V1: Fim Homologação | W1: Início Implantação | X1: Fim Implantação | Y1: Ciclo de Ideação | Z1: Ciclo de Desenvolvimento | AA1: Ciclo Homologação | AB1: Ciclo de Implantação | AC1: Lead Time | AD1: Costumer Lead Time | AE1: Tipo Sustentação | AF1: Projeto | AG1: Jornada dona do Epico | AH1: Σ Estimativa de trabalho restante | AI1: Alteração de escopo (após a última PIP)? | AJ1: Responsável | AK1: Tempo bloqueado | AL1: Dias Bloqueados | AM1: Squad Responsável | AN1: OKRs de 2025 | AO1: Tipo Sustentação
A2: Incidente | B2: [INC0796440]Tenho um Erro/Problema com o PTC - Dynamics Athenas - Envio de reatórios | C2: SGGU-6546 | D2: Backlog | G2: [SGGU] PI 3/26 | M2: [SGGU] SP 26.3.1 | AF2: [Jornada Secretaria e Gestor de Unidades] Gestor de Unidades | AG2: Jornada Secretaria e Gestor de Unidades
A3: Incidente | B3: [INC0796379]Tenho um Erro/Problema com o PTC - Dynamics Athenas - Inativação de curso e ofertas | C3: SGGU-6545 | D3: Backlog | G3: [SGGU] PI 3/26 | M3: [SGGU] SP 26.3.1 | AF3: [Jornada Secretaria e Gestor de Unidades] Gestor de Unidades | AG3: Jornada Secretaria e Gestor de Unidades
A4: Incidente | B4: [INC0796118]Tenho um Erro/Problema no Dynamics - Gestão de unidades - Reportar um erro/problema | C4: SGGU-6541 | D4: Em Andamento | G4: [SGGU] PI 3/26 | M4: [SGGU] SP 26.3.1 | AF4: [Jornada Secretaria e Gestor de Unidades] Gestor de Unidades | AG4: Jornada Secretaria e Gestor de Unidades
A5: Incidente | B5: [INC0796099]Tenho um Erro/Problema no Dynamics - Gestão de unidades - Reportar um erro/problema | C5: SGGU-6540 | D5: Aceito | G5: [SGGU] PI 3/26 | M5: [SGGU] SP 26.3.1 | AF5: [Jornada Secretaria e Gestor de Unidades] Gestor de Unidades | AG5: Jornada Secretaria e Gestor de Unidades
A6: Incidente | B6: [INC0756582]Tenho um Erro/Problema no Dynamics - Gestão de unidades - Reportar um erro/problema | C6: SGGU-6539 | D6: Aceito | G6: [SGGU] PI 3/26 | M6: [SGGU] SP 26.2.6;[SGGU] SP 26.3.1 | AF6: [Jornada Secretaria e Gestor de Unidades] Gestor de Unidades | AG6: Jornada Secretaria e Gestor de Unidades
A7: Incidente | B7: [INC0794566]Tenho um Erro/Problema no Dynamics - Gestão de unidades - Reportar um erro/problema | C7: SGGU-6536 | D7: Backlog | G7: [SGGU] PI 3/26 | M7: [SGGU] SP 26.2.6;[SGGU] SP 26.3.1 | AF7: [Jornada Secretaria e Gestor de Unidades] Gestor de Unidades | AG7: Jornada Secretaria e Gestor de Unidades
A8: Incidente | B8: [INC0782154]Tenho um Erro/Problema com o PTC - Dynamics Athenas - Atualização de Dados Cadastrais | C8: SGGU-6535 | D8: Aceito | G8: [SGGU] PI 3/26 | M8: [SGGU] SP 26.2.6;[SGGU] SP 26.3.1 | AF8: [Jornada Secretaria e Gestor de Unidades] Gestor de Unidades | AG8: Jornada Secretaria e Gestor de Unidades
A9: Incidente | B9: [INC0794335]Tenho um Erro/Problema no Dynamics - Gestão de unidades - Reportar um erro/problema | C9: SGGU-6534 | D9: Concluído | G9: [SGGU] PI 3/26 | M9: [SGGU] SP 26.2.6;[SGGU] SP 26.3.1 | AF9: [Jornada Secretaria e Gestor de Unidades] Gestor de Unidades | AG9: Jornada Secretaria e Gestor de Unidades
A10: Incidente | B10: [INC0793763]Tenho um Erro/Problema no Dynamics - Gestão de unidades - Reportar um erro/problema | C10: SGGU-6490 | D10: Concluído | G10: [SGGU] PI 3/26 | M10: [SGGU] SP 26.2.6;[SGGU] SP 26.3.1 | AF10: [Jornada Secretaria e Gestor de Unidades] Gestor de Unidades | AG10: Jornada Secretaria e Gestor de Unidades
A11: Teste | B11: Apoio criação de oferta de Serviço Social para time de estágio | C11: SGGU-6446 | D11: Backlog | G11: [SGGU] PI 3/26 | H11: JAES-650 | K11: 2 | L11: 2 | M11: [SGGU] SP 26.3.3 | AF11: [Jornada Secretaria e Gestor de Unidades] Gestor de Unidades | AG11: Jornada Secretaria e Gestor de Unidades
A12: História | B12: [Curso MEC] Mapear quais tabelas, campos e filtros precisam ter ajuste no layout para apresentar o código vínculo (bk) e código mec (atributo) | C12: SGGU-6444 | D12: Backlog | G12: [SGGU] PI 3/26 | H12: SGGS-11290 | K12: 5 | L12: 5 | M12: [SGGU] SP 26.3.3 | AF12: [Jornada Secretaria e Gestor de Unidades] Gestor de Unidades | AG12: Jornada Secretaria e Gestor de Unidades
A13: História | B13: [Curso MEC] Frontend - Realizar alterações para consumir o Código Vínculo (BK) - Curso SEMI | C13: SGGU-6431 | D13: Backlog | G13: [SGGU] PI 3/26 | H13: SGGS-11290 | K13: 5 | L13: 5 | M13: [SGGU] SP 26.3.5 | AF13: [Jornada Secretaria e Gestor de Unidades] Gestor de Unidades | AG13: Jornada Secretaria e Gestor de Unidades
A14: Enabler | B14: [Curso MEC] Backend - Realizar alterações para consumir o Código Vínculo (BK) - Curso SEMI | C14: SGGU-6430 | D14: Backlog | G14: [SGGU] PI 3/26 | H14: SGGS-11290 | K14: 8 | L14: 8 | M14: [SGGU] SP 26.3.4 | AF14: [Jornada Secretaria e Gestor de Unidades] Gestor de Unidades | AG14: Jornada Secretaria e Gestor de Unidades
A15: Enabler | B15: [Curso MEC] Mapear fluxos e alterações que deverão passar a consumir o novo Código Vínculo (BK) e Código MEC (atributo) | C15: SGGU-6429 | D15: Backlog | G15: [SGGU] PI 3/26 | H15: SGGS-11290 | K15: 5 | L15: 5 | M15: [SGGU] SP 26.3.3 | AF15: [Jornada Secretaria e Gestor de Unidades] Gestor de Unidades | AG15: Jornada Secretaria e Gestor de Unidades
A16: Enabler | B16: [Curso MEC] Backend - Realizar alterações para consumir o Código Vínculo (BK) - Tipo de Produto | C16: SGGU-6428 | D16: Backlog | G16: [SGGU] PI 3/26 | H16: SGGS-11290 | K16: 8 | L16: 8 | M16: [SGGU] SP 26.3.4 | AF16: [Jornada Secretaria e Gestor de Unidades] Gestor de Unidades | AG16: Jornada Secretaria e Gestor de Unidades
A17: Enabler | B17: [Curso MEC] Backend - Realizar alterações para consumir o Código Vínculo (BK) - Curso por tipo de produto | C17: SGGU-6427 | D17: Backlog | G17: [SGGU] PI 3/26 | H17: SGGS-11290 | K17: 8 | L17: 8 | M17: [SGGU] SP 26.3.4 | AF17: [Jornada Secretaria e Gestor de Unidades] Gestor de Unidades | AG17: Jornada Secretaria e Gestor de Unidades
A18: Enabler | B18: [Curso MEC] Backend - Realizar alterações para consumir o Código Vínculo (BK) - Portfólio Padrão | C18: SGGU-6426 | D18: Backlog | G18: [SGGU] PI 3/26 | H18: SGGS-11290 | K18: 8 | L18: 8 | M18: [SGGU] SP 26.3.4 | AF18: [Jornada Secretaria e Gestor de Unidades] Gestor de Unidades | AG18: Jornada Secretaria e Gestor de Unidades
A19: História | B19: [Curso MEC] Frontend - Realizar alterações para consumir o Código Vínculo (BK) - Curso por tipo de produto | C19: SGGU-6425 | D19: Backlog | G19: [SGGU] PI 3/26 | H19: SGGS-11290 | K19: 5 | L19: 5 | M19: [SGGU] SP 26.3.5 | AF19: [Jornada Secretaria e Gestor de Unidades] Gestor de Unidades | AG19: Jornada Secretaria e Gestor de Unidades
A20: História | B20: [Curso MEC] Frontend - Realizar alterações para consumir o Código Vínculo (BK) - Portfólio Padrão | C20: SGGU-6424 | D20: Backlog | G20: [SGGU] PI 3/26 | H20: SGGS-11290 | K20: 5 | L20: 5 | M20: [SGGU] SP 26.3.5 | AF20: [Jornada Secretaria e Gestor de Unidades] Gestor de Unidades | AG20: Jornada Secretaria e Gestor de Unidades
A21: Solicitação de Serviço | B21: [RITM0718223]Solicitação de Serviço ao PTC - Gestão de Unidades - Gestão de Unidades | C21: SGGU-6422 | D21: Backlog | G21: [SGGU] PI 3/26 | M21: [SGGU] SP 26.3.1 | AF21: [Jornada Secretaria e Gestor de Unidades] Gestor de Unidades | AG21: Jornada Secretaria e Gestor de Unidades
A22: Teste | B22: [SGGU-5187] Teste Integrado | C22: SGGU-6420 | D22: Backlog | G22: [SGGU] PI 3/26 | H22: SGGU-5187 | K22: 1 | L22: 1 | M22: [SGGU] SP 26.3.5 | AF22: [Jornada Secretaria e Gestor de Unidades] Gestor de Unidades | AG22: Jornada Secretaria e Gestor de Unidades
A23: Incidente | B23: [INC0792429]Tenho um Erro/Problema com o PTC - Dynamics Athenas - Alocação do tutor a turma | C23: SGGU-6418 | D23: Concluído | G23: [SGGU] PI 3/26 | M23: [SGGU] SP 26.2.6;[SGGU] SP 26.3.1 | AF23: [Jornada Secretaria e Gestor de Unidades] Gestor de Unidades | AG23: Jornada Secretaria e Gestor de Unidades
A24: Incidente | B24: [INC0791299]Tenho um Erro/Problema com o PTC - Dynamics Athenas - Alocação do tutor a turma | C24: SGGU-6413 | D24: Aceito | G24: [SGGU] PI 3/26 | M24: [SGGU] SP 26.2.6;[SGGU] SP 26.3.1 | AF24: [Jornada Secretaria e Gestor de Unidades] Gestor de Unidades | AG24: Jornada Secretaria e Gestor de Unidades
A25: Solicitação de Serviço | B25: [RITM0717458]Solicitação de Serviço ao PTC - Gestão de Unidades - Gestão de Unidades | C25: SGGU-6400 | D25: Concluído | G25: [SGGU] PI 3/26 | M25: [SGGU] SP 26.2.6;[SGGU] SP 26.3.1 | AF25: [Jornada Secretaria e Gestor de Unidades] Gestor de Unidades | AG25: Jornada Secretaria e Gestor de Unidades
A26: Enabler | B26: [GU] [Síncrona Mediada] Analisar o recebimento das informações no tópico | C26: SGGU-6399 | D26: Backlog | G26: [SGGU] PI 3/26 | H26: APAP-10055 | K26: 0 | L26: 2 | M26: [SGGU] SP 26.3.4 | AF26: [Jornada Secretaria e Gestor de Unidades] Gestor de Unidades | AG26: Jornada Secretaria e Gestor de Unidades
A27: Enabler | B27: [GU] [Síncrona Mediada] Teste Regrevisso | C27: SGGU-6392 | D27: Backlog | G27: [SGGU] PI 3/26 | H27: APAP-10055 | K27: 5 | L27: 5 | M27: [SGGU] SP 26.3.6 | AF27: [Jornada Secretaria e Gestor de Unidades] Gestor de Unidades | AG27: Jornada Secretaria e Gestor de Unidades
A28: Enabler | B28: [185] [GU] Validação customização dos plugins | C28: SGGU-6390 | D28: Backlog | G28: [SGGU] PI 3/26 | H28: ARTSG-185 | K28: 1 | L28: 1 | M28: [SGGU] SP 26.3.3 | AF28: [Jornada Secretaria e Gestor de Unidades] Gestor de Unidades | AG28: Jornada Secretaria e Gestor de Unidades
A29: Enabler | B29: [185] [GU] Validação customização dos plugins | C29: SGGU-6389 | D29: Backlog | G29: [SGGU] PI 3/26 | H29: ARTSG-185 | K29: 1 | L29: 1 | M29: [SGGU] SP 26.3.2 | AF29: [Jornada Secretaria e Gestor de Unidades] Gestor de Unidades | AG29: Jornada Secretaria e Gestor de Unidades
A30: Enabler | B30: [GU] [Síncrona Mediada] Consumir tópicos e realizar teste de conectividade | C30: SGGU-6388 | D30: Backlog | G30: [SGGU] PI 3/26 | H30: APAP-10055 | K30: 8 | L30: 8 | M30: [SGGU] SP 26.3.5 | AF30: [Jornada Secretaria e Gestor de Unidades] Gestor de Unidades | AG30: Jornada Secretaria e Gestor de Unidades
A31: Enabler | B31: [185] [GU] Validação customização dos plugins | C31: SGGU-6387 | D31: Backlog | G31: [SGGU] PI 3/26 | H31: ARTSG-185 | K31: 1 | L31: 1 | M31: [SGGU] SP 26.3.1 | AF31: [Jornada Secretaria e Gestor de Unidades] Gestor de Unidades | AG31: Jornada Secretaria e Gestor de Unidades
A32: História | B32: [GU] [Síncrona Mediada] Criar nova tabela/layout/menu | C32: SGGU-6385 | D32: Backlog | G32: [SGGU] PI 3/26 | H32: APAP-10055 | K32: 3 | L32: 3 | M32: [SGGU] SP 26.3.4 | AF32: [Jornada Secretaria e Gestor de Unidades] Gestor de Unidades | AG32: Jornada Secretaria e Gestor de Unidades
A33: Enabler | B33: [SGGU-5202] Parametrização - Atualizar consulta para resgatar a Aula da tabela correta | C33: SGGU-6381 | D33: Backlog | G33: [SGGU] PI 3/26 | H33: SGGU-5288 | K33: 0 | L33: 3 | M33: [SGGU] SP 26.3.2 | AF33: [Jornada Secretaria e Gestor de Unidades] Gestor de Unidades | AG33: Jornada Secretaria e Gestor de Unidades
A34: História | B34: [SGGU-5187] Plano de virada - Add acesso ao menu por perfil de acesso | C34: SGGU-6367 | D34: Backlog | G34: [SGGU] PI 3/26 | H34: SGGU-5187 | K34: 2 | L34: 2 | M34: [SGGU] SP 26.3.5 | AF34: [Jornada Secretaria e Gestor de Unidades] Gestor de Unidades | AG34: Jornada Secretaria e Gestor de Unidades
A35: Enabler | B35: [SGGU-5187] Plano de virada - Ajuste no Console para Inicialização e Conclusão do BPF de Mediadores Legados | C35: SGGU-6366 | D35: Backlog | G35: [SGGU] PI 3/26 | H35: SGGU-5187 | K35: 2 | L35: 2 | M35: [SGGU] SP 26.3.5 | AF35: [Jornada Secretaria e Gestor de Unidades] Gestor de Unidades | AG35: Jornada Secretaria e Gestor de Unidades
A36: Débito Técnico | B36: [SGGU-5187] Correção da Regra de Reaproveitamento de Documentos entre Semestres | C36: SGGU-6364 | D36: Em Andamento | G36: [SGGU] PI 3/26 | H36: SGGU-5187 | K36: 5 | L36: 5 | M36: [SGGU] SP 26.3.1 | AF36: [Jornada Secretaria e Gestor de Unidades] Gestor de Unidades | AG36: Jornada Secretaria e Gestor de Unidades
A37: Enabler | B37: [Estabilizar Deploy] Levantamento dos itens da solução mediador | C37: SGGU-6356 | D37: Backlog | G37: [SGGU] PI 3/26 | H37: ARTSG-190 | K37: 3 | L37: 3 | M37: [SGGU] SP 26.3.1 | AF37: [Jornada Secretaria e Gestor de Unidades] Gestor de Unidades | AG37: Jornada Secretaria e Gestor de Unidades
... A49: Enabler | B49: [ARTPT-669] Plano virada de ambiente do Épico para PRD | C49: SGGU-6318 | D49: Backlog | G49: [SGGU] PI 3/26 | H49: ARTPT-669 | K49: 1 | L49: 1 | M49: [SGGU] SP 26.3.1 | AF49: [Jornada Secretaria e Gestor de Unidades] Gestor de Unidades | AG49: Jornada Secretaria e Gestor de Unidades
A50: Sustentação | B50: Atendimento à Solicitações de Serviço | C50: SGGU-6317 | D50: Backlog | G50: [SGGU] PI 3/26 | K50: 3 | L50: 3 | M50: [SGGU] SP 26.3.6 | AF50: [Jornada Secretaria e Gestor de Unidades] Gestor de Unidades | AG50: Jornada Secretaria e Gestor de Unidades | AO50: Solicitação de Serviço
A51: Sustentação | B51: Atendimento à Solicitações de Serviço | C51: SGGU-6316 | D51: Backlog | G51: [SGGU] PI 3/26 | K51: 3 | L51: 3 | M51: [SGGU] SP 26.3.5 | AF51: [Jornada Secretaria e Gestor de Unidades] Gestor de Unidades | AG51: Jornada Secretaria e Gestor de Unidades | AO51: Solicitação de Serviço
A52: Sustentação | B52: Atendimento à Solicitações de Serviço | C52: SGGU-6315 | D52: Backlog | G52: [SGGU] PI 3/26 | K52: 3 | L52: 3 | M52: [SGGU] SP 26.3.3 | AF52: [Jornada Secretaria e Gestor de Unidades] Gestor de Unidades | AG52: Jornada Secretaria e Gestor de Unidades | AO52: Solicitação de Serviço
A53: Sustentação | B53: Atendimento à Solicitações de Serviço | C53: SGGU-6314 | D53: Backlog | G53: [SGGU] PI 3/26 | K53: 3 | L53: 3 | M53: [SGGU] SP 26.3.4 | AF53: [Jornada Secretaria e Gestor de Unidades] Gestor de Unidades | AG53: Jornada Secretaria e Gestor de Unidades | AO53: Solicitação de Serviço
A54: Sustentação | B54: Atendimento à Solicitações de Serviço | C54: SGGU-6313 | D54: Backlog | G54: [SGGU] PI 3/26 | K54: 3 | L54: 3 | M54: [SGGU] SP 26.3.2 | AF54: [Jornada Secretaria e Gestor de Unidades] Gestor de Unidades | AG54: Jornada Secretaria e Gestor de Unidades | AO54: Solicitação de Serviço
A55: Sustentação | B55: Atendimento à Solicitações de Serviço | C55: SGGU-6312 | D55: Aceito | G55: [SGGU] PI 3/26 | K55: 3 | L55: 3 | M55: [SGGU] SP 26.3.1 | AF55: [Jornada Secretaria e Gestor de Unidades] Gestor de Unidades | AG55: Jornada Secretaria e Gestor de Unidades | AO55: Solicitação de Serviço
A56: Sustentação | B56: Protocolo de Sustentação para INCIDENTES | C56: SGGU-6311 | D56: Backlog | G56: [SGGU] PI 3/26 | K56: 8 | L56: 5 | M56: [SGGU] SP 26.3.6 | AF56: [Jornada Secretaria e Gestor de Unidades] Gestor de Unidades | AG56: Jornada Secretaria e Gestor de Unidades | AO56: Incidente
A57: Sustentação | B57: Protocolo de Sustentação para INCIDENTES | C57: SGGU-6310 | D57: Backlog | G57: [SGGU] PI 3/26 | K57: 8 | L57: 5 | M57: [SGGU] SP 26.3.5 | AF57: [Jornada Secretaria e Gestor de Unidades] Gestor de Unidades | AG57: Jornada Secretaria e Gestor de Unidades | AO57: Incidente
A58: Sustentação | B58: Protocolo de Sustentação para INCIDENTES | C58: SGGU-6309 | D58: Backlog | G58: [SGGU] PI 3/26 | K58: 8 | L58: 8 | M58: [SGGU] SP 26.3.4 | AF58: [Jornada Secretaria e Gestor de Unidades] Gestor de Unidades | AG58: Jornada Secretaria e Gestor de Unidades | AO58: Incidente
A59: Sustentação | B59: Protocolo de Sustentação para INCIDENTES | C59: SGGU-6308 | D59: Backlog | G59: [SGGU] PI 3/26 | K59: 8 | L59: 8 | M59: [SGGU] SP 26.3.3 | AF59: [Jornada Secretaria e Gestor de Unidades] Gestor de Unidades | AG59: Jornada Secretaria e Gestor de Unidades | AO59: Incidente
A60: Sustentação | B60: Protocolo de Sustentação para INCIDENTES | C60: SGGU-6307 | D60: Backlog | G60: [SGGU] PI 3/26 | K60: 8 | L60: 5 | M60: [SGGU] SP 26.3.2 | AF60: [Jornada Secretaria e Gestor de Unidades] Gestor de Unidades | AG60: Jornada Secretaria e Gestor de Unidades | AO60: Incidente
A61: Sustentação | B61: Protocolo de Sustentação para INCIDENTES | C61: SGGU-6306 | D61: Aceito | G61: [SGGU] PI 3/26 | K61: 8 | L61: 5 | M61: [SGGU] SP 26.3.1 | AF61: [Jornada Secretaria e Gestor de Unidades] Gestor de Unidades | AG61: Jornada Secretaria e Gestor de Unidades | AO61: Incidente
A62: Enabler | B62: Automação de Testes 26.3.6 | C62: SGGU-6305 | D62: Backlog | G62: [SGGU] PI 3/26 | K62: 1 | L62: 1 | M62: [SGGU] SP 26.3.6 | AF62: [Jornada Secretaria e Gestor de Unidades] Gestor de Unidades | AG62: Jornada Secretaria e Gestor de Unidades
A63: Enabler | B63: Automação de Testes 26.3.5 | C63: SGGU-6304 | D63: Backlog | G63: [SGGU] PI 3/26 | K63: 1 | L63: 1 | M63: [SGGU] SP 26.3.5 | AF63: [Jornada Secretaria e Gestor de Unidades] Gestor de Unidades | AG63: Jornada Secretaria e Gestor de Unidades
A64: Enabler | B64: Automação de Testes 26.3.4 | C64: SGGU-6303 | D64: Backlog | G64: [SGGU] PI 3/26 | K64: 1 | L64: 1 | M64: [SGGU] SP 26.3.4 | AF64: [Jornada Secretaria e Gestor de Unidades] Gestor de Unidades | AG64: Jornada Secretaria e Gestor de Unidades
A65: Enabler | B65: Automação de Testes 26.3.3 | C65: SGGU-6302 | D65: Backlog | G65: [SGGU] PI 3/26 | K65: 1 | L65: 1 | M65: [SGGU] SP 26.3.3 | AF65: [Jornada Secretaria e Gestor de Unidades] Gestor de Unidades | AG65: Jornada Secretaria e Gestor de Unidades
A66: Enabler | B66: Automação de Testes 26.3.2 | C66: SGGU-6301 | D66: Backlog | G66: [SGGU] PI 3/26 | K66: 1 | L66: 1 | M66: [SGGU] SP 26.3.2 | AF66: [Jornada Secretaria e Gestor de Unidades] Gestor de Unidades | AG66: Jornada Secretaria e Gestor de Unidades
A67: Enabler | B67: Automação de Testes 26.3.1 | C67: SGGU-6300 | D67: Backlog | G67: [SGGU] PI 3/26 | K67: 1 | L67: 1 | M67: [SGGU] SP 26.3.1 | AF67: [Jornada Secretaria e Gestor de Unidades] Gestor de Unidades | AG67: Jornada Secretaria e Gestor de Unidades
A68: Enabler | B68: Deploy 26.3.6 | C68: SGGU-6299 | D68: Backlog | G68: [SGGU] PI 3/26 | K68: 1 | L68: 1 | M68: [SGGU] SP 26.3.6 | AF68: [Jornada Secretaria e Gestor de Unidades] Gestor de Unidades | AG68: Jornada Secretaria e Gestor de Unidades
A69: Enabler | B69: Deploy 26.3.5 | C69: SGGU-6298 | D69: Backlog | G69: [SGGU] PI 3/26 | K69: 1 | L69: 1 | M69: [SGGU] SP 26.3.5 | AF69: [Jornada Secretaria e Gestor de Unidades] Gestor de Unidades | AG69: Jornada Secretaria e Gestor de Unidades
A70: Enabler | B70: Deploy 26.3.4 | C70: SGGU-6297 | D70: Backlog | G70: [SGGU] PI 3/26 | K70: 1 | L70: 1 | M70: [SGGU] SP 26.3.4 | AF70: [Jornada Secretaria e Gestor de Unidades] Gestor de Unidades | AG70: Jornada Secretaria e Gestor de Unidades
A71: Enabler | B71: Deploy 26.3.3 | C71: SGGU-6296 | D71: Backlog | G71: [SGGU] PI 3/26 | K71: 1 | L71: 1 | M71: [SGGU] SP 26.3.3 | AF71: [Jornada Secretaria e Gestor de Unidades] Gestor de Unidades | AG71: Jornada Secretaria e Gestor de Unidades
A72: Enabler | B72: Deploy 26.3.2 | C72: SGGU-6295 | D72: Backlog | G72: [SGGU] PI 3/26 | K72: 1 | L72: 1 | M72: [SGGU] SP 26.3.2 | AF72: [Jornada Secretaria e Gestor de Unidades] Gestor de Unidades | AG72: Jornada Secretaria e Gestor de Unidades
A73: Enabler | B73: Deploy 26.3.1 | C73: SGGU-6294 | D73: Backlog | G73: [SGGU] PI 3/26 | K73: 1 | L73: 1 | M73: [SGGU] SP 26.3.1 | AF73: [Jornada Secretaria e Gestor de Unidades] Gestor de Unidades | AG73: Jornada Secretaria e Gestor de Unidades
A74: História | B74: [CNPJ Alfanumérico] Ajustar campo CNPJ para permitir o preenchimento alfanumérico | C74: SGGU-6107 | D74: Backlog | G74: [SGGU] PI 3/26 | H74: ARTSG-313 | K74: 0 | L74: 3 | M74: [SGGU] SP 26.3.1 | AF74: [Jornada Secretaria e Gestor de Unidades] Gestor de Unidades | AG74: Jornada Secretaria e Gestor de Unidades
A75: História | B75: [SGGU-5202] Alocação - Atualizar consulta para resgatar a CH e Disciplina da tabela correta | C75: SGGU-6106 | D75: Em Andamento | G75: [SGGU] PI 3/26 | H75: SGGU-5288 | K75: 0 | L75: 3 | M75: [SGGU] SP 26.3.1 | AF75: [Jornada Secretaria e Gestor de Unidades] Gestor de Unidades | AG75: Jornada Secretaria e Gestor de Unidades
A76: Segurança | B76: [SEC][QA][Secretaria][SGGU] - Testes de Segurança PI 26.3 | C76: SGGU-6025 | D76: Backlog | G76: [SGGU] PI 3/26 | H76: SDIA-1212 | K76: 0 | L76: 0 | M76: [SGGU] SP 26.3.5 | AF76: [Jornada Secretaria e Gestor de Unidades] Gestor de Unidades | AG76: Jornada Secretaria e Gestor de Unidades
A77: Teste | B77: [SGGU-5187] Teste Integrado | C77: SGGU-5598 | D77: Backlog | G77: [SGGU] PI 3/26 | H77: SGGU-5187 | K77: 0 | L77: 1 | M77: [SGGU] SP 26.3.4 | AF77: [Jornada Secretaria e Gestor de Unidades] Gestor de Unidades | AG77: Jornada Secretaria e Gestor de Unidades
A78: História | B78: [SGGU-5202] Alocação/Parametrização - Realizar desenvolvimento para inativação a partir da turma | C78: SGGU-5438 | D78: Backlog | G78: [SGGU] PI 3/26 | H78: SGGU-5288 | K78: 8 | L78: 8 | M78: [SGGU] SP 26.3.2 | AF78: [Jornada Secretaria e Gestor de Unidades] Gestor de Unidades | AG78: Jornada Secretaria e Gestor de Unidades
A79: Spike | B79: [SGGU-5202] Realizar estudo para inativar Alocação/Parametrização a partir da inativação da turma | C79: SGGU-5437 | D79: Em Andamento | G79: [SGGU] PI 3/26 | H79: SGGU-5288 | K79: 3 | L79: 3 | M79: [SGGU] SP 26.3.1 | AF79: [Jornada Secretaria e Gestor de Unidades] Gestor de Unidades | AG79: Jornada Secretaria e Gestor de Unidades
A80: Débito Técnico | B80: [Logs por Origem] Ajuste por tabela Portfólio padrão | C80: SGGU-5331 | D80: Backlog | G80: [SGGU] PI 3/26 | H80: ARTSG-193 | K80: 8 | L80: 5 | M80: [SGGU] SP 26.3.3 | AF80: [Jornada Secretaria e Gestor de Unidades] Gestor de Unidades | AG80: Jornada Secretaria e Gestor de Unidades
A81: Débito Técnico | B81: [Logs por Origem] Ajuste por tabela unidade | C81: SGGU-5326 | D81: Backlog | G81: [SGGU] PI 3/26 | H81: ARTSG-193 | K81: 8 | L81: 5 | M81: [SGGU] SP 26.3.3 | AF81: [Jornada Secretaria e Gestor de Unidades] Gestor de Unidades | AG81: Jornada Secretaria e Gestor de Unidades
A82: Débito Técnico | B82: [Logs por Origem] Ajuste por tabela tipos de produtos | C82: SGGU-5325 | D82: Backlog | G82: [SGGU] PI 3/26 | H82: ARTSG-193 | K82: 8 | L82: 8 | M82: [SGGU] SP 26.3.3 | AF82: [Jornada Secretaria e Gestor de Unidades] Gestor de Unidades | AG82: Jornada Secretaria e Gestor de Unidades
A83: Débito Técnico | B83: [Logs por Origem] Ajuste por tabela Curso por tipo | C83: SGGU-5324 | D83: Backlog | G83: [SGGU] PI 3/26 | H83: ARTSG-193 | K83: 8 | L83: 5 | M83: [SGGU] SP 26.3.2 | AF83: [Jornada Secretaria e Gestor de Unidades] Gestor de Unidades | AG83: Jornada Secretaria e Gestor de Unidades
A84: Débito Técnico | B84: [Logs por Origem] Ajuste por tabela Curso Semi | C84: SGGU-5323 | D84: Backlog | G84: [SGGU] PI 3/26 | H84: ARTSG-193 | K84: 8 | L84: 8 | M84: [SGGU] SP 26.3.2 | AF84: [Jornada Secretaria e Gestor de Unidades] Gestor de Unidades | AG84: Jornada Secretaria e Gestor de Unidades
A85: Enabler | B85: [Logs por Origem] Mapear fluxos e tabelas para ajustar os logs por registro | C85: SGGU-5321 | D85: Backlog | G85: [SGGU] PI 3/26 | H85: ARTSG-193 | K85: 2 | L85: 2 | M85: [SGGU] SP 26.3.2 | AF85: [Jornada Secretaria e Gestor de Unidades] Gestor de Unidades | AG85: Jornada Secretaria e Gestor de Unidades
... A89: Enabler | B89: [Estabilizar Deploy] Levantamento, Documentação e Estratégia de Segregação das Soluções Dynamics | C89: SGGU-5316 | D89: Em Andamento | G89: [SGGU] PI 3/26 | H89: ARTSG-190 | K89: 5 | L89: 3 | M89: [SGGU] SP 26.3.1 | AF89: [Jornada Secretaria e Gestor de Unidades] Gestor de Unidades | AG89: Jornada Secretaria e Gestor de Unidades
A90: Incidente | B90: [INC0778380]Tenho um Erro/Problema com o PTC - Dynamics Athenas - Inativação de curso e ofertas | C90: SGSE-4183 | D90: Backlog | G90: [SGSE] PI 3/26 | M90: [SGSE] SP 26.3.1 | AF90: [Jornada Secretaria e Gestor de Unidades] Secretaria - Enturmação | AG90: Jornada Secretaria e Gestor de Unidades
A91: Sustentação | B91: [SGSE] - IT 1 - PI 3/26 ] Solicitação de Serviço | C91: SGSE-4176 | D91: Backlog | G91: [SGSE] PI 3/26 | K91: 2 | L91: 2 | M91: [SGSE] SP 26.3.1 | AF91: [Jornada Secretaria e Gestor de Unidades] Secretaria - Enturmação | AG91: Jornada Secretaria e Gestor de Unidades | AO91: Solicitação de Serviço
A92: Sustentação | B92: [SGSE] - IT 1 - PI 3/26 ] Incidentes | C92: SGSE-4175 | D92: Backlog | G92: [SGSE] PI 3/26 | K92: 5 | L92: 5 | M92: [SGSE] SP 26.3.1 | AF92: [Jornada Secretaria e Gestor de Unidades] Secretaria - Enturmação | AG92: Jornada Secretaria e Gestor de Unidades | AO92: Incidente
A93: Incidente | B93: [INC0790661]Tenho um Erro/Problema com o PTC - Ambiente do Aluno / AVA Sofia - Visão de disciplinas | C93: SGSE-4154 | D93: Aceito | G93: [SGSE] PI 3/26 | M93: [SGSE] SP 26.3.1 | AF93: [Jornada Secretaria e Gestor de Unidades] Secretaria - Enturmação | AG93: Jornada Secretaria e Gestor de Unidades
A94: Incidente | B94: [INC0792175]Tenho um Erro/Problema com o PTC - Ambiente do Aluno / AVA Sofia - Visão de disciplinas | C94: SGSE-4153 | D94: Aceito | G94: [SGSE] PI 3/26 | M94: [SGSE] SP 26.3.1 | AF94: [Jornada Secretaria e Gestor de Unidades] Secretaria - Enturmação | AG94: Jornada Secretaria e Gestor de Unidades
A95: Incidente | B95: [INC0746077]Tenho um Erro/Problema com o PTC - Financeiro SAP - Rematrícula | C95: SGSE-4152 | D95: Backlog | G95: [SGSE] PI 3/26 | M95: [SGSE] SP 26.3.1 | AF95: [Jornada Secretaria e Gestor de Unidades] Secretaria - Enturmação | AG95: Jornada Secretaria e Gestor de Unidades
A96: Incidente | B96: [INC0794804]Tenho um Erro/Problema com o PTC - Dynamics Athenas - Alocação e disponibilização de disciplinas | C96: SGSE-4149 | D96: Concluído | G96: [SGSE] PI 3/26 | M96: [SGSE] SP 26.2.6;[SGSE] SP 26.3.1 | AF96: [Jornada Secretaria e Gestor de Unidades] Secretaria - Enturmação | AG96: Jornada Secretaria e Gestor de Unidades
A97: Incidente | B97: [INC0794342]Tenho um Erro/Problema com o PTC - Dynamics Athenas - Alocação e disponibilização de disciplinas | C97: SGSE-4143 | D97: Concluído | G97: [SGSE] PI 3/26 | M97: [SGSE] SP 26.2.6;[SGSE] SP 26.3.1 | AF97: [Jornada Secretaria e Gestor de Unidades] Secretaria - Enturmação | AG97: Jornada Secretaria e Gestor de Unidades
A98: Incidente | B98: [INC0794260]Tenho um Erro/Problema com o PTC - Dynamics Athenas - Alocação e disponibilização de disciplinas | C98: SGSE-4142 | D98: Backlog | G98: [SGSE] PI 3/26 | M98: [SGSE] SP 26.2.6;[SGSE] SP 26.3.1 | AF98: [Jornada Secretaria e Gestor de Unidades] Secretaria - Enturmação | AG98: Jornada Secretaria e Gestor de Unidades
A99: Incidente | B99: [INC0794182]Tenho um Erro/Problema com o PTC - Dynamics Athenas - Alocação e disponibilização de disciplinas | C99: SGSE-4141 | D99: Backlog | G99: [SGSE] PI 3/26 | M99: [SGSE] SP 26.2.6;[SGSE] SP 26.3.1 | AF99: [Jornada Secretaria e Gestor de Unidades] Secretaria - Enturmação | AG99: Jornada Secretaria e Gestor de Unidades
A100: Incidente | B100: [INC0794177]Tenho um Erro/Problema com o PTC - Dynamics Athenas - Alocação e disponibilização de disciplinas | C100: SGSE-4140 | D100: Aceito | G100: [SGSE] PI 3/26 | M100: [SGSE] SP 26.2.6;[SGSE] SP 26.3.1 | AF100: [Jornada Secretaria e Gestor de Unidades] Secretaria - Enturmação | AG100: Jornada Secretaria e Gestor de Unidades
A101: Incidente | B101: [INC0793701]Tenho um Erro/Problema com o PTC - Dynamics Athenas - Alocação e disponibilização de disciplinas | C101: SGSE-4139 | D101: Bloqueado | G101: [SGSE] PI 3/26 | M101: [SGSE] SP 26.2.6;[SGSE] SP 26.3.1 | AF101: [Jornada Secretaria e Gestor de Unidades] Secretaria - Enturmação | AG101: Jornada Secretaria e Gestor de Unidades
A102: Teste | B102: [691] Teste Mobile de Sofia | C102: SGSE-4138 | D102: Backlog | G102: [SGSE] PI 3/26 | H102: ARTPT-691 | K102: 1 | L102: 1 | M102: [SGSE] SP 26.3.2 | AF102: [Jornada Secretaria e Gestor de Unidades] Secretaria - Enturmação | AG102: Jornada Secretaria e Gestor de Unidades
A103: Suporte | B103: [Transf. Externa] Tratar passivo de alunos com matriz e série divergente | C103: SGSE-4137 | D103: Backlog | G103: [SGSE] PI 3/26 | H103: ARTPT-691 | K103: 1 | L103: 1 | M103: [SGSE] SP 26.3.1 | AF103: [Jornada Secretaria e Gestor de Unidades] Secretaria - Enturmação | AG103: Jornada Secretaria e Gestor de Unidades
A104: Teste | B104: [Teste integrado - ARTDF-379] Formando Reprovado - Enturmação | C104: SGSE-4136 | D104: Backlog | G104: [SGSE] PI 3/26 | K104: 1 | L104: 1 | M104: [SGSE] SP 26.3.1 | AF104: [Jornada Secretaria e Gestor de Unidades] Secretaria - Enturmação | AG104: Jornada Secretaria e Gestor de Unidades
A105: História | B105: [680 - Vers. Matriz] Alterar a controladora para reconhecer a geração do Historico Curricular na Rematricula | C105: SGSE-4135 | D105: Backlog | G105: [SGSE] PI 3/26 | H105: ARTPT-680 | K105: 8 | L105: 8 | M105: [SGSE] SP 26.3.5 | AF105: [Jornada Secretaria e Gestor de Unidades] Secretaria - Enturmação | AG105: Jornada Secretaria e Gestor de Unidades
A106: Spike | B106: [680 - Vers. Matriz] Spike – Análise de Impactos na geração do Histórico Curricular fracionado por série | C106: SGSE-4134 | D106: Backlog | G106: [SGSE] PI 3/26 | H106: ARTPT-680 | K106: 2 | L106: 2 | M106: [SGSE] SP 26.3.3 | AF106: [Jornada Secretaria e Gestor de Unidades] Secretaria - Enturmação | AG106: Jornada Secretaria e Gestor de Unidades
A107: História | B107: [196 - SAG] Alterção de View e formulário do histórico curricular e estoque | C107: SGSE-4133 | D107: Backlog | G107: [SGSE] PI 3/26 | H107: ARTJA-196 | K107: 2 | L107: 2 | M107: [SGSE] SP 26.3.3 | AF107: [Jornada Secretaria e Gestor de Unidades] Secretaria - Enturmação | AG107: Jornada Secretaria e Gestor de Unidades
A108: História | B108: Alterar composição da bussineskey na criação do histórico curricular | C108: SGSE-4132 | D108: Backlog | G108: [SGSE] PI 3/26 | H108: ARTSG-270 | K108: 5 | L108: 5 | M108: [SGSE] SP 26.3.4 | AF108: [Jornada Secretaria e Gestor de Unidades] Secretaria - Enturmação | AG108: Jornada Secretaria e Gestor de Unidades
A109: Teste | B109: [DT - Aloc. Disciplinas] Teste integrado - Remover obrigatoriedade do docente na alocação - sprint 2 | C109: SGSE-4131 | D109: Backlog | G109: [SGSE] PI 3/26 | H109: ARTSG-270 | K109: 1 | L109: 1 | M109: [SGSE] SP 26.3.2 | AF109: [Jornada Secretaria e Gestor de Unidades] Secretaria - Enturmação | AG109: Jornada Secretaria e Gestor de Unidades
A110: História | B110: Alteração de retorno da API de turmas para docência - Retornar somente turmas Veteranas | C110: SGSE-4130 | D110: Backlog | G110: [SGSE] PI 3/26 | H110: ARTPT-691 | K110: 1 | L110: 1 | M110: [SGSE] SP 26.3.1 | AF110: [Jornada Secretaria e Gestor de Unidades] Secretaria - Enturmação | AG110: Jornada Secretaria e Gestor de Unidades
A111: História | B111: [680 - Vers. Matriz] Tratar históricos já gerados | C111: SGSE-4129 | D111: Backlog | G111: [SGSE] PI 3/26 | H111: ARTPT-680 | K111: 8 | L111: 8 | M111: [SGSE] SP 26.3.5 | AF111: [Jornada Secretaria e Gestor de Unidades] Secretaria - Enturmação | AG111: Jornada Secretaria e Gestor de Unidades
A112: História | B112: [680 - Vers. Matriz] Disponibilizar acionamento manual da geração do Histórico Curricular e pré-alocação para área de negócio | C112: SGSE-4128 | D112: Backlog | G112: [SGSE] PI 3/26 | H112: ARTPT-680 | K112: 8 | L112: 8 | M112: [SGSE] SP 26.3.5 | AF112: [Jornada Secretaria e Gestor de Unidades] Secretaria - Enturmação | AG112: Jornada Secretaria e Gestor de Unidades
A113: História | B113: [680 - Vers. Matriz] Gerar Histórico Curricular e pré-alocar a série correspondente na rematrícula na data parametrizada | C113: SGSE-4127 | D113: Backlog | G113: [SGSE] PI 3/26 | H113: ARTPT-680 | K113: 8 | L113: 8 | M113: [SGSE] SP 26.3.4 | AF113: [Jornada Secretaria e Gestor de Unidades] Secretaria - Enturmação | AG113: Jornada Secretaria e Gestor de Unidades
A114: História | B114: [680 - Vers. Matriz] Gerar Histórico Curricular apenas da série atual na matrícula inicial | C114: SGSE-4126 | D114: Backlog | G114: [SGSE] PI 3/26 | H114: ARTPT-680 | K114: 8 | L114: 8 | M114: [SGSE] SP 26.3.4 | AF114: [Jornada Secretaria e Gestor de Unidades] Secretaria - Enturmação | AG114: Jornada Secretaria e Gestor de Unidades
...

Sheet Extração Jira - Itens
A1: Tipo de item | B1: Chave | C1: Sprint | D1: Projeto | E1: Status | F1: Versões corrigidas | G1: Story Points | H1: Resumo | I1: Story point estimate | J1: Σ de Tempo Gasto | K1: Tipo | L1: Categoria do status | M1: Pai | N1: Alteração de escopo (após a última PIP)? | O1: Resolução | P1: Criado | Q1: Ponto de compromisso | R1: Inicio do fluxo | S1: Fim do fluxo | T1: Início Homologação | U1: Fim Homologação | V1: Início Implantação | W1: Fim Implantação | X1: Ciclo de Ideação | Y1: Ciclo de Desenvolvimento | Z1: Ciclo Homologação | AA1: Ciclo de Implantação | AB1: Lead Time | AC1: Costumer Lead Time | AD1: Tipo Sustentação | AE1: Este item sofreu antecipação de Sprint? | AF1: Ambiente | AG1: Tempo total bloqueado | AH1: Tempo Gasto (horas) | AI1: Check Dias | AJ1: Tempo de Bloqueio (Dias) | AK1: Ideação | AL1: Check Ideação | AM1: Desenvolvimento | AN1: Check Desenvolvimento | AO1: Homologação | AP1: Check Homologação | AQ1: Implantação | AR1: Check Implantação | AS1: Lead Time | AT1: Check Lead time | AU1: Epico
A2: Incidente | B2: SGTB-2860 | C2: [SGTB] SP 26.3.6 | D2: [Jornada Secretaria e Gestor de Unidades] Thunderbolts | E2: Aceito | F2: [SGTB] PI 3/26 | H2: [INC0821305]Tenho um Erro/Problema com o Sistema Colaborar - Colaborar - Cursos extensão | J2: 900 | L2: Itens concluídos | O2: Abertura indevida | P2: 46289.504 | Q2: 46279 | R2: 46290 | AH2: =IF(J2="","",J2/3600) -> 0.25 | AI2: =IF(COUNTIF(AG2, "*dia*"), "VERDADEIRO", "FALSO") -> FALSO | AJ2: =IF(AI2="VERDADEIRO",LEFT(AG2,2),0) -> 0 | AK2: =IF(OR(A2="Solicitação de Serviço",A2="Incidente",P2="",Q2=""),"",IF((NETWORKDAYS.INTL(P2,Q2,1)-1)=0,1,NETWORKDAYS.INTL(P2,Q2,1)-1)) | AL2: =IF(X2="","",AK2=X2) | AM2: =IF(OR(A2="Solicitação de Serviço",A2="Incidente",R2="",S2=""),"",IF((NETWORKDAYS.INTL(R2,S2,1)-1)=0,1,NETWORKDAYS.INTL(R2,S2,1)-1-AJ2)) | AN2: =IF(Y2="","",AM2=Y2) | AO2: =IF(OR(A2="Solicitação de Serviço",A2="Incidente",T2="",U2=""),"",IF((NETWORKDAYS.INTL(T2,U2,1)-1)=0,1,NETWORKDAYS.INTL(T2,U2,1)-1)) | AP2: =IF(Z2="","",AO2=Z2) | AQ2: =IF(OR(A2="Solicitação de Serviço",A2="Incidente",V2="",W2=""),"",IF((NETWORKDAYS.INTL(V2,W2,1)-1)=0,1,IF((NETWORKDAYS.INTL(V2,W2,1)-1)<0,"",NETWORKDAYS.INTL(V2,W2,1)-1))) | AR2: =IF(AA2="","",AQ2=AA2) | AS2: =IF(OR(A2="Solicitação de Serviço",A2="Incidente",P2=""),"",IF(OR(A2="História",A2="Enabler",A2="Débito Técnico"),IF(W2="","",NETWORKDAYS.INTL(P2,W2,1)-1),IF(U2="","",NETWORKDAYS.INTL(P2,U2,1)-1))) | AT2: =IF(OR(A2="Solicitação de Serviço",A2="Incidente",A2="Sustentação"),"",IF(P2="","",IF(OR(A2="História",A2="Enabler",A2="Débito Técnico"),AS2=AC2,AS2=AB2))) | AU2: =IF(M2="","",M2)
A3: Incidente | B3: SGTB-2856 | C3: [SGTB] SP 26.4.1;[SGTB] SP 26.3.6 | D3: [Jornada Secretaria e Gestor de Unidades] Thunderbolts | E3: Aceito | F3: [SGTB] PI 3/26 | H3: [INC0819324]Tenho um Erro/Problema com o Sistema - AVA (LMS) - AVA (LMS) | J3: 1800 | L3: Itens concluídos | O3: Concluído | P3: 46289.433 | Q3: 46279 | R3: 46289 | S3: 46289 | AH3: =IF(J3="","",J3/3600) -> 0.5 | AI3: =IF(COUNTIF(AG3, "*dia*"), "VERDADEIRO", "FALSO") -> FALSO | AJ3: =IF(AI3="VERDADEIRO",LEFT(AG3,2),0) -> 0 | AK3: =IF(OR(A3="Solicitação de Serviço",A3="Incidente",P3="",Q3=""),"",IF((NETWORKDAYS.INTL(P3,Q3,1)-1)=0,1,NETWORKDAYS.INTL(P3,Q3,1)-1)) | AL3: =IF(X3="","",AK3=X3) | AM3: =IF(OR(A3="Solicitação de Serviço",A3="Incidente",R3="",S3=""),"",IF((NETWORKDAYS.INTL(R3,S3,1)-1)=0,1,NETWORKDAYS.INTL(R3,S3,1)-1-AJ3)) | AN3: =IF(Y3="","",AM3=Y3) | AO3: =IF(OR(A3="Solicitação de Serviço",A3="Incidente",T3="",U3=""),"",IF((NETWORKDAYS.INTL(T3,U3,1)-1)=0,1,NETWORKDAYS.INTL(T3,U3,1)-1)) | AP3: =IF(Z3="","",AO3=Z3) | AQ3: =IF(OR(A3="Solicitação de Serviço",A3="Incidente",V3="",W3=""),"",IF((NETWORKDAYS.INTL(V3,W3,1)-1)=0,1,IF((NETWORKDAYS.INTL(V3,W3,1)-1)<0,"",NETWORKDAYS.INTL(V3,W3,1)-1))) | AR3: =IF(AA3="","",AQ3=AA3) | AS3: =IF(OR(A3="Solicitação de Serviço",A3="Incidente",P3=""),"",IF(OR(A3="História",A3="Enabler",A3="Débito Técnico"),IF(W3="","",NETWORKDAYS.INTL(P3,W3,1)-1),IF(U3="","",NETWORKDAYS.INTL(P3,U3,1)-1))) | AT3: =IF(OR(A3="Solicitação de Serviço",A3="Incidente",A3="Sustentação"),"",IF(P3="","",IF(OR(A3="História",A3="Enabler",A3="Débito Técnico"),AS3=AC3,AS3=AB3))) | AU3: =IF(M3="","",M3)
A4: Incidente | B4: SGTB-2855 | C4: [SGTB] SP 26.4.1;[SGTB] SP 26.3.6 | D4: [Jornada Secretaria e Gestor de Unidades] Thunderbolts | E4: Aceito | F4: [SGTB] PI 3/26 | H4: [INC0817975]Tenho um Erro/Problema com o Sistema - AVA Presencial/Moodle - Acesso ao AVA/Disciplina | J4: 3600 | L4: Itens concluídos | O4: Concluído | P4: 46289.433 | Q4: 46279 | R4: 46289 | S4: 46289 | AH4: =IF(J4="","",J4/3600) -> 1 | AI4: =IF(COUNTIF(AG4, "*dia*"), "VERDADEIRO", "FALSO") -> FALSO | AJ4: =IF(AI4="VERDADEIRO",LEFT(AG4,2),0) -> 0 | AK4: =IF(OR(A4="Solicitação de Serviço",A4="Incidente",P4="",Q4=""),"",IF((NETWORKDAYS.INTL(P4,Q4,1)-1)=0,1,NETWORKDAYS.INTL(P4,Q4,1)-1)) | AL4: =IF(X4="","",AK4=X4) | AM4: =IF(OR(A4="Solicitação de Serviço",A4="Incidente",R4="",S4=""),"",IF((NETWORKDAYS.INTL(R4,S4,1)-1)=0,1,NETWORKDAYS.INTL(R4,S4,1)-1-AJ4)) | AN4: =IF(Y4="","",AM4=Y4) | AO4: =IF(OR(A4="Solicitação de Serviço",A4="Incidente",T4="",U4=""),"",IF((NETWORKDAYS.INTL(T4,U4,1)-1)=0,1,NETWORKDAYS.INTL(T4,U4,1)-1)) | AP4: =IF(Z4="","",AO4=Z4) | AQ4: =IF(OR(A4="Solicitação de Serviço",A4="Incidente",V4="",W4=""),"",IF((NETWORKDAYS.INTL(V4,W4,1)-1)=0,1,IF((NETWORKDAYS.INTL(V4,W4,1)-1)<0,"",NETWORKDAYS.INTL(V4,W4,1)-1))) | AR4: =IF(AA4="","",AQ4=AA4) | AS4: =IF(OR(A4="Solicitação de Serviço",A4="Incidente",P4=""),"",IF(OR(A4="História",A4="Enabler",A4="Débito Técnico"),IF(W4="","",NETWORKDAYS.INTL(P4,W4,1)-1),IF(U4="","",NETWORKDAYS.INTL(P4,U4,1)-1))) | AT4: =IF(OR(A4="Solicitação de Serviço",A4="Incidente",A4="Sustentação"),"",IF(P4="","",IF(OR(A4="História",A4="Enabler",A4="Débito Técnico"),AS4=AC4,AS4=AB4))) | AU4: =IF(M4="","",M4)
A5: Incidente | B5: SGTB-2853 | C5: [SGTB] SP 26.3.6 | D5: [Jornada Secretaria e Gestor de Unidades] Thunderbolts | E5: Aceito | F5: [SGTB] PI 3/26 | H5: [INC0822380]Tenho um Erro/Problema com o Sistema - Ajuste de Horário - Acadêmico | J5: 1800 | L5: Itens concluídos | O5: Abertura indevida | P5: 46289.403 | Q5: 46279 | R5: 46289 | AH5: =IF(J5="","",J5/3600) -> 0.5 | AI5: =IF(COUNTIF(AG5, "*dia*"), "VERDADEIRO", "FALSO") -> FALSO | AJ5: =IF(AI5="VERDADEIRO",LEFT(AG5,2),0) -> 0 | AK5: =IF(OR(A5="Solicitação de Serviço",A5="Incidente",P5="",Q5=""),"",IF((NETWORKDAYS.INTL(P5,Q5,1)-1)=0,1,NETWORKDAYS.INTL(P5,Q5,1)-1)) | AL5: =IF(X5="","",AK5=X5) | AM5: =IF(OR(A5="Solicitação de Serviço",A5="Incidente",R5="",S5=""),"",IF((NETWORKDAYS.INTL(R5,S5,1)-1)=0,1,NETWORKDAYS.INTL(R5,S5,1)-1-AJ5)) | AN5: =IF(Y5="","",AM5=Y5) | AO5: =IF(OR(A5="Solicitação de Serviço",A5="Incidente",T5="",U5=""),"",IF((NETWORKDAYS.INTL(T5,U5,1)-1)=0,1,NETWORKDAYS.INTL(T5,U5,1)-1)) | AP5: =IF(Z5="","",AO5=Z5) | AQ5: =IF(OR(A5="Solicitação de Serviço",A5="Incidente",V5="",W5=""),"",IF((NETWORKDAYS.INTL(V5,W5,1)-1)=0,1,IF((NETWORKDAYS.INTL(V5,W5,1)-1)<0,"",NETWORKDAYS.INTL(V5,W5,1)-1))) | AR5: =IF(AA5="","",AQ5=AA5) | AS5: =IF(OR(A5="Solicitação de Serviço",A5="Incidente",P5=""),"",IF(OR(A5="História",A5="Enabler",A5="Débito Técnico"),IF(W5="","",NETWORKDAYS.INTL(P5,W5,1)-1),IF(U5="","",NETWORKDAYS.INTL(P5,U5,1)-1))) | AT5: =IF(OR(A5="Solicitação de Serviço",A5="Incidente",A5="Sustentação"),"",IF(P5="","",IF(OR(A5="História",A5="Enabler",A5="Débito Técnico"),AS5=AC5,AS5=AB5))) | AU5: =IF(M5="","",M5)
A6: Solicitação de Serviço | B6: SGTB-2848 | C6: [SGTB] SP 26.4.1;[SGTB] SP 26.3.6 | D6: [Jornada Secretaria e Gestor de Unidades] Thunderbolts | E6: Aceito | F6: [SGTB] PI 3/26 | H6: [RITM0746664]Solicitar Serviço ao Sistema - Olimpo - Olimpo / Professores | J6: 600 | L6: Itens concluídos | O6: Concluído | P6: 46288.683 | Q6: 46279 | R6: 46290 | S6: 46290 | AH6: =IF(J6="","",J6/3600) -> 0.16666667 | AI6: =IF(COUNTIF(AG6, "*dia*"), "VERDADEIRO", "FALSO") -> FALSO | AJ6: =IF(AI6="VERDADEIRO",LEFT(AG6,2),0) -> 0 | AK6: =IF(OR(A6="Solicitação de Serviço",A6="Incidente",P6="",Q6=""),"",IF((NETWORKDAYS.INTL(P6,Q6,1)-1)=0,1,NETWORKDAYS.INTL(P6,Q6,1)-1)) | AL6: =IF(X6="","",AK6=X6) | AM6: =IF(OR(A6="Solicitação de Serviço",A6="Incidente",R6="",S6=""),"",IF((NETWORKDAYS.INTL(R6,S6,1)-1)=0,1,NETWORKDAYS.INTL(R6,S6,1)-1-AJ6)) | AN6: =IF(Y6="","",AM6=Y6) | AO6: =IF(OR(A6="Solicitação de Serviço",A6="Incidente",T6="",U6=""),"",IF((NETWORKDAYS.INTL(T6,U6,1)-1)=0,1,NETWORKDAYS.INTL(T6,U6,1)-1)) | AP6: =IF(Z6="","",AO6=Z6) | AQ6: =IF(OR(A6="Solicitação de Serviço",A6="Incidente",V6="",W6=""),"",IF((NETWORKDAYS.INTL(V6,W6,1)-1)=0,1,IF((NETWORKDAYS.INTL(V6,W6,1)-1)<0,"",NETWORKDAYS.INTL(V6,W6,1)-1))) | AR6: =IF(AA6="","",AQ6=AA6) | AS6: =IF(OR(A6="Solicitação de Serviço",A6="Incidente",P6=""),"",IF(OR(A6="História",A6="Enabler",A6="Débito Técnico"),IF(W6="","",NETWORKDAYS.INTL(P6,W6,1)-1),IF(U6="","",NETWORKDAYS.INTL(P6,U6,1)-1))) | AT6: =IF(OR(A6="Solicitação de Serviço",A6="Incidente",A6="Sustentação"),"",IF(P6="","",IF(OR(A6="História",A6="Enabler",A6="Débito Técnico"),AS6=AC6,AS6=AB6))) | AU6: =IF(M6="","",M6)
A7: Incidente | B7: SGTB-2847 | C7: [SGTB] SP 26.3.6 | D7: [Jornada Secretaria e Gestor de Unidades] Thunderbolts | E7: Aceito | F7: [SGTB] PI 3/26 | H7: [INC0822099]Tenho um Erro/Problema com o Sistema - Prisma - Usuários do Prisma | J7: 3600 | L7: Itens concluídos | O7: Abertura indevida | P7: 46288.681 | Q7: 46279 | R7: 46288 | AH7: =IF(J7="","",J7/3600) -> 1 | AI7: =IF(COUNTIF(AG7, "*dia*"), "VERDADEIRO", "FALSO") -> FALSO | AJ7: =IF(AI7="VERDADEIRO",LEFT(AG7,2),0) -> 0 | AK7: =IF(OR(A7="Solicitação de Serviço",A7="Incidente",P7="",Q7=""),"",IF((NETWORKDAYS.INTL(P7,Q7,1)-1)=0,1,NETWORKDAYS.INTL(P7,Q7,1)-1)) | AL7: =IF(X7="","",AK7=X7) | AM7: =IF(OR(A7="Solicitação de Serviço",A7="Incidente",R7="",S7=""),"",IF((NETWORKDAYS.INTL(R7,S7,1)-1)=0,1,NETWORKDAYS.INTL(R7,S7,1)-1-AJ7)) | AN7: =IF(Y7="","",AM7=Y7) | AO7: =IF(OR(A7="Solicitação de Serviço",A7="Incidente",T7="",U7=""),"",IF((NETWORKDAYS.INTL(T7,U7,1)-1)=0,1,NETWORKDAYS.INTL(T7,U7,1)-1)) | AP7: =IF(Z7="","",AO7=Z7) | AQ7: =IF(OR(A7="Solicitação de Serviço",A7="Incidente",V7="",W7=""),"",IF((NETWORKDAYS.INTL(V7,W7,1)-1)=0,1,IF((NETWORKDAYS.INTL(V7,W7,1)-1)<0,"",NETWORKDAYS.INTL(V7,W7,1)-1))) | AR7: =IF(AA7="","",AQ7=AA7) | AS7: =IF(OR(A7="Solicitação de Serviço",A7="Incidente",P7=""),"",IF(OR(A7="História",A7="Enabler",A7="Débito Técnico"),IF(W7="","",NETWORKDAYS.INTL(P7,W7,1)-1),IF(U7="","",NETWORKDAYS.INTL(P7,U7,1)-1))) | AT7: =IF(OR(A7="Solicitação de Serviço",A7="Incidente",A7="Sustentação"),"",IF(P7="","",IF(OR(A7="História",A7="Enabler",A7="Débito Técnico"),AS7=AC7,AS7=AB7))) | AU7: =IF(M7="","",M7)
A8: Incidente | B8: SGTB-2840 | C8: [SGTB] SP 26.4.1;[SGTB] SP 26.3.6 | D8: [Jornada Secretaria e Gestor de Unidades] Thunderbolts | E8: Aceito | F8: [SGTB] PI 3/26 | H8: [INC0819723]Tenho um Erro/Problema com o Sistema - Olimpo - Matrícula | J8: 10800 | L8: Itens concluídos | O8: Concluído | P8: 46288.458 | Q8: 46279 | R8: 46289 | S8: 46289 | AH8: =IF(J8="","",J8/3600) -> 3 | AI8: =IF(COUNTIF(AG8, "*dia*"), "VERDADEIRO", "FALSO") -> FALSO | AJ8: =IF(AI8="VERDADEIRO",LEFT(AG8,2),0) -> 0 | AK8: =IF(OR(A8="Solicitação de Serviço",A8="Incidente",P8="",Q8=""),"",IF((NETWORKDAYS.INTL(P8,Q8,1)-1)=0,1,NETWORKDAYS.INTL(P8,Q8,1)-1)) | AL8: =IF(X8="","",AK8=X8) | AM8: =IF(OR(A8="Solicitação de Serviço",A8="Incidente",R8="",S8=""),"",IF((NETWORKDAYS.INTL(R8,S8,1)-1)=0,1,NETWORKDAYS.INTL(R8,S8,1)-1-AJ8)) | AN8: =IF(Y8="","",AM8=Y8) | AO8: =IF(OR(A8="Solicitação de Serviço",A8="Incidente",T8="",U8=""),"",IF((NETWORKDAYS.INTL(T8,U8,1)-1)=0,1,NETWORKDAYS.INTL(T8,U8,1)-1)) | AP8: =IF(Z8="","",AO8=Z8) | AQ8: =IF(OR(A8="Solicitação de Serviço",A8="Incidente",V8="",W8=""),"",IF((NETWORKDAYS.INTL(V8,W8,1)-1)=0,1,IF((NETWORKDAYS.INTL(V8,W8,1)-1)<0,"",NETWORKDAYS.INTL(V8,W8,1)-1))) | AR8: =IF(AA8="","",AQ8=AA8) | AS8: =IF(OR(A8="Solicitação de Serviço",A8="Incidente",P8=""),"",IF(OR(A8="História",A8="Enabler",A8="Débito Técnico"),IF(W8="","",NETWORKDAYS.INTL(P8,W8,1)-1),IF(U8="","",NETWORKDAYS.INTL(P8,U8,1)-1))) | AT8: =IF(OR(A8="Solicitação de Serviço",A8="Incidente",A8="Sustentação"),"",IF(P8="","",IF(OR(A8="História",A8="Enabler",A8="Débito Técnico"),AS8=AC8,AS8=AB8))) | AU8: =IF(M8="","",M8)
A9: Incidente | B9: SGTB-2837 | C9: [SGTB] SP 26.3.6 | D9: [Jornada Secretaria e Gestor de Unidades] Thunderbolts | E9: Aceito | F9: [SGTB] PI 3/26 | H9: [INC0821361]Tenho um Erro/Problema com o Sistema - Extranet - Requerimento | J9: 900 | L9: Itens concluídos | O9: Abertura indevida | P9: 46288.45 | Q9: 46279 | R9: 46288 | AH9: =IF(J9="","",J9/3600) -> 0.25 | AI9: =IF(COUNTIF(AG9, "*dia*"), "VERDADEIRO", "FALSO") -> FALSO | AJ9: =IF(AI9="VERDADEIRO",LEFT(AG9,2),0) -> 0 | AK9: =IF(OR(A9="Solicitação de Serviço",A9="Incidente",P9="",Q9=""),"",IF((NETWORKDAYS.INTL(P9,Q9,1)-1)=0,1,NETWORKDAYS.INTL(P9,Q9,1)-1)) | AL9: =IF(X9="","",AK9=X9) | AM9: =IF(OR(A9="Solicitação de Serviço",A9="Incidente",R9="",S9=""),"",IF((NETWORKDAYS.INTL(R9,S9,1)-1)=0,1,NETWORKDAYS.INTL(R9,S9,1)-1-AJ9)) | AN9: =IF(Y9="","",AM9=Y9) | AO9: =IF(OR(A9="Solicitação de Serviço",A9="Incidente",T9="",U9=""),"",IF((NETWORKDAYS.INTL(T9,U9,1)-1)=0,1,NETWORKDAYS.INTL(T9,U9,1)-1)) | AP9: =IF(Z9="","",AO9=Z9) | AQ9: =IF(OR(A9="Solicitação de Serviço",A9="Incidente",V9="",W9=""),"",IF((NETWORKDAYS.INTL(V9,W9,1)-1)=0,1,IF((NETWORKDAYS.INTL(V9,W9,1)-1)<0,"",NETWORKDAYS.INTL(V9,W9,1)-1))) | AR9: =IF(AA9="","",AQ9=AA9) | AS9: =IF(OR(A9="Solicitação de Serviço",A9="Incidente",P9=""),"",IF(OR(A9="História",A9="Enabler",A9="Débito Técnico"),IF(W9="","",NETWORKDAYS.INTL(P9,W9,1)-1),IF(U9="","",NETWORKDAYS.INTL(P9,U9,1)-1))) | AT9: =IF(OR(A9="Solicitação de Serviço",A9="Incidente",A9="Sustentação"),"",IF(P9="","",IF(OR(A9="História",A9="Enabler",A9="Débito Técnico"),AS9=AC9,AS9=AB9))) | AU9: =IF(M9="","",M9)
A10: Incidente | B10: SGTB-2835 | C10: [SGTB] SP 26.3.6 | D10: [Jornada Secretaria e Gestor de Unidades] Thunderbolts | E10: Aceito | F10: [SGTB] PI 3/26 | H10: [INC0821364]Tenho um Erro/Problema com o Sistema - Extranet - (Extranet) Atendimento | J10: 900 | L10: Itens concluídos | O10: Abertura indevida | P10: 46288.444 | Q10: 46279 | R10: 46288 | AH10: =IF(J10="","",J10/3600) -> 0.25 | AI10: =IF(COUNTIF(AG10, "*dia*"), "VERDADEIRO", "FALSO") -> FALSO | AJ10: =IF(AI10="VERDADEIRO",LEFT(AG10,2),0) -> 0 | AK10: =IF(OR(A10="Solicitação de Serviço",A10="Incidente",P10="",Q10=""),"",IF((NETWORKDAYS.INTL(P10,Q10,1)-1)=0,1,NETWORKDAYS.INTL(P10,Q10,1)-1)) | AL10: =IF(X10="","",AK10=X10) | AM10: =IF(OR(A10="Solicitação de Serviço",A10="Incidente",R10="",S10=""),"",IF((NETWORKDAYS.INTL(R10,S10,1)-1)=0,1,NETWORKDAYS.INTL(R10,S10,1)-1-AJ10)) | AN10: =IF(Y10="","",AM10=Y10) | AO10: =IF(OR(A10="Solicitação de Serviço",A10="Incidente",T10="",U10=""),"",IF((NETWORKDAYS.INTL(T10,U10,1)-1)=0,1,NETWORKDAYS.INTL(T10,U10,1)-1)) | AP10: =IF(Z10="","",AO10=Z10) | AQ10: =IF(OR(A10="Solicitação de Serviço",A10="Incidente",V10="",W10=""),"",IF((NETWORKDAYS.INTL(V10,W10,1)-1)=0,1,IF((NETWORKDAYS.INTL(V10,W10,1)-1)<0,"",NETWORKDAYS.INTL(V10,W10,1)-1))) | AR10: =IF(AA10="","",AQ10=AA10) | AS10: =IF(OR(A10="Solicitação de Serviço",A10="Incidente",P10=""),"",IF(OR(A10="História",A10="Enabler",A10="Débito Técnico"),IF(W10="","",NETWORKDAYS.INTL(P10,W10,1)-1),IF(U10="","",NETWORKDAYS.INTL(P10,U10,1)-1))) | AT10: =IF(OR(A10="Solicitação de Serviço",A10="Incidente",A10="Sustentação"),"",IF(P10="","",IF(OR(A10="História",A10="Enabler",A10="Débito Técnico"),AS10=AC10,AS10=AB10))) | AU10: =IF(M10="","",M10)
A11: Incidente | B11: SGTB-2829 | C11: [SGTB] SP 26.4.1;[SGTB] SP 26.3.6 | D11: [Jornada Secretaria e Gestor de Unidades] Thunderbolts | E11: Aceito | F11: [SGTB] PI 3/26 | H11: [INC0821332]Tenho um Erro/Problema com o Sistema - Portal do Professor - Portal do Professor | J11: 3600 | L11: Itens concluídos | O11: Concluído | P11: 46287.653 | Q11: 46279 | R11: 46288 | S11: 46288 | AH11: =IF(J11="","",J11/3600) -> 1 | AI11: =IF(COUNTIF(AG11, "*dia*"), "VERDADEIRO", "FALSO") -> FALSO | AJ11: =IF(AI11="VERDADEIRO",LEFT(AG11,2),0) -> 0 | AK11: =IF(OR(A11="Solicitação de Serviço",A11="Incidente",P11="",Q11=""),"",IF((NETWORKDAYS.INTL(P11,Q11,1)-1)=0,1,NETWORKDAYS.INTL(P11,Q11,1)-1)) | AL11: =IF(X11="","",AK11=X11) | AM11: =IF(OR(A11="Solicitação de Serviço",A11="Incidente",R11="",S11=""),"",IF((NETWORKDAYS.INTL(R11,S11,1)-1)=0,1,NETWORKDAYS.INTL(R11,S11,1)-1-AJ11)) | AN11: =IF(Y11="","",AM11=Y11) | AO11: =IF(OR(A11="Solicitação de Serviço",A11="Incidente",T11="",U11=""),"",IF((NETWORKDAYS.INTL(T11,U11,1)-1)=0,1,NETWORKDAYS.INTL(T11,U11,1)-1)) | AP11: =IF(Z11="","",AO11=Z11) | AQ11: =IF(OR(A11="Solicitação de Serviço",A11="Incidente",V11="",W11=""),"",IF((NETWORKDAYS.INTL(V11,W11,1)-1)=0,1,IF((NETWORKDAYS.INTL(V11,W11,1)-1)<0,"",NETWORKDAYS.INTL(V11,W11,1)-1))) | AR11: =IF(AA11="","",AQ11=AA11) | AS11: =IF(OR(A11="Solicitação de Serviço",A11="Incidente",P11=""),"",IF(OR(A11="História",A11="Enabler",A11="Débito Técnico"),IF(W11="","",NETWORKDAYS.INTL(P11,W11,1)-1),IF(U11="","",NETWORKDAYS.INTL(P11,U11,1)-1))) | AT11: =IF(OR(A11="Solicitação de Serviço",A11="Incidente",A11="Sustentação"),"",IF(P11="","",IF(OR(A11="História",A11="Enabler",A11="Débito Técnico"),AS11=AC11,AS11=AB11))) | AU11: =IF(M11="","",M11)
A12: Solicitação de Serviço | B12: SGTB-2828 | C12: [SGTB] SP 26.4.1;[SGTB] SP 26.3.6 | D12: [Jornada Secretaria e Gestor de Unidades] Thunderbolts | E12: Aceito | F12: [SGTB] PI 3/26 | H12: [RITM0746021]Solicitar um serviço para o Sistema Colaborar - Colaborar - Extranet Colaborar | J12: 1800 | L12: Itens concluídos | O12: Concluído | P12: 46287.635 | Q12: 46279 | R12: 46288 | S12: 46288 | AH12: =IF(J12="","",J12/3600) -> 0.5 | AI12: =IF(COUNTIF(AG12, "*dia*"), "VERDADEIRO", "FALSO") -> FALSO | AJ12: =IF(AI12="VERDADEIRO",LEFT(AG12,2),0) -> 0 | AK12: =IF(OR(A12="Solicitação de Serviço",A12="Incidente",P12="",Q12=""),"",IF((NETWORKDAYS.INTL(P12,Q12,1)-1)=0,1,NETWORKDAYS.INTL(P12,Q12,1)-1)) | AL12: =IF(X12="","",AK12=X12) | AM12: =IF(OR(A12="Solicitação de Serviço",A12="Incidente",R12="",S12=""),"",IF((NETWORKDAYS.INTL(R12,S12,1)-1)=0,1,NETWORKDAYS.INTL(R12,S12,1)-1-AJ12)) | AN12: =IF(Y12="","",AM12=Y12) | AO12: =IF(OR(A12="Solicitação de Serviço",A12="Incidente",T12="",U12=""),"",IF((NETWORKDAYS.INTL(T12,U12,1)-1)=0,1,NETWORKDAYS.INTL(T12,U12,1)-1)) | AP12: =IF(Z12="","",AO12=Z12) | AQ12: =IF(OR(A12="Solicitação de Serviço",A12="Incidente",V12="",W12=""),"",IF((NETWORKDAYS.INTL(V12,W12,1)-1)=0,1,IF((NETWORKDAYS.INTL(V12,W12,1)-1)<0,"",NETWORKDAYS.INTL(V12,W12,1)-1))) | AR12: =IF(AA12="","",AQ12=AA12) | AS12: =IF(OR(A12="Solicitação de Serviço",A12="Incidente",P12=""),"",IF(OR(A12="História",A12="Enabler",A12="Débito Técnico"),IF(W12="","",NETWORKDAYS.INTL(P12,W12,1)-1),IF(U12="","",NETWORKDAYS.INTL(P12,U12,1)-1))) | AT12: =IF(OR(A12="Solicitação de Serviço",A12="Incidente",A12="Sustentação"),"",IF(P12="","",IF(OR(A12="História",A12="Enabler",A12="Débito Técnico"),AS12=AC12,AS12=AB12))) | AU12: =IF(M12="","",M12)
A13: Incidente | B13: SGTB-2824 | C13: [SGTB] SP 26.4.1;[SGTB] SP 26.3.6 | D13: [Jornada Secretaria e Gestor de Unidades] Thunderbolts | E13: Aceito | F13: [SGTB] PI 3/26 | H13: [INC0821219]Tenho um Erro/Problema com o Sistema Colaborar - Colaborar - GED (DGA) | J13: 900 | L13: Itens concluídos | O13: Concluído | P13: 46287.614 | Q13: 46279 | R13: 46289 | S13: 46289 | AH13: =IF(J13="","",J13/3600) -> 0.25 | AI13: =IF(COUNTIF(AG13, "*dia*"), "VERDADEIRO", "FALSO") -> FALSO | AJ13: =IF(AI13="VERDADEIRO",LEFT(AG13,2),0) -> 0 | AK13: =IF(OR(A13="Solicitação de Serviço",A13="Incidente",P13="",Q13=""),"",IF((NETWORKDAYS.INTL(P13,Q13,1)-1)=0,1,NETWORKDAYS.INTL(P13,Q13,1)-1)) | AL13: =IF(X13="","",AK13=X13) | AM13: =IF(OR(A13="Solicitação de Serviço",A13="Incidente",R13="",S13=""),"",IF((NETWORKDAYS.INTL(R13,S13,1)-1)=0,1,NETWORKDAYS.INTL(R13,S13,1)-1-AJ13)) | AN13: =IF(Y13="","",AM13=Y13) | AO13: =IF(OR(A13="Solicitação de Serviço",A13="Incidente",T13="",U13=""),"",IF((NETWORKDAYS.INTL(T13,U13,1)-1)=0,1,NETWORKDAYS.INTL(T13,U13,1)-1)) | AP13: =IF(Z13="","",AO13=Z13) | AQ13: =IF(OR(A13="Solicitação de Serviço",A13="Incidente",V13="",W13=""),"",IF((NETWORKDAYS.INTL(V13,W13,1)-1)=0,1,IF((NETWORKDAYS.INTL(V13,W13,1)-1)<0,"",NETWORKDAYS.INTL(V13,W13,1)-1))) | AR13: =IF(AA13="","",AQ13=AA13) | AS13: =IF(OR(A13="Solicitação de Serviço",A13="Incidente",P13=""),"",IF(OR(A13="História",A13="Enabler",A13="Débito Técnico"),IF(W13="","",NETWORKDAYS.INTL(P13,W13,1)-1),IF(U13="","",NETWORKDAYS.INTL(P13,U13,1)-1))) | AT13: =IF(OR(A13="Solicitação de Serviço",A13="Incidente",A13="Sustentação"),"",IF(P13="","",IF(OR(A13="História",A13="Enabler",A13="Débito Técnico"),AS13=AC13,AS13=AB13))) | AU13: =IF(M13="","",M13)
A14: Incidente | B14: SGTB-2819 | C14: [SGTB] SP 26.4.1;[SGTB] SP 26.3.6 | D14: [Jornada Secretaria e Gestor de Unidades] Thunderbolts | E14: Aceito | F14: [SGTB] PI 3/26 | H14: [INC0821235]Tenho um Erro/Problema com o Sistema - Portal Prisma - Prisma - Usuários do Prisma | J14: 25200 | L14: Itens concluídos | O14: Concluído | P14: 46287.509 | Q14: 46279 | R14: 46289 | S14: 46289 | AH14: =IF(J14="","",J14/3600) -> 7 | AI14: =IF(COUNTIF(AG14, "*dia*"), "VERDADEIRO", "FALSO") -> FALSO | AJ14: =IF(AI14="VERDADEIRO",LEFT(AG14,2),0) -> 0 | AK14: =IF(OR(A14="Solicitação de Serviço",A14="Incidente",P14="",Q14=""),"",IF((NETWORKDAYS.INTL(P14,Q14,1)-1)=0,1,NETWORKDAYS.INTL(P14,Q14,1)-1)) | AL14: =IF(X14="","",AK14=X14) | AM14: =IF(OR(A14="Solicitação de Serviço",A14="Incidente",R14="",S14=""),"",IF((NETWORKDAYS.INTL(R14,S14,1)-1)=0,1,NETWORKDAYS.INTL(R14,S14,1)-1-AJ14)) | AN14: =IF(Y14="","",AM14=Y14) | AO14: =IF(OR(A14="Solicitação de Serviço",A14="Incidente",T14="",U14=""),"",IF((NETWORKDAYS.INTL(T14,U14,1)-1)=0,1,NETWORKDAYS.INTL(T14,U14,1)-1)) | AP14: =IF(Z14="","",AO14=Z14) | AQ14: =IF(OR(A14="Solicitação de Serviço",A14="Incidente",V14="",W14=""),"",IF((NETWORKDAYS.INTL(V14,W14,1)-1)=0,1,IF((NETWORKDAYS.INTL(V14,W14,1)-1)<0,"",NETWORKDAYS.INTL(V14,W14,1)-1))) | AR14: =IF(AA14="","",AQ14=AA14) | AS14: =IF(OR(A14="Solicitação de Serviço",A14="Incidente",P14=""),"",IF(OR(A14="História",A14="Enabler",A14="Débito Técnico"),IF(W14="","",NETWORKDAYS.INTL(P14,W14,1)-1),IF(U14="","",NETWORKDAYS.INTL(P14,U14,1)-1))) | AT14: =IF(OR(A14="Solicitação de Serviço",A14="Incidente",A14="Sustentação"),"",IF(P14="","",IF(OR(A14="História",A14="Enabler",A14="Débito Técnico"),AS14=AC14,AS14=AB14))) | AU14: =IF(M14="","",M14)
A15: Incidente | B15: SGTB-2818 | C15: [SGTB] SP 26.3.6 | D15: [Jornada Secretaria e Gestor de Unidades] Thunderbolts | E15: Aceito | F15: [SGTB] PI 3/26 | H15: [INC0819611]Tenho um Erro/Problema com o Sistema Colaborar - Colaborar - Administração de usuários | J15: 600 | L15: Itens concluídos | O15: Abertura indevida | P15: 46287.496 | Q15: 46279 | R15: 46288 | AH15: =IF(J15="","",J15/3600) -> 0.16666667 | AI15: =IF(COUNTIF(AG15, "*dia*"), "VERDADEIRO", "FALSO") -> FALSO | AJ15: =IF(AI15="VERDADEIRO",LEFT(AG15,2),0) -> 0 | AK15: =IF(OR(A15="Solicitação de Serviço",A15="Incidente",P15="",Q15=""),"",IF((NETWORKDAYS.INTL(P15,Q15,1)-1)=0,1,NETWORKDAYS.INTL(P15,Q15,1)-1)) | AL15: =IF(X15="","",AK15=X15) | AM15: =IF(OR(A15="Solicitação de Serviço",A15="Incidente",R15="",S15=""),"",IF((NETWORKDAYS.INTL(R15,S15,1)-1)=0,1,NETWORKDAYS.INTL(R15,S15,1)-1-AJ15)) | AN15: =IF(Y15="","",AM15=Y15) | AO15: =IF(OR(A15="Solicitação de Serviço",A15="Incidente",T15="",U15=""),"",IF((NETWORKDAYS.INTL(T15,U15,1)-1)=0,1,NETWORKDAYS.INTL(T15,U15,1)-1)) | AP15: =IF(Z15="","",AO15=Z15) | AQ15: =IF(OR(A15="Solicitação de Serviço",A15="Incidente",V15="",W15=""),"",IF((NETWORKDAYS.INTL(V15,W15,1)-1)=0,1,IF((NETWORKDAYS.INTL(V15,W15,1)-1)<0,"",NETWORKDAYS.INTL(V15,W15,1)-1))) | AR15: =IF(AA15="","",AQ15=AA15) | AS15: =IF(OR(A15="Solicitação de Serviço",A15="Incidente",P15=""),"",IF(OR(A15="História",A15="Enabler",A15="Débito Técnico"),IF(W15="","",NETWORKDAYS.INTL(P15,W15,1)-1),IF(U15="","",NETWORKDAYS.INTL(P15,U15,1)-1))) | AT15: =IF(OR(A15="Solicitação de Serviço",A15="Incidente",A15="Sustentação"),"",IF(P15="","",IF(OR(A15="História",A15="Enabler",A15="Débito Técnico"),AS15=AC15,AS15=AB15))) | AU15: =IF(M15="","",M15)
A16: Incidente | B16: SGTB-2815 | C16: [SGTB] SP 26.4.1;[SGTB] SP 26.3.6 | D16: [Jornada Secretaria e Gestor de Unidades] Thunderbolts | E16: Aceito | F16: [SGTB] PI 3/26 | H16: [INC0818183]Tenho um Erro/Problema com o PTC - Dynamics Athenas - Ocorrências | J16: 600 | L16: Itens concluídos | O16: Concluído | P16: 46287.49 | Q16: 46279 | R16: 46287 | S16: 46287 | AH16: =IF(J16="","",J16/3600) -> 0.16666667 | AI16: =IF(COUNTIF(AG16, "*dia*"), "VERDADEIRO", "FALSO") -> FALSO | AJ16: =IF(AI16="VERDADEIRO",LEFT(AG16,2),0) -> 0 | AK16: =IF(OR(A16="Solicitação de Serviço",A16="Incidente",P16="",Q16=""),"",IF((NETWORKDAYS.INTL(P16,Q16,1)-1)=0,1,NETWORKDAYS.INTL(P16,Q16,1)-1)) | AL16: =IF(X16="","",AK16=X16) | AM16: =IF(OR(A16="Solicitação de Serviço",A16="Incidente",R16="",S16=""),"",IF((NETWORKDAYS.INTL(R16,S16,1)-1)=0,1,NETWORKDAYS.INTL(R16,S16,1)-1-AJ16)) | AN16: =IF(Y16="","",AM16=Y16) | AO16: =IF(OR(A16="Solicitação de Serviço",A16="Incidente",T16="",U16=""),"",IF((NETWORKDAYS.INTL(T16,U16,1)-1)=0,1,NETWORKDAYS.INTL(T16,U16,1)-1)) | AP16: =IF(Z16="","",AO16=Z16) | AQ16: =IF(OR(A16="Solicitação de Serviço",A16="Incidente",V16="",W16=""),"",IF((NETWORKDAYS.INTL(V16,W16,1)-1)=0,1,IF((NETWORKDAYS.INTL(V16,W16,1)-1)<0,"",NETWORKDAYS.INTL(V16,W16,1)-1))) | AR16: =IF(AA16="","",AQ16=AA16) | AS16: =IF(OR(A16="Solicitação de Serviço",A16="Incidente",P16=""),"",IF(OR(A16="História",A16="Enabler",A16="Débito Técnico"),IF(W16="","",NETWORKDAYS.INTL(P16,W16,1)-1),IF(U16="","",NETWORKDAYS.INTL(P16,U16,1)-1))) | AT16: =IF(OR(A16="Solicitação de Serviço",A16="Incidente",A16="Sustentação"),"",IF(P16="","",IF(OR(A16="História",A16="Enabler",A16="Débito Técnico"),AS16=AC16,AS16=AB16))) | AU16: =IF(M16="","",M16)
A17: Incidente | B17: SGTB-2814 | C17: [SGTB] SP 26.3.6 | D17: [Jornada Secretaria e Gestor de Unidades] Thunderbolts | E17: Aceito | F17: [SGTB] PI 3/26 | H17: [INC0821180]Tenho um Erro/Problema com o Sistema - Olimpo - Concurso | L17: Itens concluídos | O17: Abertura indevida | P17: 46287.48 | Q17: 46279 | R17: 46287 | AH17: =IF(J17="","",J17/3600) | AI17: =IF(COUNTIF(AG17, "*dia*"), "VERDADEIRO", "FALSO") -> FALSO | AJ17: =IF(AI17="VERDADEIRO",LEFT(AG17,2),0) -> 0 | AK17: =IF(OR(A17="Solicitação de Serviço",A17="Incidente",P17="",Q17=""),"",IF((NETWORKDAYS.INTL(P17,Q17,1)-1)=0,1,NETWORKDAYS.INTL(P17,Q17,1)-1)) | AL17: =IF(X17="","",AK17=X17) | AM17: =IF(OR(A17="Solicitação de Serviço",A17="Incidente",R17="",S17=""),"",IF((NETWORKDAYS.INTL(R17,S17,1)-1)=0,1,NETWORKDAYS.INTL(R17,S17,1)-1-AJ17)) | AN17: =IF(Y17="","",AM17=Y17) | AO17: =IF(OR(A17="Solicitação de Serviço",A17="Incidente",T17="",U17=""),"",IF((NETWORKDAYS.INTL(T17,U17,1)-1)=0,1,NETWORKDAYS.INTL(T17,U17,1)-1)) | AP17: =IF(Z17="","",AO17=Z17) | AQ17: =IF(OR(A17="Solicitação de Serviço",A17="Incidente",V17="",W17=""),"",IF((NETWORKDAYS.INTL(V17,W17,1)-1)=0,1,IF((NETWORKDAYS.INTL(V17,W17,1)-1)<0,"",NETWORKDAYS.INTL(V17,W17,1)-1))) | AR17: =IF(AA17="","",AQ17=AA17) | AS17: =IF(OR(A17="Solicitação de Serviço",A17="Incidente",P17=""),"",IF(OR(A17="História",A17="Enabler",A17="Débito Técnico"),IF(W17="","",NETWORKDAYS.INTL(P17,W17,1)-1),IF(U17="","",NETWORKDAYS.INTL(P17,U17,1)-1))) | AT17: =IF(OR(A17="Solicitação de Serviço",A17="Incidente",A17="Sustentação"),"",IF(P17="","",IF(OR(A17="História",A17="Enabler",A17="Débito Técnico"),AS17=AC17,AS17=AB17))) | AU17: =IF(M17="","",M17)
A18: Incidente | B18: SGTB-2812 | C18: [SGTB] SP 26.4.1;[SGTB] SP 26.3.6 | D18: [Jornada Secretaria e Gestor de Unidades] Thunderbolts | E18: Aceito | F18: [SGTB] PI 3/26 | H18: [INC0821189]Tenho um Erro/Problema com o Sistema - Extranet - Enturmacao | J18: 25200 | L18: Itens concluídos | O18: Concluído | P18: 46287.46 | Q18: 46279 | R18: 46287 | S18: 46288 | AH18: =IF(J18="","",J18/3600) -> 7 | AI18: =IF(COUNTIF(AG18, "*dia*"), "VERDADEIRO", "FALSO") -> FALSO | AJ18: =IF(AI18="VERDADEIRO",LEFT(AG18,2),0) -> 0 | AK18: =IF(OR(A18="Solicitação de Serviço",A18="Incidente",P18="",Q18=""),"",IF((NETWORKDAYS.INTL(P18,Q18,1)-1)=0,1,NETWORKDAYS.INTL(P18,Q18,1)-1)) | AL18: =IF(X18="","",AK18=X18) | AM18: =IF(OR(A18="Solicitação de Serviço",A18="Incidente",R18="",S18=""),"",IF((NETWORKDAYS.INTL(R18,S18,1)-1)=0,1,NETWORKDAYS.INTL(R18,S18,1)-1-AJ18)) | AN18: =IF(Y18="","",AM18=Y18) | AO18: =IF(OR(A18="Solicitação de Serviço",A18="Incidente",T18="",U18=""),"",IF((NETWORKDAYS.INTL(T18,U18,1)-1)=0,1,NETWORKDAYS.INTL(T18,U18,1)-1)) | AP18: =IF(Z18="","",AO18=Z18) | AQ18: =IF(OR(A18="Solicitação de Serviço",A18="Incidente",V18="",W18=""),"",IF((NETWORKDAYS.INTL(V18,W18,1)-1)=0,1,IF((NETWORKDAYS.INTL(V18,W18,1)-1)<0,"",NETWORKDAYS.INTL(V18,W18,1)-1))) | AR18: =IF(AA18="","",AQ18=AA18) | AS18: =IF(OR(A18="Solicitação de Serviço",A18="Incidente",P18=""),"",IF(OR(A18="História",A18="Enabler",A18="Débito Técnico"),IF(W18="","",NETWORKDAYS.INTL(P18,W18,1)-1),IF(U18="","",NETWORKDAYS.INTL(P18,U18,1)-1))) | AT18: =IF(OR(A18="Solicitação de Serviço",A18="Incidente",A18="Sustentação"),"",IF(P18="","",IF(OR(A18="História",A18="Enabler",A18="Débito Técnico"),AS18=AC18,AS18=AB18))) | AU18: =IF(M18="","",M18)
A19: Incidente | B19: SGTB-2797 | C19: [SGTB] SP 26.3.6 | D19: [Jornada Secretaria e Gestor de Unidades] Thunderbolts | E19: Aceito | F19: [SGTB] PI 3/26 | H19: [INC0821158]Tenho um Erro/Problema com o Sistema Colaborar - Administrativo [Secretaria] - Operações Acadêmicas - Secretaria - Atendimento EAD | J19: 600 | L19: Itens concluídos | O19: Abertura indevida | P19: 46287.388 | Q19: 46279 | R19: 46287 | AH19: =IF(J19="","",J19/3600) -> 0.16666667 | AI19: =IF(COUNTIF(AG19, "*dia*"), "VERDADEIRO", "FALSO") -> FALSO | AJ19: =IF(AI19="VERDADEIRO",LEFT(AG19,2),0) -> 0 | AK19: =IF(OR(A19="Solicitação de Serviço",A19="Incidente",P19="",Q19=""),"",IF((NETWORKDAYS.INTL(P19,Q19,1)-1)=0,1,NETWORKDAYS.INTL(P19,Q19,1)-1)) | AL19: =IF(X19="","",AK19=X19) | AM19: =IF(OR(A19="Solicitação de Serviço",A19="Incidente",R19="",S19=""),"",IF((NETWORKDAYS.INTL(R19,S19,1)-1)=0,1,NETWORKDAYS.INTL(R19,S19,1)-1-AJ19)) | AN19: =IF(Y19="","",AM19=Y19) | AO19: =IF(OR(A19="Solicitação de Serviço",A19="Incidente",T19="",U19=""),"",IF((NETWORKDAYS.INTL(T19,U19,1)-1)=0,1,NETWORKDAYS.INTL(T19,U19,1)-1)) | AP19: =IF(Z19="","",AO19=Z19) | AQ19: =IF(OR(A19="Solicitação de Serviço",A19="Incidente",V19="",W19=""),"",IF((NETWORKDAYS.INTL(V19,W19,1)-1)=0,1,IF((NETWORKDAYS.INTL(V19,W19,1)-1)<0,"",NETWORKDAYS.INTL(V19,W19,1)-1))) | AR19: =IF(AA19="","",AQ19=AA19) | AS19: =IF(OR(A19="Solicitação de Serviço",A19="Incidente",P19=""),"",IF(OR(A19="História",A19="Enabler",A19="Débito Técnico"),IF(W19="","",NETWORKDAYS.INTL(P19,W19,1)-1),IF(U19="","",NETWORKDAYS.INTL(P19,U19,1)-1))) | AT19: =IF(OR(A19="Solicitação de Serviço",A19="Incidente",A19="Sustentação"),"",IF(P19="","",IF(OR(A19="História",A19="Enabler",A19="Débito Técnico"),AS19=AC19,AS19=AB19))) | AU19: =IF(M19="","",M19)
A20: Incidente | B20: SGTB-2746 | C20: [SGTB] SP 26.3.6 | D20: [Jornada Secretaria e Gestor de Unidades] Thunderbolts | E20: Aceito | F20: [SGTB] PI 3/26 | H20: [INC0818151]Tenho um Erro/Problema com o Sistema - PDA:Portal do aluno - Graduação - Erro no Estudar no AVA | L20: Itens concluídos | O20: Abertura indevida | P20: 46286.522 | Q20: 46279 | R20: 46286 | AH20: =IF(J20="","",J20/3600) | AI20: =IF(COUNTIF(AG20, "*dia*"), "VERDADEIRO", "FALSO") -> FALSO | AJ20: =IF(AI20="VERDADEIRO",LEFT(AG20,2),0) -> 0 | AK20: =IF(OR(A20="Solicitação de Serviço",A20="Incidente",P20="",Q20=""),"",IF((NETWORKDAYS.INTL(P20,Q20,1)-1)=0,1,NETWORKDAYS.INTL(P20,Q20,1)-1)) | AL20: =IF(X20="","",AK20=X20) | AM20: =IF(OR(A20="Solicitação de Serviço",A20="Incidente",R20="",S20=""),"",IF((NETWORKDAYS.INTL(R20,S20,1)-1)=0,1,NETWORKDAYS.INTL(R20,S20,1)-1-AJ20)) | AN20: =IF(Y20="","",AM20=Y20) | AO20: =IF(OR(A20="Solicitação de Serviço",A20="Incidente",T20="",U20=""),"",IF((NETWORKDAYS.INTL(T20,U20,1)-1)=0,1,NETWORKDAYS.INTL(T20,U20,1)-1)) | AP20: =IF(Z20="","",AO20=Z20) | AQ20: =IF(OR(A20="Solicitação de Serviço",A20="Incidente",V20="",W20=""),"",IF((NETWORKDAYS.INTL(V20,W20,1)-1)=0,1,IF((NETWORKDAYS.INTL(V20,W20,1)-1)<0,"",NETWORKDAYS.INTL(V20,W20,1)-1))) | AR20: =IF(AA20="","",AQ20=AA20) | AS20: =IF(OR(A20="Solicitação de Serviço",A20="Incidente",P20=""),"",IF(OR(A20="História",A20="Enabler",A20="Débito Técnico"),IF(W20="","",NETWORKDAYS.INTL(P20,W20,1)-1),IF(U20="","",NETWORKDAYS.INTL(P20,U20,1)-1))) | AT20: =IF(OR(A20="Solicitação de Serviço",A20="Incidente",A20="Sustentação"),"",IF(P20="","",IF(OR(A20="História",A20="Enabler",A20="Débito Técnico"),AS20=AC20,AS20=AB20))) | AU20: =IF(M20="","",M20)
A21: Incidente | B21: SGTB-2745 | C21: [SGTB] SP 26.3.6 | D21: [Jornada Secretaria e Gestor de Unidades] Thunderbolts | E21: Aceito | F21: [SGTB] PI 3/26 | H21: [INC0808474]Tenho um Erro/Problema com o Sistema - AVA (LMS) - AVA (LMS) | J21: 1800 | L21: Itens concluídos | O21: Abertura indevida | P21: 46286.501 | Q21: 46279 | R21: 46286 | AH21: =IF(J21="","",J21/3600) -> 0.5 | AI21: =IF(COUNTIF(AG21, "*dia*"), "VERDADEIRO", "FALSO") -> FALSO | AJ21: =IF(AI21="VERDADEIRO",LEFT(AG21,2),0) -> 0 | AK21: =IF(OR(A21="Solicitação de Serviço",A21="Incidente",P21="",Q21=""),"",IF((NETWORKDAYS.INTL(P21,Q21,1)-1)=0,1,NETWORKDAYS.INTL(P21,Q21,1)-1)) | AL21: =IF(X21="","",AK21=X21) | AM21: =IF(OR(A21="Solicitação de Serviço",A21="Incidente",R21="",S21=""),"",IF((NETWORKDAYS.INTL(R21,S21,1)-1)=0,1,NETWORKDAYS.INTL(R21,S21,1)-1-AJ21)) | AN21: =IF(Y21="","",AM21=Y21) | AO21: =IF(OR(A21="Solicitação de Serviço",A21="Incidente",T21="",U21=""),"",IF((NETWORKDAYS.INTL(T21,U21,1)-1)=0,1,NETWORKDAYS.INTL(T21,U21,1)-1)) | AP21: =IF(Z21="","",AO21=Z21) | AQ21: =IF(OR(A21="Solicitação de Serviço",A21="Incidente",V21="",W21=""),"",IF((NETWORKDAYS.INTL(V21,W21,1)-1)=0,1,IF((NETWORKDAYS.INTL(V21,W21,1)-1)<0,"",NETWORKDAYS.INTL(V21,W21,1)-1))) | AR21: =IF(AA21="","",AQ21=AA21) | AS21: =IF(OR(A21="Solicitação de Serviço",A21="Incidente",P21=""),"",IF(OR(A21="História",A21="Enabler",A21="Débito Técnico"),IF(W21="","",NETWORKDAYS.INTL(P21,W21,1)-1),IF(U21="","",NETWORKDAYS.INTL(P21,U21,1)-1))) | AT21: =IF(OR(A21="Solicitação de Serviço",A21="Incidente",A21="Sustentação"),"",IF(P21="","",IF(OR(A21="História",A21="Enabler",A21="Débito Técnico"),AS21=AC21,AS21=AB21))) | AU21: =IF(M21="","",M21)
A22: Incidente | B22: SGTB-2743 | C22: [SGTB] SP 26.4.1;[SGTB] SP 26.3.6 | D22: [Jornada Secretaria e Gestor de Unidades] Thunderbolts | E22: Aceito | F22: [SGTB] PI 3/26 | H22: [INC0819805]Tenho um Erro/Problema com o Sistema - Olimpo - BD - Olimpo Banco de Dados | J22: 14400 | L22: Itens concluídos | O22: Concluído | P22: 46286.454 | Q22: 46279 | R22: 46286 | S22: 46288 | AH22: =IF(J22="","",J22/3600) -> 4 | AI22: =IF(COUNTIF(AG22, "*dia*"), "VERDADEIRO", "FALSO") -> FALSO | AJ22: =IF(AI22="VERDADEIRO",LEFT(AG22,2),0) -> 0 | AK22: =IF(OR(A22="Solicitação de Serviço",A22="Incidente",P22="",Q22=""),"",IF((NETWORKDAYS.INTL(P22,Q22,1)-1)=0,1,NETWORKDAYS.INTL(P22,Q22,1)-1)) | AL22: =IF(X22="","",AK22=X22) | AM22: =IF(OR(A22="Solicitação de Serviço",A22="Incidente",R22="",S22=""),"",IF((NETWORKDAYS.INTL(R22,S22,1)-1)=0,1,NETWORKDAYS.INTL(R22,S22,1)-1-AJ22)) | AN22: =IF(Y22="","",AM22=Y22) | AO22: =IF(OR(A22="Solicitação de Serviço",A22="Incidente",T22="",U22=""),"",IF((NETWORKDAYS.INTL(T22,U22,1)-1)=0,1,NETWORKDAYS.INTL(T22,U22,1)-1)) | AP22: =IF(Z22="","",AO22=Z22) | AQ22: =IF(OR(A22="Solicitação de Serviço",A22="Incidente",V22="",W22=""),"",IF((NETWORKDAYS.INTL(V22,W22,1)-1)=0,1,IF((NETWORKDAYS.INTL(V22,W22,1)-1)<0,"",NETWORKDAYS.INTL(V22,W22,1)-1))) | AR22: =IF(AA22="","",AQ22=AA22) | AS22: =IF(OR(A22="Solicitação de Serviço",A22="Incidente",P22=""),"",IF(OR(A22="História",A22="Enabler",A22="Débito Técnico"),IF(W22="","",NETWORKDAYS.INTL(P22,W22,1)-1),IF(U22="","",NETWORKDAYS.INTL(P22,U22,1)-1))) | AT22: =IF(OR(A22="Solicitação de Serviço",A22="Incidente",A22="Sustentação"),"",IF(P22="","",IF(OR(A22="História",A22="Enabler",A22="Débito Técnico"),AS22=AC22,AS22=AB22))) | AU22: =IF(M22="","",M22)
A23: Incidente | B23: SGTB-2742 | C23: [SGTB] SP 26.4.1;[SGTB] SP 26.3.6 | D23: [Jornada Secretaria e Gestor de Unidades] Thunderbolts | E23: Aceito | F23: [SGTB] PI 3/26 | H23: [INC0819839]Tenho um Erro/Problema com o Sistema - Olimpo - Desktop - Consulta | J23: 3600 | L23: Itens concluídos | O23: Concluído | P23: 46286.454 | Q23: 46279 | R23: 46286 | S23: 46286 | AH23: =IF(J23="","",J23/3600) -> 1 | AI23: =IF(COUNTIF(AG23, "*dia*"), "VERDADEIRO", "FALSO") -> FALSO | AJ23: =IF(AI23="VERDADEIRO",LEFT(AG23,2),0) -> 0 | AK23: =IF(OR(A23="Solicitação de Serviço",A23="Incidente",P23="",Q23=""),"",IF((NETWORKDAYS.INTL(P23,Q23,1)-1)=0,1,NETWORKDAYS.INTL(P23,Q23,1)-1)) | AL23: =IF(X23="","",AK23=X23) | AM23: =IF(OR(A23="Solicitação de Serviço",A23="Incidente",R23="",S23=""),"",IF((NETWORKDAYS.INTL(R23,S23,1)-1)=0,1,NETWORKDAYS.INTL(R23,S23,1)-1-AJ23)) | AN23: =IF(Y23="","",AM23=Y23) | AO23: =IF(OR(A23="Solicitação de Serviço",A23="Incidente",T23="",U23=""),"",IF((NETWORKDAYS.INTL(T23,U23,1)-1)=0,1,NETWORKDAYS.INTL(T23,U23,1)-1)) | AP23: =IF(Z23="","",AO23=Z23) | AQ23: =IF(OR(A23="Solicitação de Serviço",A23="Incidente",V23="",W23=""),"",IF((NETWORKDAYS.INTL(V23,W23,1)-1)=0,1,IF((NETWORKDAYS.INTL(V23,W23,1)-1)<0,"",NETWORKDAYS.INTL(V23,W23,1)-1))) | AR23: =IF(AA23="","",AQ23=AA23) | AS23: =IF(OR(A23="Solicitação de Serviço",A23="Incidente",P23=""),"",IF(OR(A23="História",A23="Enabler",A23="Débito Técnico"),IF(W23="","",NETWORKDAYS.INTL(P23,W23,1)-1),IF(U23="","",NETWORKDAYS.INTL(P23,U23,1)-1))) | AT23: =IF(OR(A23="Solicitação de Serviço",A23="Incidente",A23="Sustentação"),"",IF(P23="","",IF(OR(A23="História",A23="Enabler",A23="Débito Técnico"),AS23=AC23,AS23=AB23))) | AU23: =IF(M23="","",M23)
A24: Incidente | B24: SGTB-2741 | C24: [SGTB] SP 26.4.1;[SGTB] SP 26.3.6 | D24: [Jornada Secretaria e Gestor de Unidades] Thunderbolts | E24: Aceito | F24: [SGTB] PI 3/26 | H24: [INC0820663]Tenho um Erro/Problema com o Sistema - Olimpo - Matrícula | J24: 3600 | L24: Itens concluídos | O24: Concluído | P24: 46286.449 | Q24: 46279 | R24: 46288 | S24: 46288 | AH24: =IF(J24="","",J24/3600) -> 1 | AI24: =IF(COUNTIF(AG24, "*dia*"), "VERDADEIRO", "FALSO") -> FALSO | AJ24: =IF(AI24="VERDADEIRO",LEFT(AG24,2),0) -> 0 | AK24: =IF(OR(A24="Solicitação de Serviço",A24="Incidente",P24="",Q24=""),"",IF((NETWORKDAYS.INTL(P24,Q24,1)-1)=0,1,NETWORKDAYS.INTL(P24,Q24,1)-1)) | AL24: =IF(X24="","",AK24=X24) | AM24: =IF(OR(A24="Solicitação de Serviço",A24="Incidente",R24="",S24=""),"",IF((NETWORKDAYS.INTL(R24,S24,1)-1)=0,1,NETWORKDAYS.INTL(R24,S24,1)-1-AJ24)) | AN24: =IF(Y24="","",AM24=Y24) | AO24: =IF(OR(A24="Solicitação de Serviço",A24="Incidente",T24="",U24=""),"",IF((NETWORKDAYS.INTL(T24,U24,1)-1)=0,1,NETWORKDAYS.INTL(T24,U24,1)-1)) | AP24: =IF(Z24="","",AO24=Z24) | AQ24: =IF(OR(A24="Solicitação de Serviço",A24="Incidente",V24="",W24=""),"",IF((NETWORKDAYS.INTL(V24,W24,1)-1)=0,1,IF((NETWORKDAYS.INTL(V24,W24,1)-1)<0,"",NETWORKDAYS.INTL(V24,W24,1)-1))) | AR24: =IF(AA24="","",AQ24=AA24) | AS24: =IF(OR(A24="Solicitação de Serviço",A24="Incidente",P24=""),"",IF(OR(A24="História",A24="Enabler",A24="Débito Técnico"),IF(W24="","",NETWORKDAYS.INTL(P24,W24,1)-1),IF(U24="","",NETWORKDAYS.INTL(P24,U24,1)-1))) | AT24: =IF(OR(A24="Solicitação de Serviço",A24="Incidente",A24="Sustentação"),"",IF(P24="","",IF(OR(A24="História",A24="Enabler",A24="Débito Técnico"),AS24=AC24,AS24=AB24))) | AU24: =IF(M24="","",M24)
A25: Incidente | B25: SGTB-2738 | C25: [SGTB] SP 26.4.1;[SGTB] SP 26.3.6 | D25: [Jornada Secretaria e Gestor de Unidades] Thunderbolts | E25: Aceito | F25: [SGTB] PI 3/26 | H25: [INC0819881]Tenho um Erro/Problema com o Sistema - Portal do Professor - Portal do Professor | J25: 7200 | L25: Itens concluídos | O25: Concluído | P25: 46283.824 | Q25: 46279 | R25: 46286 | S25: 46288 | AH25: =IF(J25="","",J25/3600) -> 2 | AI25: =IF(COUNTIF(AG25, "*dia*"), "VERDADEIRO", "FALSO") -> FALSO | AJ25: =IF(AI25="VERDADEIRO",LEFT(AG25,2),0) -> 0 | AK25: =IF(OR(A25="Solicitação de Serviço",A25="Incidente",P25="",Q25=""),"",IF((NETWORKDAYS.INTL(P25,Q25,1)-1)=0,1,NETWORKDAYS.INTL(P25,Q25,1)-1)) | AL25: =IF(X25="","",AK25=X25) | AM25: =IF(OR(A25="Solicitação de Serviço",A25="Incidente",R25="",S25=""),"",IF((NETWORKDAYS.INTL(R25,S25,1)-1)=0,1,NETWORKDAYS.INTL(R25,S25,1)-1-AJ25)) | AN25: =IF(Y25="","",AM25=Y25) | AO25: =IF(OR(A25="Solicitação de Serviço",A25="Incidente",T25="",U25=""),"",IF((NETWORKDAYS.INTL(T25,U25,1)-1)=0,1,NETWORKDAYS.INTL(T25,U25,1)-1)) | AP25: =IF(Z25="","",AO25=Z25) | AQ25: =IF(OR(A25="Solicitação de Serviço",A25="Incidente",V25="",W25=""),"",IF((NETWORKDAYS.INTL(V25,W25,1)-1)=0,1,IF((NETWORKDAYS.INTL(V25,W25,1)-1)<0,"",NETWORKDAYS.INTL(V25,W25,1)-1))) | AR25: =IF(AA25="","",AQ25=AA25) | AS25: =IF(OR(A25="Solicitação de Serviço",A25="Incidente",P25=""),"",IF(OR(A25="História",A25="Enabler",A25="Débito Técnico"),IF(W25="","",NETWORKDAYS.INTL(P25,W25,1)-1),IF(U25="","",NETWORKDAYS.INTL(P25,U25,1)-1))) | AT25: =IF(OR(A25="Solicitação de Serviço",A25="Incidente",A25="Sustentação"),"",IF(P25="","",IF(OR(A25="História",A25="Enabler",A25="Débito Técnico"),AS25=AC25,AS25=AB25))) | AU25: =IF(M25="","",M25)
A26: Incidente | B26: SGTB-2737 | C26: [SGTB] SP 26.3.6 | D26: [Jornada Secretaria e Gestor de Unidades] Thunderbolts | E26: Aceito | F26: [SGTB] PI 3/26 | H26: [INC0819751]Tenho um Erro/Problema com o Sistema - Olimpo - Matrícula | J26: 900 | L26: Itens concluídos | O26: Concluído | P26: 46283.667 | Q26: 46279 | R26: 46286 | S26: 46286 | AH26: =IF(J26="","",J26/3600) -> 0.25 | AI26: =IF(COUNTIF(AG26, "*dia*"), "VERDADEIRO", "FALSO") -> FALSO | AJ26: =IF(AI26="VERDADEIRO",LEFT(AG26,2),0) -> 0 | AK26: =IF(OR(A26="Solicitação de Serviço",A26="Incidente",P26="",Q26=""),"",IF((NETWORKDAYS.INTL(P26,Q26,1)-1)=0,1,NETWORKDAYS.INTL(P26,Q26,1)-1)) | AL26: =IF(X26="","",AK26=X26) | AM26: =IF(OR(A26="Solicitação de Serviço",A26="Incidente",R26="",S26=""),"",IF((NETWORKDAYS.INTL(R26,S26,1)-1)=0,1,NETWORKDAYS.INTL(R26,S26,1)-1-AJ26)) | AN26: =IF(Y26="","",AM26=Y26) | AO26: =IF(OR(A26="Solicitação de Serviço",A26="Incidente",T26="",U26=""),"",IF((NETWORKDAYS.INTL(T26,U26,1)-1)=0,1,NETWORKDAYS.INTL(T26,U26,1)-1)) | AP26: =IF(Z26="","",AO26=Z26) | AQ26: =IF(OR(A26="Solicitação de Serviço",A26="Incidente",V26="",W26=""),"",IF((NETWORKDAYS.INTL(V26,W26,1)-1)=0,1,IF((NETWORKDAYS.INTL(V26,W26,1)-1)<0,"",NETWORKDAYS.INTL(V26,W26,1)-1))) | AR26: =IF(AA26="","",AQ26=AA26) | AS26: =IF(OR(A26="Solicitação de Serviço",A26="Incidente",P26=""),"",IF(OR(A26="História",A26="Enabler",A26="Débito Técnico"),IF(W26="","",NETWORKDAYS.INTL(P26,W26,1)-1),IF(U26="","",NETWORKDAYS.INTL(P26,U26,1)-1))) | AT26: =IF(OR(A26="Solicitação de Serviço",A26="Incidente",A26="Sustentação"),"",IF(P26="","",IF(OR(A26="História",A26="Enabler",A26="Débito Técnico"),AS26=AC26,AS26=AB26))) | AU26: =IF(M26="","",M26)
A27: Incidente | B27: SGTB-2736 | C27: [SGTB] SP 26.4.1;[SGTB] SP 26.3.6 | D27: [Jornada Secretaria e Gestor de Unidades] Thunderbolts | E27: Aceito | F27: [SGTB] PI 3/26 | H27: [INC0819294]Tenho um Erro/Problema com o Sistema - AVA (LMS) - AVA (LMS) | J27: 25200 | L27: Itens concluídos | O27: Concluído | P27: 46283.661 | Q27: 46279 | R27: 46288 | S27: 46288 | AH27: =IF(J27="","",J27/3600) -> 7 | AI27: =IF(COUNTIF(AG27, "*dia*"), "VERDADEIRO", "FALSO") -> FALSO | AJ27: =IF(AI27="VERDADEIRO",LEFT(AG27,2),0) -> 0 | AK27: =IF(OR(A27="Solicitação de Serviço",A27="Incidente",P27="",Q27=""),"",IF((NETWORKDAYS.INTL(P27,Q27,1)-1)=0,1,NETWORKDAYS.INTL(P27,Q27,1)-1)) | AL27: =IF(X27="","",AK27=X27) | AM27: =IF(OR(A27="Solicitação de Serviço",A27="Incidente",R27="",S27=""),"",IF((NETWORKDAYS.INTL(R27,S27,1)-1)=0,1,NETWORKDAYS.INTL(R27,S27,1)-1-AJ27)) | AN27: =IF(Y27="","",AM27=Y27) | AO27: =IF(OR(A27="Solicitação de Serviço",A27="Incidente",T27="",U27=""),"",IF((NETWORKDAYS.INTL(T27,U27,1)-1)=0,1,NETWORKDAYS.INTL(T27,U27,1)-1)) | AP27: =IF(Z27="","",AO27=Z27) | AQ27: =IF(OR(A27="Solicitação de Serviço",A27="Incidente",V27="",W27=""),"",IF((NETWORKDAYS.INTL(V27,W27,1)-1)=0,1,IF((NETWORKDAYS.INTL(V27,W27,1)-1)<0,"",NETWORKDAYS.INTL(V27,W27,1)-1))) | AR27: =IF(AA27="","",AQ27=AA27) | AS27: =IF(OR(A27="Solicitação de Serviço",A27="Incidente",P27=""),"",IF(OR(A27="História",A27="Enabler",A27="Débito Técnico"),IF(W27="","",NETWORKDAYS.INTL(P27,W27,1)-1),IF(U27="","",NETWORKDAYS.INTL(P27,U27,1)-1))) | AT27: =IF(OR(A27="Solicitação de Serviço",A27="Incidente",A27="Sustentação"),"",IF(P27="","",IF(OR(A27="História",A27="Enabler",A27="Débito Técnico"),AS27=AC27,AS27=AB27))) | AU27: =IF(M27="","",M27)
A28: Incidente | B28: SGTB-2733 | C28: [SGTB] SP 26.3.6 | D28: [Jornada Secretaria e Gestor de Unidades] Thunderbolts | E28: Aceito | F28: [SGTB] PI 3/26 | H28: [INC0819155]Tenho um Erro/Problema com o Sistema - Portal Prisma - Prisma | J28: 1800 | L28: Itens concluídos | O28: Abertura indevida | P28: 46283.594 | Q28: 46279 | R28: 46286 | AH28: =IF(J28="","",J28/3600) -> 0.5 | AI28: =IF(COUNTIF(AG28, "*dia*"), "VERDADEIRO", "FALSO") -> FALSO | AJ28: =IF(AI28="VERDADEIRO",LEFT(AG28,2),0) -> 0 | AK28: =IF(OR(A28="Solicitação de Serviço",A28="Incidente",P28="",Q28=""),"",IF((NETWORKDAYS.INTL(P28,Q28,1)-1)=0,1,NETWORKDAYS.INTL(P28,Q28,1)-1)) | AL28: =IF(X28="","",AK28=X28) | AM28: =IF(OR(A28="Solicitação de Serviço",A28="Incidente",R28="",S28=""),"",IF((NETWORKDAYS.INTL(R28,S28,1)-1)=0,1,NETWORKDAYS.INTL(R28,S28,1)-1-AJ28)) | AN28: =IF(Y28="","",AM28=Y28) | AO28: =IF(OR(A28="Solicitação de Serviço",A28="Incidente",T28="",U28=""),"",IF((NETWORKDAYS.INTL(T28,U28,1)-1)=0,1,NETWORKDAYS.INTL(T28,U28,1)-1)) | AP28: =IF(Z28="","",AO28=Z28) | AQ28: =IF(OR(A28="Solicitação de Serviço",A28="Incidente",V28="",W28=""),"",IF((NETWORKDAYS.INTL(V28,W28,1)-1)=0,1,IF((NETWORKDAYS.INTL(V28,W28,1)-1)<0,"",NETWORKDAYS.INTL(V28,W28,1)-1))) | AR28: =IF(AA28="","",AQ28=AA28) | AS28: =IF(OR(A28="Solicitação de Serviço",A28="Incidente",P28=""),"",IF(OR(A28="História",A28="Enabler",A28="Débito Técnico"),IF(W28="","",NETWORKDAYS.INTL(P28,W28,1)-1),IF(U28="","",NETWORKDAYS.INTL(P28,U28,1)-1))) | AT28: =IF(OR(A28="Solicitação de Serviço",A28="Incidente",A28="Sustentação"),"",IF(P28="","",IF(OR(A28="História",A28="Enabler",A28="Débito Técnico"),AS28=AC28,AS28=AB28))) | AU28: =IF(M28="","",M28)
A29: Solicitação de Serviço | B29: SGTB-2732 | C29: [SGTB] SP 26.4.1;[SGTB] SP 26.3.6 | D29: [Jornada Secretaria e Gestor de Unidades] Thunderbolts | E29: Aceito | F29: [SGTB] PI 3/26 | H29: [RITM0744746]Solicitar Serviço ao Sistema - Olimpo - Matrícula | J29: 3600 | L29: Itens concluídos | O29: Concluído | P29: 46283.592 | Q29: 46279 | R29: 46290 | S29: 46290 | AH29: =IF(J29="","",J29/3600) -> 1 | AI29: =IF(COUNTIF(AG29, "*dia*"), "VERDADEIRO", "FALSO") -> FALSO | AJ29: =IF(AI29="VERDADEIRO",LEFT(AG29,2),0) -> 0 | AK29: =IF(OR(A29="Solicitação de Serviço",A29="Incidente",P29="",Q29=""),"",IF((NETWORKDAYS.INTL(P29,Q29,1)-1)=0,1,NETWORKDAYS.INTL(P29,Q29,1)-1)) | AL29: =IF(X29="","",AK29=X29) | AM29: =IF(OR(A29="Solicitação de Serviço",A29="Incidente",R29="",S29=""),"",IF((NETWORKDAYS.INTL(R29,S29,1)-1)=0,1,NETWORKDAYS.INTL(R29,S29,1)-1-AJ29)) | AN29: =IF(Y29="","",AM29=Y29) | AO29: =IF(OR(A29="Solicitação de Serviço",A29="Incidente",T29="",U29=""),"",IF((NETWORKDAYS.INTL(T29,U29,1)-1)=0,1,NETWORKDAYS.INTL(T29,U29,1)-1)) | AP29: =IF(Z29="","",AO29=Z29) | AQ29: =IF(OR(A29="Solicitação de Serviço",A29="Incidente",V29="",W29=""),"",IF((NETWORKDAYS.INTL(V29,W29,1)-1)=0,1,IF((NETWORKDAYS.INTL(V29,W29,1)-1)<0,"",NETWORKDAYS.INTL(V29,W29,1)-1))) | AR29: =IF(AA29="","",AQ29=AA29) | AS29: =IF(OR(A29="Solicitação de Serviço",A29="Incidente",P29=""),"",IF(OR(A29="História",A29="Enabler",A29="Débito Técnico"),IF(W29="","",NETWORKDAYS.INTL(P29,W29,1)-1),IF(U29="","",NETWORKDAYS.INTL(P29,U29,1)-1))) | AT29: =IF(OR(A29="Solicitação de Serviço",A29="Incidente",A29="Sustentação"),"",IF(P29="","",IF(OR(A29="História",A29="Enabler",A29="Débito Técnico"),AS29=AC29,AS29=AB29))) | AU29: =IF(M29="","",M29)
A30: Incidente | B30: SGTB-2731 | C30: [SGTB] SP 26.3.6 | D30: [Jornada Secretaria e Gestor de Unidades] Thunderbolts | E30: Aceito | F30: [SGTB] PI 3/26 | H30: [INC0819652]Tenho um Erro/Problema com o Sistema - Portal do Professor - Portal do Professor | L30: Itens concluídos | O30: Abertura indevida | P30: 46283.492 | Q30: 46279 | R30: 46283 | AH30: =IF(J30="","",J30/3600) | AI30: =IF(COUNTIF(AG30, "*dia*"), "VERDADEIRO", "FALSO") -> FALSO | AJ30: =IF(AI30="VERDADEIRO",LEFT(AG30,2),0) -> 0 | AK30: =IF(OR(A30="Solicitação de Serviço",A30="Incidente",P30="",Q30=""),"",IF((NETWORKDAYS.INTL(P30,Q30,1)-1)=0,1,NETWORKDAYS.INTL(P30,Q30,1)-1)) | AL30: =IF(X30="","",AK30=X30) | AM30: =IF(OR(A30="Solicitação de Serviço",A30="Incidente",R30="",S30=""),"",IF((NETWORKDAYS.INTL(R30,S30,1)-1)=0,1,NETWORKDAYS.INTL(R30,S30,1)-1-AJ30)) | AN30: =IF(Y30="","",AM30=Y30) | AO30: =IF(OR(A30="Solicitação de Serviço",A30="Incidente",T30="",U30=""),"",IF((NETWORKDAYS.INTL(T30,U30,1)-1)=0,1,NETWORKDAYS.INTL(T30,U30,1)-1)) | AP30: =IF(Z30="","",AO30=Z30) | AQ30: =IF(OR(A30="Solicitação de Serviço",A30="Incidente",V30="",W30=""),"",IF((NETWORKDAYS.INTL(V30,W30,1)-1)=0,1,IF((NETWORKDAYS.INTL(V30,W30,1)-1)<0,"",NETWORKDAYS.INTL(V30,W30,1)-1))) | AR30: =IF(AA30="","",AQ30=AA30) | AS30: =IF(OR(A30="Solicitação de Serviço",A30="Incidente",P30=""),"",IF(OR(A30="História",A30="Enabler",A30="Débito Técnico"),IF(W30="","",NETWORKDAYS.INTL(P30,W30,1)-1),IF(U30="","",NETWORKDAYS.INTL(P30,U30,1)-1))) | AT30: =IF(OR(A30="Solicitação de Serviço",A30="Incidente",A30="Sustentação"),"",IF(P30="","",IF(OR(A30="História",A30="Enabler",A30="Débito Técnico"),AS30=AC30,AS30=AB30))) | AU30: =IF(M30="","",M30)
A31: Incidente | B31: SGTB-2730 | C31: [SGTB] SP 26.4.1;[SGTB] SP 26.3.6 | D31: [Jornada Secretaria e Gestor de Unidades] Thunderbolts | E31: Aceito | F31: [SGTB] PI 3/26 | H31: [INC0819637]Tenho um Erro/Problema com o Sistema - Portal Prisma - Prisma - Usuários do Prisma | J31: 7200 | L31: Itens concluídos | O31: Concluído | P31: 46283.474 | Q31: 46279 | R31: 46286 | S31: 46287 | AH31: =IF(J31="","",J31/3600) -> 2 | AI31: =IF(COUNTIF(AG31, "*dia*"), "VERDADEIRO", "FALSO") -> FALSO | AJ31: =IF(AI31="VERDADEIRO",LEFT(AG31,2),0) -> 0 | AK31: =IF(OR(A31="Solicitação de Serviço",A31="Incidente",P31="",Q31=""),"",IF((NETWORKDAYS.INTL(P31,Q31,1)-1)=0,1,NETWORKDAYS.INTL(P31,Q31,1)-1)) | AL31: =IF(X31="","",AK31=X31) | AM31: =IF(OR(A31="Solicitação de Serviço",A31="Incidente",R31="",S31=""),"",IF((NETWORKDAYS.INTL(R31,S31,1)-1)=0,1,NETWORKDAYS.INTL(R31,S31,1)-1-AJ31)) | AN31: =IF(Y31="","",AM31=Y31) | AO31: =IF(OR(A31="Solicitação de Serviço",A31="Incidente",T31="",U31=""),"",IF((NETWORKDAYS.INTL(T31,U31,1)-1)=0,1,NETWORKDAYS.INTL(T31,U31,1)-1)) | AP31: =IF(Z31="","",AO31=Z31) | AQ31: =IF(OR(A31="Solicitação de Serviço",A31="Incidente",V31="",W31=""),"",IF((NETWORKDAYS.INTL(V31,W31,1)-1)=0,1,IF((NETWORKDAYS.INTL(V31,W31,1)-1)<0,"",NETWORKDAYS.INTL(V31,W31,1)-1))) | AR31: =IF(AA31="","",AQ31=AA31) | AS31: =IF(OR(A31="Solicitação de Serviço",A31="Incidente",P31=""),"",IF(OR(A31="História",A31="Enabler",A31="Débito Técnico"),IF(W31="","",NETWORKDAYS.INTL(P31,W31,1)-1),IF(U31="","",NETWORKDAYS.INTL(P31,U31,1)-1))) | AT31: =IF(OR(A31="Solicitação de Serviço",A31="Incidente",A31="Sustentação"),"",IF(P31="","",IF(OR(A31="História",A31="Enabler",A31="Débito Técnico"),AS31=AC31,AS31=AB31))) | AU31: =IF(M31="","",M31)
A32: Incidente | B32: SGTB-2726 | C32: [SGTB] SP 26.3.6 | D32: [Jornada Secretaria e Gestor de Unidades] Thunderbolts | E32: Aceito | F32: [SGTB] PI 3/26 | H32: [INC0818587]Tenho um Erro/Problema com o Sistema - AVA Presencial/Moodle - Extrato de pontos e notas | L32: Itens concluídos | O32: Abertura indevida | P32: 46282.442 | Q32: 46279 | R32: 46282 | AH32: =IF(J32="","",J32/3600) | AI32: =IF(COUNTIF(AG32, "*dia*"), "VERDADEIRO", "FALSO") -> FALSO | AJ32: =IF(AI32="VERDADEIRO",LEFT(AG32,2),0) -> 0 | AK32: =IF(OR(A32="Solicitação de Serviço",A32="Incidente",P32="",Q32=""),"",IF((NETWORKDAYS.INTL(P32,Q32,1)-1)=0,1,NETWORKDAYS.INTL(P32,Q32,1)-1)) | AL32: =IF(X32="","",AK32=X32) | AM32: =IF(OR(A32="Solicitação de Serviço",A32="Incidente",R32="",S32=""),"",IF((NETWORKDAYS.INTL(R32,S32,1)-1)=0,1,NETWORKDAYS.INTL(R32,S32,1)-1-AJ32)) | AN32: =IF(Y32="","",AM32=Y32) | AO32: =IF(OR(A32="Solicitação de Serviço",A32="Incidente",T32="",U32=""),"",IF((NETWORKDAYS.INTL(T32,U32,1)-1)=0,1,NETWORKDAYS.INTL(T32,U32,1)-1)) | AP32: =IF(Z32="","",AO32=Z32) | AQ32: =IF(OR(A32="Solicitação de Serviço",A32="Incidente",V32="",W32=""),"",IF((NETWORKDAYS.INTL(V32,W32,1)-1)=0,1,IF((NETWORKDAYS.INTL(V32,W32,1)-1)<0,"",NETWORKDAYS.INTL(V32,W32,1)-1))) | AR32: =IF(AA32="","",AQ32=AA32) | AS32: =IF(OR(A32="Solicitação de Serviço",A32="Incidente",P32=""),"",IF(OR(A32="História",A32="Enabler",A32="Débito Técnico"),IF(W32="","",NETWORKDAYS.INTL(P32,W32,1)-1),IF(U32="","",NETWORKDAYS.INTL(P32,U32,1)-1))) | AT32: =IF(OR(A32="Solicitação de Serviço",A32="Incidente",A32="Sustentação"),"",IF(P32="","",IF(OR(A32="História",A32="Enabler",A32="Débito Técnico"),AS32=AC32,AS32=AB32))) | AU32: =IF(M32="","",M32)
A33: Solicitação de Serviço | B33: SGTB-2725 | C33: [SGTB] SP 26.4.1;[SGTB] SP 26.3.6 | D33: [Jornada Secretaria e Gestor de Unidades] Thunderbolts | E33: Aceito | F33: [SGTB] PI 3/26 | H33: [RITM0740591]Solicitar Serviço ao Sistema - Olimpo - (Olimpo) Contrato | J33: 1800 | L33: Itens concluídos | O33: Concluído | P33: 46282.44 | Q33: 46279 | R33: 46290 | S33: 46290 | AH33: =IF(J33="","",J33/3600) -> 0.5 | AI33: =IF(COUNTIF(AG33, "*dia*"), "VERDADEIRO", "FALSO") -> FALSO | AJ33: =IF(AI33="VERDADEIRO",LEFT(AG33,2),0) -> 0 | AK33: =IF(OR(A33="Solicitação de Serviço",A33="Incidente",P33="",Q33=""),"",IF((NETWORKDAYS.INTL(P33,Q33,1)-1)=0,1,NETWORKDAYS.INTL(P33,Q33,1)-1)) | AL33: =IF(X33="","",AK33=X33) | AM33: =IF(OR(A33="Solicitação de Serviço",A33="Incidente",R33="",S33=""),"",IF((NETWORKDAYS.INTL(R33,S33,1)-1)=0,1,NETWORKDAYS.INTL(R33,S33,1)-1-AJ33)) | AN33: =IF(Y33="","",AM33=Y33) | AO33: =IF(OR(A33="Solicitação de Serviço",A33="Incidente",T33="",U33=""),"",IF((NETWORKDAYS.INTL(T33,U33,1)-1)=0,1,NETWORKDAYS.INTL(T33,U33,1)-1)) | AP33: =IF(Z33="","",AO33=Z33) | AQ33: =IF(OR(A33="Solicitação de Serviço",A33="Incidente",V33="",W33=""),"",IF((NETWORKDAYS.INTL(V33,W33,1)-1)=0,1,IF((NETWORKDAYS.INTL(V33,W33,1)-1)<0,"",NETWORKDAYS.INTL(V33,W33,1)-1))) | AR33: =IF(AA33="","",AQ33=AA33) | AS33: =IF(OR(A33="Solicitação de Serviço",A33="Incidente",P33=""),"",IF(OR(A33="História",A33="Enabler",A33="Débito Técnico"),IF(W33="","",NETWORKDAYS.INTL(P33,W33,1)-1),IF(U33="","",NETWORKDAYS.INTL(P33,U33,1)-1))) | AT33: =IF(OR(A33="Solicitação de Serviço",A33="Incidente",A33="Sustentação"),"",IF(P33="","",IF(OR(A33="História",A33="Enabler",A33="Débito Técnico"),AS33=AC33,AS33=AB33))) | AU33: =IF(M33="","",M33)
A34: Solicitação de Serviço | B34: SGTB-2723 | C34: [SGTB] SP 26.4.1;[SGTB] SP 26.3.6 | D34: [Jornada Secretaria e Gestor de Unidades] Thunderbolts | E34: Aceito | F34: [SGTB] PI 3/26 | H34: [RITM0744482]Solicitar Serviço ao Sistema - Olimpo - Enturmacao - krotonEnturmacao | J34: 1800 | L34: Itens concluídos | O34: Concluído | P34: 46282.44 | Q34: 46279 | R34: 46290 | S34: 46290 | AH34: =IF(J34="","",J34/3600) -> 0.5 | AI34: =IF(COUNTIF(AG34, "*dia*"), "VERDADEIRO", "FALSO") -> FALSO | AJ34: =IF(AI34="VERDADEIRO",LEFT(AG34,2),0) -> 0 | AK34: =IF(OR(A34="Solicitação de Serviço",A34="Incidente",P34="",Q34=""),"",IF((NETWORKDAYS.INTL(P34,Q34,1)-1)=0,1,NETWORKDAYS.INTL(P34,Q34,1)-1)) | AL34: =IF(X34="","",AK34=X34) | AM34: =IF(OR(A34="Solicitação de Serviço",A34="Incidente",R34="",S34=""),"",IF((NETWORKDAYS.INTL(R34,S34,1)-1)=0,1,NETWORKDAYS.INTL(R34,S34,1)-1-AJ34)) | AN34: =IF(Y34="","",AM34=Y34) | AO34: =IF(OR(A34="Solicitação de Serviço",A34="Incidente",T34="",U34=""),"",IF((NETWORKDAYS.INTL(T34,U34,1)-1)=0,1,NETWORKDAYS.INTL(T34,U34,1)-1)) | AP34: =IF(Z34="","",AO34=Z34) | AQ34: =IF(OR(A34="Solicitação de Serviço",A34="Incidente",V34="",W34=""),"",IF((NETWORKDAYS.INTL(V34,W34,1)-1)=0,1,IF((NETWORKDAYS.INTL(V34,W34,1)-1)<0,"",NETWORKDAYS.INTL(V34,W34,1)-1))) | AR34: =IF(AA34="","",AQ34=AA34) | AS34: =IF(OR(A34="Solicitação de Serviço",A34="Incidente",P34=""),"",IF(OR(A34="História",A34="Enabler",A34="Débito Técnico"),IF(W34="","",NETWORKDAYS.INTL(P34,W34,1)-1),IF(U34="","",NETWORKDAYS.INTL(P34,U34,1)-1))) | AT34: =IF(OR(A34="Solicitação de Serviço",A34="Incidente",A34="Sustentação"),"",IF(P34="","",IF(OR(A34="História",A34="Enabler",A34="Débito Técnico"),AS34=AC34,AS34=AB34))) | AU34: =IF(M34="","",M34)
A35: Incidente | B35: SGTB-2720 | C35: [SGTB] SP 26.3.6 | D35: [Jornada Secretaria e Gestor de Unidades] Thunderbolts | E35: Aceito | F35: [SGTB] PI 3/26 | H35: [INC0818148]Tenho um Erro/Problema com o Sistema - AVA Presencial/Moodle - Acesso ao AVA/Disciplina | J35: 7200 | L35: Itens concluídos | O35: Concluído | P35: 46282.415 | Q35: 46279 | R35: 46282 | S35: 46283 | AH35: =IF(J35="","",J35/3600) -> 2 | AI35: =IF(COUNTIF(AG35, "*dia*"), "VERDADEIRO", "FALSO") -> FALSO | AJ35: =IF(AI35="VERDADEIRO",LEFT(AG35,2),0) -> 0 | AK35: =IF(OR(A35="Solicitação de Serviço",A35="Incidente",P35="",Q35=""),"",IF((NETWORKDAYS.INTL(P35,Q35,1)-1)=0,1,NETWORKDAYS.INTL(P35,Q35,1)-1)) | AL35: =IF(X35="","",AK35=X35) | AM35: =IF(OR(A35="Solicitação de Serviço",A35="Incidente",R35="",S35=""),"",IF((NETWORKDAYS.INTL(R35,S35,1)-1)=0,1,NETWORKDAYS.INTL(R35,S35,1)-1-AJ35)) | AN35: =IF(Y35="","",AM35=Y35) | AO35: =IF(OR(A35="Solicitação de Serviço",A35="Incidente",T35="",U35=""),"",IF((NETWORKDAYS.INTL(T35,U35,1)-1)=0,1,NETWORKDAYS.INTL(T35,U35,1)-1)) | AP35: =IF(Z35="","",AO35=Z35) | AQ35: =IF(OR(A35="Solicitação de Serviço",A35="Incidente",V35="",W35=""),"",IF((NETWORKDAYS.INTL(V35,W35,1)-1)=0,1,IF((NETWORKDAYS.INTL(V35,W35,1)-1)<0,"",NETWORKDAYS.INTL(V35,W35,1)-1))) | AR35: =IF(AA35="","",AQ35=AA35) | AS35: =IF(OR(A35="Solicitação de Serviço",A35="Incidente",P35=""),"",IF(OR(A35="História",A35="Enabler",A35="Débito Técnico"),IF(W35="","",NETWORKDAYS.INTL(P35,W35,1)-1),IF(U35="","",NETWORKDAYS.INTL(P35,U35,1)-1))) | AT35: =IF(OR(A35="Solicitação de Serviço",A35="Incidente",A35="Sustentação"),"",IF(P35="","",IF(OR(A35="História",A35="Enabler",A35="Débito Técnico"),AS35=AC35,AS35=AB35))) | AU35: =IF(M35="","",M35)
A36: Solicitação de Serviço | B36: SGTB-2715 | C36: [SGTB] SP 26.3.6 | D36: [Jornada Secretaria e Gestor de Unidades] Thunderbolts | E36: Aceito | F36: [SGTB] PI 3/26 | H36: [RITM0743304]Solicitar Serviço ao Sistema - Olimpo - (Olimpo) Contrato | J36: 3600 | L36: Itens concluídos | O36: Concluído | P36: 46281.912 | Q36: 46279 | R36: 46282 | S36: 46282 | AH36: =IF(J36="","",J36/3600) -> 1 | AI36: =IF(COUNTIF(AG36, "*dia*"), "VERDADEIRO", "FALSO") -> FALSO | AJ36: =IF(AI36="VERDADEIRO",LEFT(AG36,2),0) -> 0 | AK36: =IF(OR(A36="Solicitação de Serviço",A36="Incidente",P36="",Q36=""),"",IF((NETWORKDAYS.INTL(P36,Q36,1)-1)=0,1,NETWORKDAYS.INTL(P36,Q36,1)-1)) | AL36: =IF(X36="","",AK36=X36) | AM36: =IF(OR(A36="Solicitação de Serviço",A36="Incidente",R36="",S36=""),"",IF((NETWORKDAYS.INTL(R36,S36,1)-1)=0,1,NETWORKDAYS.INTL(R36,S36,1)-1-AJ36)) | AN36: =IF(Y36="","",AM36=Y36) | AO36: =IF(OR(A36="Solicitação de Serviço",A36="Incidente",T36="",U36=""),"",IF((NETWORKDAYS.INTL(T36,U36,1)-1)=0,1,NETWORKDAYS.INTL(T36,U36,1)-1)) | AP36: =IF(Z36="","",AO36=Z36) | AQ36: =IF(OR(A36="Solicitação de Serviço",A36="Incidente",V36="",W36=""),"",IF((NETWORKDAYS.INTL(V36,W36,1)-1)=0,1,IF((NETWORKDAYS.INTL(V36,W36,1)-1)<0,"",NETWORKDAYS.INTL(V36,W36,1)-1))) | AR36: =IF(AA36="","",AQ36=AA36) | AS36: =IF(OR(A36="Solicitação de Serviço",A36="Incidente",P36=""),"",IF(OR(A36="História",A36="Enabler",A36="Débito Técnico"),IF(W36="","",NETWORKDAYS.INTL(P36,W36,1)-1),IF(U36="","",NETWORKDAYS.INTL(P36,U36,1)-1))) | AT36: =IF(OR(A36="Solicitação de Serviço",A36="Incidente",A36="Sustentação"),"",IF(P36="","",IF(OR(A36="História",A36="Enabler",A36="Débito Técnico"),AS36=AC36,AS36=AB36))) | AU36: =IF(M36="","",M36)
A37: Incidente | B37: SGTB-2714 | C37: [SGTB] SP 26.3.6 | D37: [Jornada Secretaria e Gestor de Unidades] Thunderbolts | E37: Aceito | F37: [SGTB] PI 3/26 | H37: [INC0818837]Tenho um Erro/Problema com o Sistema - Portal Prisma - Prisma - Cadastro de Comunicados / Banner | J37: 25200 | L37: Itens concluídos | O37: Concluído | P37: 46281.728 | Q37: 46279 | R37: 46282 | S37: 46282 | AH37: =IF(J37="","",J37/3600) -> 7 | AI37: =IF(COUNTIF(AG37, "*dia*"), "VERDADEIRO", "FALSO") -> FALSO | AJ37: =IF(AI37="VERDADEIRO",LEFT(AG37,2),0) -> 0 | AK37: =IF(OR(A37="Solicitação de Serviço",A37="Incidente",P37="",Q37=""),"",IF((NETWORKDAYS.INTL(P37,Q37,1)-1)=0,1,NETWORKDAYS.INTL(P37,Q37,1)-1)) | AL37: =IF(X37="","",AK37=X37) | AM37: =IF(OR(A37="Solicitação de Serviço",A37="Incidente",R37="",S37=""),"",IF((NETWORKDAYS.INTL(R37,S37,1)-1)=0,1,NETWORKDAYS.INTL(R37,S37,1)-1-AJ37)) | AN37: =IF(Y37="","",AM37=Y37) | AO37: =IF(OR(A37="Solicitação de Serviço",A37="Incidente",T37="",U37=""),"",IF((NETWORKDAYS.INTL(T37,U37,1)-1)=0,1,NETWORKDAYS.INTL(T37,U37,1)-1)) | AP37: =IF(Z37="","",AO37=Z37) | AQ37: =IF(OR(A37="Solicitação de Serviço",A37="Incidente",V37="",W37=""),"",IF((NETWORKDAYS.INTL(V37,W37,1)-1)=0,1,IF((NETWORKDAYS.INTL(V37,W37,1)-1)<0,"",NETWORKDAYS.INTL(V37,W37,1)-1))) | AR37: =IF(AA37="","",AQ37=AA37) | AS37: =IF(OR(A37="Solicitação de Serviço",A37="Incidente",P37=""),"",IF(OR(A37="História",A37="Enabler",A37="Débito Técnico"),IF(W37="","",NETWORKDAYS.INTL(P37,W37,1)-1),IF(U37="","",NETWORKDAYS.INTL(P37,U37,1)-1))) | AT37: =IF(OR(A37="Solicitação de Serviço",A37="Incidente",A37="Sustentação"),"",IF(P37="","",IF(OR(A37="História",A37="Enabler",A37="Débito Técnico"),AS37=AC37,AS37=AB37))) | AU37: =IF(M37="","",M37)
A38: Solicitação de Serviço | B38: SGTB-2706 | C38: [SGTB] SP 26.3.6 | D38: [Jornada Secretaria e Gestor de Unidades] Thunderbolts | E38: Aceito | F38: [SGTB] PI 3/26 | H38: [RITM0744294]Solicitar Serviço ao Sistema - Portal do Professor - Portal do Professor | J38: 3600 | L38: Itens concluídos | O38: Concluído | P38: 46281.524 | Q38: 46279 | R38: 46282 | S38: 46282 | AH38: =IF(J38="","",J38/3600) -> 1 | AI38: =IF(COUNTIF(AG38, "*dia*"), "VERDADEIRO", "FALSO") -> FALSO | AJ38: =IF(AI38="VERDADEIRO",LEFT(AG38,2),0) -> 0 | AK38: =IF(OR(A38="Solicitação de Serviço",A38="Incidente",P38="",Q38=""),"",IF((NETWORKDAYS.INTL(P38,Q38,1)-1)=0,1,NETWORKDAYS.INTL(P38,Q38,1)-1)) | AL38: =IF(X38="","",AK38=X38) | AM38: =IF(OR(A38="Solicitação de Serviço",A38="Incidente",R38="",S38=""),"",IF((NETWORKDAYS.INTL(R38,S38,1)-1)=0,1,NETWORKDAYS.INTL(R38,S38,1)-1-AJ38)) | AN38: =IF(Y38="","",AM38=Y38) | AO38: =IF(OR(A38="Solicitação de Serviço",A38="Incidente",T38="",U38=""),"",IF((NETWORKDAYS.INTL(T38,U38,1)-1)=0,1,NETWORKDAYS.INTL(T38,U38,1)-1)) | AP38: =IF(Z38="","",AO38=Z38) | AQ38: =IF(OR(A38="Solicitação de Serviço",A38="Incidente",V38="",W38=""),"",IF((NETWORKDAYS.INTL(V38,W38,1)-1)=0,1,IF((NETWORKDAYS.INTL(V38,W38,1)-1)<0,"",NETWORKDAYS.INTL(V38,W38,1)-1))) | AR38: =IF(AA38="","",AQ38=AA38) | AS38: =IF(OR(A38="Solicitação de Serviço",A38="Incidente",P38=""),"",IF(OR(A38="História",A38="Enabler",A38="Débito Técnico"),IF(W38="","",NETWORKDAYS.INTL(P38,W38,1)-1),IF(U38="","",NETWORKDAYS.INTL(P38,U38,1)-1))) | AT38: =IF(OR(A38="Solicitação de Serviço",A38="Incidente",A38="Sustentação"),"",IF(P38="","",IF(OR(A38="História",A38="Enabler",A38="Débito Técnico"),AS38=AC38,AS38=AB38))) | AU38: =IF(M38="","",M38)
A39: Incidente | B39: SGTB-2705 | C39: [SGTB] SP 26.3.6 | D39: [Jornada Secretaria e Gestor de Unidades] Thunderbolts | E39: Aceito | F39: [SGTB] PI 3/26 | H39: [INC0818637]Tenho um Erro/Problema com o Sistema - Portal Prisma - Prisma | J39: 900 | L39: Itens concluídos | O39: Concluído | P39: 46281.515 | Q39: 46279 | R39: 46283 | S39: 46283 | AH39: =IF(J39="","",J39/3600) -> 0.25 | AI39: =IF(COUNTIF(AG39, "*dia*"), "VERDADEIRO", "FALSO") -> FALSO | AJ39: =IF(AI39="VERDADEIRO",LEFT(AG39,2),0) -> 0 | AK39: =IF(OR(A39="Solicitação de Serviço",A39="Incidente",P39="",Q39=""),"",IF((NETWORKDAYS.INTL(P39,Q39,1)-1)=0,1,NETWORKDAYS.INTL(P39,Q39,1)-1)) | AL39: =IF(X39="","",AK39=X39) | AM39: =IF(OR(A39="Solicitação de Serviço",A39="Incidente",R39="",S39=""),"",IF((NETWORKDAYS.INTL(R39,S39,1)-1)=0,1,NETWORKDAYS.INTL(R39,S39,1)-1-AJ39)) | AN39: =IF(Y39="","",AM39=Y39) | AO39: =IF(OR(A39="Solicitação de Serviço",A39="Incidente",T39="",U39=""),"",IF((NETWORKDAYS.INTL(T39,U39,1)-1)=0,1,NETWORKDAYS.INTL(T39,U39,1)-1)) | AP39: =IF(Z39="","",AO39=Z39) | AQ39: =IF(OR(A39="Solicitação de Serviço",A39="Incidente",V39="",W39=""),"",IF((NETWORKDAYS.INTL(V39,W39,1)-1)=0,1,IF((NETWORKDAYS.INTL(V39,W39,1)-1)<0,"",NETWORKDAYS.INTL(V39,W39,1)-1))) | AR39: =IF(AA39="","",AQ39=AA39) | AS39: =IF(OR(A39="Solicitação de Serviço",A39="Incidente",P39=""),"",IF(OR(A39="História",A39="Enabler",A39="Débito Técnico"),IF(W39="","",NETWORKDAYS.INTL(P39,W39,1)-1),IF(U39="","",NETWORKDAYS.INTL(P39,U39,1)-1))) | AT39: =IF(OR(A39="Solicitação de Serviço",A39="Incidente",A39="Sustentação"),"",IF(P39="","",IF(OR(A39="História",A39="Enabler",A39="Débito Técnico"),AS39=AC39,AS39=AB39))) | AU39: =IF(M39="","",M39)
A40: Incidente | B40: SGTB-2704 | C40: [SGTB] SP 26.3.6 | D40: [Jornada Secretaria e Gestor de Unidades] Thunderbolts | E40: Aceito | F40: [SGTB] PI 3/26 | H40: [INC0818646]Tenho um Erro/Problema com o Sistema - Portal Prisma - Prisma | J40: 900 | L40: Itens concluídos | O40: Concluído | P40: 46281.515 | Q40: 46279 | R40: 46283 | S40: 46283 | AH40: =IF(J40="","",J40/3600) -> 0.25 | AI40: =IF(COUNTIF(AG40, "*dia*"), "VERDADEIRO", "FALSO") -> FALSO | AJ40: =IF(AI40="VERDADEIRO",LEFT(AG40,2),0) -> 0 | AK40: =IF(OR(A40="Solicitação de Serviço",A40="Incidente",P40="",Q40=""),"",IF((NETWORKDAYS.INTL(P40,Q40,1)-1)=0,1,NETWORKDAYS.INTL(P40,Q40,1)-1)) | AL40: =IF(X40="","",AK40=X40) | AM40: =IF(OR(A40="Solicitação de Serviço",A40="Incidente",R40="",S40=""),"",IF((NETWORKDAYS.INTL(R40,S40,1)-1)=0,1,NETWORKDAYS.INTL(R40,S40,1)-1-AJ40)) | AN40: =IF(Y40="","",AM40=Y40) | AO40: =IF(OR(A40="Solicitação de Serviço",A40="Incidente",T40="",U40=""),"",IF((NETWORKDAYS.INTL(T40,U40,1)-1)=0,1,NETWORKDAYS.INTL(T40,U40,1)-1)) | AP40: =IF(Z40="","",AO40=Z40) | AQ40: =IF(OR(A40="Solicitação de Serviço",A40="Incidente",V40="",W40=""),"",IF((NETWORKDAYS.INTL(V40,W40,1)-1)=0,1,IF((NETWORKDAYS.INTL(V40,W40,1)-1)<0,"",NETWORKDAYS.INTL(V40,W40,1)-1))) | AR40: =IF(AA40="","",AQ40=AA40) | AS40: =IF(OR(A40="Solicitação de Serviço",A40="Incidente",P40=""),"",IF(OR(A40="História",A40="Enabler",A40="Débito Técnico"),IF(W40="","",NETWORKDAYS.INTL(P40,W40,1)-1),IF(U40="","",NETWORKDAYS.INTL(P40,U40,1)-1))) | AT40: =IF(OR(A40="Solicitação de Serviço",A40="Incidente",A40="Sustentação"),"",IF(P40="","",IF(OR(A40="História",A40="Enabler",A40="Débito Técnico"),AS40=AC40,AS40=AB40))) | AU40: =IF(M40="","",M40)
A41: Incidente | B41: SGTB-2703 | C41: [SGTB] SP 26.3.6 | D41: [Jornada Secretaria e Gestor de Unidades] Thunderbolts | E41: Aceito | F41: [SGTB] PI 3/26 | H41: [INC0818645]Tenho um Erro/Problema com o Sistema - Portal Prisma - Prisma | J41: 900 | L41: Itens concluídos | O41: Concluído | P41: 46281.515 | Q41: 46279 | R41: 46283 | S41: 46283 | AH41: =IF(J41="","",J41/3600) -> 0.25 | AI41: =IF(COUNTIF(AG41, "*dia*"), "VERDADEIRO", "FALSO") -> FALSO | AJ41: =IF(AI41="VERDADEIRO",LEFT(AG41,2),0) -> 0 | AK41: =IF(OR(A41="Solicitação de Serviço",A41="Incidente",P41="",Q41=""),"",IF((NETWORKDAYS.INTL(P41,Q41,1)-1)=0,1,NETWORKDAYS.INTL(P41,Q41,1)-1)) | AL41: =IF(X41="","",AK41=X41) | AM41: =IF(OR(A41="Solicitação de Serviço",A41="Incidente",R41="",S41=""),"",IF((NETWORKDAYS.INTL(R41,S41,1)-1)=0,1,NETWORKDAYS.INTL(R41,S41,1)-1-AJ41)) | AN41: =IF(Y41="","",AM41=Y41) | AO41: =IF(OR(A41="Solicitação de Serviço",A41="Incidente",T41="",U41=""),"",IF((NETWORKDAYS.INTL(T41,U41,1)-1)=0,1,NETWORKDAYS.INTL(T41,U41,1)-1)) | AP41: =IF(Z41="","",AO41=Z41) | AQ41: =IF(OR(A41="Solicitação de Serviço",A41="Incidente",V41="",W41=""),"",IF((NETWORKDAYS.INTL(V41,W41,1)-1)=0,1,IF((NETWORKDAYS.INTL(V41,W41,1)-1)<0,"",NETWORKDAYS.INTL(V41,W41,1)-1))) | AR41: =IF(AA41="","",AQ41=AA41) | AS41: =IF(OR(A41="Solicitação de Serviço",A41="Incidente",P41=""),"",IF(OR(A41="História",A41="Enabler",A41="Débito Técnico"),IF(W41="","",NETWORKDAYS.INTL(P41,W41,1)-1),IF(U41="","",NETWORKDAYS.INTL(P41,U41,1)-1))) | AT41: =IF(OR(A41="Solicitação de Serviço",A41="Incidente",A41="Sustentação"),"",IF(P41="","",IF(OR(A41="História",A41="Enabler",A41="Débito Técnico"),AS41=AC41,AS41=AB41))) | AU41: =IF(M41="","",M41)
A42: Incidente | B42: SGTB-2702 | C42: [SGTB] SP 26.3.6 | D42: [Jornada Secretaria e Gestor de Unidades] Thunderbolts | E42: Aceito | F42: [SGTB] PI 3/26 | H42: [INC0818650]Tenho um Erro/Problema com o Sistema - Prisma - Usuários do Prisma | L42: Itens concluídos | O42: Abertura indevida | P42: 46281.478 | Q42: 46279 | R42: 46282 | AH42: =IF(J42="","",J42/3600) | AI42: =IF(COUNTIF(AG42, "*dia*"), "VERDADEIRO", "FALSO") -> FALSO | AJ42: =IF(AI42="VERDADEIRO",LEFT(AG42,2),0) -> 0 | AK42: =IF(OR(A42="Solicitação de Serviço",A42="Incidente",P42="",Q42=""),"",IF((NETWORKDAYS.INTL(P42,Q42,1)-1)=0,1,NETWORKDAYS.INTL(P42,Q42,1)-1)) | AL42: =IF(X42="","",AK42=X42) | AM42: =IF(OR(A42="Solicitação de Serviço",A42="Incidente",R42="",S42=""),"",IF((NETWORKDAYS.INTL(R42,S42,1)-1)=0,1,NETWORKDAYS.INTL(R42,S42,1)-1-AJ42)) | AN42: =IF(Y42="","",AM42=Y42) | AO42: =IF(OR(A42="Solicitação de Serviço",A42="Incidente",T42="",U42=""),"",IF((NETWORKDAYS.INTL(T42,U42,1)-1)=0,1,NETWORKDAYS.INTL(T42,U42,1)-1)) | AP42: =IF(Z42="","",AO42=Z42) | AQ42: =IF(OR(A42="Solicitação de Serviço",A42="Incidente",V42="",W42=""),"",IF((NETWORKDAYS.INTL(V42,W42,1)-1)=0,1,IF((NETWORKDAYS.INTL(V42,W42,1)-1)<0,"",NETWORKDAYS.INTL(V42,W42,1)-1))) | AR42: =IF(AA42="","",AQ42=AA42) | AS42: =IF(OR(A42="Solicitação de Serviço",A42="Incidente",P42=""),"",IF(OR(A42="História",A42="Enabler",A42="Débito Técnico"),IF(W42="","",NETWORKDAYS.INTL(P42,W42,1)-1),IF(U42="","",NETWORKDAYS.INTL(P42,U42,1)-1))) | AT42: =IF(OR(A42="Solicitação de Serviço",A42="Incidente",A42="Sustentação"),"",IF(P42="","",IF(OR(A42="História",A42="Enabler",A42="Débito Técnico"),AS42=AC42,AS42=AB42))) | AU42: =IF(M42="","",M42)
A43: Incidente | B43: SGTB-2694 | C43: [SGTB] SP 26.3.6 | D43: [Jornada Secretaria e Gestor de Unidades] Thunderbolts | E43: Aceito | F43: [SGTB] PI 3/26 | H43: [INC0818572]Tenho um Erro/Problema com o Sistema - Portal Prisma - Prisma - Usuários do Prisma | J43: 900 | L43: Itens concluídos | O43: Concluído | P43: 46281.377 | Q43: 46279 | R43: 46281 | S43: 46281 | AH43: =IF(J43="","",J43/3600) -> 0.25 | AI43: =IF(COUNTIF(AG43, "*dia*"), "VERDADEIRO", "FALSO") -> FALSO | AJ43: =IF(AI43="VERDADEIRO",LEFT(AG43,2),0) -> 0 | AK43: =IF(OR(A43="Solicitação de Serviço",A43="Incidente",P43="",Q43=""),"",IF((NETWORKDAYS.INTL(P43,Q43,1)-1)=0,1,NETWORKDAYS.INTL(P43,Q43,1)-1)) | AL43: =IF(X43="","",AK43=X43) | AM43: =IF(OR(A43="Solicitação de Serviço",A43="Incidente",R43="",S43=""),"",IF((NETWORKDAYS.INTL(R43,S43,1)-1)=0,1,NETWORKDAYS.INTL(R43,S43,1)-1-AJ43)) | AN43: =IF(Y43="","",AM43=Y43) | AO43: =IF(OR(A43="Solicitação de Serviço",A43="Incidente",T43="",U43=""),"",IF((NETWORKDAYS.INTL(T43,U43,1)-1)=0,1,NETWORKDAYS.INTL(T43,U43,1)-1)) | AP43: =IF(Z43="","",AO43=Z43) | AQ43: =IF(OR(A43="Solicitação de Serviço",A43="Incidente",V43="",W43=""),"",IF((NETWORKDAYS.INTL(V43,W43,1)-1)=0,1,IF((NETWORKDAYS.INTL(V43,W43,1)-1)<0,"",NETWORKDAYS.INTL(V43,W43,1)-1))) | AR43: =IF(AA43="","",AQ43=AA43) | AS43: =IF(OR(A43="Solicitação de Serviço",A43="Incidente",P43=""),"",IF(OR(A43="História",A43="Enabler",A43="Débito Técnico"),IF(W43="","",NETWORKDAYS.INTL(P43,W43,1)-1),IF(U43="","",NETWORKDAYS.INTL(P43,U43,1)-1))) | AT43: =IF(OR(A43="Solicitação de Serviço",A43="Incidente",A43="Sustentação"),"",IF(P43="","",IF(OR(A43="História",A43="Enabler",A43="Débito Técnico"),AS43=AC43,AS43=AB43))) | AU43: =IF(M43="","",M43)
A44: Incidente | B44: SGTB-2693 | C44: [SGTB] SP 26.3.6 | D44: [Jornada Secretaria e Gestor de Unidades] Thunderbolts | E44: Aceito | F44: [SGTB] PI 3/26 | H44: [INC0816495]Tenho um Erro/Problema com o Sistema - AVA Presencial/Moodle - Acesso ao AVA/Disciplina | J44: 1800 | L44: Itens concluídos | O44: Concluído | P44: 46280.746 | Q44: 46279 | R44: 46281 | S44: 46281 | AH44: =IF(J44="","",J44/3600) -> 0.5 | AI44: =IF(COUNTIF(AG44, "*dia*"), "VERDADEIRO", "FALSO") -> FALSO | AJ44: =IF(AI44="VERDADEIRO",LEFT(AG44,2),0) -> 0 | AK44: =IF(OR(A44="Solicitação de Serviço",A44="Incidente",P44="",Q44=""),"",IF((NETWORKDAYS.INTL(P44,Q44,1)-1)=0,1,NETWORKDAYS.INTL(P44,Q44,1)-1)) | AL44: =IF(X44="","",AK44=X44) | AM44: =IF(OR(A44="Solicitação de Serviço",A44="Incidente",R44="",S44=""),"",IF((NETWORKDAYS.INTL(R44,S44,1)-1)=0,1,NETWORKDAYS.INTL(R44,S44,1)-1-AJ44)) | AN44: =IF(Y44="","",AM44=Y44) | AO44: =IF(OR(A44="Solicitação de Serviço",A44="Incidente",T44="",U44=""),"",IF((NETWORKDAYS.INTL(T44,U44,1)-1)=0,1,NETWORKDAYS.INTL(T44,U44,1)-1)) | AP44: =IF(Z44="","",AO44=Z44) | AQ44: =IF(OR(A44="Solicitação de Serviço",A44="Incidente",V44="",W44=""),"",IF((NETWORKDAYS.INTL(V44,W44,1)-1)=0,1,IF((NETWORKDAYS.INTL(V44,W44,1)-1)<0,"",NETWORKDAYS.INTL(V44,W44,1)-1))) | AR44: =IF(AA44="","",AQ44=AA44) | AS44: =IF(OR(A44="Solicitação de Serviço",A44="Incidente",P44=""),"",IF(OR(A44="História",A44="Enabler",A44="Débito Técnico"),IF(W44="","",NETWORKDAYS.INTL(P44,W44,1)-1),IF(U44="","",NETWORKDAYS.INTL(P44,U44,1)-1))) | AT44: =IF(OR(A44="Solicitação de Serviço",A44="Incidente",A44="Sustentação"),"",IF(P44="","",IF(OR(A44="História",A44="Enabler",A44="Débito Técnico"),AS44=AC44,AS44=AB44))) | AU44: =IF(M44="","",M44)
A45: Incidente | B45: SGTB-2692 | C45: [SGTB] SP 26.3.6 | D45: [Jornada Secretaria e Gestor de Unidades] Thunderbolts | E45: Aceito | F45: [SGTB] PI 3/26 | H45: [INC0818316]Tenho um Erro/Problema com o Sistema - Sistema U - (Sistema U) Histórico Escolar | J45: 900 | L45: Itens concluídos | O45: Abertura indevida | P45: 46280.737 | Q45: 46279 | R45: 46281 | AH45: =IF(J45="","",J45/3600) -> 0.25 | AI45: =IF(COUNTIF(AG45, "*dia*"), "VERDADEIRO", "FALSO") -> FALSO | AJ45: =IF(AI45="VERDADEIRO",LEFT(AG45,2),0) -> 0 | AK45: =IF(OR(A45="Solicitação de Serviço",A45="Incidente",P45="",Q45=""),"",IF((NETWORKDAYS.INTL(P45,Q45,1)-1)=0,1,NETWORKDAYS.INTL(P45,Q45,1)-1)) | AL45: =IF(X45="","",AK45=X45) | AM45: =IF(OR(A45="Solicitação de Serviço",A45="Incidente",R45="",S45=""),"",IF((NETWORKDAYS.INTL(R45,S45,1)-1)=0,1,NETWORKDAYS.INTL(R45,S45,1)-1-AJ45)) | AN45: =IF(Y45="","",AM45=Y45) | AO45: =IF(OR(A45="Solicitação de Serviço",A45="Incidente",T45="",U45=""),"",IF((NETWORKDAYS.INTL(T45,U45,1)-1)=0,1,NETWORKDAYS.INTL(T45,U45,1)-1)) | AP45: =IF(Z45="","",AO45=Z45) | AQ45: =IF(OR(A45="Solicitação de Serviço",A45="Incidente",V45="",W45=""),"",IF((NETWORKDAYS.INTL(V45,W45,1)-1)=0,1,IF((NETWORKDAYS.INTL(V45,W45,1)-1)<0,"",NETWORKDAYS.INTL(V45,W45,1)-1))) | AR45: =IF(AA45="","",AQ45=AA45) | AS45: =IF(OR(A45="Solicitação de Serviço",A45="Incidente",P45=""),"",IF(OR(A45="História",A45="Enabler",A45="Débito Técnico"),IF(W45="","",NETWORKDAYS.INTL(P45,W45,1)-1),IF(U45="","",NETWORKDAYS.INTL(P45,U45,1)-1))) | AT45: =IF(OR(A45="Solicitação de Serviço",A45="Incidente",A45="Sustentação"),"",IF(P45="","",IF(OR(A45="História",A45="Enabler",A45="Débito Técnico"),AS45=AC45,AS45=AB45))) | AU45: =IF(M45="","",M45)
A46: Incidente | B46: SGTB-2691 | C46: [SGTB] SP 26.3.6 | D46: [Jornada Secretaria e Gestor de Unidades] Thunderbolts | E46: Aceito | F46: [SGTB] PI 3/26 | H46: [INC0818334]Tenho um Erro/Problema com o Sistema - Portal do Professor - Portal do Professor | L46: Itens concluídos | O46: Abertura indevida | P46: 46280.735 | Q46: 46279 | R46: 46282 | AH46: =IF(J46="","",J46/3600) | AI46: =IF(COUNTIF(AG46, "*dia*"), "VERDADEIRO", "FALSO") -> FALSO | AJ46: =IF(AI46="VERDADEIRO",LEFT(AG46,2),0) -> 0 | AK46: =IF(OR(A46="Solicitação de Serviço",A46="Incidente",P46="",Q46=""),"",IF((NETWORKDAYS.INTL(P46,Q46,1)-1)=0,1,NETWORKDAYS.INTL(P46,Q46,1)-1)) | AL46: =IF(X46="","",AK46=X46) | AM46: =IF(OR(A46="Solicitação de Serviço",A46="Incidente",R46="",S46=""),"",IF((NETWORKDAYS.INTL(R46,S46,1)-1)=0,1,NETWORKDAYS.INTL(R46,S46,1)-1-AJ46)) | AN46: =IF(Y46="","",AM46=Y46) | AO46: =IF(OR(A46="Solicitação de Serviço",A46="Incidente",T46="",U46=""),"",IF((NETWORKDAYS.INTL(T46,U46,1)-1)=0,1,NETWORKDAYS.INTL(T46,U46,1)-1)) | AP46: =IF(Z46="","",AO46=Z46) | AQ46: =IF(OR(A46="Solicitação de Serviço",A46="Incidente",V46="",W46=""),"",IF((NETWORKDAYS.INTL(V46,W46,1)-1)=0,1,IF((NETWORKDAYS.INTL(V46,W46,1)-1)<0,"",NETWORKDAYS.INTL(V46,W46,1)-1))) | AR46: =IF(AA46="","",AQ46=AA46) | AS46: =IF(OR(A46="Solicitação de Serviço",A46="Incidente",P46=""),"",IF(OR(A46="História",A46="Enabler",A46="Débito Técnico"),IF(W46="","",NETWORKDAYS.INTL(P46,W46,1)-1),IF(U46="","",NETWORKDAYS.INTL(P46,U46,1)-1))) | AT46: =IF(OR(A46="Solicitação de Serviço",A46="Incidente",A46="Sustentação"),"",IF(P46="","",IF(OR(A46="História",A46="Enabler",A46="Débito Técnico"),AS46=AC46,AS46=AB46))) | AU46: =IF(M46="","",M46)
A47: Incidente | B47: SGTB-2690 | C47: [SGTB] SP 26.3.6 | D47: [Jornada Secretaria e Gestor de Unidades] Thunderbolts | E47: Aceito | F47: [SGTB] PI 3/26 | H47: [INC0764376]Tenho um Erro/Problema no Dynamics - Gestão de unidades - Reportar um erro/problema | J47: 1800 | L47: Itens concluídos | O47: Concluído | P47: 46280.683 | Q47: 46279 | R47: 46283 | S47: 46283 | AH47: =IF(J47="","",J47/3600) -> 0.5 | AI47: =IF(COUNTIF(AG47, "*dia*"), "VERDADEIRO", "FALSO") -> FALSO | AJ47: =IF(AI47="VERDADEIRO",LEFT(AG47,2),0) -> 0 | AK47: =IF(OR(A47="Solicitação de Serviço",A47="Incidente",P47="",Q47=""),"",IF((NETWORKDAYS.INTL(P47,Q47,1)-1)=0,1,NETWORKDAYS.INTL(P47,Q47,1)-1)) | AL47: =IF(X47="","",AK47=X47) | AM47: =IF(OR(A47="Solicitação de Serviço",A47="Incidente",R47="",S47=""),"",IF((NETWORKDAYS.INTL(R47,S47,1)-1)=0,1,NETWORKDAYS.INTL(R47,S47,1)-1-AJ47)) | AN47: =IF(Y47="","",AM47=Y47) | AO47: =IF(OR(A47="Solicitação de Serviço",A47="Incidente",T47="",U47=""),"",IF((NETWORKDAYS.INTL(T47,U47,1)-1)=0,1,NETWORKDAYS.INTL(T47,U47,1)-1)) | AP47: =IF(Z47="","",AO47=Z47) | AQ47: =IF(OR(A47="Solicitação de Serviço",A47="Incidente",V47="",W47=""),"",IF((NETWORKDAYS.INTL(V47,W47,1)-1)=0,1,IF((NETWORKDAYS.INTL(V47,W47,1)-1)<0,"",NETWORKDAYS.INTL(V47,W47,1)-1))) | AR47: =IF(AA47="","",AQ47=AA47) | AS47: =IF(OR(A47="Solicitação de Serviço",A47="Incidente",P47=""),"",IF(OR(A47="História",A47="Enabler",A47="Débito Técnico"),IF(W47="","",NETWORKDAYS.INTL(P47,W47,1)-1),IF(U47="","",NETWORKDAYS.INTL(P47,U47,1)-1))) | AT47: =IF(OR(A47="Solicitação de Serviço",A47="Incidente",A47="Sustentação"),"",IF(P47="","",IF(OR(A47="História",A47="Enabler",A47="Débito Técnico"),AS47=AC47,AS47=AB47))) | AU47: =IF(M47="","",M47)
A48: Incidente | B48: SGTB-2688 | C48: [SGTB] SP 26.3.6 | D48: [Jornada Secretaria e Gestor de Unidades] Thunderbolts | E48: Aceito | F48: [SGTB] PI 3/26 | H48: [INC0816361]Tenho um Erro/Problema com o Sistema - AVA Presencial/Moodle - Acesso ao AVA/Disciplina | J48: 600 | L48: Itens concluídos | O48: Concluído | P48: 46280.666 | Q48: 46279 | R48: 46281 | S48: 46281 | AH48: =IF(J48="","",J48/3600) -> 0.16666667 | AI48: =IF(COUNTIF(AG48, "*dia*"), "VERDADEIRO", "FALSO") -> FALSO | AJ48: =IF(AI48="VERDADEIRO",LEFT(AG48,2),0) -> 0 | AK48: =IF(OR(A48="Solicitação de Serviço",A48="Incidente",P48="",Q48=""),"",IF((NETWORKDAYS.INTL(P48,Q48,1)-1)=0,1,NETWORKDAYS.INTL(P48,Q48,1)-1)) | AL48: =IF(X48="","",AK48=X48) | AM48: =IF(OR(A48="Solicitação de Serviço",A48="Incidente",R48="",S48=""),"",IF((NETWORKDAYS.INTL(R48,S48,1)-1)=0,1,NETWORKDAYS.INTL(R48,S48,1)-1-AJ48)) | AN48: =IF(Y48="","",AM48=Y48) | AO48: =IF(OR(A48="Solicitação de Serviço",A48="Incidente",T48="",U48=""),"",IF((NETWORKDAYS.INTL(T48,U48,1)-1)=0,1,NETWORKDAYS.INTL(T48,U48,1)-1)) | AP48: =IF(Z48="","",AO48=Z48) | AQ48: =IF(OR(A48="Solicitação de Serviço",A48="Incidente",V48="",W48=""),"",IF((NETWORKDAYS.INTL(V48,W48,1)-1)=0,1,IF((NETWORKDAYS.INTL(V48,W48,1)-1)<0,"",NETWORKDAYS.INTL(V48,W48,1)-1))) | AR48: =IF(AA48="","",AQ48=AA48) | AS48: =IF(OR(A48="Solicitação de Serviço",A48="Incidente",P48=""),"",IF(OR(A48="História",A48="Enabler",A48="Débito Técnico"),IF(W48="","",NETWORKDAYS.INTL(P48,W48,1)-1),IF(U48="","",NETWORKDAYS.INTL(P48,U48,1)-1))) | AT48: =IF(OR(A48="Solicitação de Serviço",A48="Incidente",A48="Sustentação"),"",IF(P48="","",IF(OR(A48="História",A48="Enabler",A48="Débito Técnico"),AS48=AC48,AS48=AB48))) | AU48: =IF(M48="","",M48)
A49: Incidente | B49: SGTB-2687 | C49: [SGTB] SP 26.3.6 | D49: [Jornada Secretaria e Gestor de Unidades] Thunderbolts | E49: Aceito | F49: [SGTB] PI 3/26 | H49: [INC0816358]Tenho um Erro/Problema com o Sistema - AVA Presencial/Moodle - Acesso ao AVA/Disciplina | J49: 600 | L49: Itens concluídos | O49: Concluído | P49: 46280.665 | Q49: 46279 | R49: 46281 | S49: 46281 | AH49: =IF(J49="","",J49/3600) -> 0.16666667 | AI49: =IF(COUNTIF(AG49, "*dia*"), "VERDADEIRO", "FALSO") -> FALSO | AJ49: =IF(AI49="VERDADEIRO",LEFT(AG49,2),0) -> 0 | AK49: =IF(OR(A49="Solicitação de Serviço",A49="Incidente",P49="",Q49=""),"",IF((NETWORKDAYS.INTL(P49,Q49,1)-1)=0,1,NETWORKDAYS.INTL(P49,Q49,1)-1)) | AL49: =IF(X49="","",AK49=X49) | AM49: =IF(OR(A49="Solicitação de Serviço",A49="Incidente",R49="",S49=""),"",IF((NETWORKDAYS.INTL(R49,S49,1)-1)=0,1,NETWORKDAYS.INTL(R49,S49,1)-1-AJ49)) | AN49: =IF(Y49="","",AM49=Y49) | AO49: =IF(OR(A49="Solicitação de Serviço",A49="Incidente",T49="",U49=""),"",IF((NETWORKDAYS.INTL(T49,U49,1)-1)=0,1,NETWORKDAYS.INTL(T49,U49,1)-1)) | AP49: =IF(Z49="","",AO49=Z49) | AQ49: =IF(OR(A49="Solicitação de Serviço",A49="Incidente",V49="",W49=""),"",IF((NETWORKDAYS.INTL(V49,W49,1)-1)=0,1,IF((NETWORKDAYS.INTL(V49,W49,1)-1)<0,"",NETWORKDAYS.INTL(V49,W49,1)-1))) | AR49: =IF(AA49="","",AQ49=AA49) | AS49: =IF(OR(A49="Solicitação de Serviço",A49="Incidente",P49=""),"",IF(OR(A49="História",A49="Enabler",A49="Débito Técnico"),IF(W49="","",NETWORKDAYS.INTL(P49,W49,1)-1),IF(U49="","",NETWORKDAYS.INTL(P49,U49,1)-1))) | AT49: =IF(OR(A49="Solicitação de Serviço",A49="Incidente",A49="Sustentação"),"",IF(P49="","",IF(OR(A49="História",A49="Enabler",A49="Débito Técnico"),AS49=AC49,AS49=AB49))) | AU49: =IF(M49="","",M49)
A50: Incidente | B50: SGTB-2686 | C50: [SGTB] SP 26.3.6 | D50: [Jornada Secretaria e Gestor de Unidades] Thunderbolts | E50: Aceito | F50: [SGTB] PI 3/26 | H50: [INC0816359]Tenho um Erro/Problema com o Sistema - AVA Presencial/Moodle - Acesso ao AVA/Disciplina | J50: 600 | L50: Itens concluídos | O50: Concluído | P50: 46280.665 | Q50: 46279 | R50: 46281 | S50: 46281 | AH50: =IF(J50="","",J50/3600) -> 0.16666667 | AI50: =IF(COUNTIF(AG50, "*dia*"), "VERDADEIRO", "FALSO") -> FALSO | AJ50: =IF(AI50="VERDADEIRO",LEFT(AG50,2),0) -> 0 | AK50: =IF(OR(A50="Solicitação de Serviço",A50="Incidente",P50="",Q50=""),"",IF((NETWORKDAYS.INTL(P50,Q50,1)-1)=0,1,NETWORKDAYS.INTL(P50,Q50,1)-1)) | AL50: =IF(X50="","",AK50=X50) | AM50: =IF(OR(A50="Solicitação de Serviço",A50="Incidente",R50="",S50=""),"",IF((NETWORKDAYS.INTL(R50,S50,1)-1)=0,1,NETWORKDAYS.INTL(R50,S50,1)-1-AJ50)) | AN50: =IF(Y50="","",AM50=Y50) | AO50: =IF(OR(A50="Solicitação de Serviço",A50="Incidente",T50="",U50=""),"",IF((NETWORKDAYS.INTL(T50,U50,1)-1)=0,1,NETWORKDAYS.INTL(T50,U50,1)-1)) | AP50: =IF(Z50="","",AO50=Z50) | AQ50: =IF(OR(A50="Solicitação de Serviço",A50="Incidente",V50="",W50=""),"",IF((NETWORKDAYS.INTL(V50,W50,1)-1)=0,1,IF((NETWORKDAYS.INTL(V50,W50,1)-1)<0,"",NETWORKDAYS.INTL(V50,W50,1)-1))) | AR50: =IF(AA50="","",AQ50=AA50) | AS50: =IF(OR(A50="Solicitação de Serviço",A50="Incidente",P50=""),"",IF(OR(A50="História",A50="Enabler",A50="Débito Técnico"),IF(W50="","",NETWORKDAYS.INTL(P50,W50,1)-1),IF(U50="","",NETWORKDAYS.INTL(P50,U50,1)-1))) | AT50: =IF(OR(A50="Solicitação de Serviço",A50="Incidente",A50="Sustentação"),"",IF(P50="","",IF(OR(A50="História",A50="Enabler",A50="Débito Técnico"),AS50=AC50,AS50=AB50))) | AU50: =IF(M50="","",M50)
A51: Incidente | B51: SGTB-2679 | C51: [SGTB] SP 26.3.6 | D51: [Jornada Secretaria e Gestor de Unidades] Thunderbolts | E51: Aceito | F51: [SGTB] PI 3/26 | H51: [INC0818123]Tenho um Erro/Problema com o Sistema - Portal Prisma - Prisma - Portal Prisma (Banco de Dados) | J51: 1800 | L51: Itens concluídos | O51: Concluído | P51: 46280.456 | Q51: 46279 | R51: 46280 | S51: 46280 | AH51: =IF(J51="","",J51/3600) -> 0.5 | AI51: =IF(COUNTIF(AG51, "*dia*"), "VERDADEIRO", "FALSO") -> FALSO | AJ51: =IF(AI51="VERDADEIRO",LEFT(AG51,2),0) -> 0 | AK51: =IF(OR(A51="Solicitação de Serviço",A51="Incidente",P51="",Q51=""),"",IF((NETWORKDAYS.INTL(P51,Q51,1)-1)=0,1,NETWORKDAYS.INTL(P51,Q51,1)-1)) | AL51: =IF(X51="","",AK51=X51) | AM51: =IF(OR(A51="Solicitação de Serviço",A51="Incidente",R51="",S51=""),"",IF((NETWORKDAYS.INTL(R51,S51,1)-1)=0,1,NETWORKDAYS.INTL(R51,S51,1)-1-AJ51)) | AN51: =IF(Y51="","",AM51=Y51) | AO51: =IF(OR(A51="Solicitação de Serviço",A51="Incidente",T51="",U51=""),"",IF((NETWORKDAYS.INTL(T51,U51,1)-1)=0,1,NETWORKDAYS.INTL(T51,U51,1)-1)) | AP51: =IF(Z51="","",AO51=Z51) | AQ51: =IF(OR(A51="Solicitação de Serviço",A51="Incidente",V51="",W51=""),"",IF((NETWORKDAYS.INTL(V51,W51,1)-1)=0,1,IF((NETWORKDAYS.INTL(V51,W51,1)-1)<0,"",NETWORKDAYS.INTL(V51,W51,1)-1))) | AR51: =IF(AA51="","",AQ51=AA51) | AS51: =IF(OR(A51="Solicitação de Serviço",A51="Incidente",P51=""),"",IF(OR(A51="História",A51="Enabler",A51="Débito Técnico"),IF(W51="","",NETWORKDAYS.INTL(P51,W51,1)-1),IF(U51="","",NETWORKDAYS.INTL(P51,U51,1)-1))) | AT51: =IF(OR(A51="Solicitação de Serviço",A51="Incidente",A51="Sustentação"),"",IF(P51="","",IF(OR(A51="História",A51="Enabler",A51="Débito Técnico"),AS51=AC51,AS51=AB51))) | AU51: =IF(M51="","",M51)
A52: Solicitação de Serviço | B52: SGTB-2678 | C52: [SGTB] SP 26.3.6 | D52: [Jornada Secretaria e Gestor de Unidades] Thunderbolts | E52: Aceito | F52: [SGTB] PI 3/26 | H52: [RITM0739554]Solicitar Serviço ao Sistema - Prisma - Licenças Dynamics | J52: 900 | L52: Itens concluídos | O52: Concluído | P52: 46280.393 | Q52: 46279 | R52: 46283 | S52: 46283 | AH52: =IF(J52="","",J52/3600) -> 0.25 | AI52: =IF(COUNTIF(AG52, "*dia*"), "VERDADEIRO", "FALSO") -> FALSO | AJ52: =IF(AI52="VERDADEIRO",LEFT(AG52,2),0) -> 0 | AK52: =IF(OR(A52="Solicitação de Serviço",A52="Incidente",P52="",Q52=""),"",IF((NETWORKDAYS.INTL(P52,Q52,1)-1)=0,1,NETWORKDAYS.INTL(P52,Q52,1)-1)) | AL52: =IF(X52="","",AK52=X52) | AM52: =IF(OR(A52="Solicitação de Serviço",A52="Incidente",R52="",S52=""),"",IF((NETWORKDAYS.INTL(R52,S52,1)-1)=0,1,NETWORKDAYS.INTL(R52,S52,1)-1-AJ52)) | AN52: =IF(Y52="","",AM52=Y52) | AO52: =IF(OR(A52="Solicitação de Serviço",A52="Incidente",T52="",U52=""),"",IF((NETWORKDAYS.INTL(T52,U52,1)-1)=0,1,NETWORKDAYS.INTL(T52,U52,1)-1)) | AP52: =IF(Z52="","",AO52=Z52) | AQ52: =IF(OR(A52="Solicitação de Serviço",A52="Incidente",V52="",W52=""),"",IF((NETWORKDAYS.INTL(V52,W52,1)-1)=0,1,IF((NETWORKDAYS.INTL(V52,W52,1)-1)<0,"",NETWORKDAYS.INTL(V52,W52,1)-1))) | AR52: =IF(AA52="","",AQ52=AA52) | AS52: =IF(OR(A52="Solicitação de Serviço",A52="Incidente",P52=""),"",IF(OR(A52="História",A52="Enabler",A52="Débito Técnico"),IF(W52="","",NETWORKDAYS.INTL(P52,W52,1)-1),IF(U52="","",NETWORKDAYS.INTL(P52,U52,1)-1))) | AT52: =IF(OR(A52="Solicitação de Serviço",A52="Incidente",A52="Sustentação"),"",IF(P52="","",IF(OR(A52="História",A52="Enabler",A52="Débito Técnico"),AS52=AC52,AS52=AB52))) | AU52: =IF(M52="","",M52)
A53: Solicitação de Serviço | B53: SGTB-2677 | C53: [SGTB] SP 26.3.6 | D53: [Jornada Secretaria e Gestor de Unidades] Thunderbolts | E53: Aceito | F53: [SGTB] PI 3/26 | H53: [RITM0742908]Solicitar Serviço ao Sistema - Prisma - Licenças Dynamics | J53: 900 | L53: Itens concluídos | O53: Concluído | P53: 46280.393 | Q53: 46279 | R53: 46283 | S53: 46283 | AH53: =IF(J53="","",J53/3600) -> 0.25 | AI53: =IF(COUNTIF(AG53, "*dia*"), "VERDADEIRO", "FALSO") -> FALSO | AJ53: =IF(AI53="VERDADEIRO",LEFT(AG53,2),0) -> 0 | AK53: =IF(OR(A53="Solicitação de Serviço",A53="Incidente",P53="",Q53=""),"",IF((NETWORKDAYS.INTL(P53,Q53,1)-1)=0,1,NETWORKDAYS.INTL(P53,Q53,1)-1)) | AL53: =IF(X53="","",AK53=X53) | AM53: =IF(OR(A53="Solicitação de Serviço",A53="Incidente",R53="",S53=""),"",IF((NETWORKDAYS.INTL(R53,S53,1)-1)=0,1,NETWORKDAYS.INTL(R53,S53,1)-1-AJ53)) | AN53: =IF(Y53="","",AM53=Y53) | AO53: =IF(OR(A53="Solicitação de Serviço",A53="Incidente",T53="",U53=""),"",IF((NETWORKDAYS.INTL(T53,U53,1)-1)=0,1,NETWORKDAYS.INTL(T53,U53,1)-1)) | AP53: =IF(Z53="","",AO53=Z53) | AQ53: =IF(OR(A53="Solicitação de Serviço",A53="Incidente",V53="",W53=""),"",IF((NETWORKDAYS.INTL(V53,W53,1)-1)=0,1,IF((NETWORKDAYS.INTL(V53,W53,1)-1)<0,"",NETWORKDAYS.INTL(V53,W53,1)-1))) | AR53: =IF(AA53="","",AQ53=AA53) | AS53: =IF(OR(A53="Solicitação de Serviço",A53="Incidente",P53=""),"",IF(OR(A53="História",A53="Enabler",A53="Débito Técnico"),IF(W53="","",NETWORKDAYS.INTL(P53,W53,1)-1),IF(U53="","",NETWORKDAYS.INTL(P53,U53,1)-1))) | AT53: =IF(OR(A53="Solicitação de Serviço",A53="Incidente",A53="Sustentação"),"",IF(P53="","",IF(OR(A53="História",A53="Enabler",A53="Débito Técnico"),AS53=AC53,AS53=AB53))) | AU53: =IF(M53="","",M53)
A54: Incidente | B54: SGTB-2675 | C54: [SGTB] SP 26.3.6 | D54: [Jornada Secretaria e Gestor de Unidades] Thunderbolts | E54: Aceito | F54: [SGTB] PI 3/26 | H54: [INC0818075]Tenho um Erro/Problema com o Sistema - Portal Prisma - Prisma - Usuários do Prisma | J54: 900 | L54: Itens concluídos | O54: Abertura indevida | P54: 46280.389 | Q54: 46279 | R54: 46281 | AH54: =IF(J54="","",J54/3600) -> 0.25 | AI54: =IF(COUNTIF(AG54, "*dia*"), "VERDADEIRO", "FALSO") -> FALSO | AJ54: =IF(AI54="VERDADEIRO",LEFT(AG54,2),0) -> 0 | AK54: =IF(OR(A54="Solicitação de Serviço",A54="Incidente",P54="",Q54=""),"",IF((NETWORKDAYS.INTL(P54,Q54,1)-1)=0,1,NETWORKDAYS.INTL(P54,Q54,1)-1)) | AL54: =IF(X54="","",AK54=X54) | AM54: =IF(OR(A54="Solicitação de Serviço",A54="Incidente",R54="",S54=""),"",IF((NETWORKDAYS.INTL(R54,S54,1)-1)=0,1,NETWORKDAYS.INTL(R54,S54,1)-1-AJ54)) | AN54: =IF(Y54="","",AM54=Y54) | AO54: =IF(OR(A54="Solicitação de Serviço",A54="Incidente",T54="",U54=""),"",IF((NETWORKDAYS.INTL(T54,U54,1)-1)=0,1,NETWORKDAYS.INTL(T54,U54,1)-1)) | AP54: =IF(Z54="","",AO54=Z54) | AQ54: =IF(OR(A54="Solicitação de Serviço",A54="Incidente",V54="",W54=""),"",IF((NETWORKDAYS.INTL(V54,W54,1)-1)=0,1,IF((NETWORKDAYS.INTL(V54,W54,1)-1)<0,"",NETWORKDAYS.INTL(V54,W54,1)-1))) | AR54: =IF(AA54="","",AQ54=AA54) | AS54: =IF(OR(A54="Solicitação de Serviço",A54="Incidente",P54=""),"",IF(OR(A54="História",A54="Enabler",A54="Débito Técnico"),IF(W54="","",NETWORKDAYS.INTL(P54,W54,1)-1),IF(U54="","",NETWORKDAYS.INTL(P54,U54,1)-1))) | AT54: =IF(OR(A54="Solicitação de Serviço",A54="Incidente",A54="Sustentação"),"",IF(P54="","",IF(OR(A54="História",A54="Enabler",A54="Débito Técnico"),AS54=AC54,AS54=AB54))) | AU54: =IF(M54="","",M54)
A55: Incidente | B55: SGTB-2669 | C55: [SGTB] SP 26.3.6 | D55: [Jornada Secretaria e Gestor de Unidades] Thunderbolts | E55: Aceito | F55: [SGTB] PI 3/26 | H55: [INC0817953]Tenho um Erro/Problema com o Sistema - Olimpo - Sala especial | L55: Itens concluídos | O55: Abertura indevida | P55: 46279.719 | Q55: 46279 | R55: 46280 | AH55: =IF(J55="","",J55/3600) | AI55: =IF(COUNTIF(AG55, "*dia*"), "VERDADEIRO", "FALSO") -> FALSO | AJ55: =IF(AI55="VERDADEIRO",LEFT(AG55,2),0) -> 0 | AK55: =IF(OR(A55="Solicitação de Serviço",A55="Incidente",P55="",Q55=""),"",IF((NETWORKDAYS.INTL(P55,Q55,1)-1)=0,1,NETWORKDAYS.INTL(P55,Q55,1)-1)) | AL55: =IF(X55="","",AK55=X55) | AM55: =IF(OR(A55="Solicitação de Serviço",A55="Incidente",R55="",S55=""),"",IF((NETWORKDAYS.INTL(R55,S55,1)-1)=0,1,NETWORKDAYS.INTL(R55,S55,1)-1-AJ55)) | AN55: =IF(Y55="","",AM55=Y55) | AO55: =IF(OR(A55="Solicitação de Serviço",A55="Incidente",T55="",U55=""),"",IF((NETWORKDAYS.INTL(T55,U55,1)-1)=0,1,NETWORKDAYS.INTL(T55,U55,1)-1)) | AP55: =IF(Z55="","",AO55=Z55) | AQ55: =IF(OR(A55="Solicitação de Serviço",A55="Incidente",V55="",W55=""),"",IF((NETWORKDAYS.INTL(V55,W55,1)-1)=0,1,IF((NETWORKDAYS.INTL(V55,W55,1)-1)<0,"",NETWORKDAYS.INTL(V55,W55,1)-1))) | AR55: =IF(AA55="","",AQ55=AA55) | AS55: =IF(OR(A55="Solicitação de Serviço",A55="Incidente",P55=""),"",IF(OR(A55="História",A55="Enabler",A55="Débito Técnico"),IF(W55="","",NETWORKDAYS.INTL(P55,W55,1)-1),IF(U55="","",NETWORKDAYS.INTL(P55,U55,1)-1))) | AT55: =IF(OR(A55="Solicitação de Serviço",A55="Incidente",A55="Sustentação"),"",IF(P55="","",IF(OR(A55="História",A55="Enabler",A55="Débito Técnico"),AS55=AC55,AS55=AB55))) | AU55: =IF(M55="","",M55)
A56: Incidente | B56: SGTB-2667 | C56: [SGTB] SP 26.3.6 | D56: [Jornada Secretaria e Gestor de Unidades] Thunderbolts | E56: Aceito | F56: [SGTB] PI 3/26 | H56: [INC0817929]Tenho um Erro/Problema com o Sistema - Portal do Professor - Portal do Professor | L56: Itens concluídos | O56: Abertura indevida | P56: 46279.672 | Q56: 46279 | R56: 46280 | AH56: =IF(J56="","",J56/3600) | AI56: =IF(COUNTIF(AG56, "*dia*"), "VERDADEIRO", "FALSO") -> FALSO | AJ56: =IF(AI56="VERDADEIRO",LEFT(AG56,2),0) -> 0 | AK56: =IF(OR(A56="Solicitação de Serviço",A56="Incidente",P56="",Q56=""),"",IF((NETWORKDAYS.INTL(P56,Q56,1)-1)=0,1,NETWORKDAYS.INTL(P56,Q56,1)-1)) | AL56: =IF(X56="","",AK56=X56) | AM56: =IF(OR(A56="Solicitação de Serviço",A56="Incidente",R56="",S56=""),"",IF((NETWORKDAYS.INTL(R56,S56,1)-1)=0,1,NETWORKDAYS.INTL(R56,S56,1)-1-AJ56)) | AN56: =IF(Y56="","",AM56=Y56) | AO56: =IF(OR(A56="Solicitação de Serviço",A56="Incidente",T56="",U56=""),"",IF((NETWORKDAYS.INTL(T56,U56,1)-1)=0,1,NETWORKDAYS.INTL(T56,U56,1)-1)) | AP56: =IF(Z56="","",AO56=Z56) | AQ56: =IF(OR(A56="Solicitação de Serviço",A56="Incidente",V56="",W56=""),"",IF((NETWORKDAYS.INTL(V56,W56,1)-1)=0,1,IF((NETWORKDAYS.INTL(V56,W56,1)-1)<0,"",NETWORKDAYS.INTL(V56,W56,1)-1))) | AR56: =IF(AA56="","",AQ56=AA56) | AS56: =IF(OR(A56="Solicitação de Serviço",A56="Incidente",P56=""),"",IF(OR(A56="História",A56="Enabler",A56="Débito Técnico"),IF(W56="","",NETWORKDAYS.INTL(P56,W56,1)-1),IF(U56="","",NETWORKDAYS.INTL(P56,U56,1)-1))) | AT56: =IF(OR(A56="Solicitação de Serviço",A56="Incidente",A56="Sustentação"),"",IF(P56="","",IF(OR(A56="História",A56="Enabler",A56="Débito Técnico"),AS56=AC56,AS56=AB56))) | AU56: =IF(M56="","",M56)
A57: Incidente | B57: SGTB-2662 | C57: [SGTB] SP 26.3.6 | D57: [Jornada Secretaria e Gestor de Unidades] Thunderbolts | E57: Aceito | F57: [SGTB] PI 3/26 | H57: [INC0817914]Tenho um Erro/Problema com o Sistema - Portal do Professor - Portal do Professor | L57: Itens concluídos | O57: Abertura indevida | P57: 46279.668 | Q57: 46279 | R57: 46280 | AH57: =IF(J57="","",J57/3600) | AI57: =IF(COUNTIF(AG57, "*dia*"), "VERDADEIRO", "FALSO") -> FALSO | AJ57: =IF(AI57="VERDADEIRO",LEFT(AG57,2),0) -> 0 | AK57: =IF(OR(A57="Solicitação de Serviço",A57="Incidente",P57="",Q57=""),"",IF((NETWORKDAYS.INTL(P57,Q57,1)-1)=0,1,NETWORKDAYS.INTL(P57,Q57,1)-1)) | AL57: =IF(X57="","",AK57=X57) | AM57: =IF(OR(A57="Solicitação de Serviço",A57="Incidente",R57="",S57=""),"",IF((NETWORKDAYS.INTL(R57,S57,1)-1)=0,1,NETWORKDAYS.INTL(R57,S57,1)-1-AJ57)) | AN57: =IF(Y57="","",AM57=Y57) | AO57: =IF(OR(A57="Solicitação de Serviço",A57="Incidente",T57="",U57=""),"",IF((NETWORKDAYS.INTL(T57,U57,1)-1)=0,1,NETWORKDAYS.INTL(T57,U57,1)-1)) | AP57: =IF(Z57="","",AO57=Z57) | AQ57: =IF(OR(A57="Solicitação de Serviço",A57="Incidente",V57="",W57=""),"",IF((NETWORKDAYS.INTL(V57,W57,1)-1)=0,1,IF((NETWORKDAYS.INTL(V57,W57,1)-1)<0,"",NETWORKDAYS.INTL(V57,W57,1)-1))) | AR57: =IF(AA57="","",AQ57=AA57) | AS57: =IF(OR(A57="Solicitação de Serviço",A57="Incidente",P57=""),"",IF(OR(A57="História",A57="Enabler",A57="Débito Técnico"),IF(W57="","",NETWORKDAYS.INTL(P57,W57,1)-1),IF(U57="","",NETWORKDAYS.INTL(P57,U57,1)-1))) | AT57: =IF(OR(A57="Solicitação de Serviço",A57="Incidente",A57="Sustentação"),"",IF(P57="","",IF(OR(A57="História",A57="Enabler",A57="Débito Técnico"),AS57=AC57,AS57=AB57))) | AU57: =IF(M57="","",M57)
A58: Teste | B58: SGTB-2661 | C58: [SGTB] SP 26.3.6 | D58: [Jornada Secretaria e Gestor de Unidades] Thunderbolts | E58: Aceito | F58: [SGTB] PI 3/26 | G58: 2 | H58: [RADE MEC] Teste Integrado com o RADE - Lançamento de Notas - Parte 2 | I58: 2 | J58: 55800 | L58: Itens concluídos | M58: SGTB-1013 | O58: Concluído | P58: 46279.663 | Q58: 46279 | R58: 46283 | S58: 46290 | T58: 46290 | U58: 46290 | V58: 46290 | Z58: 1 | AB58: 9 | AH58: =IF(J58="","",J58/3600) -> 15.5 | AI58: =IF(COUNTIF(AG58, "*dia*"), "VERDADEIRO", "FALSO") -> FALSO | AJ58: =IF(AI58="VERDADEIRO",LEFT(AG58,2),0) -> 0 | AK58: =IF(OR(A58="Solicitação de Serviço",A58="Incidente",P58="",Q58=""),"",IF((NETWORKDAYS.INTL(P58,Q58,1)-1)=0,1,NETWORKDAYS.INTL(P58,Q58,1)-1)) -> 1 | AL58: =IF(X58="","",AK58=X58) | AM58: =IF(OR(A58="Solicitação de Serviço",A58="Incidente",R58="",S58=""),"",IF((NETWORKDAYS.INTL(R58,S58,1)-1)=0,1,NETWORKDAYS.INTL(R58,S58,1)-1-AJ58)) -> 5 | AN58: =IF(Y58="","",AM58=Y58) | AO58: =IF(OR(A58="Solicitação de Serviço",A58="Incidente",T58="",U58=""),"",IF((NETWORKDAYS.INTL(T58,U58,1)-1)=0,1,NETWORKDAYS.INTL(T58,U58,1)-1)) -> 1 | AP58: =IF(Z58="","",AO58=Z58) -> TRUE | AQ58: =IF(OR(A58="Solicitação de Serviço",A58="Incidente",V58="",W58=""),"",IF((NETWORKDAYS.INTL(V58,W58,1)-1)=0,1,IF((NETWORKDAYS.INTL(V58,W58,1)-1)<0,"",NETWORKDAYS.INTL(V58,W58,1)-1))) | AR58: =IF(AA58="","",AQ58=AA58) | AS58: =IF(OR(A58="Solicitação de Serviço",A58="Incidente",P58=""),"",IF(OR(A58="História",A58="Enabler",A58="Débito Técnico"),IF(W58="","",NETWORKDAYS.INTL(P58,W58,1)-1),IF(U58="","",NETWORKDAYS.INTL(P58,U58,1)-1))) -> 9 | AT58: =IF(OR(A58="Solicitação de Serviço",A58="Incidente",A58="Sustentação"),"",IF(P58="","",IF(OR(A58="História",A58="Enabler",A58="Débito Técnico"),AS58=AC58,AS58=AB58))) -> TRUE | AU58: =IF(M58="","",M58) -> SGTB-1013
A59: Enabler | B59: SGTB-2650 | C59: [SGTB] SP 26.3.6 | D59: [Jornada Secretaria e Gestor de Unidades] Thunderbolts | E59: Aceito | F59: [SGTB] PI 3/26 | G59: 2 | H59: Deploy | I59: 2 | J59: 97200 | L59: Itens concluídos | O59: Concluído | P59: 46279.641 | Q59: 46279 | R59: 46290 | S59: 46290 | T59: 46290 | U59: 46290 | V59: 46290 | Y59: 1 | AB59: 9 | AH59: =IF(J59="","",J59/3600) -> 27 | AI59: =IF(COUNTIF(AG59, "*dia*"), "VERDADEIRO", "FALSO") -> FALSO | AJ59: =IF(AI59="VERDADEIRO",LEFT(AG59,2),0) -> 0 | AK59: =IF(OR(A59="Solicitação de Serviço",A59="Incidente",P59="",Q59=""),"",IF((NETWORKDAYS.INTL(P59,Q59,1)-1)=0,1,NETWORKDAYS.INTL(P59,Q59,1)-1)) -> 1 | AL59: =IF(X59="","",AK59=X59) | AM59: =IF(OR(A59="Solicitação de Serviço",A59="Incidente",R59="",S59=""),"",IF((NETWORKDAYS.INTL(R59,S59,1)-1)=0,1,NETWORKDAYS.INTL(R59,S59,1)-1-AJ59)) -> 1 | AN59: =IF(Y59="","",AM59=Y59) -> TRUE | AO59: =IF(OR(A59="Solicitação de Serviço",A59="Incidente",T59="",U59=""),"",IF((NETWORKDAYS.INTL(T59,U59,1)-1)=0,1,NETWORKDAYS.INTL(T59,U59,1)-1)) -> 1 | AP59: =IF(Z59="","",AO59=Z59) | AQ59: =IF(OR(A59="Solicitação de Serviço",A59="Incidente",V59="",W59=""),"",IF((NETWORKDAYS.INTL(V59,W59,1)-1)=0,1,IF((NETWORKDAYS.INTL(V59,W59,1)-1)<0,"",NETWORKDAYS.INTL(V59,W59,1)-1))) | AR59: =IF(AA59="","",AQ59=AA59) | AS59: =IF(OR(A59="Solicitação de Serviço",A59="Incidente",P59=""),"",IF(OR(A59="História",A59="Enabler",A59="Débito Técnico"),IF(W59="","",NETWORKDAYS.INTL(P59,W59,1)-1),IF(U59="","",NETWORKDAYS.INTL(P59,U59,1)-1))) | AT59: =IF(OR(A59="Solicitação de Serviço",A59="Incidente",A59="Sustentação"),"",IF(P59="","",IF(OR(A59="História",A59="Enabler",A59="Débito Técnico"),AS59=AC59,AS59=AB59))) -> TRUE | AU59: =IF(M59="","",M59)
A60: Incidente | B60: SGTB-2643 | C60: [SGTB] SP 26.3.6 | D60: [Jornada Secretaria e Gestor de Unidades] Thunderbolts | E60: Aceito | F60: [SGTB] PI 3/26 | H60: [INC0816364]Tenho um Erro/Problema com o Sistema Colaborar - Colaborar - (Colaborar) Enade | J60: 25200 | L60: Itens concluídos | O60: Concluído | P60: 46279.456 | Q60: 46279 | R60: 46280 | S60: 46280 | AH60: =IF(J60="","",J60/3600) -> 7 | AI60: =IF(COUNTIF(AG60, "*dia*"), "VERDADEIRO", "FALSO") -> FALSO | AJ60: =IF(AI60="VERDADEIRO",LEFT(AG60,2),0) -> 0 | AK60: =IF(OR(A60="Solicitação de Serviço",A60="Incidente",P60="",Q60=""),"",IF((NETWORKDAYS.INTL(P60,Q60,1)-1)=0,1,NETWORKDAYS.INTL(P60,Q60,1)-1)) | AL60: =IF(X60="","",AK60=X60) | AM60: =IF(OR(A60="Solicitação de Serviço",A60="Incidente",R60="",S60=""),"",IF((NETWORKDAYS.INTL(R60,S60,1)-1)=0,1,NETWORKDAYS.INTL(R60,S60,1)-1-AJ60)) | AN60: =IF(Y60="","",AM60=Y60) | AO60: =IF(OR(A60="Solicitação de Serviço",A60="Incidente",T60="",U60=""),"",IF((NETWORKDAYS.INTL(T60,U60,1)-1)=0,1,NETWORKDAYS.INTL(T60,U60,1)-1)) | AP60: =IF(Z60="","",AO60=Z60) | AQ60: =IF(OR(A60="Solicitação de Serviço",A60="Incidente",V60="",W60=""),"",IF((NETWORKDAYS.INTL(V60,W60,1)-1)=0,1,IF((NETWORKDAYS.INTL(V60,W60,1)-1)<0,"",NETWORKDAYS.INTL(V60,W60,1)-1))) | AR60: =IF(AA60="","",AQ60=AA60) | AS60: =IF(OR(A60="Solicitação de Serviço",A60="Incidente",P60=""),"",IF(OR(A60="História",A60="Enabler",A60="Débito Técnico"),IF(W60="","",NETWORKDAYS.INTL(P60,W60,1)-1),IF(U60="","",NETWORKDAYS.INTL(P60,U60,1)-1))) | AT60: =IF(OR(A60="Solicitação de Serviço",A60="Incidente",A60="Sustentação"),"",IF(P60="","",IF(OR(A60="História",A60="Enabler",A60="Débito Técnico"),AS60=AC60,AS60=AB60))) | AU60: =IF(M60="","",M60)
A61: Incidente | B61: SGTB-2637 | C61: [SGTB] SP 26.3.6 | D61: [Jornada Secretaria e Gestor de Unidades] Thunderbolts | E61: Aceito | F61: [SGTB] PI 3/26 | H61: [INC0817335]Tenho um Erro/Problema com o Sistema - Portal Prisma - Prisma - Usuários do Prisma | J61: 900 | L61: Itens concluídos | O61: Concluído | P61: 46276.591 | Q61: 46279 | R61: 46279 | S61: 46279 | AH61: =IF(J61="","",J61/3600) -> 0.25 | AI61: =IF(COUNTIF(AG61, "*dia*"), "VERDADEIRO", "FALSO") -> FALSO | AJ61: =IF(AI61="VERDADEIRO",LEFT(AG61,2),0) -> 0 | AK61: =IF(OR(A61="Solicitação de Serviço",A61="Incidente",P61="",Q61=""),"",IF((NETWORKDAYS.INTL(P61,Q61,1)-1)=0,1,NETWORKDAYS.INTL(P61,Q61,1)-1)) | AL61: =IF(X61="","",AK61=X61) | AM61: =IF(OR(A61="Solicitação de Serviço",A61="Incidente",R61="",S61=""),"",IF((NETWORKDAYS.INTL(R61,S61,1)-1)=0,1,NETWORKDAYS.INTL(R61,S61,1)-1-AJ61)) | AN61: =IF(Y61="","",AM61=Y61) | AO61: =IF(OR(A61="Solicitação de Serviço",A61="Incidente",T61="",U61=""),"",IF((NETWORKDAYS.INTL(T61,U61,1)-1)=0,1,NETWORKDAYS.INTL(T61,U61,1)-1)) | AP61: =IF(Z61="","",AO61=Z61) | AQ61: =IF(OR(A61="Solicitação de Serviço",A61="Incidente",V61="",W61=""),"",IF((NETWORKDAYS.INTL(V61,W61,1)-1)=0,1,IF((NETWORKDAYS.INTL(V61,W61,1)-1)<0,"",NETWORKDAYS.INTL(V61,W61,1)-1))) | AR61: =IF(AA61="","",AQ61=AA61) | AS61: =IF(OR(A61="Solicitação de Serviço",A61="Incidente",P61=""),"",IF(OR(A61="História",A61="Enabler",A61="Débito Técnico"),IF(W61="","",NETWORKDAYS.INTL(P61,W61,1)-1),IF(U61="","",NETWORKDAYS.INTL(P61,U61,1)-1))) | AT61: =IF(OR(A61="Solicitação de Serviço",A61="Incidente",A61="Sustentação"),"",IF(P61="","",IF(OR(A61="História",A61="Enabler",A61="Débito Técnico"),AS61=AC61,AS61=AB61))) | AU61: =IF(M61="","",M61)
A62: Incidente | B62: SGTB-2630 | C62: [SGTB] SP 26.3.6 | D62: [Jornada Secretaria e Gestor de Unidades] Thunderbolts | E62: Aceito | F62: [SGTB] PI 3/26 | H62: [INC0814653]Tenho um Erro/Problema com o Sistema - AVA Presencial/Moodle - Acesso ao AVA/Disciplina | J62: 3600 | L62: Itens concluídos | O62: Concluído | P62: 46275.694 | Q62: 46279 | R62: 46279 | S62: 46279 | AH62: =IF(J62="","",J62/3600) -> 1 | AI62: =IF(COUNTIF(AG62, "*dia*"), "VERDADEIRO", "FALSO") -> FALSO | AJ62: =IF(AI62="VERDADEIRO",LEFT(AG62,2),0) -> 0 | AK62: =IF(OR(A62="Solicitação de Serviço",A62="Incidente",P62="",Q62=""),"",IF((NETWORKDAYS.INTL(P62,Q62,1)-1)=0,1,NETWORKDAYS.INTL(P62,Q62,1)-1)) | AL62: =IF(X62="","",AK62=X62) | AM62: =IF(OR(A62="Solicitação de Serviço",A62="Incidente",R62="",S62=""),"",IF((NETWORKDAYS.INTL(R62,S62,1)-1)=0,1,NETWORKDAYS.INTL(R62,S62,1)-1-AJ62)) | AN62: =IF(Y62="","",AM62=Y62) | AO62: =IF(OR(A62="Solicitação de Serviço",A62="Incidente",T62="",U62=""),"",IF((NETWORKDAYS.INTL(T62,U62,1)-1)=0,1,NETWORKDAYS.INTL(T62,U62,1)-1)) | AP62: =IF(Z62="","",AO62=Z62) | AQ62: =IF(OR(A62="Solicitação de Serviço",A62="Incidente",V62="",W62=""),"",IF((NETWORKDAYS.INTL(V62,W62,1)-1)=0,1,IF((NETWORKDAYS.INTL(V62,W62,1)-1)<0,"",NETWORKDAYS.INTL(V62,W62,1)-1))) | AR62: =IF(AA62="","",AQ62=AA62) | AS62: =IF(OR(A62="Solicitação de Serviço",A62="Incidente",P62=""),"",IF(OR(A62="História",A62="Enabler",A62="Débito Técnico"),IF(W62="","",NETWORKDAYS.INTL(P62,W62,1)-1),IF(U62="","",NETWORKDAYS.INTL(P62,U62,1)-1))) | AT62: =IF(OR(A62="Solicitação de Serviço",A62="Incidente",A62="Sustentação"),"",IF(P62="","",IF(OR(A62="História",A62="Enabler",A62="Débito Técnico"),AS62=AC62,AS62=AB62))) | AU62: =IF(M62="","",M62)
A63: Incidente | B63: SGTB-2624 | C63: [SGTB] SP 26.3.5;[SGTB] SP 26.3.6 | D63: [Jornada Secretaria e Gestor de Unidades] Thunderbolts | E63: Aceito | F63: [SGTB] PI 3/26 | H63: [INC0816985]Tenho um Erro/Problema com o Sistema - Portal Prisma - Prisma - Usuários do Prisma | J63: 900 | L63: Itens concluídos | O63: Concluído | P63: 46275.59 | Q63: 46265 | R63: 46275 | S63: 46275 | AH63: =IF(J63="","",J63/3600) -> 0.25 | AI63: =IF(COUNTIF(AG63, "*dia*"), "VERDADEIRO", "FALSO") -> FALSO | AJ63: =IF(AI63="VERDADEIRO",LEFT(AG63,2),0) -> 0 | AK63: =IF(OR(A63="Solicitação de Serviço",A63="Incidente",P63="",Q63=""),"",IF((NETWORKDAYS.INTL(P63,Q63,1)-1)=0,1,NETWORKDAYS.INTL(P63,Q63,1)-1)) | AL63: =IF(X63="","",AK63=X63) | AM63: =IF(OR(A63="Solicitação de Serviço",A63="Incidente",R63="",S63=""),"",IF((NETWORKDAYS.INTL(R63,S63,1)-1)=0,1,NETWORKDAYS.INTL(R63,S63,1)-1-AJ63)) | AN63: =IF(Y63="","",AM63=Y63) | AO63: =IF(OR(A63="Solicitação de Serviço",A63="Incidente",T63="",U63=""),"",IF((NETWORKDAYS.INTL(T63,U63,1)-1)=0,1,NETWORKDAYS.INTL(T63,U63,1)-1)) | AP63: =IF(Z63="","",AO63=Z63) | AQ63: =IF(OR(A63="Solicitação de Serviço",A63="Incidente",V63="",W63=""),"",IF((NETWORKDAYS.INTL(V63,W63,1)-1)=0,1,IF((NETWORKDAYS.INTL(V63,W63,1)-1)<0,"",NETWORKDAYS.INTL(V63,W63,1)-1))) | AR63: =IF(AA63="","",AQ63=AA63) | AS63: =IF(OR(A63="Solicitação de Serviço",A63="Incidente",P63=""),"",IF(OR(A63="História",A63="Enabler",A63="Débito Técnico"),IF(W63="","",NETWORKDAYS.INTL(P63,W63,1)-1),IF(U63="","",NETWORKDAYS.INTL(P63,U63,1)-1))) | AT63: =IF(OR(A63="Solicitação de Serviço",A63="Incidente",A63="Sustentação"),"",IF(P63="","",IF(OR(A63="História",A63="Enabler",A63="Débito Técnico"),AS63=AC63,AS63=AB63))) | AU63: =IF(M63="","",M63)
A64: Incidente | B64: SGTB-2620 | C64: [SGTB] SP 26.3.5;[SGTB] SP 26.3.6 | D64: [Jornada Secretaria e Gestor de Unidades] Thunderbolts | E64: Aceito | F64: [SGTB] PI 3/26 | H64: [INC0814924]Tenho um Erro/Problema com o Sistema - Portal do Aluno - EaD - Solicitação do Serviço Colaborar | J64: 7200 | L64: Itens concluídos | O64: Concluído | P64: 46275.465 | Q64: 46265 | R64: 46275 | S64: 46275 | AH64: =IF(J64="","",J64/3600) -> 2 | AI64: =IF(COUNTIF(AG64, "*dia*"), "VERDADEIRO", "FALSO") -> FALSO | AJ64: =IF(AI64="VERDADEIRO",LEFT(AG64,2),0) -> 0 | AK64: =IF(OR(A64="Solicitação de Serviço",A64="Incidente",P64="",Q64=""),"",IF((NETWORKDAYS.INTL(P64,Q64,1)-1)=0,1,NETWORKDAYS.INTL(P64,Q64,1)-1)) | AL64: =IF(X64="","",AK64=X64) | AM64: =IF(OR(A64="Solicitação de Serviço",A64="Incidente",R64="",S64=""),"",IF((NETWORKDAYS.INTL(R64,S64,1)-1)=0,1,NETWORKDAYS.INTL(R64,S64,1)-1-AJ64)) | AN64: =IF(Y64="","",AM64=Y64) | AO64: =IF(OR(A64="Solicitação de Serviço",A64="Incidente",T64="",U64=""),"",IF((NETWORKDAYS.INTL(T64,U64,1)-1)=0,1,NETWORKDAYS.INTL(T64,U64,1)-1)) | AP64: =IF(Z64="","",AO64=Z64) | AQ64: =IF(OR(A64="Solicitação de Serviço",A64="Incidente",V64="",W64=""),"",IF((NETWORKDAYS.INTL(V64,W64,1)-1)=0,1,IF((NETWORKDAYS.INTL(V64,W64,1)-1)<0,"",NETWORKDAYS.INTL(V64,W64,1)-1))) | AR64: =IF(AA64="","",AQ64=AA64) | AS64: =IF(OR(A64="Solicitação de Serviço",A64="Incidente",P64=""),"",IF(OR(A64="História",A64="Enabler",A64="Débito Técnico"),IF(W64="","",NETWORKDAYS.INTL(P64,W64,1)-1),IF(U64="","",NETWORKDAYS.INTL(P64,U64,1)-1))) | AT64: =IF(OR(A64="Solicitação de Serviço",A64="Incidente",A64="Sustentação"),"",IF(P64="","",IF(OR(A64="História",A64="Enabler",A64="Débito Técnico"),AS64=AC64,AS64=AB64))) | AU64: =IF(M64="","",M64)
A65: Incidente | B65: SGTB-2613 | C65: [SGTB] SP 26.3.5;[SGTB] SP 26.3.6 | D65: [Jornada Secretaria e Gestor de Unidades] Thunderbolts | E65: Aceito | F65: [SGTB] PI 3/26 | H65: [INC0816751]Tenho um Erro/Problema com o Sistema - Portal Prisma - Prisma - Usuários do Prisma | J65: 600 | L65: Itens concluídos | O65: Concluído | P65: 46274.847 | Q65: 46265 | R65: 46275 | S65: 46275 | AH65: =IF(J65="","",J65/3600) -> 0.16666667 | AI65: =IF(COUNTIF(AG65, "*dia*"), "VERDADEIRO", "FALSO") -> FALSO | AJ65: =IF(AI65="VERDADEIRO",LEFT(AG65,2),0) -> 0 | AK65: =IF(OR(A65="Solicitação de Serviço",A65="Incidente",P65="",Q65=""),"",IF((NETWORKDAYS.INTL(P65,Q65,1)-1)=0,1,NETWORKDAYS.INTL(P65,Q65,1)-1)) | AL65: =IF(X65="","",AK65=X65) | AM65: =IF(OR(A65="Solicitação de Serviço",A65="Incidente",R65="",S65=""),"",IF((NETWORKDAYS.INTL(R65,S65,1)-1)=0,1,NETWORKDAYS.INTL(R65,S65,1)-1-AJ65)) | AN65: =IF(Y65="","",AM65=Y65) | AO65: =IF(OR(A65="Solicitação de Serviço",A65="Incidente",T65="",U65=""),"",IF((NETWORKDAYS.INTL(T65,U65,1)-1)=0,1,NETWORKDAYS.INTL(T65,U65,1)-1)) | AP65: =IF(Z65="","",AO65=Z65) | AQ65: =IF(OR(A65="Solicitação de Serviço",A65="Incidente",V65="",W65=""),"",IF((NETWORKDAYS.INTL(V65,W65,1)-1)=0,1,IF((NETWORKDAYS.INTL(V65,W65,1)-1)<0,"",NETWORKDAYS.INTL(V65,W65,1)-1))) | AR65: =IF(AA65="","",AQ65=AA65) | AS65: =IF(OR(A65="Solicitação de Serviço",A65="Incidente",P65=""),"",IF(OR(A65="História",A65="Enabler",A65="Débito Técnico"),IF(W65="","",NETWORKDAYS.INTL(P65,W65,1)-1),IF(U65="","",NETWORKDAYS.INTL(P65,U65,1)-1))) | AT65: =IF(OR(A65="Solicitação de Serviço",A65="Incidente",A65="Sustentação"),"",IF(P65="","",IF(OR(A65="História",A65="Enabler",A65="Débito Técnico"),AS65=AC65,AS65=AB65))) | AU65: =IF(M65="","",M65)
A66: Incidente | B66: SGTB-2612 | C66: [SGTB] SP 26.3.6 | D66: [Jornada Secretaria e Gestor de Unidades] Thunderbolts | E66: Aceito | F66: [SGTB] PI 3/26 | H66: [INC0816705]Tenho um Erro/Problema com o Sistema - Portal Prisma - Prisma - Usuários do Prisma | J66: 14400 | L66: Itens concluídos | O66: Abertura indevida | P66: 46274.765 | Q66: 46279 | R66: 46280 | AH66: =IF(J66="","",J66/3600) -> 4 | AI66: =IF(COUNTIF(AG66, "*dia*"), "VERDADEIRO", "FALSO") -> FALSO | AJ66: =IF(AI66="VERDADEIRO",LEFT(AG66,2),0) -> 0 | AK66: =IF(OR(A66="Solicitação de Serviço",A66="Incidente",P66="",Q66=""),"",IF((NETWORKDAYS.INTL(P66,Q66,1)-1)=0,1,NETWORKDAYS.INTL(P66,Q66,1)-1)) | AL66: =IF(X66="","",AK66=X66) | AM66: =IF(OR(A66="Solicitação de Serviço",A66="Incidente",R66="",S66=""),"",IF((NETWORKDAYS.INTL(R66,S66,1)-1)=0,1,NETWORKDAYS.INTL(R66,S66,1)-1-AJ66)) | AN66: =IF(Y66="","",AM66=Y66) | AO66: =IF(OR(A66="Solicitação de Serviço",A66="Incidente",T66="",U66=""),"",IF((NETWORKDAYS.INTL(T66,U66,1)-1)=0,1,NETWORKDAYS.INTL(T66,U66,1)-1)) | AP66: =IF(Z66="","",AO66=Z66) | AQ66: =IF(OR(A66="Solicitação de Serviço",A66="Incidente",V66="",W66=""),"",IF((NETWORKDAYS.INTL(V66,W66,1)-1)=0,1,IF((NETWORKDAYS.INTL(V66,W66,1)-1)<0,"",NETWORKDAYS.INTL(V66,W66,1)-1))) | AR66: =IF(AA66="","",AQ66=AA66) | AS66: =IF(OR(A66="Solicitação de Serviço",A66="Incidente",P66=""),"",IF(OR(A66="História",A66="Enabler",A66="Débito Técnico"),IF(W66="","",NETWORKDAYS.INTL(P66,W66,1)-1),IF(U66="","",NETWORKDAYS.INTL(P66,U66,1)-1))) | AT66: =IF(OR(A66="Solicitação de Serviço",A66="Incidente",A66="Sustentação"),"",IF(P66="","",IF(OR(A66="História",A66="Enabler",A66="Débito Técnico"),AS66=AC66,AS66=AB66))) | AU66: =IF(M66="","",M66)
A67: Solicitação de Serviço | B67: SGTB-2609 | C67: [SGTB] SP 26.3.6 | D67: [Jornada Secretaria e Gestor de Unidades] Thunderbolts | E67: Aceito | F67: [SGTB] PI 3/26 | H67: [RITM0736644]Solicitar um Serviço de Liberação de Acesso e Reset de Senha - Olimpo | J67: 3600 | L67: Itens concluídos | O67: Concluído | P67: 46274.707 | Q67: 46279 | R67: 46279 | S67: 46279 | AH67: =IF(J67="","",J67/3600) -> 1 | AI67: =IF(COUNTIF(AG67, "*dia*"), "VERDADEIRO", "FALSO") -> FALSO | AJ67: =IF(AI67="VERDADEIRO",LEFT(AG67,2),0) -> 0 | AK67: =IF(OR(A67="Solicitação de Serviço",A67="Incidente",P67="",Q67=""),"",IF((NETWORKDAYS.INTL(P67,Q67,1)-1)=0,1,NETWORKDAYS.INTL(P67,Q67,1)-1)) | AL67: =IF(X67="","",AK67=X67) | AM67: =IF(OR(A67="Solicitação de Serviço",A67="Incidente",R67="",S67=""),"",IF((NETWORKDAYS.INTL(R67,S67,1)-1)=0,1,NETWORKDAYS.INTL(R67,S67,1)-1-AJ67)) | AN67: =IF(Y67="","",AM67=Y67) | AO67: =IF(OR(A67="Solicitação de Serviço",A67="Incidente",T67="",U67=""),"",IF((NETWORKDAYS.INTL(T67,U67,1)-1)=0,1,NETWORKDAYS.INTL(T67,U67,1)-1)) | AP67: =IF(Z67="","",AO67=Z67) | AQ67: =IF(OR(A67="Solicitação de Serviço",A67="Incidente",V67="",W67=""),"",IF((NETWORKDAYS.INTL(V67,W67,1)-1)=0,1,IF((NETWORKDAYS.INTL(V67,W67,1)-1)<0,"",NETWORKDAYS.INTL(V67,W67,1)-1))) | AR67: =IF(AA67="","",AQ67=AA67) | AS67: =IF(OR(A67="Solicitação de Serviço",A67="Incidente",P67=""),"",IF(OR(A67="História",A67="Enabler",A67="Débito Técnico"),IF(W67="","",NETWORKDAYS.INTL(P67,W67,1)-1),IF(U67="","",NETWORKDAYS.INTL(P67,U67,1)-1))) | AT67: =IF(OR(A67="Solicitação de Serviço",A67="Incidente",A67="Sustentação"),"",IF(P67="","",IF(OR(A67="História",A67="Enabler",A67="Débito Técnico"),AS67=AC67,AS67=AB67))) | AU67: =IF(M67="","",M67)
A68: Solicitação de Serviço | B68: SGTB-2608 | C68: [SGTB] SP 26.3.5;[SGTB] SP 26.3.6 | D68: [Jornada Secretaria e Gestor de Unidades] Thunderbolts | E68: Aceito | F68: [SGTB] PI 3/26 | H68: [RITM0742000]Solicitar Serviço ao Sistema - Olimpo - Ministrada - Olimpo - Ministrada | J68: 14400 | L68: Itens concluídos | O68: Concluído | P68: 46274.664 | Q68: 46265 | R68: 46275 | S68: 46275 | AH68: =IF(J68="","",J68/3600) -> 4 | AI68: =IF(COUNTIF(AG68, "*dia*"), "VERDADEIRO", "FALSO") -> FALSO | AJ68: =IF(AI68="VERDADEIRO",LEFT(AG68,2),0) -> 0 | AK68: =IF(OR(A68="Solicitação de Serviço",A68="Incidente",P68="",Q68=""),"",IF((NETWORKDAYS.INTL(P68,Q68,1)-1)=0,1,NETWORKDAYS.INTL(P68,Q68,1)-1)) | AL68: =IF(X68="","",AK68=X68) | AM68: =IF(OR(A68="Solicitação de Serviço",A68="Incidente",R68="",S68=""),"",IF((NETWORKDAYS.INTL(R68,S68,1)-1)=0,1,NETWORKDAYS.INTL(R68,S68,1)-1-AJ68)) | AN68: =IF(Y68="","",AM68=Y68) | AO68: =IF(OR(A68="Solicitação de Serviço",A68="Incidente",T68="",U68=""),"",IF((NETWORKDAYS.INTL(T68,U68,1)-1)=0,1,NETWORKDAYS.INTL(T68,U68,1)-1)) | AP68: =IF(Z68="","",AO68=Z68) | AQ68: =IF(OR(A68="Solicitação de Serviço",A68="Incidente",V68="",W68=""),"",IF((NETWORKDAYS.INTL(V68,W68,1)-1)=0,1,IF((NETWORKDAYS.INTL(V68,W68,1)-1)<0,"",NETWORKDAYS.INTL(V68,W68,1)-1))) | AR68: =IF(AA68="","",AQ68=AA68) | AS68: =IF(OR(A68="Solicitação de Serviço",A68="Incidente",P68=""),"",IF(OR(A68="História",A68="Enabler",A68="Débito Técnico"),IF(W68="","",NETWORKDAYS.INTL(P68,W68,1)-1),IF(U68="","",NETWORKDAYS.INTL(P68,U68,1)-1))) | AT68: =IF(OR(A68="Solicitação de Serviço",A68="Incidente",A68="Sustentação"),"",IF(P68="","",IF(OR(A68="História",A68="Enabler",A68="Débito Técnico"),AS68=AC68,AS68=AB68))) | AU68: =IF(M68="","",M68)
A69: Solicitação de Serviço | B69: SGTB-2606 | C69: [SGTB] SP 26.3.6 | D69: [Jornada Secretaria e Gestor de Unidades] Thunderbolts | E69: Aceito | F69: [SGTB] PI 3/26 | H69: [RITM0741969]Solicitar Serviço ao Sistema - Portal do Professor - Portal do Professor | J69: 3600 | L69: Itens concluídos | O69: Concluído | P69: 46274.55 | Q69: 46279 | R69: 46281 | S69: 46281 | AH69: =IF(J69="","",J69/3600) -> 1 | AI69: =IF(COUNTIF(AG69, "*dia*"), "VERDADEIRO", "FALSO") -> FALSO | AJ69: =IF(AI69="VERDADEIRO",LEFT(AG69,2),0) -> 0 | AK69: =IF(OR(A69="Solicitação de Serviço",A69="Incidente",P69="",Q69=""),"",IF((NETWORKDAYS.INTL(P69,Q69,1)-1)=0,1,NETWORKDAYS.INTL(P69,Q69,1)-1)) | AL69: =IF(X69="","",AK69=X69) | AM69: =IF(OR(A69="Solicitação de Serviço",A69="Incidente",R69="",S69=""),"",IF((NETWORKDAYS.INTL(R69,S69,1)-1)=0,1,NETWORKDAYS.INTL(R69,S69,1)-1-AJ69)) | AN69: =IF(Y69="","",AM69=Y69) | AO69: =IF(OR(A69="Solicitação de Serviço",A69="Incidente",T69="",U69=""),"",IF((NETWORKDAYS.INTL(T69,U69,1)-1)=0,1,NETWORKDAYS.INTL(T69,U69,1)-1)) | AP69: =IF(Z69="","",AO69=Z69) | AQ69: =IF(OR(A69="Solicitação de Serviço",A69="Incidente",V69="",W69=""),"",IF((NETWORKDAYS.INTL(V69,W69,1)-1)=0,1,IF((NETWORKDAYS.INTL(V69,W69,1)-1)<0,"",NETWORKDAYS.INTL(V69,W69,1)-1))) | AR69: =IF(AA69="","",AQ69=AA69) | AS69: =IF(OR(A69="Solicitação de Serviço",A69="Incidente",P69=""),"",IF(OR(A69="História",A69="Enabler",A69="Débito Técnico"),IF(W69="","",NETWORKDAYS.INTL(P69,W69,1)-1),IF(U69="","",NETWORKDAYS.INTL(P69,U69,1)-1))) | AT69: =IF(OR(A69="Solicitação de Serviço",A69="Incidente",A69="Sustentação"),"",IF(P69="","",IF(OR(A69="História",A69="Enabler",A69="Débito Técnico"),AS69=AC69,AS69=AB69))) | AU69: =IF(M69="","",M69)
A70: Incidente | B70: SGTB-2605 | C70: [SGTB] SP 26.3.5 | D70: [Jornada Secretaria e Gestor de Unidades] Thunderbolts | E70: Aceito | F70: [SGTB] PI 3/26 | H70: [INC0814488]Tenho um Erro/Problema com o Sistema - PDA:Portal do aluno - Graduação - Erro no Ajuste de horário | J70: 10800 | L70: Itens concluídos | O70: Concluído | P70: 46274.512 | Q70: 46265 | R70: 46276 | S70: 46276 | AH70: =IF(J70="","",J70/3600) -> 3 | AI70: =IF(COUNTIF(AG70, "*dia*"), "VERDADEIRO", "FALSO") -> FALSO | AJ70: =IF(AI70="VERDADEIRO",LEFT(AG70,2),0) -> 0 | AK70: =IF(OR(A70="Solicitação de Serviço",A70="Incidente",P70="",Q70=""),"",IF((NETWORKDAYS.INTL(P70,Q70,1)-1)=0,1,NETWORKDAYS.INTL(P70,Q70,1)-1)) | AL70: =IF(X70="","",AK70=X70) | AM70: =IF(OR(A70="Solicitação de Serviço",A70="Incidente",R70="",S70=""),"",IF((NETWORKDAYS.INTL(R70,S70,1)-1)=0,1,NETWORKDAYS.INTL(R70,S70,1)-1-AJ70)) | AN70: =IF(Y70="","",AM70=Y70) | AO70: =IF(OR(A70="Solicitação de Serviço",A70="Incidente",T70="",U70=""),"",IF((NETWORKDAYS.INTL(T70,U70,1)-1)=0,1,NETWORKDAYS.INTL(T70,U70,1)-1)) | AP70: =IF(Z70="","",AO70=Z70) | AQ70: =IF(OR(A70="Solicitação de Serviço",A70="Incidente",V70="",W70=""),"",IF((NETWORKDAYS.INTL(V70,W70,1)-1)=0,1,IF((NETWORKDAYS.INTL(V70,W70,1)-1)<0,"",NETWORKDAYS.INTL(V70,W70,1)-1))) | AR70: =IF(AA70="","",AQ70=AA70) | AS70: =IF(OR(A70="Solicitação de Serviço",A70="Incidente",P70=""),"",IF(OR(A70="História",A70="Enabler",A70="Débito Técnico"),IF(W70="","",NETWORKDAYS.INTL(P70,W70,1)-1),IF(U70="","",NETWORKDAYS.INTL(P70,U70,1)-1))) | AT70: =IF(OR(A70="Solicitação de Serviço",A70="Incidente",A70="Sustentação"),"",IF(P70="","",IF(OR(A70="História",A70="Enabler",A70="Débito Técnico"),AS70=AC70,AS70=AB70))) | AU70: =IF(M70="","",M70)
A71: Incidente | B71: SGTB-2604 | C71: [SGTB] SP 26.3.5 | D71: [Jornada Secretaria e Gestor de Unidades] Thunderbolts | E71: Aceito | F71: [SGTB] PI 3/26 | H71: [INC0813281]Tenho um Erro/Problema com o Sistema Colaborar - Colaborar - Chat | J71: 7200 | L71: Itens concluídos | O71: Abertura indevida | P71: 46274.476 | Q71: 46265 | R71: 46275 | AH71: =IF(J71="","",J71/3600) -> 2 | AI71: =IF(COUNTIF(AG71, "*dia*"), "VERDADEIRO", "FALSO") -> FALSO | AJ71: =IF(AI71="VERDADEIRO",LEFT(AG71,2),0) -> 0 | AK71: =IF(OR(A71="Solicitação de Serviço",A71="Incidente",P71="",Q71=""),"",IF((NETWORKDAYS.INTL(P71,Q71,1)-1)=0,1,NETWORKDAYS.INTL(P71,Q71,1)-1)) | AL71: =IF(X71="","",AK71=X71) | AM71: =IF(OR(A71="Solicitação de Serviço",A71="Incidente",R71="",S71=""),"",IF((NETWORKDAYS.INTL(R71,S71,1)-1)=0,1,NETWORKDAYS.INTL(R71,S71,1)-1-AJ71)) | AN71: =IF(Y71="","",AM71=Y71) | AO71: =IF(OR(A71="Solicitação de Serviço",A71="Incidente",T71="",U71=""),"",IF((NETWORKDAYS.INTL(T71,U71,1)-1)=0,1,NETWORKDAYS.INTL(T71,U71,1)-1)) | AP71: =IF(Z71="","",AO71=Z71) | AQ71: =IF(OR(A71="Solicitação de Serviço",A71="Incidente",V71="",W71=""),"",IF((NETWORKDAYS.INTL(V71,W71,1)-1)=0,1,IF((NETWORKDAYS.INTL(V71,W71,1)-1)<0,"",NETWORKDAYS.INTL(V71,W71,1)-1))) | AR71: =IF(AA71="","",AQ71=AA71) | AS71: =IF(OR(A71="Solicitação de Serviço",A71="Incidente",P71=""),"",IF(OR(A71="História",A71="Enabler",A71="Débito Técnico"),IF(W71="","",NETWORKDAYS.INTL(P71,W71,1)-1),IF(U71="","",NETWORKDAYS.INTL(P71,U71,1)-1))) | AT71: =IF(OR(A71="Solicitação de Serviço",A71="Incidente",A71="Sustentação"),"",IF(P71="","",IF(OR(A71="História",A71="Enabler",A71="Débito Técnico"),AS71=AC71,AS71=AB71))) | AU71: =IF(M71="","",M71)
A72: Incidente | B72: SGTB-2603 | C72: [SGTB] SP 26.3.5 | D72: [Jornada Secretaria e Gestor de Unidades] Thunderbolts | E72: Aceito | F72: [SGTB] PI 3/26 | H72: [INC0816086]Tenho um Erro/Problema com o PTC - Ingresso - Captação - Backoffice | J72: 600 | L72: Itens concluídos | O72: Abertura indevida | P72: 46274.434 | Q72: 46265 | R72: 46274 | AH72: =IF(J72="","",J72/3600) -> 0.16666667 | AI72: =IF(COUNTIF(AG72, "*dia*"), "VERDADEIRO", "FALSO") -> FALSO | AJ72: =IF(AI72="VERDADEIRO",LEFT(AG72,2),0) -> 0 | AK72: =IF(OR(A72="Solicitação de Serviço",A72="Incidente",P72="",Q72=""),"",IF((NETWORKDAYS.INTL(P72,Q72,1)-1)=0,1,NETWORKDAYS.INTL(P72,Q72,1)-1)) | AL72: =IF(X72="","",AK72=X72) | AM72: =IF(OR(A72="Solicitação de Serviço",A72="Incidente",R72="",S72=""),"",IF((NETWORKDAYS.INTL(R72,S72,1)-1)=0,1,NETWORKDAYS.INTL(R72,S72,1)-1-AJ72)) | AN72: =IF(Y72="","",AM72=Y72) | AO72: =IF(OR(A72="Solicitação de Serviço",A72="Incidente",T72="",U72=""),"",IF((NETWORKDAYS.INTL(T72,U72,1)-1)=0,1,NETWORKDAYS.INTL(T72,U72,1)-1)) | AP72: =IF(Z72="","",AO72=Z72) | AQ72: =IF(OR(A72="Solicitação de Serviço",A72="Incidente",V72="",W72=""),"",IF((NETWORKDAYS.INTL(V72,W72,1)-1)=0,1,IF((NETWORKDAYS.INTL(V72,W72,1)-1)<0,"",NETWORKDAYS.INTL(V72,W72,1)-1))) | AR72: =IF(AA72="","",AQ72=AA72) | AS72: =IF(OR(A72="Solicitação de Serviço",A72="Incidente",P72=""),"",IF(OR(A72="História",A72="Enabler",A72="Débito Técnico"),IF(W72="","",NETWORKDAYS.INTL(P72,W72,1)-1),IF(U72="","",NETWORKDAYS.INTL(P72,U72,1)-1))) | AT72: =IF(OR(A72="Solicitação de Serviço",A72="Incidente",A72="Sustentação"),"",IF(P72="","",IF(OR(A72="História",A72="Enabler",A72="Débito Técnico"),AS72=AC72,AS72=AB72))) | AU72: =IF(M72="","",M72)
A73: Incidente | B73: SGTB-2602 | C73: [SGTB] SP 26.3.5;[SGTB] SP 26.3.6 | D73: [Jornada Secretaria e Gestor de Unidades] Thunderbolts | E73: Aceito | F73: [SGTB] PI 3/26 | H73: [INC0813879]Tenho um Erro/Problema com o Sistema - AVA (LMS) - AVA (LMS) | J73: 1800 | L73: Itens concluídos | O73: Concluído | P73: 46274.431 | Q73: 46265 | R73: 46275 | S73: 46275 | AH73: =IF(J73="","",J73/3600) -> 0.5 | AI73: =IF(COUNTIF(AG73, "*dia*"), "VERDADEIRO", "FALSO") -> FALSO | AJ73: =IF(AI73="VERDADEIRO",LEFT(AG73,2),0) -> 0 | AK73: =IF(OR(A73="Solicitação de Serviço",A73="Incidente",P73="",Q73=""),"",IF((NETWORKDAYS.INTL(P73,Q73,1)-1)=0,1,NETWORKDAYS.INTL(P73,Q73,1)-1)) | AL73: =IF(X73="","",AK73=X73) | AM73: =IF(OR(A73="Solicitação de Serviço",A73="Incidente",R73="",S73=""),"",IF((NETWORKDAYS.INTL(R73,S73,1)-1)=0,1,NETWORKDAYS.INTL(R73,S73,1)-1-AJ73)) | AN73: =IF(Y73="","",AM73=Y73) | AO73: =IF(OR(A73="Solicitação de Serviço",A73="Incidente",T73="",U73=""),"",IF((NETWORKDAYS.INTL(T73,U73,1)-1)=0,1,NETWORKDAYS.INTL(T73,U73,1)-1)) | AP73: =IF(Z73="","",AO73=Z73) | AQ73: =IF(OR(A73="Solicitação de Serviço",A73="Incidente",V73="",W73=""),"",IF((NETWORKDAYS.INTL(V73,W73,1)-1)=0,1,IF((NETWORKDAYS.INTL(V73,W73,1)-1)<0,"",NETWORKDAYS.INTL(V73,W73,1)-1))) | AR73: =IF(AA73="","",AQ73=AA73) | AS73: =IF(OR(A73="Solicitação de Serviço",A73="Incidente",P73=""),"",IF(OR(A73="História",A73="Enabler",A73="Débito Técnico"),IF(W73="","",NETWORKDAYS.INTL(P73,W73,1)-1),IF(U73="","",NETWORKDAYS.INTL(P73,U73,1)-1))) | AT73: =IF(OR(A73="Solicitação de Serviço",A73="Incidente",A73="Sustentação"),"",IF(P73="","",IF(OR(A73="História",A73="Enabler",A73="Débito Técnico"),AS73=AC73,AS73=AB73))) | AU73: =IF(M73="","",M73)
A74: Incidente | B74: SGTB-2601 | C74: [SGTB] SP 26.3.5 | D74: [Jornada Secretaria e Gestor de Unidades] Thunderbolts | E74: Aceito | F74: [SGTB] PI 3/26 | H74: [INC0804216]Tenho um Erro/Problema com o Sistema - Extranet Contrato - Extranet Contrato | L74: Itens concluídos | O74: Abertura indevida | P74: 46274.428 | Q74: 46265 | R74: 46274 | AH74: =IF(J74="","",J74/3600) | AI74: =IF(COUNTIF(AG74, "*dia*"), "VERDADEIRO", "FALSO") -> FALSO | AJ74: =IF(AI74="VERDADEIRO",LEFT(AG74,2),0) -> 0 | AK74: =IF(OR(A74="Solicitação de Serviço",A74="Incidente",P74="",Q74=""),"",IF((NETWORKDAYS.INTL(P74,Q74,1)-1)=0,1,NETWORKDAYS.INTL(P74,Q74,1)-1)) | AL74: =IF(X74="","",AK74=X74) | AM74: =IF(OR(A74="Solicitação de Serviço",A74="Incidente",R74="",S74=""),"",IF((NETWORKDAYS.INTL(R74,S74,1)-1)=0,1,NETWORKDAYS.INTL(R74,S74,1)-1-AJ74)) | AN74: =IF(Y74="","",AM74=Y74) | AO74: =IF(OR(A74="Solicitação de Serviço",A74="Incidente",T74="",U74=""),"",IF((NETWORKDAYS.INTL(T74,U74,1)-1)=0,1,NETWORKDAYS.INTL(T74,U74,1)-1)) | AP74: =IF(Z74="","",AO74=Z74) | AQ74: =IF(OR(A74="Solicitação de Serviço",A74="Incidente",V74="",W74=""),"",IF((NETWORKDAYS.INTL(V74,W74,1)-1)=0,1,IF((NETWORKDAYS.INTL(V74,W74,1)-1)<0,"",NETWORKDAYS.INTL(V74,W74,1)-1))) | AR74: =IF(AA74="","",AQ74=AA74) | AS74: =IF(OR(A74="Solicitação de Serviço",A74="Incidente",P74=""),"",IF(OR(A74="História",A74="Enabler",A74="Débito Técnico"),IF(W74="","",NETWORKDAYS.INTL(P74,W74,1)-1),IF(U74="","",NETWORKDAYS.INTL(P74,U74,1)-1))) | AT74: =IF(OR(A74="Solicitação de Serviço",A74="Incidente",A74="Sustentação"),"",IF(P74="","",IF(OR(A74="História",A74="Enabler",A74="Débito Técnico"),AS74=AC74,AS74=AB74))) | AU74: =IF(M74="","",M74)
A75: Incidente | B75: SGTB-2600 | C75: [SGTB] SP 26.3.5;[SGTB] SP 26.3.6 | D75: [Jornada Secretaria e Gestor de Unidades] Thunderbolts | E75: Aceito | F75: [SGTB] PI 3/26 | H75: [INC0816190]Tenho um Erro/Problema com o Sistema - AVA 3.0 - Login Colaborar/AVA 3.0 | J75: 900 | L75: Itens concluídos | O75: Concluído | P75: 46274.427 | Q75: 46265 | R75: 46275 | S75: 46275 | AH75: =IF(J75="","",J75/3600) -> 0.25 | AI75: =IF(COUNTIF(AG75, "*dia*"), "VERDADEIRO", "FALSO") -> FALSO | AJ75: =IF(AI75="VERDADEIRO",LEFT(AG75,2),0) -> 0 | AK75: =IF(OR(A75="Solicitação de Serviço",A75="Incidente",P75="",Q75=""),"",IF((NETWORKDAYS.INTL(P75,Q75,1)-1)=0,1,NETWORKDAYS.INTL(P75,Q75,1)-1)) | AL75: =IF(X75="","",AK75=X75) | AM75: =IF(OR(A75="Solicitação de Serviço",A75="Incidente",R75="",S75=""),"",IF((NETWORKDAYS.INTL(R75,S75,1)-1)=0,1,NETWORKDAYS.INTL(R75,S75,1)-1-AJ75)) | AN75: =IF(Y75="","",AM75=Y75) | AO75: =IF(OR(A75="Solicitação de Serviço",A75="Incidente",T75="",U75=""),"",IF((NETWORKDAYS.INTL(T75,U75,1)-1)=0,1,NETWORKDAYS.INTL(T75,U75,1)-1)) | AP75: =IF(Z75="","",AO75=Z75) | AQ75: =IF(OR(A75="Solicitação de Serviço",A75="Incidente",V75="",W75=""),"",IF((NETWORKDAYS.INTL(V75,W75,1)-1)=0,1,IF((NETWORKDAYS.INTL(V75,W75,1)-1)<0,"",NETWORKDAYS.INTL(V75,W75,1)-1))) | AR75: =IF(AA75="","",AQ75=AA75) | AS75: =IF(OR(A75="Solicitação de Serviço",A75="Incidente",P75=""),"",IF(OR(A75="História",A75="Enabler",A75="Débito Técnico"),IF(W75="","",NETWORKDAYS.INTL(P75,W75,1)-1),IF(U75="","",NETWORKDAYS.INTL(P75,U75,1)-1))) | AT75: =IF(OR(A75="Solicitação de Serviço",A75="Incidente",A75="Sustentação"),"",IF(P75="","",IF(OR(A75="História",A75="Enabler",A75="Débito Técnico"),AS75=AC75,AS75=AB75))) | AU75: =IF(M75="","",M75)
A76: Incidente | B76: SGTB-2599 | C76: [SGTB] SP 26.3.5 | D76: [Jornada Secretaria e Gestor de Unidades] Thunderbolts | E76: Aceito | F76: [SGTB] PI 3/26 | H76: [INC0816251]Tenho um Erro/Problema com o Sistema - AVA Presencial - Moodle (LMS) | J76: 900 | L76: Itens concluídos | O76: Concluído | P76: 46274.426 | Q76: 46265 | R76: 46275 | S76: 46275 | AH76: =IF(J76="","",J76/3600) -> 0.25 | AI76: =IF(COUNTIF(AG76, "*dia*"), "VERDADEIRO", "FALSO") -> FALSO | AJ76: =IF(AI76="VERDADEIRO",LEFT(AG76,2),0) -> 0 | AK76: =IF(OR(A76="Solicitação de Serviço",A76="Incidente",P76="",Q76=""),"",IF((NETWORKDAYS.INTL(P76,Q76,1)-1)=0,1,NETWORKDAYS.INTL(P76,Q76,1)-1)) | AL76: =IF(X76="","",AK76=X76) | AM76: =IF(OR(A76="Solicitação de Serviço",A76="Incidente",R76="",S76=""),"",IF((NETWORKDAYS.INTL(R76,S76,1)-1)=0,1,NETWORKDAYS.INTL(R76,S76,1)-1-AJ76)) | AN76: =IF(Y76="","",AM76=Y76) | AO76: =IF(OR(A76="Solicitação de Serviço",A76="Incidente",T76="",U76=""),"",IF((NETWORKDAYS.INTL(T76,U76,1)-1)=0,1,NETWORKDAYS.INTL(T76,U76,1)-1)) | AP76: =IF(Z76="","",AO76=Z76) | AQ76: =IF(OR(A76="Solicitação de Serviço",A76="Incidente",V76="",W76=""),"",IF((NETWORKDAYS.INTL(V76,W76,1)-1)=0,1,IF((NETWORKDAYS.INTL(V76,W76,1)-1)<0,"",NETWORKDAYS.INTL(V76,W76,1)-1))) | AR76: =IF(AA76="","",AQ76=AA76) | AS76: =IF(OR(A76="Solicitação de Serviço",A76="Incidente",P76=""),"",IF(OR(A76="História",A76="Enabler",A76="Débito Técnico"),IF(W76="","",NETWORKDAYS.INTL(P76,W76,1)-1),IF(U76="","",NETWORKDAYS.INTL(P76,U76,1)-1))) | AT76: =IF(OR(A76="Solicitação de Serviço",A76="Incidente",A76="Sustentação"),"",IF(P76="","",IF(OR(A76="História",A76="Enabler",A76="Débito Técnico"),AS76=AC76,AS76=AB76))) | AU76: =IF(M76="","",M76)
A77: Incidente | B77: SGTB-2597 | C77: [SGTB] SP 26.3.5 | D77: [Jornada Secretaria e Gestor de Unidades] Thunderbolts | E77: Aceito | F77: [SGTB] PI 3/26 | H77: [INC0816369]Tenho um Erro/Problema com o Sistema - Olimpo - BD - ALUNO Schema | J77: 1800 | L77: Itens concluídos | O77: Concluído | P77: 46274.393 | Q77: 46265 | R77: 46275 | S77: 46275 | AH77: =IF(J77="","",J77/3600) -> 0.5 | AI77: =IF(COUNTIF(AG77, "*dia*"), "VERDADEIRO", "FALSO") -> FALSO | AJ77: =IF(AI77="VERDADEIRO",LEFT(AG77,2),0) -> 0 | AK77: =IF(OR(A77="Solicitação de Serviço",A77="Incidente",P77="",Q77=""),"",IF((NETWORKDAYS.INTL(P77,Q77,1)-1)=0,1,NETWORKDAYS.INTL(P77,Q77,1)-1)) | AL77: =IF(X77="","",AK77=X77) | AM77: =IF(OR(A77="Solicitação de Serviço",A77="Incidente",R77="",S77=""),"",IF((NETWORKDAYS.INTL(R77,S77,1)-1)=0,1,NETWORKDAYS.INTL(R77,S77,1)-1-AJ77)) | AN77: =IF(Y77="","",AM77=Y77) | AO77: =IF(OR(A77="Solicitação de Serviço",A77="Incidente",T77="",U77=""),"",IF((NETWORKDAYS.INTL(T77,U77,1)-1)=0,1,NETWORKDAYS.INTL(T77,U77,1)-1)) | AP77: =IF(Z77="","",AO77=Z77) | AQ77: =IF(OR(A77="Solicitação de Serviço",A77="Incidente",V77="",W77=""),"",IF((NETWORKDAYS.INTL(V77,W77,1)-1)=0,1,IF((NETWORKDAYS.INTL(V77,W77,1)-1)<0,"",NETWORKDAYS.INTL(V77,W77,1)-1))) | AR77: =IF(AA77="","",AQ77=AA77) | AS77: =IF(OR(A77="Solicitação de Serviço",A77="Incidente",P77=""),"",IF(OR(A77="História",A77="Enabler",A77="Débito Técnico"),IF(W77="","",NETWORKDAYS.INTL(P77,W77,1)-1),IF(U77="","",NETWORKDAYS.INTL(P77,U77,1)-1))) | AT77: =IF(OR(A77="Solicitação de Serviço",A77="Incidente",A77="Sustentação"),"",IF(P77="","",IF(OR(A77="História",A77="Enabler",A77="Débito Técnico"),AS77=AC77,AS77=AB77))) | AU77: =IF(M77="","",M77)
A78: Incidente | B78: SGTB-2594 | C78: [SGTB] SP 26.3.6 | D78: [Jornada Secretaria e Gestor de Unidades] Thunderbolts | E78: Aceito | F78: [SGTB] PI 3/26 | H78: [INC0815993]Tenho um Erro/Problema no Dynamics - Gestão de unidades - Reportar um erro/problema | J78: 3600 | L78: Itens concluídos | O78: Concluído | P78: 46273.653 | Q78: 46279 | R78: 46279 | S78: 46280 | AH78: =IF(J78="","",J78/3600) -> 1 | AI78: =IF(COUNTIF(AG78, "*dia*"), "VERDADEIRO", "FALSO") -> FALSO | AJ78: =IF(AI78="VERDADEIRO",LEFT(AG78,2),0) -> 0 | AK78: =IF(OR(A78="Solicitação de Serviço",A78="Incidente",P78="",Q78=""),"",IF((NETWORKDAYS.INTL(P78,Q78,1)-1)=0,1,NETWORKDAYS.INTL(P78,Q78,1)-1)) | AL78: =IF(X78="","",AK78=X78) | AM78: =IF(OR(A78="Solicitação de Serviço",A78="Incidente",R78="",S78=""),"",IF((NETWORKDAYS.INTL(R78,S78,1)-1)=0,1,NETWORKDAYS.INTL(R78,S78,1)-1-AJ78)) | AN78: =IF(Y78="","",AM78=Y78) | AO78: =IF(OR(A78="Solicitação de Serviço",A78="Incidente",T78="",U78=""),"",IF((NETWORKDAYS.INTL(T78,U78,1)-1)=0,1,NETWORKDAYS.INTL(T78,U78,1)-1)) | AP78: =IF(Z78="","",AO78=Z78) | AQ78: =IF(OR(A78="Solicitação de Serviço",A78="Incidente",V78="",W78=""),"",IF((NETWORKDAYS.INTL(V78,W78,1)-1)=0,1,IF((NETWORKDAYS.INTL(V78,W78,1)-1)<0,"",NETWORKDAYS.INTL(V78,W78,1)-1))) | AR78: =IF(AA78="","",AQ78=AA78) | AS78: =IF(OR(A78="Solicitação de Serviço",A78="Incidente",P78=""),"",IF(OR(A78="História",A78="Enabler",A78="Débito Técnico"),IF(W78="","",NETWORKDAYS.INTL(P78,W78,1)-1),IF(U78="","",NETWORKDAYS.INTL(P78,U78,1)-1))) | AT78: =IF(OR(A78="Solicitação de Serviço",A78="Incidente",A78="Sustentação"),"",IF(P78="","",IF(OR(A78="História",A78="Enabler",A78="Débito Técnico"),AS78=AC78,AS78=AB78))) | AU78: =IF(M78="","",M78)
A79: Incidente | B79: SGTB-2591 | C79: [SGTB] SP 26.3.6 | D79: [Jornada Secretaria e Gestor de Unidades] Thunderbolts | E79: Aceito | F79: [SGTB] PI 3/26 | H79: [INC0816173]Tenho um Erro/Problema com o Sistema - Portal Prisma - Prisma - Usuários do Prisma | J79: 25200 | L79: Itens concluídos | O79: Concluído | P79: 46273.633 | Q79: 46279 | R79: 46274 | S79: 46280 | AH79: =IF(J79="","",J79/3600) -> 7 | AI79: =IF(COUNTIF(AG79, "*dia*"), "VERDADEIRO", "FALSO") -> FALSO | AJ79: =IF(AI79="VERDADEIRO",LEFT(AG79,2),0) -> 0 | AK79: =IF(OR(A79="Solicitação de Serviço",A79="Incidente",P79="",Q79=""),"",IF((NETWORKDAYS.INTL(P79,Q79,1)-1)=0,1,NETWORKDAYS.INTL(P79,Q79,1)-1)) | AL79: =IF(X79="","",AK79=X79) | AM79: =IF(OR(A79="Solicitação de Serviço",A79="Incidente",R79="",S79=""),"",IF((NETWORKDAYS.INTL(R79,S79,1)-1)=0,1,NETWORKDAYS.INTL(R79,S79,1)-1-AJ79)) | AN79: =IF(Y79="","",AM79=Y79) | AO79: =IF(OR(A79="Solicitação de Serviço",A79="Incidente",T79="",U79=""),"",IF((NETWORKDAYS.INTL(T79,U79,1)-1)=0,1,NETWORKDAYS.INTL(T79,U79,1)-1)) | AP79: =IF(Z79="","",AO79=Z79) | AQ79: =IF(OR(A79="Solicitação de Serviço",A79="Incidente",V79="",W79=""),"",IF((NETWORKDAYS.INTL(V79,W79,1)-1)=0,1,IF((NETWORKDAYS.INTL(V79,W79,1)-1)<0,"",NETWORKDAYS.INTL(V79,W79,1)-1))) | AR79: =IF(AA79="","",AQ79=AA79) | AS79: =IF(OR(A79="Solicitação de Serviço",A79="Incidente",P79=""),"",IF(OR(A79="História",A79="Enabler",A79="Débito Técnico"),IF(W79="","",NETWORKDAYS.INTL(P79,W79,1)-1),IF(U79="","",NETWORKDAYS.INTL(P79,U79,1)-1))) | AT79: =IF(OR(A79="Solicitação de Serviço",A79="Incidente",A79="Sustentação"),"",IF(P79="","",IF(OR(A79="História",A79="Enabler",A79="Débito Técnico"),AS79=AC79,AS79=AB79))) | AU79: =IF(M79="","",M79)
A80: Incidente | B80: SGTB-2590 | C80: [SGTB] SP 26.3.5;[SGTB] SP 26.3.6 | D80: [Jornada Secretaria e Gestor de Unidades] Thunderbolts | E80: Aceito | F80: [SGTB] PI 3/26 | H80: [INC0811842]Tenho um Erro/Problema com o Sistema Colaborar - Colaborar - Administração de usuários | J80: 3600 | L80: Itens concluídos | O80: Concluído | P80: 46273.582 | Q80: 46265 | R80: 46274 | S80: 46274 | AH80: =IF(J80="","",J80/3600) -> 1 | AI80: =IF(COUNTIF(AG80, "*dia*"), "VERDADEIRO", "FALSO") -> FALSO | AJ80: =IF(AI80="VERDADEIRO",LEFT(AG80,2),0) -> 0 | AK80: =IF(OR(A80="Solicitação de Serviço",A80="Incidente",P80="",Q80=""),"",IF((NETWORKDAYS.INTL(P80,Q80,1)-1)=0,1,NETWORKDAYS.INTL(P80,Q80,1)-1)) | AL80: =IF(X80="","",AK80=X80) | AM80: =IF(OR(A80="Solicitação de Serviço",A80="Incidente",R80="",S80=""),"",IF((NETWORKDAYS.INTL(R80,S80,1)-1)=0,1,NETWORKDAYS.INTL(R80,S80,1)-1-AJ80)) | AN80: =IF(Y80="","",AM80=Y80) | AO80: =IF(OR(A80="Solicitação de Serviço",A80="Incidente",T80="",U80=""),"",IF((NETWORKDAYS.INTL(T80,U80,1)-1)=0,1,NETWORKDAYS.INTL(T80,U80,1)-1)) | AP80: =IF(Z80="","",AO80=Z80) | AQ80: =IF(OR(A80="Solicitação de Serviço",A80="Incidente",V80="",W80=""),"",IF((NETWORKDAYS.INTL(V80,W80,1)-1)=0,1,IF((NETWORKDAYS.INTL(V80,W80,1)-1)<0,"",NETWORKDAYS.INTL(V80,W80,1)-1))) | AR80: =IF(AA80="","",AQ80=AA80) | AS80: =IF(OR(A80="Solicitação de Serviço",A80="Incidente",P80=""),"",IF(OR(A80="História",A80="Enabler",A80="Débito Técnico"),IF(W80="","",NETWORKDAYS.INTL(P80,W80,1)-1),IF(U80="","",NETWORKDAYS.INTL(P80,U80,1)-1))) | AT80: =IF(OR(A80="Solicitação de Serviço",A80="Incidente",A80="Sustentação"),"",IF(P80="","",IF(OR(A80="História",A80="Enabler",A80="Débito Técnico"),AS80=AC80,AS80=AB80))) | AU80: =IF(M80="","",M80)
A81: Incidente | B81: SGTB-2588 | C81: [SGTB] SP 26.3.5;[SGTB] SP 26.3.6 | D81: [Jornada Secretaria e Gestor de Unidades] Thunderbolts | E81: Aceito | F81: [SGTB] PI 3/26 | H81: [INC0816019]Tenho um Erro/Problema com o Sistema - Portal Prisma - Prisma - Usuários do Prisma | J81: 600 | L81: Itens concluídos | O81: Concluído | P81: 46273.481 | Q81: 46265 | R81: 46273 | S81: 46275 | AH81: =IF(J81="","",J81/3600) -> 0.16666667 | AI81: =IF(COUNTIF(AG81, "*dia*"), "VERDADEIRO", "FALSO") -> FALSO | AJ81: =IF(AI81="VERDADEIRO",LEFT(AG81,2),0) -> 0 | AK81: =IF(OR(A81="Solicitação de Serviço",A81="Incidente",P81="",Q81=""),"",IF((NETWORKDAYS.INTL(P81,Q81,1)-1)=0,1,NETWORKDAYS.INTL(P81,Q81,1)-1)) | AL81: =IF(X81="","",AK81=X81) | AM81: =IF(OR(A81="Solicitação de Serviço",A81="Incidente",R81="",S81=""),"",IF((NETWORKDAYS.INTL(R81,S81,1)-1)=0,1,NETWORKDAYS.INTL(R81,S81,1)-1-AJ81)) | AN81: =IF(Y81="","",AM81=Y81) | AO81: =IF(OR(A81="Solicitação de Serviço",A81="Incidente",T81="",U81=""),"",IF((NETWORKDAYS.INTL(T81,U81,1)-1)=0,1,NETWORKDAYS.INTL(T81,U81,1)-1)) | AP81: =IF(Z81="","",AO81=Z81) | AQ81: =IF(OR(A81="Solicitação de Serviço",A81="Incidente",V81="",W81=""),"",IF((NETWORKDAYS.INTL(V81,W81,1)-1)=0,1,IF((NETWORKDAYS.INTL(V81,W81,1)-1)<0,"",NETWORKDAYS.INTL(V81,W81,1)-1))) | AR81: =IF(AA81="","",AQ81=AA81) | AS81: =IF(OR(A81="Solicitação de Serviço",A81="Incidente",P81=""),"",IF(OR(A81="História",A81="Enabler",A81="Débito Técnico"),IF(W81="","",NETWORKDAYS.INTL(P81,W81,1)-1),IF(U81="","",NETWORKDAYS.INTL(P81,U81,1)-1))) | AT81: =IF(OR(A81="Solicitação de Serviço",A81="Incidente",A81="Sustentação"),"",IF(P81="","",IF(OR(A81="História",A81="Enabler",A81="Débito Técnico"),AS81=AC81,AS81=AB81))) | AU81: =IF(M81="","",M81)
A82: Incidente | B82: SGTB-2587 | C82: [SGTB] SP 26.3.5;[SGTB] SP 26.3.6 | D82: [Jornada Secretaria e Gestor de Unidades] Thunderbolts | E82: Aceito | F82: [SGTB] PI 3/26 | H82: [INC0815972]Tenho um Erro/Problema com o Sistema - Ajuste de Horário - Ajuste de Horário | J82: 10800 | L82: Itens concluídos | O82: Concluído | P82: 46273.435 | Q82: 46265 | R82: 46275 | S82: 46276 | AH82: =IF(J82="","",J82/3600) -> 3 | AI82: =IF(COUNTIF(AG82, "*dia*"), "VERDADEIRO", "FALSO") -> FALSO | AJ82: =IF(AI82="VERDADEIRO",LEFT(AG82,2),0) -> 0 | AK82: =IF(OR(A82="Solicitação de Serviço",A82="Incidente",P82="",Q82=""),"",IF((NETWORKDAYS.INTL(P82,Q82,1)-1)=0,1,NETWORKDAYS.INTL(P82,Q82,1)-1)) | AL82: =IF(X82="","",AK82=X82) | AM82: =IF(OR(A82="Solicitação de Serviço",A82="Incidente",R82="",S82=""),"",IF((NETWORKDAYS.INTL(R82,S82,1)-1)=0,1,NETWORKDAYS.INTL(R82,S82,1)-1-AJ82)) | AN82: =IF(Y82="","",AM82=Y82) | AO82: =IF(OR(A82="Solicitação de Serviço",A82="Incidente",T82="",U82=""),"",IF((NETWORKDAYS.INTL(T82,U82,1)-1)=0,1,NETWORKDAYS.INTL(T82,U82,1)-1)) | AP82: =IF(Z82="","",AO82=Z82) | AQ82: =IF(OR(A82="Solicitação de Serviço",A82="Incidente",V82="",W82=""),"",IF((NETWORKDAYS.INTL(V82,W82,1)-1)=0,1,IF((NETWORKDAYS.INTL(V82,W82,1)-1)<0,"",NETWORKDAYS.INTL(V82,W82,1)-1))) | AR82: =IF(AA82="","",AQ82=AA82) | AS82: =IF(OR(A82="Solicitação de Serviço",A82="Incidente",P82=""),"",IF(OR(A82="História",A82="Enabler",A82="Débito Técnico"),IF(W82="","",NETWORKDAYS.INTL(P82,W82,1)-1),IF(U82="","",NETWORKDAYS.INTL(P82,U82,1)-1))) | AT82: =IF(OR(A82="Solicitação de Serviço",A82="Incidente",A82="Sustentação"),"",IF(P82="","",IF(OR(A82="História",A82="Enabler",A82="Débito Técnico"),AS82=AC82,AS82=AB82))) | AU82: =IF(M82="","",M82)
A83: Incidente | B83: SGTB-2586 | C83: [SGTB] SP 26.3.5;[SGTB] SP 26.3.6 | D83: [Jornada Secretaria e Gestor de Unidades] Thunderbolts | E83: Aceito | F83: [SGTB] PI 3/26 | H83: [INC0812962]Tenho um Erro/Problema com o Sistema - AVA Presencial/Moodle - Acesso ao AVA/Disciplina | J83: 3600 | L83: Itens concluídos | O83: Concluído | P83: 46273.434 | Q83: 46265 | R83: 46275 | S83: 46275 | AH83: =IF(J83="","",J83/3600) -> 1 | AI83: =IF(COUNTIF(AG83, "*dia*"), "VERDADEIRO", "FALSO") -> FALSO | AJ83: =IF(AI83="VERDADEIRO",LEFT(AG83,2),0) -> 0 | AK83: =IF(OR(A83="Solicitação de Serviço",A83="Incidente",P83="",Q83=""),"",IF((NETWORKDAYS.INTL(P83,Q83,1)-1)=0,1,NETWORKDAYS.INTL(P83,Q83,1)-1)) | AL83: =IF(X83="","",AK83=X83) | AM83: =IF(OR(A83="Solicitação de Serviço",A83="Incidente",R83="",S83=""),"",IF((NETWORKDAYS.INTL(R83,S83,1)-1)=0,1,NETWORKDAYS.INTL(R83,S83,1)-1-AJ83)) | AN83: =IF(Y83="","",AM83=Y83) | AO83: =IF(OR(A83="Solicitação de Serviço",A83="Incidente",T83="",U83=""),"",IF((NETWORKDAYS.INTL(T83,U83,1)-1)=0,1,NETWORKDAYS.INTL(T83,U83,1)-1)) | AP83: =IF(Z83="","",AO83=Z83) | AQ83: =IF(OR(A83="Solicitação de Serviço",A83="Incidente",V83="",W83=""),"",IF((NETWORKDAYS.INTL(V83,W83,1)-1)=0,1,IF((NETWORKDAYS.INTL(V83,W83,1)-1)<0,"",NETWORKDAYS.INTL(V83,W83,1)-1))) | AR83: =IF(AA83="","",AQ83=AA83) | AS83: =IF(OR(A83="Solicitação de Serviço",A83="Incidente",P83=""),"",IF(OR(A83="História",A83="Enabler",A83="Débito Técnico"),IF(W83="","",NETWORKDAYS.INTL(P83,W83,1)-1),IF(U83="","",NETWORKDAYS.INTL(P83,U83,1)-1))) | AT83: =IF(OR(A83="Solicitação de Serviço",A83="Incidente",A83="Sustentação"),"",IF(P83="","",IF(OR(A83="História",A83="Enabler",A83="Débito Técnico"),AS83=AC83,AS83=AB83))) | AU83: =IF(M83="","",M83)
A84: Solicitação de Serviço | B84: SGTB-2584 | C84: [SGTB] SP 26.3.5;[SGTB] SP 26.3.6 | D84: [Jornada Secretaria e Gestor de Unidades] Thunderbolts | E84: Aceito | F84: [SGTB] PI 3/26 | H84: [RITM0741170]Solicitar Serviço ao Sistema - Portal do Professor - Portal do Professor | J84: 7200 | L84: Itens concluídos | O84: Concluído | P84: 46269.817 | Q84: 46265 | R84: 46273 | S84: 46273 | AH84: =IF(J84="","",J84/3600) -> 2 | AI84: =IF(COUNTIF(AG84, "*dia*"), "VERDADEIRO", "FALSO") -> FALSO | AJ84: =IF(AI84="VERDADEIRO",LEFT(AG84,2),0) -> 0 | AK84: =IF(OR(A84="Solicitação de Serviço",A84="Incidente",P84="",Q84=""),"",IF((NETWORKDAYS.INTL(P84,Q84,1)-1)=0,1,NETWORKDAYS.INTL(P84,Q84,1)-1)) | AL84: =IF(X84="","",AK84=X84) | AM84: =IF(OR(A84="Solicitação de Serviço",A84="Incidente",R84="",S84=""),"",IF((NETWORKDAYS.INTL(R84,S84,1)-1)=0,1,NETWORKDAYS.INTL(R84,S84,1)-1-AJ84)) | AN84: =IF(Y84="","",AM84=Y84) | AO84: =IF(OR(A84="Solicitação de Serviço",A84="Incidente",T84="",U84=""),"",IF((NETWORKDAYS.INTL(T84,U84,1)-1)=0,1,NETWORKDAYS.INTL(T84,U84,1)-1)) | AP84: =IF(Z84="","",AO84=Z84) | AQ84: =IF(OR(A84="Solicitação de Serviço",A84="Incidente",V84="",W84=""),"",IF((NETWORKDAYS.INTL(V84,W84,1)-1)=0,1,IF((NETWORKDAYS.INTL(V84,W84,1)-1)<0,"",NETWORKDAYS.INTL(V84,W84,1)-1))) | AR84: =IF(AA84="","",AQ84=AA84) | AS84: =IF(OR(A84="Solicitação de Serviço",A84="Incidente",P84=""),"",IF(OR(A84="História",A84="Enabler",A84="Débito Técnico"),IF(W84="","",NETWORKDAYS.INTL(P84,W84,1)-1),IF(U84="","",NETWORKDAYS.INTL(P84,U84,1)-1))) | AT84: =IF(OR(A84="Solicitação de Serviço",A84="Incidente",A84="Sustentação"),"",IF(P84="","",IF(OR(A84="História",A84="Enabler",A84="Débito Técnico"),AS84=AC84,AS84=AB84))) | AU84: =IF(M84="","",M84)
A85: Incidente | B85: SGTB-2581 | C85: [SGTB] SP 26.3.5 | D85: [Jornada Secretaria e Gestor de Unidades] Thunderbolts | E85: Aceito | F85: [SGTB] PI 3/26 | H85: [INC0815220]Tenho um Erro/Problema com o PTC - Ingresso - Captação - Área do Candidato | L85: Itens concluídos | O85: Abertura indevida | P85: 46269.488 | Q85: 46265 | R85: 46269 | AH85: =IF(J85="","",J85/3600) | AI85: =IF(COUNTIF(AG85, "*dia*"), "VERDADEIRO", "FALSO") -> FALSO | AJ85: =IF(AI85="VERDADEIRO",LEFT(AG85,2),0) -> 0 | AK85: =IF(OR(A85="Solicitação de Serviço",A85="Incidente",P85="",Q85=""),"",IF((NETWORKDAYS.INTL(P85,Q85,1)-1)=0,1,NETWORKDAYS.INTL(P85,Q85,1)-1)) | AL85: =IF(X85="","",AK85=X85) | AM85: =IF(OR(A85="Solicitação de Serviço",A85="Incidente",R85="",S85=""),"",IF((NETWORKDAYS.INTL(R85,S85,1)-1)=0,1,NETWORKDAYS.INTL(R85,S85,1)-1-AJ85)) | AN85: =IF(Y85="","",AM85=Y85) | AO85: =IF(OR(A85="Solicitação de Serviço",A85="Incidente",T85="",U85=""),"",IF((NETWORKDAYS.INTL(T85,U85,1)-1)=0,1,NETWORKDAYS.INTL(T85,U85,1)-1)) | AP85: =IF(Z85="","",AO85=Z85) | AQ85: =IF(OR(A85="Solicitação de Serviço",A85="Incidente",V85="",W85=""),"",IF((NETWORKDAYS.INTL(V85,W85,1)-1)=0,1,IF((NETWORKDAYS.INTL(V85,W85,1)-1)<0,"",NETWORKDAYS.INTL(V85,W85,1)-1))) | AR85: =IF(AA85="","",AQ85=AA85) | AS85: =IF(OR(A85="Solicitação de Serviço",A85="Incidente",P85=""),"",IF(OR(A85="História",A85="Enabler",A85="Débito Técnico"),IF(W85="","",NETWORKDAYS.INTL(P85,W85,1)-1),IF(U85="","",NETWORKDAYS.INTL(P85,U85,1)-1))) | AT85: =IF(OR(A85="Solicitação de Serviço",A85="Incidente",A85="Sustentação"),"",IF(P85="","",IF(OR(A85="História",A85="Enabler",A85="Débito Técnico"),AS85=AC85,AS85=AB85))) | AU85: =IF(M85="","",M85)
A86: Incidente | B86: SGTB-2580 | C86: [SGTB] SP 26.3.5;[SGTB] SP 26.3.6 | D86: [Jornada Secretaria e Gestor de Unidades] Thunderbolts | E86: Aceito | F86: [SGTB] PI 3/26 | H86: [INC0815329]Tenho um Erro/Problema com o Sistema - Extranet - Relatorios | L86: Itens concluídos | O86: Concluído | P86: 46269.423 | Q86: 46265 | R86: 46273 | S86: 46273 | AH86: =IF(J86="","",J86/3600) | AI86: =IF(COUNTIF(AG86, "*dia*"), "VERDADEIRO", "FALSO") -> FALSO | AJ86: =IF(AI86="VERDADEIRO",LEFT(AG86,2),0) -> 0 | AK86: =IF(OR(A86="Solicitação de Serviço",A86="Incidente",P86="",Q86=""),"",IF((NETWORKDAYS.INTL(P86,Q86,1)-1)=0,1,NETWORKDAYS.INTL(P86,Q86,1)-1)) | AL86: =IF(X86="","",AK86=X86) | AM86: =IF(OR(A86="Solicitação de Serviço",A86="Incidente",R86="",S86=""),"",IF((NETWORKDAYS.INTL(R86,S86,1)-1)=0,1,NETWORKDAYS.INTL(R86,S86,1)-1-AJ86)) | AN86: =IF(Y86="","",AM86=Y86) | AO86: =IF(OR(A86="Solicitação de Serviço",A86="Incidente",T86="",U86=""),"",IF((NETWORKDAYS.INTL(T86,U86,1)-1)=0,1,NETWORKDAYS.INTL(T86,U86,1)-1)) | AP86: =IF(Z86="","",AO86=Z86) | AQ86: =IF(OR(A86="Solicitação de Serviço",A86="Incidente",V86="",W86=""),"",IF((NETWORKDAYS.INTL(V86,W86,1)-1)=0,1,IF((NETWORKDAYS.INTL(V86,W86,1)-1)<0,"",NETWORKDAYS.INTL(V86,W86,1)-1))) | AR86: =IF(AA86="","",AQ86=AA86) | AS86: =IF(OR(A86="Solicitação de Serviço",A86="Incidente",P86=""),"",IF(OR(A86="História",A86="Enabler",A86="Débito Técnico"),IF(W86="","",NETWORKDAYS.INTL(P86,W86,1)-1),IF(U86="","",NETWORKDAYS.INTL(P86,U86,1)-1))) | AT86: =IF(OR(A86="Solicitação de Serviço",A86="Incidente",A86="Sustentação"),"",IF(P86="","",IF(OR(A86="História",A86="Enabler",A86="Débito Técnico"),AS86=AC86,AS86=AB86))) | AU86: =IF(M86="","",M86)
A87: Incidente | B87: SGTB-2574 | C87: [SGTB] SP 26.3.5 | D87: [Jornada Secretaria e Gestor de Unidades] Thunderbolts | E87: Aceito | F87: [SGTB] PI 3/26 | H87: [INC0815172]Tenho um Erro/Problema com o Sistema - Prisma - Unidades dos Polos | L87: Itens concluídos | O87: Concluído | P87: 46268.722 | Q87: 46265 | R87: 46269 | S87: 46269 | AH87: =IF(J87="","",J87/3600) | AI87: =IF(COUNTIF(AG87, "*dia*"), "VERDADEIRO", "FALSO") -> FALSO | AJ87: =IF(AI87="VERDADEIRO",LEFT(AG87,2),0) -> 0 | AK87: =IF(OR(A87="Solicitação de Serviço",A87="Incidente",P87="",Q87=""),"",IF((NETWORKDAYS.INTL(P87,Q87,1)-1)=0,1,NETWORKDAYS.INTL(P87,Q87,1)-1)) | AL87: =IF(X87="","",AK87=X87) | AM87: =IF(OR(A87="Solicitação de Serviço",A87="Incidente",R87="",S87=""),"",IF((NETWORKDAYS.INTL(R87,S87,1)-1)=0,1,NETWORKDAYS.INTL(R87,S87,1)-1-AJ87)) | AN87: =IF(Y87="","",AM87=Y87) | AO87: =IF(OR(A87="Solicitação de Serviço",A87="Incidente",T87="",U87=""),"",IF((NETWORKDAYS.INTL(T87,U87,1)-1)=0,1,NETWORKDAYS.INTL(T87,U87,1)-1)) | AP87: =IF(Z87="","",AO87=Z87) | AQ87: =IF(OR(A87="Solicitação de Serviço",A87="Incidente",V87="",W87=""),"",IF((NETWORKDAYS.INTL(V87,W87,1)-1)=0,1,IF((NETWORKDAYS.INTL(V87,W87,1)-1)<0,"",NETWORKDAYS.INTL(V87,W87,1)-1))) | AR87: =IF(AA87="","",AQ87=AA87) | AS87: =IF(OR(A87="Solicitação de Serviço",A87="Incidente",P87=""),"",IF(OR(A87="História",A87="Enabler",A87="Débito Técnico"),IF(W87="","",NETWORKDAYS.INTL(P87,W87,1)-1),IF(U87="","",NETWORKDAYS.INTL(P87,U87,1)-1))) | AT87: =IF(OR(A87="Solicitação de Serviço",A87="Incidente",A87="Sustentação"),"",IF(P87="","",IF(OR(A87="História",A87="Enabler",A87="Débito Técnico"),AS87=AC87,AS87=AB87))) | AU87: =IF(M87="","",M87)
A88: Incidente | B88: SGTB-2572 | C88: [SGTB] SP 26.3.5 | D88: [Jornada Secretaria e Gestor de Unidades] Thunderbolts | E88: Aceito | F88: [SGTB] PI 3/26 | H88: [INC0815077]Tenho um Erro/Problema com o Sistema Colaborar - Colaborar - Docs Solicitação (Polo) | J88: 600 | L88: Itens concluídos | O88: Abertura indevida | P88: 46268.684 | Q88: 46265 | R88: 46268 | AH88: =IF(J88="","",J88/3600) -> 0.16666667 | AI88: =IF(COUNTIF(AG88, "*dia*"), "VERDADEIRO", "FALSO") -> FALSO | AJ88: =IF(AI88="VERDADEIRO",LEFT(AG88,2),0) -> 0 | AK88: =IF(OR(A88="Solicitação de Serviço",A88="Incidente",P88="",Q88=""),"",IF((NETWORKDAYS.INTL(P88,Q88,1)-1)=0,1,NETWORKDAYS.INTL(P88,Q88,1)-1)) | AL88: =IF(X88="","",AK88=X88) | AM88: =IF(OR(A88="Solicitação de Serviço",A88="Incidente",R88="",S88=""),"",IF((NETWORKDAYS.INTL(R88,S88,1)-1)=0,1,NETWORKDAYS.INTL(R88,S88,1)-1-AJ88)) | AN88: =IF(Y88="","",AM88=Y88) | AO88: =IF(OR(A88="Solicitação de Serviço",A88="Incidente",T88="",U88=""),"",IF((NETWORKDAYS.INTL(T88,U88,1)-1)=0,1,NETWORKDAYS.INTL(T88,U88,1)-1)) | AP88: =IF(Z88="","",AO88=Z88) | AQ88: =IF(OR(A88="Solicitação de Serviço",A88="Incidente",V88="",W88=""),"",IF((NETWORKDAYS.INTL(V88,W88,1)-1)=0,1,IF((NETWORKDAYS.INTL(V88,W88,1)-1)<0,"",NETWORKDAYS.INTL(V88,W88,1)-1))) | AR88: =IF(AA88="","",AQ88=AA88) | AS88: =IF(OR(A88="Solicitação de Serviço",A88="Incidente",P88=""),"",IF(OR(A88="História",A88="Enabler",A88="Débito Técnico"),IF(W88="","",NETWORKDAYS.INTL(P88,W88,1)-1),IF(U88="","",NETWORKDAYS.INTL(P88,U88,1)-1))) | AT88: =IF(OR(A88="Solicitação de Serviço",A88="Incidente",A88="Sustentação"),"",IF(P88="","",IF(OR(A88="História",A88="Enabler",A88="Débito Técnico"),AS88=AC88,AS88=AB88))) | AU88: =IF(M88="","",M88)
A89: Incidente | B89: SGTB-2571 | C89: [SGTB] SP 26.3.5 | D89: [Jornada Secretaria e Gestor de Unidades] Thunderbolts | E89: Aceito | F89: [SGTB] PI 3/26 | H89: [INC0815039]Tenho um Erro/Problema com o Sistema - Prisma - Usuários do Prisma | J89: 600 | L89: Itens concluídos | O89: Abertura indevida | P89: 46268.599 | Q89: 46265 | R89: 46268 | AH89: =IF(J89="","",J89/3600) -> 0.16666667 | AI89: =IF(COUNTIF(AG89, "*dia*"), "VERDADEIRO", "FALSO") -> FALSO | AJ89: =IF(AI89="VERDADEIRO",LEFT(AG89,2),0) -> 0 | AK89: =IF(OR(A89="Solicitação de Serviço",A89="Incidente",P89="",Q89=""),"",IF((NETWORKDAYS.INTL(P89,Q89,1)-1)=0,1,NETWORKDAYS.INTL(P89,Q89,1)-1)) | AL89: =IF(X89="","",AK89=X89) | AM89: =IF(OR(A89="Solicitação de Serviço",A89="Incidente",R89="",S89=""),"",IF((NETWORKDAYS.INTL(R89,S89,1)-1)=0,1,NETWORKDAYS.INTL(R89,S89,1)-1-AJ89)) | AN89: =IF(Y89="","",AM89=Y89) | AO89: =IF(OR(A89="Solicitação de Serviço",A89="Incidente",T89="",U89=""),"",IF((NETWORKDAYS.INTL(T89,U89,1)-1)=0,1,NETWORKDAYS.INTL(T89,U89,1)-1)) | AP89: =IF(Z89="","",AO89=Z89) | AQ89: =IF(OR(A89="Solicitação de Serviço",A89="Incidente",V89="",W89=""),"",IF((NETWORKDAYS.INTL(V89,W89,1)-1)=0,1,IF((NETWORKDAYS.INTL(V89,W89,1)-1)<0,"",NETWORKDAYS.INTL(V89,W89,1)-1))) | AR89: =IF(AA89="","",AQ89=AA89) | AS89: =IF(OR(A89="Solicitação de Serviço",A89="Incidente",P89=""),"",IF(OR(A89="História",A89="Enabler",A89="Débito Técnico"),IF(W89="","",NETWORKDAYS.INTL(P89,W89,1)-1),IF(U89="","",NETWORKDAYS.INTL(P89,U89,1)-1))) | AT89: =IF(OR(A89="Solicitação de Serviço",A89="Incidente",A89="Sustentação"),"",IF(P89="","",IF(OR(A89="História",A89="Enabler",A89="Débito Técnico"),AS89=AC89,AS89=AB89))) | AU89: =IF(M89="","",M89)
A90: Incidente | B90: SGTB-2569 | C90: [SGTB] SP 26.3.5 | D90: [Jornada Secretaria e Gestor de Unidades] Thunderbolts | E90: Aceito | F90: [SGTB] PI 3/26 | H90: [INC0814825]Tenho um Erro/Problema com o Sistema - Portal Prisma - Prisma - Portal Prisma (PortalUnificado) | J90: 600 | L90: Itens concluídos | O90: Concluído | P90: 46268.433 | Q90: 46265 | R90: 46268 | S90: 46268 | AH90: =IF(J90="","",J90/3600) -> 0.16666667 | AI90: =IF(COUNTIF(AG90, "*dia*"), "VERDADEIRO", "FALSO") -> FALSO | AJ90: =IF(AI90="VERDADEIRO",LEFT(AG90,2),0) -> 0 | AK90: =IF(OR(A90="Solicitação de Serviço",A90="Incidente",P90="",Q90=""),"",IF((NETWORKDAYS.INTL(P90,Q90,1)-1)=0,1,NETWORKDAYS.INTL(P90,Q90,1)-1)) | AL90: =IF(X90="","",AK90=X90) | AM90: =IF(OR(A90="Solicitação de Serviço",A90="Incidente",R90="",S90=""),"",IF((NETWORKDAYS.INTL(R90,S90,1)-1)=0,1,NETWORKDAYS.INTL(R90,S90,1)-1-AJ90)) | AN90: =IF(Y90="","",AM90=Y90) | AO90: =IF(OR(A90="Solicitação de Serviço",A90="Incidente",T90="",U90=""),"",IF((NETWORKDAYS.INTL(T90,U90,1)-1)=0,1,NETWORKDAYS.INTL(T90,U90,1)-1)) | AP90: =IF(Z90="","",AO90=Z90) | AQ90: =IF(OR(A90="Solicitação de Serviço",A90="Incidente",V90="",W90=""),"",IF((NETWORKDAYS.INTL(V90,W90,1)-1)=0,1,IF((NETWORKDAYS.INTL(V90,W90,1)-1)<0,"",NETWORKDAYS.INTL(V90,W90,1)-1))) | AR90: =IF(AA90="","",AQ90=AA90) | AS90: =IF(OR(A90="Solicitação de Serviço",A90="Incidente",P90=""),"",IF(OR(A90="História",A90="Enabler",A90="Débito Técnico"),IF(W90="","",NETWORKDAYS.INTL(P90,W90,1)-1),IF(U90="","",NETWORKDAYS.INTL(P90,U90,1)-1))) | AT90: =IF(OR(A90="Solicitação de Serviço",A90="Incidente",A90="Sustentação"),"",IF(P90="","",IF(OR(A90="História",A90="Enabler",A90="Débito Técnico"),AS90=AC90,AS90=AB90))) | AU90: =IF(M90="","",M90)
A91: Solicitação de Serviço | B91: SGTB-2568 | C91: [SGTB] SP 26.3.5;[SGTB] SP 26.3.6 | D91: [Jornada Secretaria e Gestor de Unidades] Thunderbolts | E91: Aceito | F91: [SGTB] PI 3/26 | H91: [RITM0740428]Solicitar um serviço para o Sistema Colaborar - Administrativo (DGA) - Comunicação - Banner e mensagens Campanhas | J91: 14400 | L91: Itens concluídos | O91: Concluído | P91: 46268.397 | Q91: 46265 | R91: 46273 | S91: 46273 | AH91: =IF(J91="","",J91/3600) -> 4 | AI91: =IF(COUNTIF(AG91, "*dia*"), "VERDADEIRO", "FALSO") -> FALSO | AJ91: =IF(AI91="VERDADEIRO",LEFT(AG91,2),0) -> 0 | AK91: =IF(OR(A91="Solicitação de Serviço",A91="Incidente",P91="",Q91=""),"",IF((NETWORKDAYS.INTL(P91,Q91,1)-1)=0,1,NETWORKDAYS.INTL(P91,Q91,1)-1)) | AL91: =IF(X91="","",AK91=X91) | AM91: =IF(OR(A91="Solicitação de Serviço",A91="Incidente",R91="",S91=""),"",IF((NETWORKDAYS.INTL(R91,S91,1)-1)=0,1,NETWORKDAYS.INTL(R91,S91,1)-1-AJ91)) | AN91: =IF(Y91="","",AM91=Y91) | AO91: =IF(OR(A91="Solicitação de Serviço",A91="Incidente",T91="",U91=""),"",IF((NETWORKDAYS.INTL(T91,U91,1)-1)=0,1,NETWORKDAYS.INTL(T91,U91,1)-1)) | AP91: =IF(Z91="","",AO91=Z91) | AQ91: =IF(OR(A91="Solicitação de Serviço",A91="Incidente",V91="",W91=""),"",IF((NETWORKDAYS.INTL(V91,W91,1)-1)=0,1,IF((NETWORKDAYS.INTL(V91,W91,1)-1)<0,"",NETWORKDAYS.INTL(V91,W91,1)-1))) | AR91: =IF(AA91="","",AQ91=AA91) | AS91: =IF(OR(A91="Solicitação de Serviço",A91="Incidente",P91=""),"",IF(OR(A91="História",A91="Enabler",A91="Débito Técnico"),IF(W91="","",NETWORKDAYS.INTL(P91,W91,1)-1),IF(U91="","",NETWORKDAYS.INTL(P91,U91,1)-1))) | AT91: =IF(OR(A91="Solicitação de Serviço",A91="Incidente",A91="Sustentação"),"",IF(P91="","",IF(OR(A91="História",A91="Enabler",A91="Débito Técnico"),AS91=AC91,AS91=AB91))) | AU91: =IF(M91="","",M91)
A92: Incidente | B92: SGTB-2566 | C92: [SGTB] SP 26.3.5 | D92: [Jornada Secretaria e Gestor de Unidades] Thunderbolts | E92: Aceito | F92: [SGTB] PI 3/26 | H92: [INC0814606]Tenho um Erro/Problema com o Sistema Colaborar - Colaborar - Solicitação de Documentos | J92: 600 | L92: Itens concluídos | O92: Abertura indevida | P92: 46268.349 | Q92: 46265 | R92: 46268 | AH92: =IF(J92="","",J92/3600) -> 0.16666667 | AI92: =IF(COUNTIF(AG92, "*dia*"), "VERDADEIRO", "FALSO") -> FALSO | AJ92: =IF(AI92="VERDADEIRO",LEFT(AG92,2),0) -> 0 | AK92: =IF(OR(A92="Solicitação de Serviço",A92="Incidente",P92="",Q92=""),"",IF((NETWORKDAYS.INTL(P92,Q92,1)-1)=0,1,NETWORKDAYS.INTL(P92,Q92,1)-1)) | AL92: =IF(X92="","",AK92=X92) | AM92: =IF(OR(A92="Solicitação de Serviço",A92="Incidente",R92="",S92=""),"",IF((NETWORKDAYS.INTL(R92,S92,1)-1)=0,1,NETWORKDAYS.INTL(R92,S92,1)-1-AJ92)) | AN92: =IF(Y92="","",AM92=Y92) | AO92: =IF(OR(A92="Solicitação de Serviço",A92="Incidente",T92="",U92=""),"",IF((NETWORKDAYS.INTL(T92,U92,1)-1)=0,1,NETWORKDAYS.INTL(T92,U92,1)-1)) | AP92: =IF(Z92="","",AO92=Z92) | AQ92: =IF(OR(A92="Solicitação de Serviço",A92="Incidente",V92="",W92=""),"",IF((NETWORKDAYS.INTL(V92,W92,1)-1)=0,1,IF((NETWORKDAYS.INTL(V92,W92,1)-1)<0,"",NETWORKDAYS.INTL(V92,W92,1)-1))) | AR92: =IF(AA92="","",AQ92=AA92) | AS92: =IF(OR(A92="Solicitação de Serviço",A92="Incidente",P92=""),"",IF(OR(A92="História",A92="Enabler",A92="Débito Técnico"),IF(W92="","",NETWORKDAYS.INTL(P92,W92,1)-1),IF(U92="","",NETWORKDAYS.INTL(P92,U92,1)-1))) | AT92: =IF(OR(A92="Solicitação de Serviço",A92="Incidente",A92="Sustentação"),"",IF(P92="","",IF(OR(A92="História",A92="Enabler",A92="Débito Técnico"),AS92=AC92,AS92=AB92))) | AU92: =IF(M92="","",M92)
A93: Incidente | B93: SGTB-2563 | C93: [SGTB] SP 26.3.5 | D93: [Jornada Secretaria e Gestor de Unidades] Thunderbolts | E93: Aceito | F93: [SGTB] PI 3/26 | H93: [INC0813676]Tenho um Erro/Problema com o Sistema - Sistema U - Diploma e Colação | J93: 3600 | L93: Itens concluídos | O93: Concluído | P93: 46267.768 | Q93: 46265 | R93: 46267 | S93: 46267 | AH93: =IF(J93="","",J93/3600) -> 1 | AI93: =IF(COUNTIF(AG93, "*dia*"), "VERDADEIRO", "FALSO") -> FALSO | AJ93: =IF(AI93="VERDADEIRO",LEFT(AG93,2),0) -> 0 | AK93: =IF(OR(A93="Solicitação de Serviço",A93="Incidente",P93="",Q93=""),"",IF((NETWORKDAYS.INTL(P93,Q93,1)-1)=0,1,NETWORKDAYS.INTL(P93,Q93,1)-1)) | AL93: =IF(X93="","",AK93=X93) | AM93: =IF(OR(A93="Solicitação de Serviço",A93="Incidente",R93="",S93=""),"",IF((NETWORKDAYS.INTL(R93,S93,1)-1)=0,1,NETWORKDAYS.INTL(R93,S93,1)-1-AJ93)) | AN93: =IF(Y93="","",AM93=Y93) | AO93: =IF(OR(A93="Solicitação de Serviço",A93="Incidente",T93="",U93=""),"",IF((NETWORKDAYS.INTL(T93,U93,1)-1)=0,1,NETWORKDAYS.INTL(T93,U93,1)-1)) | AP93: =IF(Z93="","",AO93=Z93) | AQ93: =IF(OR(A93="Solicitação de Serviço",A93="Incidente",V93="",W93=""),"",IF((NETWORKDAYS.INTL(V93,W93,1)-1)=0,1,IF((NETWORKDAYS.INTL(V93,W93,1)-1)<0,"",NETWORKDAYS.INTL(V93,W93,1)-1))) | AR93: =IF(AA93="","",AQ93=AA93) | AS93: =IF(OR(A93="Solicitação de Serviço",A93="Incidente",P93=""),"",IF(OR(A93="História",A93="Enabler",A93="Débito Técnico"),IF(W93="","",NETWORKDAYS.INTL(P93,W93,1)-1),IF(U93="","",NETWORKDAYS.INTL(P93,U93,1)-1))) | AT93: =IF(OR(A93="Solicitação de Serviço",A93="Incidente",A93="Sustentação"),"",IF(P93="","",IF(OR(A93="História",A93="Enabler",A93="Débito Técnico"),AS93=AC93,AS93=AB93))) | AU93: =IF(M93="","",M93)
A94: Incidente | B94: SGTB-2559 | C94: [SGTB] SP 26.3.5;[SGTB] SP 26.3.6 | D94: [Jornada Secretaria e Gestor de Unidades] Thunderbolts | E94: Aceito | F94: [SGTB] PI 3/26 | H94: [INC0814570]Tenho um Erro/Problema com o Sistema - Portal do Professor - Portal do Professor | J94: 28800 | L94: Itens concluídos | O94: Concluído | P94: 46267.734 | Q94: 46265 | R94: 46268 | S94: 46269 | AH94: =IF(J94="","",J94/3600) -> 8 | AI94: =IF(COUNTIF(AG94, "*dia*"), "VERDADEIRO", "FALSO") -> FALSO | AJ94: =IF(AI94="VERDADEIRO",LEFT(AG94,2),0) -> 0 | AK94: =IF(OR(A94="Solicitação de Serviço",A94="Incidente",P94="",Q94=""),"",IF((NETWORKDAYS.INTL(P94,Q94,1)-1)=0,1,NETWORKDAYS.INTL(P94,Q94,1)-1)) | AL94: =IF(X94="","",AK94=X94) | AM94: =IF(OR(A94="Solicitação de Serviço",A94="Incidente",R94="",S94=""),"",IF((NETWORKDAYS.INTL(R94,S94,1)-1)=0,1,NETWORKDAYS.INTL(R94,S94,1)-1-AJ94)) | AN94: =IF(Y94="","",AM94=Y94) | AO94: =IF(OR(A94="Solicitação de Serviço",A94="Incidente",T94="",U94=""),"",IF((NETWORKDAYS.INTL(T94,U94,1)-1)=0,1,NETWORKDAYS.INTL(T94,U94,1)-1)) | AP94: =IF(Z94="","",AO94=Z94) | AQ94: =IF(OR(A94="Solicitação de Serviço",A94="Incidente",V94="",W94=""),"",IF((NETWORKDAYS.INTL(V94,W94,1)-1)=0,1,IF((NETWORKDAYS.INTL(V94,W94,1)-1)<0,"",NETWORKDAYS.INTL(V94,W94,1)-1))) | AR94: =IF(AA94="","",AQ94=AA94) | AS94: =IF(OR(A94="Solicitação de Serviço",A94="Incidente",P94=""),"",IF(OR(A94="História",A94="Enabler",A94="Débito Técnico"),IF(W94="","",NETWORKDAYS.INTL(P94,W94,1)-1),IF(U94="","",NETWORKDAYS.INTL(P94,U94,1)-1))) | AT94: =IF(OR(A94="Solicitação de Serviço",A94="Incidente",A94="Sustentação"),"",IF(P94="","",IF(OR(A94="História",A94="Enabler",A94="Débito Técnico"),AS94=AC94,AS94=AB94))) | AU94: =IF(M94="","",M94)
